Workbook
Name mos: '[1]Общие данные'!$C$23:$D$23
Name mulk: '[1]Общие данные'!$C$24:$W$24

Sheet malumot
A1: =CONCATENATE(B65," olish uchun ariza") -> mikrokredit olish uchun ariza | B1: №717-XMS
A2: =CONCATENATE(B65," olish uchun ariza sanasi QO’L BILAN KIRITILADI") -> mikrokredit olish uchun ariza sanasi QO’L BILAN KIRITILADI | B2: 07.04.2025 | D2: =180+B2 -> 45934
A4: Qarz oluvchi bo’yicha ma’lumotlar
A5: Ariza beruvchining FISh (kim? – Ibragimov Rustam Sadikovich) | B5: MATCHANOVA AZIZA BEKTURDIYEVNA
A6: agar o’zgarishlar bo’lgan bo’lsa oldingi FISh (Sadikov Rustam Sadikovich yoki yo’q) | B6: yoq | C6: ha | D6: yo’q
A7: Ariza beruvchining FISh (kim? – Ibragimov R.S.) | B7: MATCHANOVA A.B.
A8: FISh (ariza kimdan? – Ibragimov Rustam Sadikovichdan) | B8: =B5 -> MATCHANOVA AZIZA BEKTURDIYEVNA
A9: FISh (kimdan? – Ibragimov R.S.dan) | B9: =B7 -> MATCHANOVA A.B.
A10: FISh (kimga? – Ibragimov Rustam Sadikovichga) | B10: =B8 -> MATCHANOVA AZIZA BEKTURDIYEVNA
A11: FISh (kimga? – Ibragimov R.S.ga) | B11: =B9 -> MATCHANOVA A.B.
A12: FISh (kim bilan? – Ibragimov Rustam Sadikovich bilan) | B12: =B10 -> MATCHANOVA AZIZA BEKTURDIYEVNA
A13: FISh (kim bilan? – Ibragimov R.S. bilan) | B13: =B11 -> MATCHANOVA A.B.
A14: Fuqaroligi (O’zbekiston Respublikasi) | B14: O’zbekiston Respublikasi
A15: Tug’ilgan sanasi (01.10.2011 yil) | B15: 09.04.1990 y
A16: Pasport seriyasi (СА №1234567) | B16: AC 2074678
B17: XORAZM VILOYATI SHOVOT TUMANI IIB | D17: =TEXT(C17,"ДД.ММ.ГГГГ") -> 00.01.1900
B18: 43663 | C18: =TEXT(B18,"ДД.ММ.ГГГГ") -> 17.07.2019
B19: 47315 | C19: =TEXT(B19,"ДД.ММ.ГГГГ") -> 16.07.2029
A20: Kim va qachon berilgan (Toshkent shahri Chilonzor IIB tomonidan 2011 yil __.____) | B20: =""&B17&" tomonidan "&C18&" yilda berilgan" -> XORAZM VILOYATI SHOVOT TUMANI IIB tomonidan 17.07.2019 yilda berilgan | C20: =""&B17&" tomonidan "&C18&" yilda berilgan" -> XORAZM VILOYATI SHOVOT TUMANI IIB tomonidan 17.07.2019 yilda berilgan
A21: Pasportni amal qilish muddati (01.10.2011 yilgacha / yoki muddatsiz) | B21: =""&C19&" y." -> 16.07.2029 y. | C21: =""&C19&" yilgacha" -> 16.07.2029 yilgacha
A22: doimiy ro’yhatdan o’tgan joyi (Toshkent sh., Mirobod tumani, Nukus ko’chasi, 1 uy, 1 honadon) | B22: XORAZM VILOYATI SHOVOT TUMANI BOYRACHI QFY BOBORAXIM KO'CHASI 4-UY | C22: =TEXT(B19,"ДД.ММ.ГГГГ") -> 16.07.2029
A23: doimiy ro’yhatdan o’tgan joyi haqiqatdagi turar joyi bilan mos keladi/mos kelmaydi | B23: mos keladi | C23: mos keladi | D23: mos kelmaydi
A24: Ro’yhatdan o’tish joyida yashash asosi | B24: Mulk huquqi | C24: Mulk huquqi | D24: ijara | E24: служебная | F24: другое | G24: -
A25: Telefon raqami kod bilan ((99871) 277 77 77) | B25: 91 860-86-87 O'ZI
A26: Mo’ljal | B26: SHOVOT TUMANI BOYRACH QFY MADANIYAT MARKAZI
B27: =IF(B23="mos keladi",B22,B28) -> XORAZM VILOYATI SHOVOT TUMANI BOYRACHI QFY BOBORAXIM KO'CHASI 4-UY
A28: Haqiqatdagi yashash joyi (Toshkent sh., Mirobod tumani, Nukus ko’chasi, 1 uy, 1 honadon) | B28: XORAZM VILOYATI SHOVOT TUMANI BOYRACHI QFY BOBORAXIM KO'CHASI 4-UY
A29: Haqiqatdagi yashash joyida turish asosi | B29: Mulk huquqi | C29: Mulk huquqi | D29: ijara | E29: xizmat | F29: boshqa | G29: -
A30: Mijozning jinsi | B30: ayol | C30: erkak | D30: ayol
A31: Tug’ilgan joyi (Toshkent) | B31: SHOVOT TUMANI
A32: Fuqaroligi (O’zbekiston Respublikasi) | B32: O’zbekiston Respublikasi
A33: Telefon raqami kod bilan ((99871) 277 77 77) | B33: 33 381-86-87 Ayoli
B34: =IF(B23="mos keladi",B26,B35) -> SHOVOT TUMANI BOYRACH QFY MADANIYAT MARKAZI
A35: Mo’ljal
A36: Oilaviy ahvoli
A37: Oila a'zolari soni (jami):
A38: Ma’lumoti
A39: Mutaxassisligi
A40: Ish telefoni raqami kod bilan ((99890) 3270000) | B40: 91 860-86-87 O'ZI
A41: Mobil telefon raqami kod bilan ((99890) 3270000) | B41: 33 381-86-87 Ayoli
A42: Ish telefoni raqami kod bilan ((99890) 3270000) | B42: 99-187-10-62 Otasi
A43: Mobil telefon raqami kod bilan ((99890) 3270000)
A44: Asosiy ish joyi | B44: O'Z O'ZINI BAND QILGAN FUQARO | C44: Yakka tartibdagi tadbirkor | D44: O'Z O'ZINI BAND QILGAN FUQARO
B45: =IF(B44=D44,CONCATENATE("MA'LUMOTNOMA ",B47,B46),C44) -> MA'LUMOTNOMA № MALUMOTNOMA № 0009500363MALUMOTNOMA № 0009500363
A46: O'Z O'ZINI BAND QILGAN BO'LSA, MA'LUMOTNOMA KIRITING | B46: MALUMOTNOMA № 0009500363
B47: =CONCATENATE(C47," ",B46) -> № MALUMOTNOMA № 0009500363 | C47: №
A48: AGAR O'Z O'ZINI BAND QILGAN FUQARO BO'LSA FAOLIYAT TURINI KIRITING | B48: TIKISH-BICHISH
A49: Lavozimi | B49: =IF(B44=C44,C44,B48) -> TIKISH-BICHISH
A50: Tashkilotning haqiqiy manzili (Toshkent sh., Mirobod tumani, Nukus ko’chasi, 1 uy, 1 honadon)
A51: Mo’ljal
A52: Ish staji, sanasidan (01.10.2011 yildan)
A53: Umumiy mehnat staji (3 yil/ 5 yil)
A54: Ish joyi telefon raqami
A55: Mijozning STIRi
A56: Mijozning unikal kodi | B56: 990000__
A57: QARZ OLUVCHINING ISH JOYI, LAVOZIMI VA O'RTACHA OYLIK DAROMADI
A58: Ish joyi | B58: =IF(B44=C44,C44,CONCATENATE(B44," ",B47)) -> O'Z O'ZINI BAND QILGAN FUQARO № MALUMOTNOMA № 0009500363
A59: Lavozimi | B59: =B49 -> TIKISH-BICHISH
A60: O’rtacha oylik daromadi | B60: 12000000 | C60: =C63/B76 -> 0.49584639
A61: Mijozning boshqa daromadlari | B61: 0 | C61: Процент годовой
A62: Ishning davomiyligi | B62: =B53 -> 0
A63: Ish joyidan ma’lumotnomaning raqami va sanasi | C63: =SUM(grafik!E9:E20) -> 61980799
A64: Kredit bo’yicha parametrlar | C64: =PROPER(B65) -> Mikrokredit | D64: =UPPER(B65) -> MIKROKREDIT
A65: Kredit turi | B65: =IF(B76>100000001,"mikrokredit",IF(B76<100000001,"mikroqarz",0)) -> mikrokredit | C65: =DATE(YEAR(B67),MONTH(B67)+B82,DAY(B67)) -> 46850
A66: Kredit shartnomasi raqami | B66: =B1 -> №717-XMS | C66: =MONTH(C65) -> 4 | D66: =IF(C66=C68,C70,IF(C66=D68,D70,IF(C66=E68,E70,IF(C66=F68,F70,IF(C66=G68,G70,IF(C66=H68,H70,IF(C66=I68,I70,IF(C66=J68,J70,IF(C66=K68,K70,IF(C66=L68,L70,IF(C66=M68,M70,IF(C66=N68,N70,)))))))))))) -> aprel | E66: =DAY(C65) -> 7 | F66: =YEAR(C65) -> 2028 | G66: =MONTH(C65) -> 4 | H66: =IF(C66=C68,C71,IF(C66=D68,D71,IF(C66=E68,E71,IF(C66=F68,F71,IF(C66=G68,G71,IF(C66=H68,H71,IF(C66=I68,I71,IF(C66=J68,J71,IF(C66=K68,K71,IF(C66=L68,L71,IF(C66=M68,M71,IF(C66=N68,N71,)))))))))))) -> aprel | I66: =YEAR(C65) -> 2028
A67: Kredit shartnomasi sanasi (14.10.2011) | B67: =B2 -> 07.04.2025 | C67: =MONTH(B67) -> 4 | D67: =IF(C67=C68,C70,IF(C67=D68,D70,IF(C67=E68,E70,IF(C67=F68,F70,IF(C67=G68,G70,IF(C67=H68,H70,IF(C67=I68,I70,IF(C67=J68,J70,IF(C67=K68,K70,IF(C67=L68,L70,IF(C67=M68,M70,IF(C67=N68,N70,)))))))))))) -> aprel | E67: =DAY(B67) -> 7 | F67: =YEAR(B67) -> 2025 | G67: =MONTH(B67) -> 4 | H67: =IF(C67=C68,C71,IF(C67=D68,D71,IF(C67=E68,E71,IF(C67=F68,F71,IF(C67=G68,G71,IF(C67=H68,H71,IF(C67=I68,I71,IF(C67=J68,J71,IF(C67=K68,K71,IF(C67=L68,L71,IF(C67=M68,M71,IF(C67=N68,N71,)))))))))))) -> aprel | I67: =YEAR(B67) -> 2025
A68: Kredit shartnomasi sanasi (14.10.2011 y.) | B68: =""&E67&" "&D67&" "&F67&" y." -> 7 aprel 2025 y. | C68: 1 | D68: 2 | E68: 3 | F68: 4 | G68: 5 | H68: 6 | I68: 7 | J68: 8 | K68: 9 | L68: 10 | M68: 11 | N68: 12
B69: =""&E67&" "&H67&" "&F67&" y." -> 7 aprel 2025 y.
B70: =B68 -> 7 aprel 2025 y. | C70: yanvar | D70: fevral | E70: mart | F70: aprel | G70: may | H70: iyun | I70: iyul | J70: avgust | K70: sentabr | L70: oktabr | M70: noyabr | N70: dekabr
B71: =B69 -> 7 aprel 2025 y. | C71: yanvar | D71: fevral | E71: mart | F71: aprel | G71: may | H71: iyun | I71: iyul | J71: avgust | K71: sentabr | L71: oktabr | M71: noyabr | N71: dekabr
A72: Tugash sanasi QO’L BILAN KIRITILADI | B72: =""&E66&" "&D66&" "&F66&" y." -> 7 aprel 2028 y.
B73: =""&E66&" "&H66&" "&F66&" y." -> 7 aprel 2028 y.
A74: Kredit shartnomasi raqami va sanasi | B74: =""&B68&"dan "&B66&"" -> 7 aprel 2025 y.dan №717-XMS
A75: =CONCATENATE(B65," miqdori (summasi)") -> mikrokredit miqdori (summasi) | B75: 110000000
A76: =CONCATENATE(B65," miqdori (summasi)") -> mikrokredit miqdori (summasi) | B76: =B75+B154 -> 125000000 | C76: Uzbek tilida
A77: QO’L BILAN KIRITILADI | B77: =""&SUBSTITUTE(SUBSTITUTE(SUBSTITUTE(TRIM(SUBSTITUTE(SUBSTITUTE(SUBSTITUTE(SUBSTITUTE(SUBSTITUTE(SUBSTITUTE(SUBSTITUTE(SUBSTITUTE(SUBSTITUTE(SUBSTITUTE(SUBSTITUTE(SUBSTITUTE(SUBSTITUTE(SUBSTITUTE(SUBSTITUTE(SUBSTITUTE(SUBSTITUTE(SUBSTITUTE(SUBSTITUTE(SUBSTITUTE(SUBSTITUTE(SUBSTITUTE(SUBSTITUTE(SUBSTITUTE(SUBSTITUTE(SUBSTITUTE(SUBSTITUTE(SUBSTITUTE(SUBSTITUTE(SUBSTITUTE(SUBSTITUTE(SUBSTITUTE(SUBSTITUTE(SUBSTITUTE(SUBSTITUTE(SUBSTITUTE(SUBSTITUTE(SUBSTITUTE(SUBSTITUTE(SUBSTITUTE(SUBSTITUTE(SUBSTITUTE(SUBSTITUTE(SUBSTITUTE(IF(LEN(INT(B76))>6,ROMAN(MID(INT(B76),1,LEN(INT(B76))-6)+0)&" million "&ROMAN(MID(INT(B76),LEN(INT(B76))-5,3)+0)&" ming "&ROMAN(MID(INT(B76),LEN(INT(B76))-2,3)+0),IF(LEN(INT(B76))>3,ROMAN(MID(INT(B76),1,LEN(INT(B76))-3)+0)&" ming "&ROMAN(MID(INT(B76),LEN(INT(B76))-2,3)+0),ROMAN(INT(B76)))),"DCCC"," sakkiz yuz"),"DCC"," yetti yuz"),"DC"," olti yuz"),"CD"," to'rt yuz"),"XC"," to'qson"),"CCC"," uch yuz"),"CC"," ikki yuz"),"D"," besh yuz"),"CM"," to'qqiz yuz"),"C"," yuz"),"XL"," qirq"),"LXXX"," sakson"),"LXX"," yetmish"),"LX"," oltmish"),"L"," ellik"),"XXX"," o'ttiz"),"XX"," yigirma"),"XIX"," o'n toqqiz"),"XVIII"," o'n sakkiz"),"XVII"," o'n yetti"),"XVI"," o'n olti"),"XV"," o'n besh"),"XIV"," o'n to'rt"),"XIII"," o'n uch"),"XII"," o'n ikki"),"XI"," o'n bir"),"IX"," to'qqiz"),"X"," o'n"),"VIII"," sakkiz"),"VII"," yetti"),"VI"," olti"),"IV"," to'rt"),"V"," besh"),"III"," uch"),"II"," ikki"),"I"," bir"),"bir ming","bir ming"),"ikki ming","ikki ming"),"uch ming","uch ming"),"to'rt ming","to'rt ming"),"bir million","bir million"),"ikki million","ikki million"),"uch million","uch million"),"to'rt million","to'rt million")),"million ming","million"),"million ming","million"),"million ming","million")&" so'm" -> yuz yigirma besh million so'm | C77: =UPPER(LEFT(SUBSTITUTE(SUBSTITUTE(SUBSTITUTE(TRIM(SUBSTITUTE(SUBSTITUTE(SUBSTITUTE(SUBSTITUTE(SUBSTITUTE(SUBSTITUTE(SUBSTITUTE(SUBSTITUTE(SUBSTITUTE(SUBSTITUTE(SUBSTITUTE(SUBSTITUTE(SUBSTITUTE(SUBSTITUTE(SUBSTITUTE(SUBSTITUTE(SUBSTITUTE(SUBSTITUTE(SUBSTITUTE(SUBSTITUTE(SUBSTITUTE(SUBSTITUTE(SUBSTITUTE(SUBSTITUTE(SUBSTITUTE(SUBSTITUTE(SUBSTITUTE(SUBSTITUTE(SUBSTITUTE(SUBSTITUTE(SUBSTITUTE(SUBSTITUTE(SUBSTITUTE(SUBSTITUTE(SUBSTITUTE(SUBSTITUTE(SUBSTITUTE(SUBSTITUTE(SUBSTITUTE(SUBSTITUTE(SUBSTITUTE(SUBSTITUTE(SUBSTITUTE(SUBSTITUTE(SUBSTITUTE(SUBSTITUTE(SUBSTITUTE(SUBSTITUTE(IF(LEN(ROUNDDOWN(B76,0))>6,ROMAN(MID(ROUNDDOWN(B76,0),1,LEN(ROUNDDOWN(B76,0))-6)+0)&" million "&ROMAN(MID(ROUNDDOWN(B76,0),LEN(ROUNDDOWN(B76,0))-5,3)+0)&" ming "&ROMAN(MID(ROUNDDOWN(B76,0),LEN(ROUNDDOWN(B76,0))-2,3)+0)&" so'm",IF(LEN(ROUNDDOWN(B76,0))>3,ROMAN(MID(ROUNDDOWN(B76,0),1,LEN(ROUNDDOWN(B76,0))-3)+0)&" ming "&ROMAN(MID(ROUNDDOWN(B76,0),LEN(ROUNDDOWN(B76,0))-2,3)+0)&" so'm",ROMAN(ROUNDDOWN(B76,0))&" so'm")),"DCCC"," sakkiz yuz"),"DCC"," yetti yuz"),"DC"," olti yuz"),"CD"," to'rt yuz"),"XC"," to'qson"),"CCC"," uch yuz"),"CC"," ikki yuz"),"D"," besh yuz"),"CM"," to'qqiz yuz"),"C"," yuz"),"XL"," qiriq"),"LXXX"," sakson"),"LXX"," yetmish"),"LX"," oltmish"),"L"," ellik"),"XXX"," o'ttiz"),"XX"," yigirma"),"XIX"," o'n tiqqiz"),"XVIII"," o'n sakkiz"),"XVII"," o'n yetti"),"XVI"," o'n olti"),"XV"," o'n besh"),"XIV"," o'n to'rt"),"XIII"," o'n uch"),"XII"," o'n ikki"),"XI"," o'n bir"),"IX"," to'qqiz"),"X"," o'n"),"VIII"," sakkiz"),"VII"," yetti"),"VI"," olti"),"IV"," to'rt"),"V"," besh"),"III"," uch"),"II"," ikki"),"I"," bir"),"bir ming","bir ming"),"ikki ming","ikki ming"),"uch ming","uch ming"),"to'rt ming","to'rt ming"),"bir million","bir million"),"ikki million","ikki million"),"uch million","uch million"),"to'rt million","to'rt million"),"bir so'm","bir so'm"),"ikki so'm","ikki so'm"),"uch so'm","uch so'm"),"to'rt so'm","to'rt so'm")),"ming million","million"),"ming million","million"),"ming million","million"),1))&MID(SUBSTITUTE(SUBSTITUTE(SUBSTITUTE(TRIM(SUBSTITUTE(SUBSTITUTE(SUBSTITUTE(SUBSTITUTE(SUBSTITUTE(SUBSTITUTE(SUBSTITUTE(SUBSTITUTE(SUBSTITUTE(SUBSTITUTE(SUBSTITUTE(SUBSTITUTE(SUBSTITUTE(SUBSTITUTE(SUBSTITUTE(SUBSTITUTE(SUBSTITUTE(SUBSTITUTE(SUBSTITUTE(SUBSTITUTE(SUBSTITUTE(SUBSTITUTE(SUBSTITUTE(SUBSTITUTE(SUBSTITUTE(SUBSTITUTE(SUBSTITUTE(SUBSTITUTE(SUBSTITUTE(SUBSTITUTE(SUBSTITUTE(SUBSTITUTE(SUBSTITUTE(SUBSTITUTE(SUBSTITUTE(SUBSTITUTE(SUBSTITUTE(SUBSTITUTE(SUBSTITUTE(SUBSTITUTE(SUBSTITUTE(SUBSTITUTE(SUBSTITUTE(SUBSTITUTE(SUBSTITUTE(SUBSTITUTE(SUBSTITUTE(SUBSTITUTE(IF(LEN(ROUNDDOWN(B76,0))>6,ROMAN(MID(ROUNDDOWN(B76,0),1,LEN(ROUNDDOWN(B76,0))-6)+0)&" million "&ROMAN(MID(ROUNDDOWN(B76,0),LEN(ROUNDDOWN(B76,0))-5,3)+0)&" "&ROMAN(MID(ROUNDDOWN(B76,0),LEN(ROUNDDOWN(B76,0))-2,3)+0)&" so'm",IF(LEN(ROUNDDOWN(B76,0))>3,ROMAN(MID(ROUNDDOWN(B76,0),1,LEN(ROUNDDOWN(B76,0))-3)+0)&" ming "&ROMAN(MID(ROUNDDOWN(B76,0),LEN(ROUNDDOWN(B76,0))-2,3)+0)&" so'm",ROMAN(ROUNDDOWN(B76,0))&" so'm")),"DCCC"," sakkiz yuz"),"DCC"," yetti yuz"),"DC"," olti yuz"),"CD"," to'rt yuz"),"XC"," to'qson"),"CCC"," uch yuz"),"CC"," ikki yuz"),"D"," besh yuz"),"CM"," to'qqiz yuz"),"C"," yuz"),"XL"," qirq"),"LXXX"," sakson"),"LXX"," yetmish"),"LX"," oltmish"),"L"," ellik"),"XXX"," o'ttiz"),"XX"," yigirma"),"XIX"," o'n to'qqiz"),"XVIII"," o'n sakkiz"),"XVII"," o'n yetti"),"XVI"," o'n olti"),"XV"," o'n besh"),"XIV"," o'n to'rt"),"XIII"," o'n uch"),"XII"," o'n ikki"),"XI"," o'n bir"),"IX"," to'qqiz"),"X"," o'n"),"VIII"," sakkiz"),"VII"," yetti"),"VI"," olti"),"IV"," to'rt"),"V"," besh"),"III"," uch"),"II"," ikki"),"I"," bir"),"bir ming","bir ming"),"ikki ming","ikki ming"),"uch ming","uch ming"),"to'rt ming","to'rt ming"),"bir million","bir million"),"ikki million","ikki million"),"uch million","uch million"),"to'rt million","to'rt million"),"bir so'm","bir so'm"),"ikki so'm","ikki so'm"),"uch so'm","uch so'm"),"to'rt so'm","to'rt so'm")),"ming million","million"),"ming million","million"),"ming million","million"),2,200)&"" -> Yuz yigirma besh million so'm
A78: Grafik turi | B78: annuitet | C78: differensial | D78: annuitet
A79: =CONCATENATE(B65,"ni to'lash sanasi (14.10.2011)") -> mikrokreditni to'lash sanasi (14.10.2011) | B79: 1 | C79: =DATE(YEAR(B67),MONTH(B67)+1,DAY(B79)) -> 45778 | D79: Пн | E79: Вт | F79: Ср | G79: Чт | H79: Пт | I79: Сб | J79: Вс
A80: =CONCATENATE(B65,"ni to'lash sanasi (14.10.2011 y.) QO’L BILAN KIRITILADI") -> mikrokreditni to'lash sanasi (14.10.2011 y.) QO’L BILAN KIRITILADI | B80: =DATE(YEAR(B67),MONTH(B67)+1,DAY(B79+C81)) -> 45778 | C80: =TEXT(C79,"ддд") -> Чт | D80: Пн | E80: Вт | F80: Ср | G80: Чт | H80: Пт | I80: Сб | J80: Вс
A81: Mikroqarzni to'lash sanasi (14.10.2011 y.) QO’L BILAN KIRITILADI | B81: =B80 -> 45778 | C81: =IF(C80=I80,2,IF(C80=J80,1,0)) -> 0
A82: =CONCATENATE(B65," muddati") -> mikrokredit muddati | B82: 36 | C82: 6 | D82: 12 | E82: 18 | F82: 24 | G82: 36
A83: =CONCATENATE(B65," muddati QO’L BILAN KIRITILADI") -> mikrokredit muddati QO’L BILAN KIRITILADI | B83: =UPPER(LEFT(SUBSTITUTE(SUBSTITUTE(SUBSTITUTE(TRIM(SUBSTITUTE(SUBSTITUTE(SUBSTITUTE(SUBSTITUTE(SUBSTITUTE(SUBSTITUTE(SUBSTITUTE(SUBSTITUTE(SUBSTITUTE(SUBSTITUTE(SUBSTITUTE(SUBSTITUTE(SUBSTITUTE(SUBSTITUTE(SUBSTITUTE(SUBSTITUTE(SUBSTITUTE(SUBSTITUTE(SUBSTITUTE(SUBSTITUTE(SUBSTITUTE(SUBSTITUTE(SUBSTITUTE(SUBSTITUTE(SUBSTITUTE(SUBSTITUTE(SUBSTITUTE(SUBSTITUTE(SUBSTITUTE(SUBSTITUTE(SUBSTITUTE(SUBSTITUTE(SUBSTITUTE(SUBSTITUTE(SUBSTITUTE(SUBSTITUTE(SUBSTITUTE(SUBSTITUTE(SUBSTITUTE(SUBSTITUTE(SUBSTITUTE(SUBSTITUTE(SUBSTITUTE(SUBSTITUTE(SUBSTITUTE(SUBSTITUTE(SUBSTITUTE(SUBSTITUTE(IF(LEN(ROUNDDOWN(B82,0))>6,ROMAN(MID(ROUNDDOWN(B82,0),1,LEN(ROUNDDOWN(B82,0))-6)+0)&" million "&ROMAN(MID(ROUNDDOWN(B82,0),LEN(ROUNDDOWN(B82,0))-5,3)+0)&" ming "&ROMAN(MID(ROUNDDOWN(B82,0),LEN(ROUNDDOWN(B82,0))-2,3)+0)&"",IF(LEN(ROUNDDOWN(B82,0))>3,ROMAN(MID(ROUNDDOWN(B82,0),1,LEN(ROUNDDOWN(B82,0))-3)+0)&" ming "&ROMAN(MID(ROUNDDOWN(B82,0),LEN(ROUNDDOWN(B82,0))-2,3)+0)&"",ROMAN(ROUNDDOWN(B82,0))&"")),"DCCC"," sakkiz yuz"),"DCC"," yetti yuz"),"DC"," olti yuz"),"CD"," to'rt yuz"),"XC"," to'qson"),"CCC"," uch yuz"),"CC"," ikki yuz"),"D"," besh yuz"),"CM"," to'qqiz yuz"),"C"," yuz"),"XL"," qiriq"),"LXXX"," sakson"),"LXX"," yetmish"),"LX"," oltmish"),"L"," ellik"),"XXX"," o'ttiz"),"XX"," yigirma"),"XIX"," o'n tiqqiz"),"XVIII"," o'n sakkiz"),"XVII"," o'n yetti"),"XVI"," o'n olti"),"XV"," o'n besh"),"XIV"," o'n to'rt"),"XIII"," o'n uch"),"XII"," o'n ikki"),"XI"," o'n bir"),"IX"," to'qqiz"),"X"," o'n"),"VIII"," sakkiz"),"VII"," yetti"),"VI"," olti"),"IV"," to'rt"),"V"," besh"),"III"," uch"),"II"," ikki"),"I"," bir"),"bir ming","bir ming"),"ikki ming","ikki ming"),"uch ming","uch ming"),"to'rt ming","to'rt ming"),"bir million","bir million"),"ikki million","ikki million"),"uch million","uch million"),"to'rt million","to'rt million"),"bir","bir"),"ikki","ikki"),"uch","uch"),"to'rt","to'rt")),"ming million","million"),"ming million","million"),"ming million","million"),1))&MID(SUBSTITUTE(SUBSTITUTE(SUBSTITUTE(TRIM(SUBSTITUTE(SUBSTITUTE(SUBSTITUTE(SUBSTITUTE(SUBSTITUTE(SUBSTITUTE(SUBSTITUTE(SUBSTITUTE(SUBSTITUTE(SUBSTITUTE(SUBSTITUTE(SUBSTITUTE(SUBSTITUTE(SUBSTITUTE(SUBSTITUTE(SUBSTITUTE(SUBSTITUTE(SUBSTITUTE(SUBSTITUTE(SUBSTITUTE(SUBSTITUTE(SUBSTITUTE(SUBSTITUTE(SUBSTITUTE(SUBSTITUTE(SUBSTITUTE(SUBSTITUTE(SUBSTITUTE(SUBSTITUTE(SUBSTITUTE(SUBSTITUTE(SUBSTITUTE(SUBSTITUTE(SUBSTITUTE(SUBSTITUTE(SUBSTITUTE(SUBSTITUTE(SUBSTITUTE(SUBSTITUTE(SUBSTITUTE(SUBSTITUTE(SUBSTITUTE(SUBSTITUTE(SUBSTITUTE(SUBSTITUTE(SUBSTITUTE(SUBSTITUTE(SUBSTITUTE(IF(LEN(ROUNDDOWN(B82,0))>6,ROMAN(MID(ROUNDDOWN(B82,0),1,LEN(ROUNDDOWN(B82,0))-6)+0)&" million "&ROMAN(MID(ROUNDDOWN(B82,0),LEN(ROUNDDOWN(B82,0))-5,3)+0)&" "&ROMAN(MID(ROUNDDOWN(B82,0),LEN(ROUNDDOWN(B82,0))-2,3)+0)&"",IF(LEN(ROUNDDOWN(B82,0))>3,ROMAN(MID(ROUNDDOWN(B82,0),1,LEN(ROUNDDOWN(B82,0))-3)+0)&" ming "&ROMAN(MID(ROUNDDOWN(B82,0),LEN(ROUNDDOWN(B82,0))-2,3)+0)&"",ROMAN(ROUNDDOWN(B82,0))&"")),"DCCC"," sakkiz yuz"),"DCC"," yetti yuz"),"DC"," olti yuz"),"CD"," to'rt yuz"),"XC"," to'qson"),"CCC"," uch yuz"),"CC"," ikki yuz"),"D"," besh yuz"),"CM"," to'qqiz yuz"),"C"," yuz"),"XL"," qirq"),"LXXX"," sakson"),"LXX"," yetmish"),"LX"," oltmish"),"L"," ellik"),"XXX"," o'ttiz"),"XX"," yigirma"),"XIX"," o'n to'qqiz"),"XVIII"," o'n sakkiz"),"XVII"," o'n yetti"),"XVI"," o'n olti"),"XV"," o'n besh"),"XIV"," o'n to'rt"),"XIII"," o'n uch"),"XII"," o'n ikki"),"XI"," o'n bir"),"IX"," to'qqiz"),"X"," o'n"),"VIII"," sakkiz"),"VII"," yetti"),"VI"," olti"),"IV"," to'rt"),"V"," besh"),"III"," uch"),"II"," ikki"),"I"," bir"),"bir ming","bir ming"),"ikki ming","ikki ming"),"uch ming","uch ming"),"to'rt ming","to'rt ming"),"bir million","bir million"),"ikki million","ikki million"),"uch million","uch million"),"to'rt million","to'rt million"),"bir","bir"),"ikki","ikki"),"uch","uch"),"to'rt","to'rt")),"ming million","million"),"ming million","million"),"ming million","million"),2,200)&" "&SUBSTITUTE(SUBSTITUTE(SUBSTITUTE(SUBSTITUTE(SUBSTITUTE(SUBSTITUTE(SUBSTITUTE(SUBSTITUTE(RIGHT(TEXT(B82," "),2)&"","1","1"),"2","2"),"3","3"),"4","4"),"11","11"),"12","12"),"13","13"),"14","14") -> O'ttiz olti
A84: Imtiyozli davr | B84: 0 | BJ84: 1 | BK84: 0
A85: =CONCATENATE(B65," stavkasi") -> mikrokredit stavkasi | B85: 0.55
A86: =CONCATENATE(B65," stavkasi") -> mikrokredit stavkasi | B86: 55
A87: =CONCATENATE(B65," stavkasi (so’z bilan)") -> mikrokredit stavkasi (so’z bilan) | B87: =UPPER(LEFT(SUBSTITUTE(SUBSTITUTE(SUBSTITUTE(TRIM(SUBSTITUTE(SUBSTITUTE(SUBSTITUTE(SUBSTITUTE(SUBSTITUTE(SUBSTITUTE(SUBSTITUTE(SUBSTITUTE(SUBSTITUTE(SUBSTITUTE(SUBSTITUTE(SUBSTITUTE(SUBSTITUTE(SUBSTITUTE(SUBSTITUTE(SUBSTITUTE(SUBSTITUTE(SUBSTITUTE(SUBSTITUTE(SUBSTITUTE(SUBSTITUTE(SUBSTITUTE(SUBSTITUTE(SUBSTITUTE(SUBSTITUTE(SUBSTITUTE(SUBSTITUTE(SUBSTITUTE(SUBSTITUTE(SUBSTITUTE(SUBSTITUTE(SUBSTITUTE(SUBSTITUTE(SUBSTITUTE(SUBSTITUTE(SUBSTITUTE(SUBSTITUTE(SUBSTITUTE(SUBSTITUTE(SUBSTITUTE(SUBSTITUTE(SUBSTITUTE(SUBSTITUTE(SUBSTITUTE(SUBSTITUTE(SUBSTITUTE(SUBSTITUTE(SUBSTITUTE(IF(LEN(ROUNDDOWN(B86,0))>6,ROMAN(MID(ROUNDDOWN(B86,0),1,LEN(ROUNDDOWN(B86,0))-6)+0)&" million "&ROMAN(MID(ROUNDDOWN(B86,0),LEN(ROUNDDOWN(B86,0))-5,3)+0)&" ming "&ROMAN(MID(ROUNDDOWN(B86,0),LEN(ROUNDDOWN(B86,0))-2,3)+0)&"",IF(LEN(ROUNDDOWN(B86,0))>3,ROMAN(MID(ROUNDDOWN(B86,0),1,LEN(ROUNDDOWN(B86,0))-3)+0)&" ming "&ROMAN(MID(ROUNDDOWN(B86,0),LEN(ROUNDDOWN(B86,0))-2,3)+0)&"",ROMAN(ROUNDDOWN(B86,0))&"")),"DCCC"," sakkiz yuz"),"DCC"," yetti yuz"),"DC"," olti yuz"),"CD"," to'rt yuz"),"XC"," to'qson"),"CCC"," uch yuz"),"CC"," ikki yuz"),"D"," besh yuz"),"CM"," to'qqiz yuz"),"C"," yuz"),"XL"," qiriq"),"LXXX"," sakson"),"LXX"," yetmish"),"LX"," oltmish"),"L"," ellik"),"XXX"," o'ttiz"),"XX"," yigirma"),"XIX"," o'n tiqqiz"),"XVIII"," o'n sakkiz"),"XVII"," o'n yetti"),"XVI"," o'n olti"),"XV"," o'n besh"),"XIV"," o'n to'rt"),"XIII"," o'n uch"),"XII"," o'n ikki"),"XI"," o'n bir"),"IX"," to'qqiz"),"X"," o'n"),"VIII"," sakkiz"),"VII"," yetti"),"VI"," olti"),"IV"," to'rt"),"V"," besh"),"III"," uch"),"II"," ikki"),"I"," bir"),"bir ming","bir ming"),"ikki ming","ikki ming"),"uch ming","uch ming"),"to'rt ming","to'rt ming"),"bir million","bir million"),"ikki million","ikki million"),"uch million","uch million"),"to'rt million","to'rt million"),"bir","bir"),"ikki","ikki"),"uch","uch"),"to'rt","to'rt")),"ming million","million"),"ming million","million"),"ming million","million"),1))&MID(SUBSTITUTE(SUBSTITUTE(SUBSTITUTE(TRIM(SUBSTITUTE(SUBSTITUTE(SUBSTITUTE(SUBSTITUTE(SUBSTITUTE(SUBSTITUTE(SUBSTITUTE(SUBSTITUTE(SUBSTITUTE(SUBSTITUTE(SUBSTITUTE(SUBSTITUTE(SUBSTITUTE(SUBSTITUTE(SUBSTITUTE(SUBSTITUTE(SUBSTITUTE(SUBSTITUTE(SUBSTITUTE(SUBSTITUTE(SUBSTITUTE(SUBSTITUTE(SUBSTITUTE(SUBSTITUTE(SUBSTITUTE(SUBSTITUTE(SUBSTITUTE(SUBSTITUTE(SUBSTITUTE(SUBSTITUTE(SUBSTITUTE(SUBSTITUTE(SUBSTITUTE(SUBSTITUTE(SUBSTITUTE(SUBSTITUTE(SUBSTITUTE(SUBSTITUTE(SUBSTITUTE(SUBSTITUTE(SUBSTITUTE(SUBSTITUTE(SUBSTITUTE(SUBSTITUTE(SUBSTITUTE(SUBSTITUTE(SUBSTITUTE(SUBSTITUTE(IF(LEN(ROUNDDOWN(B86,0))>6,ROMAN(MID(ROUNDDOWN(B86,0),1,LEN(ROUNDDOWN(B86,0))-6)+0)&" million "&ROMAN(MID(ROUNDDOWN(B86,0),LEN(ROUNDDOWN(B86,0))-5,3)+0)&" "&ROMAN(MID(ROUNDDOWN(B86,0),LEN(ROUNDDOWN(B86,0))-2,3)+0)&"",IF(LEN(ROUNDDOWN(B86,0))>3,ROMAN(MID(ROUNDDOWN(B86,0),1,LEN(ROUNDDOWN(B86,0))-3)+0)&" ming "&ROMAN(MID(ROUNDDOWN(B86,0),LEN(ROUNDDOWN(B86,0))-2,3)+0)&"",ROMAN(ROUNDDOWN(B86,0))&"")),"DCCC"," sakkiz yuz"),"DCC"," yetti yuz"),"DC"," olti yuz"),"CD"," to'rt yuz"),"XC"," to'qson"),"CCC"," uch yuz"),"CC"," ikki yuz"),"D"," besh yuz"),"CM"," to'qqiz yuz"),"C"," yuz"),"XL"," qirq"),"LXXX"," sakson"),"LXX"," yetmish"),"LX"," oltmish"),"L"," ellik"),"XXX"," o'ttiz"),"XX"," yigirma"),"XIX"," o'n to'qqiz"),"XVIII"," o'n sakkiz"),"XVII"," o'n yetti"),"XVI"," o'n olti"),"XV"," o'n besh"),"XIV"," o'n to'rt"),"XIII"," o'n uch"),"XII"," o'n ikki"),"XI"," o'n bir"),"IX"," to'qqiz"),"X"," o'n"),"VIII"," sakkiz"),"VII"," yetti"),"VI"," olti"),"IV"," to'rt"),"V"," besh"),"III"," uch"),"II"," ikki"),"I"," bir"),"bir ming","bir ming"),"ikki ming","ikki ming"),"uch ming","uch ming"),"to'rt ming","to'rt ming"),"bir million","bir million"),"ikki million","ikki million"),"uch million","uch million"),"to'rt million","to'rt million"),"bir","bir"),"ikki","ikki"),"uch","uch"),"to'rt","to'rt")),"ming million","million"),"ming million","million"),"ming million","million"),2,200)&" "&SUBSTITUTE(SUBSTITUTE(SUBSTITUTE(SUBSTITUTE(SUBSTITUTE(SUBSTITUTE(SUBSTITUTE(SUBSTITUTE(RIGHT(TEXT(B86," "),2)&"","1","1"),"2","2"),"3","3"),"4","4"),"11","11"),"12","12"),"13","13"),"14","14") -> Ellik besh | C87: =UPPER(LEFT(SUBSTITUTE(SUBSTITUTE(SUBSTITUTE(TRIM(SUBSTITUTE(SUBSTITUTE(SUBSTITUTE(SUBSTITUTE(SUBSTITUTE(SUBSTITUTE(SUBSTITUTE(SUBSTITUTE(SUBSTITUTE(SUBSTITUTE(SUBSTITUTE(SUBSTITUTE(SUBSTITUTE(SUBSTITUTE(SUBSTITUTE(SUBSTITUTE(SUBSTITUTE(SUBSTITUTE(SUBSTITUTE(SUBSTITUTE(SUBSTITUTE(SUBSTITUTE(SUBSTITUTE(SUBSTITUTE(SUBSTITUTE(SUBSTITUTE(SUBSTITUTE(SUBSTITUTE(SUBSTITUTE(SUBSTITUTE(SUBSTITUTE(SUBSTITUTE(SUBSTITUTE(SUBSTITUTE(SUBSTITUTE(SUBSTITUTE(SUBSTITUTE(SUBSTITUTE(SUBSTITUTE(SUBSTITUTE(SUBSTITUTE(SUBSTITUTE(SUBSTITUTE(SUBSTITUTE(SUBSTITUTE(SUBSTITUTE(SUBSTITUTE(SUBSTITUTE(IF(LEN(ROUNDDOWN(B86,0))>6,ROMAN(MID(ROUNDDOWN(B86,0),1,LEN(ROUNDDOWN(B86,0))-6)+0)&" million "&ROMAN(MID(ROUNDDOWN(B86,0),LEN(ROUNDDOWN(B86,0))-5,3)+0)&" ming "&ROMAN(MID(ROUNDDOWN(B86,0),LEN(ROUNDDOWN(B86,0))-2,3)+0)&"",IF(LEN(ROUNDDOWN(B86,0))>3,ROMAN(MID(ROUNDDOWN(B86,0),1,LEN(ROUNDDOWN(B86,0))-3)+0)&" ming "&ROMAN(MID(ROUNDDOWN(B86,0),LEN(ROUNDDOWN(B86,0))-2,3)+0)&"",ROMAN(ROUNDDOWN(B86,0))&"")),"DCCC"," sakkiz yuz"),"DCC"," yetti yuz"),"DC"," olti yuz"),"CD"," to'rt yuz"),"XC"," to'qson"),"CCC"," uch yuz"),"CC"," ikki yuz"),"D"," besh yuz"),"CM"," to'qqiz yuz"),"C"," yuz"),"XL"," qiriq"),"LXXX"," sakson"),"LXX"," yetmish"),"LX"," oltmish"),"L"," ellik"),"XXX"," o'ttiz"),"XX"," yigirma"),"XIX"," o'n tiqqiz"),"XVIII"," o'n sakkiz"),"XVII"," o'n yetti"),"XVI"," o'n olti"),"XV"," o'n besh"),"XIV"," o'n to'rt"),"XIII"," o'n uch"),"XII"," o'n ikki"),"XI"," o'n bir"),"IX"," to'qqiz"),"X"," o'n"),"VIII"," sakkiz"),"VII"," yetti"),"VI"," olti"),"IV"," to'rt"),"V"," besh"),"III"," uch"),"II"," ikki"),"I"," bir"),"bir ming","bir ming"),"ikki ming","ikki ming"),"uch ming","uch ming"),"to'rt ming","to'rt ming"),"bir million","bir million"),"ikki million","ikki million"),"uch million","uch million"),"to'rt million","to'rt million"),"bir","bir"),"ikki","ikki"),"uch","uch"),"to'rt","to'rt")),"ming million","million"),"ming million","million"),"ming million","million"),1))&MID(SUBSTITUTE(SUBSTITUTE(SUBSTITUTE(TRIM(SUBSTITUTE(SUBSTITUTE(SUBSTITUTE(SUBSTITUTE(SUBSTITUTE(SUBSTITUTE(SUBSTITUTE(SUBSTITUTE(SUBSTITUTE(SUBSTITUTE(SUBSTITUTE(SUBSTITUTE(SUBSTITUTE(SUBSTITUTE(SUBSTITUTE(SUBSTITUTE(SUBSTITUTE(SUBSTITUTE(SUBSTITUTE(SUBSTITUTE(SUBSTITUTE(SUBSTITUTE(SUBSTITUTE(SUBSTITUTE(SUBSTITUTE(SUBSTITUTE(SUBSTITUTE(SUBSTITUTE(SUBSTITUTE(SUBSTITUTE(SUBSTITUTE(SUBSTITUTE(SUBSTITUTE(SUBSTITUTE(SUBSTITUTE(SUBSTITUTE(SUBSTITUTE(SUBSTITUTE(SUBSTITUTE(SUBSTITUTE(SUBSTITUTE(SUBSTITUTE(SUBSTITUTE(SUBSTITUTE(SUBSTITUTE(SUBSTITUTE(SUBSTITUTE(SUBSTITUTE(IF(LEN(ROUNDDOWN(B86,0))>6,ROMAN(MID(ROUNDDOWN(B86,0),1,LEN(ROUNDDOWN(B86,0))-6)+0)&" million "&ROMAN(MID(ROUNDDOWN(B86,0),LEN(ROUNDDOWN(B86,0))-5,3)+0)&" "&ROMAN(MID(ROUNDDOWN(B86,0),LEN(ROUNDDOWN(B86,0))-2,3)+0)&"",IF(LEN(ROUNDDOWN(B86,0))>3,ROMAN(MID(ROUNDDOWN(B86,0),1,LEN(ROUNDDOWN(B86,0))-3)+0)&" ming "&ROMAN(MID(ROUNDDOWN(B86,0),LEN(ROUNDDOWN(B86,0))-2,3)+0)&"",ROMAN(ROUNDDOWN(B86,0))&"")),"DCCC"," sakkiz yuz"),"DCC"," yetti yuz"),"DC"," olti yuz"),"CD"," to'rt yuz"),"XC"," to'qson"),"CCC"," uch yuz"),"CC"," ikki yuz"),"D"," besh yuz"),"CM"," to'qqiz yuz"),"C"," yuz"),"XL"," qirq"),"LXXX"," sakson"),"LXX"," yetmish"),"LX"," oltmish"),"L"," ellik"),"XXX"," o'ttiz"),"XX"," yigirma"),"XIX"," o'n to'qqiz"),"XVIII"," o'n sakkiz"),"XVII"," o'n yetti"),"XVI"," o'n olti"),"XV"," o'n besh"),"XIV"," o'n to'rt"),"XIII"," o'n uch"),"XII"," o'n ikki"),"XI"," o'n bir"),"IX"," to'qqiz"),"X"," o'n"),"VIII"," sakkiz"),"VII"," yetti"),"VI"," olti"),"IV"," to'rt"),"V"," besh"),"III"," uch"),"II"," ikki"),"I"," bir"),"bir ming","bir ming"),"ikki ming","ikki ming"),"uch ming","uch ming"),"to'rt ming","to'rt ming"),"bir million","bir million"),"ikki million","ikki million"),"uch million","uch million"),"to'rt million","to'rt million"),"bir","bir"),"ikki","ikki"),"uch","uch"),"to'rt","to'rt")),"ming million","million"),"ming million","million"),"ming million","million"),2,200)&" "&SUBSTITUTE(SUBSTITUTE(SUBSTITUTE(SUBSTITUTE(SUBSTITUTE(SUBSTITUTE(SUBSTITUTE(SUBSTITUTE(RIGHT(TEXT(B86," "),2)&"","1","1"),"2","2"),"3","3"),"4","4"),"11","11"),"12","12"),"13","13"),"14","14") -> Ellik besh
A88: =CONCATENATE("Muddati o'tgan ",B65," bo’yicha stavka") -> Muddati o'tgan mikrokredit bo’yicha stavka | B88: 1.05
A89: QO’L BILAN KIRITILADI | B89: 105
A90: =CONCATENATE("Muddati o'tgan ",B65," bo’yicha stavka") -> Muddati o'tgan mikrokredit bo’yicha stavka | B90: bir yuz | C90: bir yuz
A91: Oylik to'lov | B91: =IF(B78=C78,LARGE(grafik!F9:F26,1),ROUND(PMT(B85/12,B82,-B76,0),-3)) -> 7155000
A92: Mijoz plastik kartasi parametrlari
A93: Bank nomi: | B93: «HAMKOR BANK» AJ
A94: H/r: | B94: 2312 0000 6000 1143 7200
A95: MFO: | B95: 00083
A96: STIR: | B96: 200242936
A97: Karta raqami: | B97: 9860 1678 4680 5015
A98: GAROV BO’YICHA MA’LUMOTLAR
B99: Birlamchi | C99: Birlamchi | D99: navbatdagi garov
A100: Garovga beruvchi mulkdormi? | B100: yo’q | C100: Ha | D100: yo’q
A101: Agar garovga beruvchi qarz oluvchi bo'lmasa, garovga kim qo'yganligini ko'rsating | B101: Garovga beruvchining o’zi | C101: Garovga beruvchining o’zi | D101: Bosh ishonchnoma bo’yicha boshqa shaxs
...

Sheet shartnoma
A1: =""&malumot!C64&" shartnoma "&malumot!B66&"" -> Mikrokredit shartnoma №717-XMS
A3: ="Toshkent shahri "&malumot!B70&"" -> Toshkent shahri 7 aprel 2025 y.
A5: =""&malumot!B157&", bundan buyon «Mikromoliya tashkiloti» deb nomlanuvchi, ishonchnoma asosida xarakat qiluvchi "&malumot!A160&" "&malumot!B160&" bir tomondan va o‘z manfaati yo‘lida hamda o‘z nomidan harakat qiluvchi O‘zbekiston Respublikasi fuqarosi "&malumot!B5&" (pasport raqami "&malumot!B16&", "&malumot!C20&" ), bundan buyon «Qarz oluvchi» deb nomlanuvchi, boshqa tomondan, birgalikda “Tomonlar” yoki alohida “Tomon” deb nomlanuvchilar, Qarz oluvchi tomonidan "&TEXT(malumot!B2,"ДД.ММ.ГГГГ")&" yil,"&malumot!B65&" olish uchun ariza berilganligini hisobga olib, ushbu "&malumot!C64&" shartnomasini (bundan keyin – «Shartnoma») quyidagilar haqida tuzdilar:" -> «CLEVER MIKROMOLIYA TASHKILOTI» MChJ, bundan buyon «Mikromoliya tashkiloti» deb nomlanuvchi, ishonchnoma asosida xarakat qiluvchi Xorazm filiali boshlig'i M.Sharipov bir tomondan va o‘z manfaati yo‘lida hamda o‘z nomidan harakat qiluvchi O‘zbekiston Respublikasi fuqarosi MATCHANOVA AZIZA BEKTURDIYEVNA (pasport raqami AC 2074678, XORAZM VILOYATI SHOVOT TUMANI IIB tomonidan 17.07.2019 yilda berilgan ), bundan buyon «Qarz oluvchi» deb nomlanuvchi, boshqa tomondan, birgalikda “Tomonlar” yoki alohida “Tomon” deb nomlanuvchilar, Qarz oluvchi tomonidan 07.04.2025 yil,mikrokredit olish uchun ariza berilganligini hisobga olib, ushbu Mikrokredit shartnomasini (bundan keyin – «Shartnoma») quyidagilar haqida tuzdilar:
A7: 1. SHARTNOMA PREDMETI
A8: ="1.1. Mikromoliya tashkiloti Qarz oluvchiga umumiy miqdori "&FIXED(malumot!B76,2)&" ("&malumot!C77&") bo‘lgan "&malumot!B65&"ni "&malumot!B71&" dan "&malumot!B73&" gacha bo'lgan muddatga naqd pul va/yoki o'tkazmasi shaklida ajratadi." -> 1.1. Mikromoliya tashkiloti Qarz oluvchiga umumiy miqdori 125 000 000,00 (Yuz yigirma besh million so'm) bo‘lgan mikrokreditni 7 aprel 2025 y. dan 7 aprel 2028 y. gacha bo'lgan muddatga naqd pul va/yoki o'tkazmasi shaklida ajratadi.
A9: ="1.2. Qarz oluvchi to‘lovlilik, muddatlilik va ta’minlanganlik tamoyillariga amal qilgan holda "&malumot!B65&"dan foydalanish majburiyatini o‘z zimmasiga oladi." -> 1.2. Qarz oluvchi to‘lovlilik, muddatlilik va ta’minlanganlik tamoyillariga amal qilgan holda mikrokreditdan foydalanish majburiyatini o‘z zimmasiga oladi.
A11: ="2. "&malumot!D64&" BERISH VA QAYTARISH TARTIBI" -> 2. MIKROKREDIT BERISH VA QAYTARISH TARTIBI
A12: ="2.1. Ushbu Shartnomaning 1.1.-bandida ko‘rsatilgan summa miqdoridagi "&malumot!B65&" Mikromoliya tashkiloti kassasidan naqd pul shaklida va/yoki plastik kartaga o‘tkazish yuli bilan beriladi." -> 2.1. Ushbu Shartnomaning 1.1.-bandida ko‘rsatilgan summa miqdoridagi mikrokredit Mikromoliya tashkiloti kassasidan naqd pul shaklida va/yoki plastik kartaga o‘tkazish yuli bilan beriladi.
A13: ="2.2. "&malumot!C64&" berish ushbu Shartnoma tuzilgan va Qarz oluvchi tomonidan ushbu shartnomaning 3-bo‘limiga muvofiq garov ta'minoti ta'minlangandan so‘ng 10 kalendar kundan kechiktirmay amalga oshiriladi." -> 2.2. Mikrokredit berish ushbu Shartnoma tuzilgan va Qarz oluvchi tomonidan ushbu shartnomaning 3-bo‘limiga muvofiq garov ta'minoti ta'minlangandan so‘ng 10 kalendar kundan kechiktirmay amalga oshiriladi.
A14: ="2.3. "&malumot!C64&" Qarz oluvchi tomonidan ushbu Shartnomaning ajralmas qismi hisoblanadigan 1-ilovasida ko‘rsatilgan to‘lov jadvalida (bundan keyin - To‘lov jadvali) belgilangan miqdor, tartib va muddatlarda qaytariladi." -> 2.3. Mikrokredit Qarz oluvchi tomonidan ushbu Shartnomaning ajralmas qismi hisoblanadigan 1-ilovasida ko‘rsatilgan to‘lov jadvalida (bundan keyin - To‘lov jadvali) belgilangan miqdor, tartib va muddatlarda qaytariladi.
A15: ="2.4. Mikromoliya tashkiloti, "&malumot!B65&" berilgan vaqtdan boshlab, "&malumot!B65&" miqdorining qoldiq summasiga "&malumot!B86&"% ("&malumot!C87&") foiz yillik va yiliga 365/366 kunlik hisobidan foizlar hisoblaydi. To'lov jadvaliga muvofiq asosiy qarz bo'yicha navbatdagi to'lov buzilgan hollarda, "&"foiz stavkasi oshiriladi va Mikromoliya tashkiloti "&malumot!B65&"ning muddati o'tgan asosiy qarz summasiga yillik "&malumot!B89&" ("&malumot!B90&") foiz miqdorida foizlar hisoblaydi." -> 2.4. Mikromoliya tashkiloti, mikrokredit berilgan vaqtdan boshlab, mikrokredit miqdorining qoldiq summasiga 55% (Ellik besh ) foiz yillik va yiliga 365/366 kunlik hisobidan foizlar hisoblaydi. To'lov jadvaliga muvofiq asosiy qarz bo'yicha navbatdagi to'lov buzilgan hollarda, foiz stavkasi oshiriladi va Mikromoliya tashkiloti mikrokreditning muddati o'tgan asosiy qarz summasiga yillik 105 (bir yuz) foiz miqdorida foizlar hisoblaydi.
A16: 2.4.1 Qarz oluvchining xisob raqamlaridan shartnomaning 4.1.2 bandida ko‘rsatilgan tartibda yechib olingan pul mablag‘lari yechib olinganidan so‘ng mijoz tomonidan kredit qarzdorligini so‘ndirish uchun bank kassalari orqali to‘langan pul mablag‘lari yoki mijoz tomonidan kredit qarzdorligini so‘ndirish uchun bank kassalari orqali to‘langandan so‘ng qarz oluvchining xisob raqamlaridan shartnomaning 4.1.2 bandida ko‘rsatilgan tartibda yechib olingan pul mablag‘larining bir oylik kredit to‘lovini so‘ndirishga yo‘naltirilgan miqdoridan ortiqcha qismi qarz oluvchining to‘lov amalga oshirilgan kundan boshlab 3 bank ish kuni ichida yo‘llagan arizasiga asosan qarz oluvchiga qaytarilishi mumkun. 2.5. Foizlar To‘lov jadvaliga muvofiq asosiy qarzni qaytarish uchun belgilangan sanada to‘lanadi. 2.5.1 Qarz oluvchi tomonidan shartnomaning 2.4 bandida ko‘rsatilgan muddatda ortiqcha to‘langan pul mablag‘larini qaytarish to‘g‘risida ariza berilmagan taqdirda to‘langan ortiqcha pul mablag‘lari mijozning asosiy qarzdorligini so‘ndirishga yo‘naltiriladi.
A17: =CONCATENATE(C17,H17,I17) -> 2.6 Qarz oluvchi tomonidan to‘lov jadvalida ko‘rsatilgan muddatdan oldin xamda to‘lov jadvalida ko‘rsatilgan oylik kredit qarzdorligini so‘ndirish miqdoridan ko‘p miqdorda to‘lovni amalga oshirib, to‘langan pul mablag‘larini asosiy kredit qarzdorligini so‘ndirishga yo‘naltirilishini so‘ralganda qarz oluvchining kredit qarzdorligini so‘ndirish uchun to‘lagan pul mablag‘laridan kredit qarzdorligi to‘langan oy uchun to‘lov jadvali bo‘yicha so‘ndirilishi lozim bo‘lgan foiz qarzdorligi summasi, to‘lov jadvalida foiz qarzdorligi so‘ndirilishi ko‘rsatilgan muddatga qadar tashkilotning xisob raqamida saqlanib to‘lov jadvalida ko‘rsatilgan sanada oylik foiz qarzdorligini so‘ndirishga yo‘naltiriladi. 2.6.1. Qarz oluvchi tomonidan olingan mikrokreditni va undan foydalanganlik uchun foizlarni qaytarish bo‘yicha muddati o‘tgan qarzdorlik hosil bo‘lganda Qarz oluvchi tomonidan ko‘rsatilgan qarzdorlikni to‘lash hisobiga to‘lanadigan summalar quyidagi tartibda hisobga olinadi: | C17: 2.6 Qarz oluvchi tomonidan to‘lov jadvalida ko‘rsatilgan muddatdan oldin xamda to‘lov jadvalida ko‘rsatilgan oylik kredit qarzdorligini so‘ndirish miqdoridan ko‘p miqdorda to‘lovni amalga oshirib, to‘langan pul mablag‘larini asosiy kredit qarzdorligini so‘ndirishga yo‘naltirilishini so‘ralganda qarz oluvchining kredit qarzdorligini so‘ndirish uchun to‘lagan pul mablag‘laridan kredit qarzdorligi to‘langan oy uchun to‘lov jadvali bo‘yicha so‘ndirilishi lozim bo‘lgan foiz qarzdorligi summasi, to‘lov jadvalida foiz qarzdorligi so‘ndirilishi ko‘rsatilgan muddatga qadar tashkilotning xisob raqamida saqlanib to‘lov jadvalida ko‘rsatilgan sanada oylik foiz qarzdorligini so‘ndirishga yo‘naltiriladi. 2.6.1. Qarz oluvchi tomonidan olingan | H17: =malumot!B65 -> mikrokredit | I17: ni va undan foydalanganlik uchun foizlarni qaytarish bo‘yicha muddati o‘tgan qarzdorlik hosil bo‘lganda Qarz oluvchi tomonidan ko‘rsatilgan qarzdorlikni to‘lash hisobiga to‘lanadigan summalar quyidagi tartibda hisobga olinadi:
A18: - jarima sanksiyalarni to‘lash; - to‘lov muddati o‘tgan foizlarni to‘lash; - to‘lov muddati o‘tgan asosiy qarzni to‘lash; - muddatli qarz bo‘yicha hisoblangan foizlarni to‘lash; - muddatli asosiy qarzni to‘lash; - Mikromoliya tashkilotning boshqa zararlarini qoplash.
A19: ="2.7. Qarz oluvchi Mikromoliya tashkilotining "&malumot!B65&" bo‘yicha asosiy summasi, hisoblangan foizlarni, penya va boshqa moliyaviy talablarini ham naqd pul shaklida, ham naqdsiz shaklda qaytarib beradi." -> 2.7. Qarz oluvchi Mikromoliya tashkilotining mikrokredit bo‘yicha asosiy summasi, hisoblangan foizlarni, penya va boshqa moliyaviy talablarini ham naqd pul shaklida, ham naqdsiz shaklda qaytarib beradi.
A20: ="2.8. Qarz oluvchi "&malumot!B65&" miqdorini muddatidan oldin qaytarish, shuningdek, bu haqida Mikromoliya tashkilotini albatta ogohlantirgan holda ulardan aniq foydalangan muddat uchun hisoblangan foizlarni to‘lash huquqiga ega." -> 2.8. Qarz oluvchi mikrokredit miqdorini muddatidan oldin qaytarish, shuningdek, bu haqida Mikromoliya tashkilotini albatta ogohlantirgan holda ulardan aniq foydalangan muddat uchun hisoblangan foizlarni to‘lash huquqiga ega.
A21: =CONCATENATE(C21,H21,I21) -> 2.9. Qarz oluvchi jismoniy shaxslarning kreditlar (mikrokreditlar) bo‘yicha qarz yukini hisoblash tartibi, qarz yukining ruxsat etilgan miqdori, shuningdek qarz yuki o‘sishini cheklash to‘g‘risidagi Nizomga muvofiq (O’zbekiston Respublikasi Adliya vazirligi tomonidan 19.12.2019 y. 3205-son bilan ro‘yxatga olingan Markaziy bank Boshqaruvining 28.09.2019 y. 24/5-son qarori bilan tasdiqlangan), qarz yuki ko‘rsatkichi har bir qarz oluvchiga qarz beruvchi tomonidan mikrokredit ajratishda uning summasi va qarz oluvchining amaldagi kredit (mikrokredit) shartnomalari bo‘yicha asosiy qarz qoldig‘i yig‘indisi bazaviy hisoblash miqdorining 50 baravaridan oshganda hisoblanadi. | C21: ="2.9. Qarz oluvchi jismoniy shaxslarning kreditlar ("&malumot!B65&"lar) bo‘yicha qarz yukini hisoblash tartibi, qarz yukining ruxsat etilgan miqdori, shuningdek qarz yuki o‘sishini cheklash to‘g‘risidagi Nizomga muvofiq (O’zbekiston Respublikasi Adliya vazirligi tomonidan 19.12.2019 y. 3205-son bilan ro‘yxatga " -> 2.9. Qarz oluvchi jismoniy shaxslarning kreditlar (mikrokreditlar) bo‘yicha qarz yukini hisoblash tartibi, qarz yukining ruxsat etilgan miqdori, shuningdek qarz yuki o‘sishini cheklash to‘g‘risidagi Nizomga muvofiq (O’zbekiston Respublikasi Adliya vazirligi tomonidan 19.12.2019 y. 3205-son bilan ro‘yxatga | H21: ="olingan Markaziy bank Boshqaruvining 28.09.2019 y. 24/5-son qarori bilan tasdiqlangan), qarz yuki ko‘rsatkichi har bir qarz oluvchiga qarz beruvchi tomonidan "&malumot!B65&" ajratishda uning summasi va " -> olingan Markaziy bank Boshqaruvining 28.09.2019 y. 24/5-son qarori bilan tasdiqlangan), qarz yuki ko‘rsatkichi har bir qarz oluvchiga qarz beruvchi tomonidan mikrokredit ajratishda uning summasi va | I21: ="qarz oluvchining amaldagi kredit ("&malumot!B65&") shartnomalari bo‘yicha asosiy qarz qoldig‘i yig‘indisi bazaviy hisoblash miqdorining 50 baravaridan oshganda hisoblanadi." -> qarz oluvchining amaldagi kredit (mikrokredit) shartnomalari bo‘yicha asosiy qarz qoldig‘i yig‘indisi bazaviy hisoblash miqdorining 50 baravaridan oshganda hisoblanadi.
A22: ="3. "&malumot!D64&" TA'MINOTI BO‘YICHA " -> 3. MIKROKREDIT TA'MINOTI BO‘YICHA
A23: ="3.1. Ushbu Shartnoma bo‘yicha taqdim etilgan "&malumot!C64&" quyidagi Mikroqarz summasiga nisbatan 150% dan kam bo'lmagan garov va Mikroqarz to'lamaslik xavfini sug'urta polisi bilan ta'minlanadi:" -> 3.1. Ushbu Shartnoma bo‘yicha taqdim etilgan Mikrokredit quyidagi Mikroqarz summasiga nisbatan 150% dan kam bo'lmagan garov va Mikroqarz to'lamaslik xavfini sug'urta polisi bilan ta'minlanadi:
A24: =IF(malumot!B110=malumot!C110,shartnoma!A28,IF(malumot!B110=malumot!D110,shartnoma!A25,0)) -> 3.1.1. Mikromoliya tashkiloti, Qarz oluvchi va BEKOV OTABEK BAXODIROVICH tomonidan 2025 yil 7 aprelda imzolangan 1-sonli garov predmeti qiymatini tasdiqlash dalolatnomasiga muvofiq QORA CHERNIY rangli, ishlab chiqarilgan yili – 2023 yil, dvigatel raqami LJ166A33XP2208188, shassi - Rakamsiz, kuzov turi - YENGIL MINIVEN, kuzov raqami №P08461541, davlat raqam belgisi 90C477ZA bo'lgan JAC M3 rusumli avtomashinasi (bundan keyin “Garov predmeti”), egalik huquqiga ega BEKOV OTABEK BAXODIROVICHga tegishli va kelishilgan garov qiymati 2025 yil 7 aprelda imzolangan 1-sonli Garov predmeti qiymatini tasdiqlash dalolatnomasiga muvifiq 165 000 000,00 (yuz oltmish besh million so'm) so'mni tashkil qiladi. Garov garovining aniq shartlari tegishli notarial rasmiylashtirilgan garov shartnomasi bilan belgilanadi.
A25: =IF(malumot!B99=malumot!C99,shartnoma!A27,IF(malumot!B99=malumot!D99,shartnoma!A26,0)) -> 3.1.1. Mikromoliya tashkiloti, Qarz oluvchi va BEKOV OTABEK BAXODIROVICH tomonidan 2025 yil 7 aprelda imzolangan 1-sonli Garov predmeti qiymatini tasdiqlash dalolatnomasiga muvofiq manzilida joylashgan, 0 bo'lgan, 0 ko'rinishidagi ko'chmas mulk (bundan keyin “Garov predmeti”), egalik huquqiga ko'ra 0ga tegishli va kelishilgan garov qiymati 2025 yil 7 aprelda imzolangan 1-sonli Garov predmeti qiymatini tasdiqlash dalolatnomasiga muvofiq 165 000 000,00 (yuz oltmish besh million so'm) so'mni tashkil qiladi. Garovning aniq shartlari tegishli tarzda notarial tasdiqlangan garov shartnomasi bilan belgilangan.
A26: ="3.1.1. "&malumot!N133&" tomonidan "&malumot!B150&" yil "&malumot!B152&" "&malumot!B151&"da imzolangan 1-sonli navbatdagi garov predmeti qiymatini tasdiqlash dalolatnomasiga muvofiq "&malumot!C130&" manzilida joylashgan, "&malumot!E133&" bo'lgan, "&malumot!E132&" ko'rinishidagi ko'chmas mulk (bundan keyin “navbatdagi garov predmeti”), egalik huquqiga ko'ra "&malumot!C124&"ga tegishli va kelishilgan garov qiymati "&malumot!B150&" yil "&malumot!B152&" "&malumot!B151&"da imzolangan 1-sonli Garov predmeti qiymatini tasdiqlash dalolatnomasiga muvofiq "&FIXED(malumot!B143,2)&" ("&malumot!B145&") so'mni tashkil qiladi. Garovning aniq shartlari tegishli tarzda notarial tasdiqlangan garov shartnomasi bilan belgilangan." -> 3.1.1. Mikromoliya tashkiloti, Qarz oluvchi va BEKOV OTABEK BAXODIROVICH tomonidan 2025 yil 7 aprelda imzolangan 1-sonli navbatdagi garov predmeti qiymatini tasdiqlash dalolatnomasiga muvofiq manzilida joylashgan, 0 bo'lgan, 0 ko'rinishidagi ko'chmas mulk (bundan keyin “navbatdagi garov predmeti”), egalik huquqiga ko'ra 0ga tegishli va kelishilgan garov qiymati 2025 yil 7 aprelda imzolangan 1-sonli Garov predmeti qiymatini tasdiqlash dalolatnomasiga muvofiq 165 000 000,00 (yuz oltmish besh million so'm) so'mni tashkil qiladi. Garovning aniq shartlari tegishli tarzda notarial tasdiqlangan garov shartnomasi bilan belgilangan.
A27: ="3.1.1. "&malumot!N133&" tomonidan "&malumot!B150&" yil "&malumot!B152&" "&malumot!B151&"da imzolangan 1-sonli Garov predmeti qiymatini tasdiqlash dalolatnomasiga muvofiq "&malumot!C130&" manzilida joylashgan, "&malumot!E133&" bo'lgan, "&malumot!E132&" ko'rinishidagi ko'chmas mulk (bundan keyin “Garov predmeti”), egalik huquqiga ko'ra "&malumot!C124&"ga tegishli va kelishilgan garov qiymati "&malumot!B150&" yil "&malumot!B152&" "&malumot!B151&"da imzolangan 1-sonli Garov predmeti qiymatini tasdiqlash dalolatnomasiga muvofiq "&FIXED(malumot!B143,2)&" ("&malumot!B145&") so'mni tashkil qiladi. Garovning aniq shartlari tegishli tarzda notarial tasdiqlangan garov shartnomasi bilan belgilangan." -> 3.1.1. Mikromoliya tashkiloti, Qarz oluvchi va BEKOV OTABEK BAXODIROVICH tomonidan 2025 yil 7 aprelda imzolangan 1-sonli Garov predmeti qiymatini tasdiqlash dalolatnomasiga muvofiq manzilida joylashgan, 0 bo'lgan, 0 ko'rinishidagi ko'chmas mulk (bundan keyin “Garov predmeti”), egalik huquqiga ko'ra 0ga tegishli va kelishilgan garov qiymati 2025 yil 7 aprelda imzolangan 1-sonli Garov predmeti qiymatini tasdiqlash dalolatnomasiga muvofiq 165 000 000,00 (yuz oltmish besh million so'm) so'mni tashkil qiladi. Garovning aniq shartlari tegishli tarzda notarial tasdiqlangan garov shartnomasi bilan belgilangan.
A28: =IF(malumot!B99=malumot!C99,A29,IF(malumot!B99=malumot!D99,A30,0)) -> 3.1.1. Mikromoliya tashkiloti, Qarz oluvchi va BEKOV OTABEK BAXODIROVICH tomonidan 2025 yil 7 aprelda imzolangan 1-sonli garov predmeti qiymatini tasdiqlash dalolatnomasiga muvofiq QORA CHERNIY rangli, ishlab chiqarilgan yili – 2023 yil, dvigatel raqami LJ166A33XP2208188, shassi - Rakamsiz, kuzov turi - YENGIL MINIVEN, kuzov raqami №P08461541, davlat raqam belgisi 90C477ZA bo'lgan JAC M3 rusumli avtomashinasi (bundan keyin “Garov predmeti”), egalik huquqiga ega BEKOV OTABEK BAXODIROVICHga tegishli va kelishilgan garov qiymati 2025 yil 7 aprelda imzolangan 1-sonli Garov predmeti qiymatini tasdiqlash dalolatnomasiga muvifiq 165 000 000,00 (yuz oltmish besh million so'm) so'mni tashkil qiladi. Garov garovining aniq shartlari tegishli notarial rasmiylashtirilgan garov shartnomasi bilan belgilanadi.
A29: ="3.1.1. "&malumot!N133&" tomonidan "&malumot!B150&" yil "&malumot!B152&" "&malumot!B151&"da imzolangan 1-sonli garov predmeti qiymatini tasdiqlash dalolatnomasiga muvofiq "&malumot!B141&" rangli, ishlab chiqarilgan yili – "&malumot!B142&" yil, dvigatel raqami "&malumot!B138&", shassi - "&malumot!B139&", kuzov turi - "&malumot!B135&", kuzov raqami №"&malumot!B136&", davlat raqam belgisi "&malumot!B133&" bo'lgan "&malumot!B132&" rusumli avtomashinasi (bundan keyin “Garov predmeti”), egalik huquqiga ega "&malumot!B124&"ga tegishli va kelishilgan garov qiymati "&malumot!B150&" yil "&malumot!B152&" "&malumot!B151&"da imzolangan 1-sonli Garov predmeti qiymatini tasdiqlash dalolatnomasiga muvifiq "&FIXED(malumot!B143,2)&" ("&malumot!B145&") so'mni tashkil qiladi. Garov garovining aniq shartlari tegishli notarial rasmiylashtirilgan garov shartnomasi bilan belgilanadi." -> 3.1.1. Mikromoliya tashkiloti, Qarz oluvchi va BEKOV OTABEK BAXODIROVICH tomonidan 2025 yil 7 aprelda imzolangan 1-sonli garov predmeti qiymatini tasdiqlash dalolatnomasiga muvofiq QORA CHERNIY rangli, ishlab chiqarilgan yili – 2023 yil, dvigatel raqami LJ166A33XP2208188, shassi - Rakamsiz, kuzov turi - YENGIL MINIVEN, kuzov raqami №P08461541, davlat raqam belgisi 90C477ZA bo'lgan JAC M3 rusumli avtomashinasi (bundan keyin “Garov predmeti”), egalik huquqiga ega BEKOV OTABEK BAXODIROVICHga tegishli va kelishilgan garov qiymati 2025 yil 7 aprelda imzolangan 1-sonli Garov predmeti qiymatini tasdiqlash dalolatnomasiga muvifiq 165 000 000,00 (yuz oltmish besh million so'm) so'mni tashkil qiladi. Garov garovining aniq shartlari tegishli notarial rasmiylashtirilgan garov shartnomasi bilan belgilanadi.
A30: ="3.1.1. "&malumot!N133&" tomonidan "&malumot!B150&" yil "&malumot!B152&" "&malumot!B151&"da imzolangan 1-sonli navbatdagi garov predmeti qiymatini tasdiqlash dalolatnomasiga muvofiq "&malumot!B141&" rangli, ishlab chiqarilgan yili – "&malumot!B142&" yil, dvigatel raqami "&malumot!B138&", shassi - "&malumot!B139&", kuzov turi - "&malumot!B135&", kuzov raqami №"&malumot!B136&", davlat raqam belgisi "&malumot!B133&" bo'lgan "&malumot!B132&" rusumli avtomashinasi (bundan keyin “navbatdagi garov predmeti”), egalik huquqiga ega "&malumot!B124&"ga tegishli va kelishilgan garov qiymati "&malumot!B150&" yil "&malumot!B152&" "&malumot!B151&"da imzolangan 1-sonli Garov predmeti qiymatini tasdiqlash dalolatnomasiga muvifiq "&FIXED(malumot!B143,2)&" ("&malumot!B145&") so'mni tashkil qiladi. Garov garovining aniq shartlari tegishli notarial rasmiylashtirilgan garov shartnomasi bilan belgilanadi." -> 3.1.1. Mikromoliya tashkiloti, Qarz oluvchi va BEKOV OTABEK BAXODIROVICH tomonidan 2025 yil 7 aprelda imzolangan 1-sonli navbatdagi garov predmeti qiymatini tasdiqlash dalolatnomasiga muvofiq QORA CHERNIY rangli, ishlab chiqarilgan yili – 2023 yil, dvigatel raqami LJ166A33XP2208188, shassi - Rakamsiz, kuzov turi - YENGIL MINIVEN, kuzov raqami №P08461541, davlat raqam belgisi 90C477ZA bo'lgan JAC M3 rusumli avtomashinasi (bundan keyin “navbatdagi garov predmeti”), egalik huquqiga ega BEKOV OTABEK BAXODIROVICHga tegishli va kelishilgan garov qiymati 2025 yil 7 aprelda imzolangan 1-sonli Garov predmeti qiymatini tasdiqlash dalolatnomasiga muvifiq 165 000 000,00 (yuz oltmish besh million so'm) so'mni tashkil qiladi. Garov garovining aniq shartlari tegishli notarial rasmiylashtirilgan garov shartnomasi bilan belgilanadi.
A31: =CONCATENATE(C31,D31) -> 3.1.2. «АО "APEX INSURANCE"» АJ sug‘urta kompaniyasi (keyingi o'rinlarda-Sug‘urtalovchi) tomonidan Mikrokredit to'lamaslik xavfini Mikroqarz summasiga nisbatan 140% dan hisoblab 15 000 000,00(o'n besh million so'm) so ' m miqdoriga sug’urta qilish. Ushbu shartnoma bo‘yicha Mikrokredit berilgunga qadar Mikromoliya tashkiloti Sug‘urtalovchi 15 000 000,00(o'n besh million so'm) so ' m miqdoridagi Mikrokreditni to‘lamaslik xavfini sug‘urta qilish shartnomasini tuzadi va Sug‘urtalovchi nomiga sug‘urta mukofotini to‘laydi, Qarz oluvchi esa Mikromoliya tashkiloti tomonidan sug‘urta mukofotini to‘langan kuni Mikromoliya tashkiloti tomonidan to‘langan sug‘urta mukofotini Mikromoliya tashkilotiga to‘laydi." | C31: ="3.1.2. «"&malumot!B153&"» АJ sug‘urta kompaniyasi (keyingi o'rinlarda-Sug‘urtalovchi) tomonidan "&malumot!C64&" to'lamaslik xavfini Mikroqarz summasiga nisbatan 140% dan hisoblab "&FIXED(malumot!B154,2)&"("&malumot!B155&") so ' m miqdoriga sug’urta qilish." -> 3.1.2. «АО "APEX INSURANCE"» АJ sug‘urta kompaniyasi (keyingi o'rinlarda-Sug‘urtalovchi) tomonidan Mikrokredit to'lamaslik xavfini Mikroqarz summasiga nisbatan 140% dan hisoblab 15 000 000,00(o'n besh million so'm) so ' m miqdoriga sug’urta qilish. | D31: =CONCATENATE(E31,F31) -> Ushbu shartnoma bo‘yicha Mikrokredit berilgunga qadar Mikromoliya tashkiloti Sug‘urtalovchi 15 000 000,00(o'n besh million so'm) so ' m miqdoridagi Mikrokreditni to‘lamaslik xavfini sug‘urta qilish shartnomasini tuzadi va Sug‘urtalovchi nomiga sug‘urta mukofotini to‘laydi, Qarz oluvchi esa Mikromoliya tashkiloti tomonidan sug‘urta mukofotini to‘langan kuni Mikromoliya tashkiloti tomonidan to‘langan sug‘urta mukofotini Mikromoliya tashkilotiga to‘laydi." | E31: =" Ushbu shartnoma bo‘yicha "&malumot!C64&" berilgunga qadar Mikromoliya tashkiloti Sug‘urtalovchi "&FIXED(malumot!B154,2)&"("&malumot!B155&") so ' m miqdoridagi "&malumot!C64&"" -> Ushbu shartnoma bo‘yicha Mikrokredit berilgunga qadar Mikromoliya tashkiloti Sug‘urtalovchi 15 000 000,00(o'n besh million so'm) so ' m miqdoridagi Mikrokredit | F31: ni to‘lamaslik xavfini sug‘urta qilish shartnomasini tuzadi va Sug‘urtalovchi nomiga sug‘urta mukofotini to‘laydi, Qarz oluvchi esa Mikromoliya tashkiloti tomonidan sug‘urta mukofotini to‘langan kuni Mikromoliya tashkiloti tomonidan to‘langan sug‘urta mukofotini Mikromoliya tashkilotiga to‘laydi."
A32: =CONCATENATE(A33,B33) -> 3.2. Qonun hujjatlariga muvofiq rasmiylashtirilgan, “Garov predmeti” hisoblangan notarial tasdiqlangan garov shartnomasi, shu jumladan “Garov predmeti”ga taʼqiq quyilganligi tasdiqlovchi xujjat Qarz oluvchi tomonidan ushbu shartnoma tuzilgandan so‘ng 10 bank kuni mobaynida Mikromoliya tashkilotiga taqdim etilishi lozim. Garov shartnomasi belgilangan muddatda taqdim etilmagan hollarda, Mikromoliya tashkiloti Qarz oluvchining manziliga yozma bildirishnoma yuborish orqali mikrokredit berishni rad etish va / yoki ushbu shartnomani bir tomonlama bekor qilish huquqiga egadir. Bunda ushbu shartnoma Qarz oluvchi tomonidan talabnoma olingan vaqtda yoki talabnoma pochta xizmati orqali yuborilgandan keyin uchinchi kuni bekor qilingan hisoblanadi.
A33: 3.2. Qonun hujjatlariga muvofiq rasmiylashtirilgan, “Garov predmeti” hisoblangan notarial tasdiqlangan garov shartnomasi, shu jumladan “Garov predmeti”ga taʼqiq quyilganligi tasdiqlovchi xujjat Qarz oluvchi tomonidan ushbu shartnoma tuzilgandan so‘ng 10 bank kuni mobaynida | B33: =CONCATENATE(A34,B34) -> Mikromoliya tashkilotiga taqdim etilishi lozim. Garov shartnomasi belgilangan muddatda taqdim etilmagan hollarda, Mikromoliya tashkiloti Qarz oluvchining manziliga yozma bildirishnoma yuborish orqali mikrokredit berishni rad etish va / yoki ushbu shartnomani bir tomonlama bekor qilish huquqiga egadir. Bunda ushbu shartnoma Qarz oluvchi tomonidan talabnoma olingan vaqtda yoki talabnoma pochta xizmati orqali yuborilgandan keyin uchinchi kuni bekor qilingan hisoblanadi.
A34: =" Mikromoliya tashkilotiga taqdim etilishi lozim. Garov shartnomasi belgilangan muddatda taqdim etilmagan hollarda, Mikromoliya tashkiloti Qarz oluvchining manziliga yozma bildirishnoma yuborish orqali "&malumot!B65&"" -> Mikromoliya tashkilotiga taqdim etilishi lozim. Garov shartnomasi belgilangan muddatda taqdim etilmagan hollarda, Mikromoliya tashkiloti Qarz oluvchining manziliga yozma bildirishnoma yuborish orqali mikrokredit | B34: berishni rad etish va / yoki ushbu shartnomani bir tomonlama bekor qilish huquqiga egadir. Bunda ushbu shartnoma Qarz oluvchi tomonidan talabnoma olingan vaqtda yoki talabnoma pochta xizmati orqali yuborilgandan keyin uchinchi kuni bekor qilingan hisoblanadi.
A35: 3.3. Asosiy qarzni, foizlar yoki ushbu shartnoma bo‘yicha belgilangan muddatdan kechiktirilganligi bo‘yicha penyalarni qaytarish muddati kechiktirilishi yuzaga kelganda va/yoki ushbu shartnoma bo‘yicha boshqa majburiyatlar buzilishi holatlarida Mikromoliya tashkiloti O‘zbekiston Respublikasining amaldagi qonunchiligiga muvofiq qarzni undirish uchun qaytarib olinmaydigan va muqarrar tartibda unidirishni garov ob'ektiga qaratish huquqiga ega bo‘ladi.
A36: 3.4. O‘zbekiston Respublikasi "Garov to‘g‘risida" gi Qonunining 27-moddasiga muvofiq Garov predmeti sug‘urtalanmaydi. Lekin Mikromoliya tashkiloti Qarz oluvchidan Mikromoliya tashkiloti foydasiga Garov obʼektini ushbu Shartnomaning to‘liq amal qilish muddatiga har turli xavflardan sug‘urta qilishni talab qilish huquqiga ega. Bunda, sug‘urta xavflari ro‘yxati, shuningdek, sug‘urta kompaniyasi Mikromoliya tashkilotining xohishiga ko‘ra belgilanadi. Sug‘urta hodisasi yuz berganda Foyda oluvchi Mikromoliya tashkiloti bo‘lishi kerak.
A37: 3.5. Undiruvni Garov narsasiga (predmetlariga) va/yoki uning (ularning) bir qismiga (qismlariga) qaratishda va/yoki Qarz oluvchining Kafildan qarzini undirishda Mikromoliya tashkiloti undiruvning birinchi navbatdagi obyektini o‘z xohishiga ko‘ra bir tomonlama tanlash yoki bir vaqtning o‘zida undiruvni Garov narsasiga (predmetlariga) qaratish va Kafilga talab qo‘yish huquqini o‘zida saqlab qoladi. Undiruvni garov narsasining bir obyektiga va/yoki uning (ularning) bir qismiga qaratish va/yoki Mikroqarzni Kafildan undirish Mikromoliya tashkilotini undiruvni garov narsasining boshqa obyektiga (obyektlariga) va/yoki uning (ularning) bir qismiga qaratish va/yoki Mikroqarzni Kafildan undirishda cheklamaydi. Qarz oluvchining Mikroqarzni Sug‘urtalovchidan undirish tartibi tegishli sug‘urta shartnomasida belgilanadi.
A39: 4. MIKROMOLIYA TASHKILOTINING HUQUQ VA MAJBURIYATLARI
A40: 4.1. Mikromoliya tashkiloti quyidagi huquqlarga ega:
A41: =CONCATENATE(C41,H41) -> 4.1.1. Ushbu Shartnomada ko‘rsatilgan asoslar bo‘yicha Qarz oluvchiga Shartnomada ko‘zda tutilgan mikrokredit summasini berilishini to‘liq yoki qisman rad etish. 4.1.2 “Mikromoliya Tashkiloti” qarz oluvchining nomidagi barcha plastik kartalaridan, xozirgi kunda mavjud va bundan so‘ng ochiladigan barcha xisob raqamlaridan (talab qilib olguncha, depozit jamg‘arib boriladigan plastik va boshqa istalgan xisob raqamlaridan) kredit to‘lovini kredit qaytarish jadvaliga asosan oyning kredit qarzdorligi qaytarilishi ko‘rsatilgan kuni akseptsiz tarzda yechib olish xuquqiga ega.Usbu bandda belgilangan harakatlarni amalga oshirish uchun bo‘lgan barcha xarajatlar Qarz oluvchi xisobidan qoplanadi. | C41: ="4.1.1. Ushbu Shartnomada ko‘rsatilgan asoslar bo‘yicha Qarz oluvchiga Shartnomada ko‘zda tutilgan "&malumot!B65&"" -> 4.1.1. Ushbu Shartnomada ko‘rsatilgan asoslar bo‘yicha Qarz oluvchiga Shartnomada ko‘zda tutilgan mikrokredit | H41: summasini berilishini to‘liq yoki qisman rad etish. 4.1.2 “Mikromoliya Tashkiloti” qarz oluvchining nomidagi barcha plastik kartalaridan, xozirgi kunda mavjud va bundan so‘ng ochiladigan barcha xisob raqamlaridan (talab qilib olguncha, depozit jamg‘arib boriladigan plastik va boshqa istalgan xisob raqamlaridan) kredit to‘lovini kredit qaytarish jadvaliga asosan oyning kredit qarzdorligi qaytarilishi ko‘rsatilgan kuni akseptsiz tarzda yechib olish xuquqiga ega.Usbu bandda belgilangan harakatlarni amalga oshirish uchun bo‘lgan barcha xarajatlar Qarz oluvchi xisobidan qoplanadi.
A42: ="4.1.2.1. "&malumot!C64&" bo‘yicha qolgan barcha qarzdorlik, foiz to‘lovlarining muddatidan oldin qaytarilishini talab qilish, shuningdek, quyidagi holatlardan biri yuzaga kelganda undirishni garov ta'minotiga qaratish:" -> 4.1.2.1. Mikrokredit bo‘yicha qolgan barcha qarzdorlik, foiz to‘lovlarining muddatidan oldin qaytarilishini talab qilish, shuningdek, quyidagi holatlardan biri yuzaga kelganda undirishni garov ta'minotiga qaratish:
A43: a) ta'minotisiz qarzdorlik yuzaga kelganda;
A44: ="b) "&malumot!B65&" summasiga hisoblanadigan asosiy qarz bo‘yicha muddati o‘tgan qarzdorlik va/yoki foizlarning yuzaga kelishi;" -> b) mikrokredit summasiga hisoblanadigan asosiy qarz bo‘yicha muddati o‘tgan qarzdorlik va/yoki foizlarning yuzaga kelishi;
A45: с) Qarz oluvchini qonun hujjatlarida belgilangan tartibda to‘lov qobiliyatiga ega emas, muomalaga layoqatli emas yoki muomalaga layoqati cheklangan deb e'lon qilish;
A46: d) Mikromoliya tashkilotiga ushbu Shartnomaning 3.1.-bandida ko‘zda tutilgan hisobotlar, axborotlar va boshqa ma'lumotlarni o‘z vaqtida taqdim etmaslik, shuningdek, moliya-xo‘jalik faoliyat va daromad to‘g‘risidagi hisobotning ishonchsizligi holatlari aniqlanganda;
A47: e) Qarz oluvchi tomonidan ushbu shartnoma shartlariga amal qilmaslik;
A48: ="f) Qarz oluvchi "&malumot!B65&" summasini olish uchun Mikromoliya tashkilotiga "&malumot!B65&" taqdim etilishi to‘g‘risida ijobiy qaror qabul qilinishi uchun muhim hisoblangan masalalar bo‘yicha yolg‘on yoki to‘liq bo‘lmagan ma'lumotlarni taqdim etganligi aniqlanganda." -> f) Qarz oluvchi mikrokredit summasini olish uchun Mikromoliya tashkilotiga mikrokredit taqdim etilishi to‘g‘risida ijobiy qaror qabul qilinishi uchun muhim hisoblangan masalalar bo‘yicha yolg‘on yoki to‘liq bo‘lmagan ma'lumotlarni taqdim etganligi aniqlanganda.
A49: 4.1.3. Ushbu shartnomaning amal qilish jarayonida Qarz oluvchining moliyaviy holatini tekshirish va Qarz oluvchi tomonidan o‘z zimmasiga olgan majburiyatlarning bajarilishini nazorat qilish.
A50: 4.1.4. Qarz oluvchi tomonidan yoki ushbu Shartnoma bo‘yicha uchinchi shaxs tomonidan ta'minot sifatida garovga qo‘yilgan mol-mulkning tegishli holatdaligi va ulardan foydalanish bo‘yicha tekshiruvlar o‘tkazish.
A51: 4.1.5. Garovga qo‘yuvchi tomonidan garovga qo‘yilgan mol-mulk buzilgan yoki belgilangan maqsadda foydalanish uchun yaroqsiz holga kelganda, bu esa Mikromoliya tashkilotining ushbu Shartnoma bo‘yicha moliyaviy talablarini qondirishga qodir bo‘lgan bozor qiymatiga ma'lum darajada ta'sir ko‘rsatganda, yoki uchinchi shaxsning (kafil) moliyaviy holatining yomonlashuvi sababli ushbu Shartnomadan kelib chiqqan majburiyatlar bo‘yicha javob berish qobiliyatiga ega bo‘lmay qolgan holatlarda Qarz oluvchidan ta'minotning qo‘shimcha turini taqdim etish yoki almashtirishni talab qilish.
A52: 4.1.6. Qonun hujjatlariga muvofiq, Qarz oluvchi tomonidan ushbu Shartnoma bo‘yicha asosiy qarz, foizlar, penya va boshqa pul majburiyatlarini o‘z vaqtida to‘lamaslik holatlarida Qarz oluvchining bank hisobvaraqlaridagi pul mablag‘larini akseptsiz tartibda yechib olish to‘g‘risida to‘lov talabnomasini berish va bunga Qarz oluvchi qaytarib olinmaydigan va so‘zsiz rozilik bildiradi.
A53: ="4.1.7. Qarz oluvchini oldindan ogohlantirmasdan "&malumot!B65&"ni qaytarish uchun haqiqatdan ham garov ta'minoti mavjudligini tekshirishni amalga oshirish." -> 4.1.7. Qarz oluvchini oldindan ogohlantirmasdan mikrokreditni qaytarish uchun haqiqatdan ham garov ta'minoti mavjudligini tekshirishni amalga oshirish.
A54: 4.1.8. Ushbu shartnoma doirasida o‘z majburiyatlarini bajarish uchun uchinchi shaxslarga barcha zarur ma'lumotlarni yetkazish.
A55: 4.1.9. Istalgan vaqtda Qarz oluvchining avvaldan roziligini olmasdan turib ushbu Shartnoma bo‘yicha uchinchi tomonga da'vo qilish huquqini berish yoki uning foydasiga voz kechish.
A56: =CONCATENATE(C56,H56) -> 4.1.10. Qarz oluvchi taqdim etilgan mikrokreditdan Shartnoma tuzilgan kundan boshlab 1 (bir) oy davomida foydalanmagan holatlarda, bu haqda Qarz oluvchini yozma ravishda xabardor qilib, Shartnoma bir tomonlama bekor qilish. Yozma xabarni jo‘natish sanasi uni taqdim etish yoki pochta orqali jo‘natish sanasi hisoblanadi. | C56: ="4.1.10. Qarz oluvchi taqdim etilgan "&malumot!B65&"dan Shartnoma tuzilgan kundan boshlab 1 (bir) oy davomida foydalanmagan" -> 4.1.10. Qarz oluvchi taqdim etilgan mikrokreditdan Shartnoma tuzilgan kundan boshlab 1 (bir) oy davomida foydalanmagan | H56: holatlarda, bu haqda Qarz oluvchini yozma ravishda xabardor qilib, Shartnoma bir tomonlama bekor qilish. Yozma xabarni jo‘natish sanasi uni taqdim etish yoki pochta orqali jo‘natish sanasi hisoblanadi.
A57: ="4.1.11. Oldingi "&malumot!B65&" to‘liq to‘lanmagunga qadar yangi "&malumot!B65&" berishni rad etish." -> 4.1.11. Oldingi mikrokredit to‘liq to‘lanmagunga qadar yangi mikrokredit berishni rad etish.
A59: 5. QARZ OLUVCHINING HUQUQ VA MAJBURIYATLARI
A60: 5.1. Qarz oluvchi quyidagi huquqlarga ega:
A61: ="5.1.1. Ushbu shartnomada nazarda tutilgan shartlar bo‘yicha "&malumot!B65&" olish, shuningdek, Mikromoliya tashkiloti tomonidan ko‘rsatiladigan pullik xizmatlardan foydalanish." -> 5.1.1. Ushbu shartnomada nazarda tutilgan shartlar bo‘yicha mikrokredit olish, shuningdek, Mikromoliya tashkiloti tomonidan ko‘rsatiladigan pullik xizmatlardan foydalanish.
A62: ="5.1.2. Shartnoma tuzilgan kundan boshlab 2 (ikki) hafta mobaynida Mikromoliya tashkilotiga bu haqda yozma xabarnoma yo‘llash orqali "&malumot!B65&"ning foydalanilmagan summasidan voz kechish." -> 5.1.2. Shartnoma tuzilgan kundan boshlab 2 (ikki) hafta mobaynida Mikromoliya tashkilotiga bu haqda yozma xabarnoma yo‘llash orqali mikrokreditning foydalanilmagan summasidan voz kechish.
A63: ="5.1.3. "&malumot!C64&" xizmatlari ko‘rsatish qoidalari bilan tanishish." -> 5.1.3. Mikrokredit xizmatlari ko‘rsatish qoidalari bilan tanishish.
A64: ="5.1.4. O‘z huquq va majburiyatlari, shu jumladan "&malumot!B65&" xizmatlari ko‘rsatish bilan bog‘liq barcha xarajatlar haqida aniq va to‘liq ma'lumot olish." -> 5.1.4. O‘z huquq va majburiyatlari, shu jumladan mikrokredit xizmatlari ko‘rsatish bilan bog‘liq barcha xarajatlar haqida aniq va to‘liq ma'lumot olish.
A65: 5.1.5. Shartnoma bo‘yicha Mikromoliya tashkilotining majburiyatlarini bajarmaslik yoki tegishli darajada bajarmaslik natijasida yuzaga kelgan zararlarni qoplashni talab qilish.
A66: 5.2. Qarz oluvchining majburiyatlari:
A67: ="5.2.1. Mikromoliya tashkilotining birinchi talabi bilan zarur hujjatlar, shuningdek "&malumot!B65&"dan foydalanishning butun davri davomida uning moliyaviy holati va to‘lash qobiliyatiga tegishli bo‘lgan ma'lumotlarni taqdim etish." -> 5.2.1. Mikromoliya tashkilotining birinchi talabi bilan zarur hujjatlar, shuningdek mikrokreditdan foydalanishning butun davri davomida uning moliyaviy holati va to‘lash qobiliyatiga tegishli bo‘lgan ma'lumotlarni taqdim etish.
A68: 5.2.2. Ushbu shartnomada nazarda tutilgan hollarda garov ta'minotini almashtirish yoki qo‘shimcha ta'minot turini taqdim etish bo‘yicha Mikromoliya tashkiloti talablarini bajarish.
A69: ="5.2.3. To‘lov jadvaliga muvofiq "&malumot!B65&", shuningdek hisoblangan foizlar to‘lovlarini amalga oshirish." -> 5.2.3. To‘lov jadvaliga muvofiq mikrokredit, shuningdek hisoblangan foizlar to‘lovlarini amalga oshirish.
A70: =CONCATENATE(C70,H70) -> 5.2.4. Mikromoliya tashkiloti vakillariga o‘zlarining moliyaviy holati, yashash joyini tekshirishga, Mikromoliya tashkiloti foydasiga garovga qo‘yilgan mol-mulk saqlanishini tekshirishga ruxsat berish, shuningdek Qarz oluvchi ob'ektlaridan istalganiga tashrif buyurish va har qanday bino, inshoot, mol-mulk, asbob-uskunalar, tovarlar va xizmatlar, shuningdek ularning mikrokredit mablag‘lari hisobiga moliyalashtirilgan hujjatlarni ko‘zdan kechirish va Mikromoliya tashkiloti tomonidan ushbu huquqni amalga oshirishga to‘sqinlik qilmaslik majburiyatini oladi. | C70: 5.2.4. Mikromoliya tashkiloti vakillariga o‘zlarining moliyaviy holati, yashash joyini tekshirishga, Mikromoliya tashkiloti foydasiga garovga qo‘yilgan mol-mulk saqlanishini tekshirishga ruxsat berish, shuningdek Qarz oluvchi ob'ektlaridan istalganiga tashrif buyurish va har qanday bino, inshoot, mol-mulk, asbob-uskunalar, tovarlar va xizmatlar, shuningdek ularning | H70: =" "&malumot!B65&" mablag‘lari hisobiga moliyalashtirilgan hujjatlarni ko‘zdan kechirish va Mikromoliya tashkiloti tomonidan ushbu huquqni amalga oshirishga to‘sqinlik qilmaslik majburiyatini oladi." -> mikrokredit mablag‘lari hisobiga moliyalashtirilgan hujjatlarni ko‘zdan kechirish va Mikromoliya tashkiloti tomonidan ushbu huquqni amalga oshirishga to‘sqinlik qilmaslik majburiyatini oladi.
A71: 5.2.5. Qarz oluvchining moliyaviy ahvoli yomonlashuvi va ushbu shartnoma bo‘yicha Qarz oluvchining Mikromoliya tashkiloti oldidagi majburiyatlarining bajarilmasligi va/yoki tegishli darajada bajarilmaslik xavfi yuzaga kelishiga olib keluvchi hech qanday majburiyat va choralarni o‘z zimmasiga olmaslik;
A72: ="5.2.6. Quyidagi holatlarda Mikromoliya tashkilotning birinchi talabi bilan "&malumot!B65&" qaytarilishi bo‘yicha qo‘shimcha garov ta'minotini taqdim etish: " -> 5.2.6. Quyidagi holatlarda Mikromoliya tashkilotning birinchi talabi bilan mikrokredit qaytarilishi bo‘yicha qo‘shimcha garov ta'minotini taqdim etish:
A73: - Qarz oluvchining moliyaviy holatining yomonlashuvi; - Garov ob'ekti va/yoki uning bir qismining yo‘q qilinishi, qiymatining pasayishi, qisman yoki to‘liq yo‘qotilishi; - qarz qaytarilmaslik xavfini ko‘paytiruvchi boshqa omillarning paydo bo‘lishi;
A74: ="5.2.7. Sud qarori asosida Qarz oluvchi – jismoniy shaxsning muomalaga layoqatsizligi yoki muomalaga layoqati cheklangan yoxud to‘lash qobiliyatiga ega emasligi (bankrotligi) tan olinganda, uning vasiysi yoki homiysi "&malumot!B65&"ning asosiy summa bo‘yicha qarzdorlikni "&malumot!B65&"dan aniq foydalanish muddati uchun foizlar bilan kechiktirmasdan to‘liq to‘lashi shart." -> 5.2.7. Sud qarori asosida Qarz oluvchi – jismoniy shaxsning muomalaga layoqatsizligi yoki muomalaga layoqati cheklangan yoxud to‘lash qobiliyatiga ega emasligi (bankrotligi) tan olinganda, uning vasiysi yoki homiysi mikrokreditning asosiy summa bo‘yicha qarzdorlikni mikrokreditdan aniq foydalanish muddati uchun foizlar bilan kechiktirmasdan to‘liq to‘lashi shart.
A75: ="5.2.8. Mikromoliya tashkilotining "&malumot!B65&" umumiy summasi va hisoblangan foizlarni muddatidan oldin qaytarish to‘g‘risidagi talabini kechiktirmasdan bajarish." -> 5.2.8. Mikromoliya tashkilotining mikrokredit umumiy summasi va hisoblangan foizlarni muddatidan oldin qaytarish to‘g‘risidagi talabini kechiktirmasdan bajarish. | H75: "&'Общие данные'!B59&"
A76: =CONCATENATE(C76,H76) -> 5.2.9. Mikromoliya tashkilotining talabi bo‘yicha Mikromoliya tashkiloti ko‘rgan, shu jumladan mikrokredit bo‘yicha (asosiy qarz, foizlar va boshqalar) qarzdorlikni majburiy va/yoki muddatidan oldin qaytarish bo‘yicha qabul qilingan choralar bilan bog‘liq bo‘lgan barcha xarajatlari va zararlarni qoplash, shuningdek ushbu shartnoma doirasida unidruvni taqdim etilgan garov ta'minotiga qaratish. | C76: ="5.2.9. Mikromoliya tashkilotining talabi bo‘yicha Mikromoliya tashkiloti ko‘rgan, shu jumladan "&malumot!B65&" bo‘yicha (asosiy qarz, foizlar va boshqalar)" -> 5.2.9. Mikromoliya tashkilotining talabi bo‘yicha Mikromoliya tashkiloti ko‘rgan, shu jumladan mikrokredit bo‘yicha (asosiy qarz, foizlar va boshqalar) | H76: qarzdorlikni majburiy va/yoki muddatidan oldin qaytarish bo‘yicha qabul qilingan choralar bilan bog‘liq bo‘lgan barcha xarajatlari va zararlarni qoplash, shuningdek ushbu shartnoma doirasida unidruvni taqdim etilgan garov ta'minotiga qaratish.
A78: 6. TOMONLARNING JAVOBGARLIGI
A79: =CONCATENATE(C79,H79) -> 6.1. Mikromoliya tashkiloti tomonidan Qarz oluvchiga pul mablag‘larini ajratib berish bo‘yicha o‘z zimmasiga olgan majburiyatlarning Shartnomaning 1.1.-bandida keltirilgan summa va muddatlarda bajarilmaslik yoki tegishli tarzda bajarilmaslik holatlarida Mikromoliya tashkiloti muddatidan o‘tgan har bir kalendar kun uchun kechiktirilgan to‘lov summasining 0,1% miqdorida, biroq ushbu Shartnomaning 1.1.-bandida ko‘rsatilgan mikrokredit miqdori umumiy summasining 50% dan ko‘p bo‘lmagan miqdorda penya ko‘rinishidagi neustoyka to‘lash majburiyatini o‘z zimmasiga oladi. | C79: 6.1. Mikromoliya tashkiloti tomonidan Qarz oluvchiga pul mablag‘larini ajratib berish bo‘yicha o‘z zimmasiga olgan majburiyatlarning Shartnomaning 1.1.-bandida keltirilgan summa va muddatlarda bajarilmaslik yoki tegishli tarzda bajarilmaslik holatlarida Mikromoliya tashkiloti muddatidan o‘tgan har bir kalendar kun uchun kechiktirilgan to‘lov summasining 0,1% miqdorida, biroq ushbu Shartnomaning 1.1.-bandida ko‘rsatilgan | H79: =""&malumot!B65&" miqdori umumiy summasining 50% dan ko‘p bo‘lmagan miqdorda penya ko‘rinishidagi neustoyka to‘lash majburiyatini o‘z zimmasiga oladi." -> mikrokredit miqdori umumiy summasining 50% dan ko‘p bo‘lmagan miqdorda penya ko‘rinishidagi neustoyka to‘lash majburiyatini o‘z zimmasiga oladi.
A80: 6.2. Jarima sanksiyalarni to‘lash Tomonlarni ushbu Shartnomada ko‘zda tutilgan zimmalaridagi majburiyatlarini bajarishdan ozod qilmaydi.
A81: 6.3. Tomonlarning ushbu Shartnomada nazarda tutilmagan javobgarligi O‘zbekiston Respublikasining amaldagi qonunchiligiga muvofiq belgilanadi.
A82: 6.4. Tomonlar O‘zbekiston Respublikasi Fuqarolik kodeksining 325-moddasiga muvofiq aybdor tomondan yetkazilgan zararni neustoykadan tashqari to‘la hajmda undirish huquqiga egadirlar.
A84: 7. FORS-MAJOR
A85: 7.1. Agar Tomonlar ular zimmasidagi majburiyatlarni tegishli darajada bajarishi yengib bo‘lmas kuch (fors-major) oqibatida mumkin bo‘lmay qolgan bo‘lsa, ya'ni aniq vaqt davri davomida aniq sharoitlarda favqulodda va oldini olib bo‘lmaydigan holatlar ekanligini isbotlay olmasalar, Shartnoma bo‘yicha o‘z majburiyatlarini bajarmagan yoki tegishli darajada bajarmagan Tomon uning shartlarini bajarishda javobgar hisoblanadi. Ushbu Shartnoma Tomonlari yengilmas kuch holatlariga quyidagilarni kiritadi: tabiiy ofat (zilzila, suv toshqini, chaqmoq chaqishi, vulqon otilishi, sel kelishi, ko‘chki, sunami va hokazo), Shartnoma bo‘yicha majburiyatlar bajarilish joyida temperatura – harorat, shamol kuchi va yog‘ingarchilik darajasining inson hayotiy faoliyati normasidan ortiq bo‘lishi; hokimiyat va boshqaruv organlari moratoriysi; qonuniy belgilangan tartibda tashkil etilgan ish tashlashlar va majburiyatlarning tegishli darajada bajarilishi uchun Shartnoma Tomonlari tarafidan yengib bo‘lmas kuch sifatida belgilangan boshqa holatlar.
A86: 7.2. Fors-major holati ta'sirida qolgan Tomon, bunday holatlar yuzaga kelgan kundan boshlab 7 (etti) kalendar kundan kechiktirmasdan boshqa Tomonni xabardor qilishi shart.
A87: 7.3. Fors-major holati boshlanganligi to‘g‘risida xabar qilmaslik yoki o‘z vaqtida xabar bermaslik fors-major holati boshlanganda Shartnoma bo‘yicha o‘z majburiyatlarini bajarish imkoniyatiga vaj qilib keltirish huquqiga ega emas.
A88: 7.4. Fors-major holati boshlanganligini vaj qilib ko‘rsatish huquqidan mahrum etilgan Tomon amaldagi qonun hujjatlariga muvofiq javobgar bo‘ladi.
A90: 8. NIZOLARNI HAL QILISH TARTIBI
A91: 8.1. Ushbu Shartnomadan kelib chiqadigan tomonlar o‘rtasidagi barcha nizolar va undan kelib chiqadigan majburiyatlar, shu jumladan shartnoma bajarilmasligi oqibatida yuzaga kelgan bajarilishi, o‘zgartirilishi, bekor qilinishi, tugatilishi Mikromoliya tashkilot joylashgan yerdagi taalluqli sudda yoki «CONSILIO» Mas'uliyati cheklangan jamiyat qoshidagi Hakamlik sudida, O‘zbekiston Respublikasining amaldagi qonun hujjatlari va uning reglamentiga muvofiq Hakamlik sudi raisi tomonidan tayinlangan, yakka tartibdagi hakamlik sudyasi tomonidan, sud ishlarini sud majlisi bayonnomasi tuzmasdan ko‘rib chiqilishi kerak bo‘ladi. U yoki bu sudga murojaat qilish huquqi da'vogarda qoladi.
A92: Qarzni undirish va garovdagi mol-mulkiga qaratish ham sud tartibida, ham suddan tashqari tartibda, shu jumladan notariusning ijro yozuvini olish yo‘li bilan amalga oshirilishi mumkin.
A93: ="8.2. Mikromoliya tashkiloti sud organlariga murojaat qilganidan keyin Qarz oluvchi tomonidan "&malumot!B65&" bo‘yicha muddati o‘tgan qarzdorlikning to‘lanishi Mikromoliya tashkilotning "&malumot!B65&" bo‘yicha qarzdorlikni muddatidan avval undirish, shu jumladan undiruvni garovdagi mol-mulkka qaratish yo‘li bilan undirish huquqidan mahrum qilmaydi." -> 8.2. Mikromoliya tashkiloti sud organlariga murojaat qilganidan keyin Qarz oluvchi tomonidan mikrokredit bo‘yicha muddati o‘tgan qarzdorlikning to‘lanishi Mikromoliya tashkilotning mikrokredit bo‘yicha qarzdorlikni muddatidan avval undirish, shu jumladan undiruvni garovdagi mol-mulkka qaratish yo‘li bilan undirish huquqidan mahrum qilmaydi.
A95: 9. SHARTNOMA SHARTLARI VA AMAL QILISH MUDDATI
A96: 9.1. Ushbu Shartnoma Tomonlar tarafidan imzolangandan keyin kuchga kiradi.
A97: ="9.2. Shartnomaning amal qilish muddati Qarz oluvchi "&malumot!B65&"ni to‘liq qaytargan, hisoblangan foizlar, penya va boshqa pul majburiyatlarini to‘lagan kunda yakunlanadi." -> 9.2. Shartnomaning amal qilish muddati Qarz oluvchi mikrokreditni to‘liq qaytargan, hisoblangan foizlar, penya va boshqa pul majburiyatlarini to‘lagan kunda yakunlanadi.
A98: 9.3. Ushbu Shartnomaga kiritiladigan barcha o‘zgartirish va qo‘shimchalar, ushbu Shartnomada kelishilgan holatlardan tashqari, ikkala Tomon tarafidan qo‘shimcha bitimni yozma shaklda imzolagan holda amalga oshiriladi.
A100: 10. SHAXSIY MA'LUMOTLARNI QAYTA ISHLASH
A101: 10.1. Ushbu shartnomani tuzish bilan, Qarz oluvchi Mikromoliya tashkilotiga uning shaxsiy ma'lumotlari, shu jumladan, familiyasi, ismi, otasining ismi, pasport ma'lumotlari (shu jumladan, pasport raqami, berilgan vaqti va sanasi, ro‘yxatdan o‘tgan manzili va boshqalar); aloqaga chiqish uchun ma'lumotlar (shu jumladan, telefon raqami, e-mail, pochta manzili va boshqalar); STIR, ushbu shartnoma maqsadiga tegishli bo‘lgan boshqa ma'lumotlarni har qanday maqsadda ishlov berishga rozilik beradi.
A102: 10.2. Rozilik, shu jumladan shahsiy ma'lumotlar bilan quyidagi harakatlarni amalga oshirishga beriladi: yig‘ish, tizimlashtirish, to‘plash, saqlash, aniqlashtirish (yangilash, o‘zgartirish), foydalanish; O‘zbekiston Respublikasi qonun hujjatlarida nazarda tutilgan hollar va darajada tarqatish, shu jumladan davlat organlari va boshqa tashkilotlarga taqdim etish, shaxsiy ma'lumotlarning egasizlantirish, blokirovka va yo‘q qilish.
A103: 10.3. Qarz oluvchi, shuningdek, Mikromoliya tashkiloti shartnoma doirasida olingan ma'lumotlarni kredit byurosi va garov reestri, skoring kompaniyasi, uyali aloqa operatori, sug‘urta kompaniyasi, reklama ishlab chiqaruvchilari va tarqatuvchilari, shuningdek Mikromoliya tashkilotining boshqa hamkorlariga taqdim etishga roziligini bildiradi.
A105: 11. BOSHQA SHARTLAR
A106: 11.1. Ushbu shartnoma kuchga kirganidan keyin, o‘zaro munosabatlarga aloqador barcha yozishmalar yoki kelishuvlar, o‘z kuchini yo‘qotadi.
A107: 11.2. Ushbu shartnomani bajarish, o‘zgartirish va bekor qilish bilan bog‘liq barcha yozishma va xabarnomalar Tomonlarning ushbu shartnomaning yakuniy qismida ko‘rsatilgan pochta manzillariga yuboriladi.
A108: 11.3. Ushbu shartnomani bajarish uchun zarur bo‘lgan ismi (nomlanishi), ro‘yxatdan o‘tgan joyi, haqiqiy yashash joyi, manzili (joylashgan yeri), bank rekvizitlari va boshqa ma'lumotlar o‘zgargan holatlarda, Tomonlarning har biri bunday o‘zgarishlar amalga oshgan kundan boshlab 5 (besh) kalendar kun ichida boshqa Tomonni bunday o‘zgarishlar haqida yozma ravishda xabardor qilishi shart.
A109: 11.4. Ushbu bitimni amalga oshirish bilan, Qarz oluvchi kelishuvning muhimligi va uni tuzishning yuridik oqibatlarini to‘liq tushunib yetishi, shu sababli Shartnomani tuzish yanglishishlar, aldov, zo‘ravonlik, tahdidlar, yomon niyatli bitim yoki murakkab holatlar (tutqinlik) ta'sirida emasligini tasdiqlaydi.
A110: 11.5. Ushbu shartnomada ko‘zda tutilmagan holatlarda Tomonlar O‘zbekiston Respublikasining amaldagi qonunchiligiga amal qiladilar.
A111: 11.6. Qarz oluvchi Mikromoliya tashkilotining oldindan yozma roziligini olmasdan turib o‘z majburiyatlari yoki huquqlarini uchinchi shaxslarga o‘tkaza olmaydi.
... A113: 12. TOMONLARNING YURIDIK MANZILLARI VA REKVIZITLARI:
...

Sheet buyruq
A2: =""&malumot!B157&" ijrochi direktorining "&malumot!B175&"dagi "&malumot!B174&"-sonli buyrug‘i" -> «CLEVER MIKROMOLIYA TASHKILOTI» MChJ ijrochi direktorining 7 aprel 2025 y.dagi №717-XMS-sonli buyrug‘i
A6: ="Men, Abduraximov Nadirbek Kamilevich "&malumot!B157&" ijrochi direktori, jismoniy shaxs "&malumot!B10&"ga quyidagi shartlarda "&malumot!B65&" berishni buyuraman:" -> Men, Abduraximov Nadirbek Kamilevich «CLEVER MIKROMOLIYA TASHKILOTI» MChJ ijrochi direktori, jismoniy shaxs MATCHANOVA AZIZA BEKTURDIYEVNAga quyidagi shartlarda mikrokredit berishni buyuraman:
A7: =kredit_ariza!A13:D13 -> Mikrokredit summasi: 125 000 000,00 (yuz yigirma besh million so'm) so'm.
A8: =kredit_ariza!A14:D14 -> Mikrokredit muddati: 36 (O'ttiz olti ) oy.
A9: =kredit_ariza!A15:D15 -> Mikrokreditdan foydalanganlik uchun foiz stavkasi: yillik 55% (Ellik besh ) foiz
A10: =kredit_ariza!A16:D16 -> Mikrokredit bo'yicha asosiy qarz va foizlarni to'lash:
A11: =kredit_ariza!A17:D17 -> - mikrokredit shartnomasi bo'yicha har oy differensial to'lovlari amalga oshiriladi
A12: =kredit_ariza!A19:D19 -> - mikrokredit shartnomasi bo'yicha har oy annuitet to'lovlari amalga oshiriladi
A13: =IF(malumot!B110="Avtotransport",buyruq!A12:E12,buyruq!A11:E11) -> - mikrokredit shartnomasi bo'yicha har oy annuitet to'lovlari amalga oshiriladi
A14: =IF(malumot!B110=malumot!D110,""&malumot!C124&"ga tegishli "&malumot!C133&" ko'rinishidagi ko'chmas mulkni quyidagi ma'lumotlarga muvofiq garovga qabul qilinsin:",""&malumot!B124&"ga tegishli "&malumot!B132&" ko'rinishidagi transport vositasini quyidagi ma'lumotlarga muvofiq garovga qabul qilinsin:") -> BEKOV OTABEK BAXODIROVICHga tegishli JAC M3 ko'rinishidagi transport vositasini quyidagi ma'lumotlarga muvofiq garovga qabul qilinsin:
A15: =""&malumot!C124&"ga tegishli "&malumot!C133&" ko'rinishidagi ko'chmas mulkni quyidagi ma'lumotlarga muvofiq garovga qabul qilinsin:" -> 0ga tegishli 0 ko'rinishidagi ko'chmas mulkni quyidagi ma'lumotlarga muvofiq garovga qabul qilinsin:
A16: =""&malumot!B124&"ga tegishli "&malumot!B132&" ko'rinishidagi transport vositasini quyidagi ma'lumotlarga muvofiq garovga qabul qilinsin:" -> BEKOV OTABEK BAXODIROVICHga tegishli JAC M3 ko'rinishidagi transport vositasini quyidagi ma'lumotlarga muvofiq garovga qabul qilinsin:
A17: =dalolatnoma!A29 -> Nomi | B17: =dalolatnoma!B29 -> Kuzov turi va kuzov raqami* | C17: =dalolatnoma!C29 -> Dvigatel va shassi raqami* | D17: =dalolatnoma!D29 -> Ishlab chiqarilgan yili va rangi* | E17: =dalolatnoma!E29 -> Kelishilgan garov qiymati, so'm
A18: =dalolatnoma!A30 -> JAC M3 | B18: =dalolatnoma!B30 -> kuzov turi - YENGIL MINIVEN, kuzov raqami P08461541 | C18: =dalolatnoma!C30 -> dvigatel raqami LJ166A33XP2208188, shassi raqami - Rakamsiz | D18: =dalolatnoma!D30 -> rangi - QORA CHERNIY, ishlab chiqarilgan yili - 2023 | E18: =dalolatnoma!E30 -> 165 000 000,00 (yuz oltmish besh million so'm)
A19: =dalolatnoma!A22:E22 -> -* avtotransport egasi: BEKOV OTABEK BAXODIROVICH
A20: =dalolatnoma!A23:E23 -> -* texnik pasport: AAG 5923045 28.03.2025y.
A21: =dalolatnoma!A24:E24 -> -* roʻyxatdan oʻtgan manzili/garaj manzili: XORAZM VILOYATI URGANCH TUMANI GOYBU QFY OQ MAKTAB MFY
A22: =dalolatnoma!A25:E25 -> -* davlat raqami: 90C477ZA
A23: =" «"&malumot!B153&"» АJ sug‘urta kompaniyasi bilan Mikroqarz to'lamaslik xavfini "&FIXED(malumot!B154,2)&"("&malumot!B155&") so'm miqdoriga sug’urta qilish shartnomasi tuzilsin" -> «АО "APEX INSURANCE"» АJ sug‘urta kompaniyasi bilan Mikroqarz to'lamaslik xavfini 15 000 000,00(o'n besh million so'm) so'm miqdoriga sug’urta qilish shartnomasi tuzilsin
A27: «CLEVER MIKROMOLIYA TASHKILOTI» MChJ ijrochi direktori | D27: N. Abduraximov

Sheet bayonnoma
A1: =""&malumot!B157&" mikromoliya tashkiloti Kredit qo‘mitasining yig‘ilishi" -> «CLEVER MIKROMOLIYA TASHKILOTI» MChJ mikromoliya tashkiloti Kredit qo‘mitasining yig‘ilishi
A2: =""&H7&" protokolidan ko'chirma" -> №717-XMS protokolidan ko'chirma
A3: Toshkent shahri | E3: =malumot!B68 -> 7 aprel 2025 y.
B4: KUN TARTIBI:
A5: =" "&H8&"."&malumot!B5&" ga "&malumot!B65&" berish masalasini ko‘rib chiqish to‘g‘risida." -> 1.MATCHANOVA AZIZA BEKTURDIYEVNA ga mikrokredit berish masalasini ko‘rib chiqish to‘g‘risida.
A7: =" "&H9&" masala yuzasidan: «Clever Mikromoliya Tashkiloti» MChJ mikromoliya tashkiloti kredit bo‘yicha menejeri "&malumot!B5&"ga "&FIXED(malumot!B76)&" ("&malumot!B77&") so‘m miqdorida, muddati "&malumot!B82&" ("&malumot!B83&") oyga va yillik 60 (Oltmish) foiz miqdorida "&malumot!B65&" berich bo‘yicha "&malumot!B5&"ning kredit arizasi va "&malumot!B157&"ning xulosasi bilan ishtirokchilarni tanishtirdi." -> Birinchi masala yuzasidan: «Clever Mikromoliya Tashkiloti» MChJ mikromoliya tashkiloti kredit bo‘yicha menejeri MATCHANOVA AZIZA BEKTURDIYEVNAga 125 000 000,00 (yuz yigirma besh million so'm) so‘m miqdorida, muddati 36 (O'ttiz olti ) oyga va yillik 60 (Oltmish) foiz miqdorida mikrokredit berich bo‘yicha MATCHANOVA AZIZA BEKTURDIYEVNAning kredit arizasi va «CLEVER MIKROMOLIYA TASHKILOTI» MChJning xulosasi bilan ishtirokchilarni tanishtirdi. | G7: Protokol raqami | H7: =malumot!B1 -> №717-XMS
G8: Savol raqami | H8: 1 | I8: 1 | J8: 2 | K8: 3 | L8: 4 | M8: 5 | N8: 6 | O8: 7 | P8: 8 | Q8: 9 | R8: 10 | S8: 11 | T8: 12 | U8: 13 | V8: 14 | W8: 15 | X8: 16 | Y8: 17 | Z8: 18 | AA8: 19 | AB8: 20 | AC8: 21 | AD8: 22 | AE8: 23 | AF8: 24 | AG8: 25
G9: Savol raqami qol bilan | H9: =IF(H8=I8,I9,IF(H8=J8,J9,IF(H8=K8,K9,IF(H8=L8,L9,IF(H8=M8,M9,IF(H8=N8,N9,IF(H8=O8,O9,IF(H8=P8,P9,IF(H8=Q8,Q9,IF(H8=R8,R9,IF(H8=S8,S9,IF(H8=T8,T9,IF(H8=U8,U9,IF(H8=V8,V9,IF(H8=W8,W9,IF(H8=X8,X9,IF(H8=Y8,Y9,IF(H8=Z8,Z9,IF(H8=AA8,AA9,IF(H8=AB8,AB9,IF(H8=AC8,AC9,IF(H8=AD8,AD9,IF(H8=AE8,AE9,IF(H8=AF8,AF9,IF(H8=AG8,AG9))))))))))))))))))))))))) -> Birinchi | I9: Birinchi | J9: Ikkinchi | K9: Uchinchi | L9: To'rtinchi | M9: Beshinchi | N9: O'ltinchi | O9: Yettinchi | P9: Sakkizinchi | Q9: Tuqqizinchi | R9: O'ninchi | S9: O'n birinchi | T9: O'n ikkinchi | U9: O'n uchinchi | V9: O'n to'rtinchi | W9: O'n beshinchi | X9: O'n oltinchi | Y9: O'n yettinchi | Z9: O'n sakkizinchi | AA9: O'n tuqqizinchi | AB9: Yigirmanchi | AC9: Yigirma birinchi | AD9: Yigizma ikkinchi | AE9: Yigirma uchinchi | AF9: Yigirma to'rtinchi | AG9: Yigirma beshinchi
A11: =""&malumot!C64&" ta’minoti:" -> Mikrokredit ta’minoti:
A13: =xulosa!A18:E18 -> 1. Egalik huquqi BEKOV OTABEK BAXODIROVICHga tegishli bo'lgan garovga olingan avtomobil markasi JAC M3, rangi - QORA CHERNIY, ishlab chiqarilgan yili - 2023, davlat raqam belgisi 90C477ZA, kuzov turi - YENGIL MINIVEN, kuzov raqami P08461541, dvigatel raqami LJ166A33XP2208188, shassi raqami - Rakamsiz
A14: ="2. «"&malumot!B153&"» АJ sug‘urta kompaniyasi tomonidan Mikroqarz to'lamaslik xavfini "&FIXED(malumot!B154,2)&"("&malumot!B155&") so ' m miqdoriga sug’urta qilish" -> 2. «АО "APEX INSURANCE"» АJ sug‘urta kompaniyasi tomonidan Mikroqarz to'lamaslik xavfini 15 000 000,00(o'n besh million so'm) so ' m miqdoriga sug’urta qilish
C15: masala yuzasidan berilgan ma’lumotlarni muhokama qilib, Kredit qo‘mitasi a’zolariga taqdim etilgan zarur hujjatlarni o‘rganib, majlisda ishtirok etgan Kredit qo‘mitasi a’zolarining taklif va mulohazalarini inobatga olgan holda | D15: =""&malumot!B157&" kredit qo‘mitasi" -> «CLEVER MIKROMOLIYA TASHKILOTI» MChJ kredit qo‘mitasi | E15: =CONCATENATE(C15,D15) -> masala yuzasidan berilgan ma’lumotlarni muhokama qilib, Kredit qo‘mitasi a’zolariga taqdim etilgan zarur hujjatlarni o‘rganib, majlisda ishtirok etgan Kredit qo‘mitasi a’zolarining taklif va mulohazalarini inobatga olgan holda «CLEVER MIKROMOLIYA TASHKILOTI» MChJ kredit qo‘mitasi
A16: =CONCATENATE(H9,E15) -> Birinchi masala yuzasidan berilgan ma’lumotlarni muhokama qilib, Kredit qo‘mitasi a’zolariga taqdim etilgan zarur hujjatlarni o‘rganib, majlisda ishtirok etgan Kredit qo‘mitasi a’zolarining taklif va mulohazalarini inobatga olgan holda «CLEVER MIKROMOLIYA TASHKILOTI» MChJ kredit qo‘mitasi
A17: QAROR QILADI:
A18: =" "&malumot!B5&"ga quyidagi shartlarda "&malumot!B65&" berish masalasi ma’qullansin:" -> MATCHANOVA AZIZA BEKTURDIYEVNAga quyidagi shartlarda mikrokredit berish masalasi ma’qullansin:
A19: ="1. "&malumot!C64&" summasi: "&FIXED(malumot!B76)&" ("&malumot!B77&") so'm." -> 1. Mikrokredit summasi: 125 000 000,00 (yuz yigirma besh million so'm) so'm.
A20: ="2. "&malumot!C64&" muddati: "&malumot!B82&" ("&malumot!B83&") oy " -> 2. Mikrokredit muddati: 36 (O'ttiz olti ) oy
A21: ="3. "&malumot!C64&"dan foydalanganlik uchun foiz stavkasi:yillik "&malumot!B86&"% ("&malumot!B87&") foiz." -> 3. Mikrokreditdan foydalanganlik uchun foiz stavkasi:yillik 55% (Ellik besh ) foiz.
A22: ="4. "&malumot!C64&" bo‘yicha asosiy qarz va foizlarni to‘lash:" -> 4. Mikrokredit bo‘yicha asosiy qarz va foizlarni to‘lash:
A23: =kredit_ariza!A19:D19 -> - mikrokredit shartnomasi bo'yicha har oy annuitet to'lovlari amalga oshiriladi
A24: 5. Mikroqarz bo‘yicha ta'minot:
A25: ="1. garov "&xulosa!A29:E29&"" -> 1. garov - BEKOV OTABEK BAXODIROVICH ga mulk huquqi asosida tegishli avtotransport vositasi JAC M3 , quyidagi tafsilotlarga muvofiq:
A26: =dalolatnoma!A29 -> Nomi | B26: =dalolatnoma!B29 -> Kuzov turi va kuzov raqami* | C26: =dalolatnoma!C29 -> Dvigatel va shassi raqami* | D26: =dalolatnoma!D29 -> Ishlab chiqarilgan yili va rangi* | E26: =dalolatnoma!E29 -> Kelishilgan garov qiymati, so'm
A27: =dalolatnoma!A30 -> JAC M3 | B27: =dalolatnoma!B30 -> kuzov turi - YENGIL MINIVEN, kuzov raqami P08461541 | C27: =dalolatnoma!C30 -> dvigatel raqami LJ166A33XP2208188, shassi raqami - Rakamsiz | D27: =dalolatnoma!D30 -> rangi - QORA CHERNIY, ishlab chiqarilgan yili - 2023 | E27: =dalolatnoma!E30 -> 165 000 000,00 (yuz oltmish besh million so'm)
A28: =dalolatnoma!A22:E22 -> -* avtotransport egasi: BEKOV OTABEK BAXODIROVICH
A29: =dalolatnoma!A23:E23 -> -* texnik pasport: AAG 5923045 28.03.2025y.
A30: =dalolatnoma!A24:E24 -> -* roʻyxatdan oʻtgan manzili/garaj manzili: XORAZM VILOYATI URGANCH TUMANI GOYBU QFY OQ MAKTAB MFY
A31: =dalolatnoma!A25:E25 -> -* davlat raqami: 90C477ZA
A33: ="6. «"&malumot!B153&"» АJ sug‘urta kompaniyasi tomonidan Mikroqarz to'lamaslik xavfini "&FIXED(malumot!B154,2)&"("&malumot!B155&") so ' m miqdoriga sug’urta qilish" -> 6. «АО "APEX INSURANCE"» АJ sug‘urta kompaniyasi tomonidan Mikroqarz to'lamaslik xavfini 15 000 000,00(o'n besh million so'm) so ' m miqdoriga sug’urta qilish
A34: ="7. Boshqa shartlar – "&IF(malumot!B110=malumot!B111,"avtotransport vositasi",IF(malumot!B110=malumot!C111,"ko'chmas mulk",0))&" shaklida garov ta'minlangandan keyin "&malumot!B65&" berish." -> 7. Boshqa shartlar – 0 shaklida garov ta'minlangandan keyin mikrokredit berish.
A36: Qaror bir ovozdan qabul qilindi.
A41: =malumot!B157&" ijrochi direktori" -> «CLEVER MIKROMOLIYA TASHKILOTI» MChJ ijrochi direktori | D41: N. Abduraximov
A45: =malumot!A169 -> Kreditlash bo’limi boshlig’i | D45: =malumot!B169 -> B. Mominov
A49: =malumot!A170 -> Monitoring bo’limi boshlig’i | D49: =malumot!B170 -> B. Jumanazarov

Sheet График дифференц
E1: Приложение №1
F2: ="к договору микрозайма "&malumot!B74&"" -> к договору микрозайма 7 aprel 2025 y.dan №717-XMS
A4: График погашения
L5: =malumot!B82 -> 36
A6: № | B6: Дата погашения | C6: Остаток основного долга | D6: Сумма погашения, сум
D7: основного долга | E7: процентов* | F7: всего*
A8: 1 | B8: =malumot!B80 -> 45778 | C8: =malumot!B76 -> 125000000 | D8: =IF(IF(C8=0,L8,IF(C8>1,I8))="",0,(IF(C8=0,L8,IF(C8>1,I8)))) -> 3472222.2 | E8: =IF(C8=0,N6,IF(C8>1,L8)) -> 4520547.8 | F8: =IF(C8=0,O6,IF(C8>1,M8)) -> 7992770.1 | G8: =B8-malumot!B67 -> 24 | H8: =DATE(YEAR(B8),12,31)-DATE(YEAR(B8),1,1)+1 -> 365 | I8: =IF(malumot!B84=0,ROUND(C8/L5,2),"") -> 3472222.2 | L8: =ROUND(C8*malumot!$B$85/H8,2)*G8 -> 4520547.8 | M8: =D8+E8 -> 7992770.1 | O8: =TEXT(B8,"ддд") -> Чт | P8: =IF(O8=$U$8,2,IF(O8=$V$8,1,0)) -> 0 | Q8: =DAY(malumot!$B$79)+P8 -> 1 | S8: Чт | T8: Пт | U8: Сб | V8: Вс
A9: 2 | B9: =IF(A9<=malumot!$B$82,DATE(YEAR(R9),MONTH(R9),DAY(IF(A9=malumot!$B$82,malumot!$B$67,IF(A9<malumot!$B$82,(Q9),IF(A9>malumot!$B$82,$H$56,0)))))) -> 45810 | C9: =C8-D8 -> 1.2152778e+08 | D9: =IF(C9=0,L9,IF(C9>1,I9)) -> 3472222.2 | E9: =IF(C9=0,N8,IF(C9>1,L9)) -> 5859969.6 | F9: =IF(C9=0,N8,IF(C9>1,M9)) -> 9332191.8 | G9: =B9-B8 -> 32 | H9: =DATE(YEAR(B9),12,31)-DATE(YEAR(B9),1,1)+1 -> 365 | I9: =IF(I8="",ROUND(C8/(L5-1),2),I8) -> 3472222.2 | L9: =ROUND(C9*malumot!$B$85/H9,2)*G9 -> 5859969.6 | M9: =D9+E9 -> 9332191.8 | O9: =TEXT(R9,"ддд") -> Вс | P9: =IF(O9=$U$8,2,IF(O9=$V$8,1,0)) -> 1 | Q9: =DAY(malumot!$B$79)+P9 -> 2 | R9: =IF(A9<=malumot!$B$82,DATE(YEAR($B$8),MONTH($B$8)+A8,DAY(malumot!$B$79)),0) -> 45809
A10: 3 | B10: =IF(A10<=malumot!$B$82,DATE(YEAR(R10),MONTH(R10),DAY(IF(A10=malumot!$B$82,malumot!$B$67,IF(A10<malumot!$B$82,(Q10),IF(A10>malumot!$B$82,$H$56,0)))))) -> 45839 | C10: =C9-D9 -> 1.1805556e+08 | D10: =IF(C10=0,L10,IF(C10>1,I10)) -> 3472222.2 | E10: =IF(C10=0,N9,IF(C10>1,L10)) -> 5158866 | F10: =IF(C10=0,N9,IF(C10>1,M10)) -> 8631088.2 | G10: =B10-B9 -> 29 | H10: =DATE(YEAR(B10),12,31)-DATE(YEAR(B10),1,1)+1 -> 365 | I10: =I9 -> 3472222.2 | L10: =ROUND(C10*malumot!$B$85/H10,2)*G10 -> 5158866 | M10: =D10+E10 -> 8631088.2 | O10: =TEXT(R10,"ддд") -> Вт | P10: =IF(O10=$U$8,2,IF(O10=$V$8,1,0)) -> 0 | Q10: =DAY(malumot!$B$79)+P10 -> 1 | R10: =IF(A10<=malumot!$B$82,DATE(YEAR($B$8),MONTH($B$8)+A9,DAY(malumot!$B$79)),0) -> 45839
A11: 4 | B11: =IF(A11<=malumot!$B$82,DATE(YEAR(R11),MONTH(R11),DAY(IF(A11=malumot!$B$82,malumot!$B$67,IF(A11<malumot!$B$82,(Q11),IF(A11>malumot!$B$82,$H$56,0)))))) -> 45870 | C11: =C10-D10 -> 1.1458333e+08 | D11: =IF(C11=0,L11,IF(C11>1,I11)) -> 3472222.2 | E11: =IF(C11=0,N10,IF(C11>1,L11)) -> 5352454.4 | F11: =IF(C11=0,N10,IF(C11>1,M11)) -> 8824676.6 | G11: =B11-B10 -> 31 | H11: =DATE(YEAR(B11),12,31)-DATE(YEAR(B11),1,1)+1 -> 365 | I11: =I10 -> 3472222.2 | L11: =ROUND(C11*malumot!$B$85/H11,2)*G11 -> 5352454.4 | M11: =D11+E11 -> 8824676.6 | O11: =TEXT(R11,"ддд") -> Пт | P11: =IF(O11=$U$8,2,IF(O11=$V$8,1,0)) -> 0 | Q11: =DAY(malumot!$B$79)+P11 -> 1 | R11: =IF(A11<=malumot!$B$82,DATE(YEAR($B$8),MONTH($B$8)+A10,DAY(malumot!$B$79)),0) -> 45870
A12: 5 | B12: =IF(A12<=malumot!$B$82,DATE(YEAR(R12),MONTH(R12),DAY(IF(A12=malumot!$B$82,malumot!$B$67,IF(A12<malumot!$B$82,(Q12),IF(A12>malumot!$B$82,$H$56,0)))))) -> 45901 | C12: =C11-D11 -> 1.1111111e+08 | D12: =IF(C12=0,L12,IF(C12>1,I12)) -> 3472222.2 | E12: =IF(C12=0,N11,IF(C12>1,L12)) -> 5190258.7 | F12: =IF(C12=0,N11,IF(C12>1,M12)) -> 8662480.9 | G12: =B12-B11 -> 31 | H12: =DATE(YEAR(B12),12,31)-DATE(YEAR(B12),1,1)+1 -> 365 | I12: =I11 -> 3472222.2 | J12: =malumot!B76 -> 125000000 | L12: =ROUND(C12*malumot!$B$85/H12,2)*G12 -> 5190258.7 | M12: =D12+E12 -> 8662480.9 | O12: =TEXT(R12,"ддд") -> Пн | P12: =IF(O12=$U$8,2,IF(O12=$V$8,1,0)) -> 0 | Q12: =DAY(malumot!$B$79)+P12 -> 1 | R12: =IF(A12<=malumot!$B$82,DATE(YEAR($B$8),MONTH($B$8)+A11,DAY(malumot!$B$79)),0) -> 45901
A13: 6 | B13: =IF(A13<=malumot!$B$82,DATE(YEAR(R13),MONTH(R13),DAY(IF(A13=malumot!$B$82,malumot!$B$67,IF(A13<malumot!$B$82,(Q13),IF(A13>malumot!$B$82,$H$56,0)))))) -> 45931 | C13: =C12-D12 -> 1.0763889e+08 | D13: =IF(C13=0,L13,IF(C13>1,I13)) -> 3472222.2 | E13: =IF(C13=0,N12,IF(C13>1,L13)) -> 4865867.7 | F13: =IF(C13=0,N12,IF(C13>1,M13)) -> 8338089.9 | G13: =B13-B12 -> 30 | H13: =DATE(YEAR(B13),12,31)-DATE(YEAR(B13),1,1)+1 -> 365 | I13: =IF(L5=H1,K13,IF(L5>H1,I12)) -> 3472222.2 | J13: =SUM($I$8:I12) -> 17361111 | K13: =$J$12-J13 -> 1.0763889e+08 | L13: =ROUND(C13*malumot!$B$85/H13,2)*G13 -> 4865867.7 | M13: =D13+E13 -> 8338089.9 | O13: =TEXT(R13,"ддд") -> Ср | P13: =IF(O13=$U$8,2,IF(O13=$V$8,1,0)) -> 0 | Q13: =DAY(malumot!$B$79)+P13 -> 1 | R13: =IF(A13<=malumot!$B$82,DATE(YEAR($B$8),MONTH($B$8)+A12,DAY(malumot!$B$79)),0) -> 45931
A14: 7 | B14: =IF(A14<=malumot!$B$82,DATE(YEAR(R14),MONTH(R14),DAY(IF(A14=malumot!$B$82,malumot!$B$67,IF(A14<malumot!$B$82,(Q14),IF(A14>malumot!$B$82,$H$56,0)))))) -> 45964 | C14: =C13-D13 -> 1.0416667e+08 | D14: =IF(C14=0,L14,IF(C14>1,I14)) -> 3472222.2 | E14: =IF(C14=0,N13,IF(C14>1,L14)) -> 5179794.5 | F14: =IF(C14=0,N13,IF(C14>1,M14)) -> 8652016.7 | G14: =B14-B13 -> 33 | H14: =DATE(YEAR(B14),12,31)-DATE(YEAR(B14),1,1)+1 -> 365 | I14: =IF($L$5=A14,K14,IF($L$5>A14,I13)) -> 3472222.2 | J14: =SUM($I$8:I13) -> 20833333 | K14: =$J$12-J14 -> 1.0416667e+08 | L14: =ROUND(C14*malumot!$B$85/H14,2)*G14 -> 5179794.5 | M14: =D14+E14 -> 8652016.7 | O14: =TEXT(R14,"ддд") -> Сб | P14: =IF(O14=$U$8,2,IF(O14=$V$8,1,0)) -> 2 | Q14: =DAY(malumot!$B$79)+P14 -> 3 | R14: =IF(A14<=malumot!$B$82,DATE(YEAR($B$8),MONTH($B$8)+A13,DAY(malumot!$B$79)),0) -> 45962
A15: 8 | B15: =IF(A15<=malumot!$B$82,DATE(YEAR(R15),MONTH(R15),DAY(IF(A15=malumot!$B$82,malumot!$B$67,IF(A15<malumot!$B$82,(Q15),IF(A15>malumot!$B$82,$H$56,0)))))) -> 45992 | C15: =C14-D14 -> 1.0069444e+08 | D15: =IF(C15=0,L15,IF(C15>1,I15)) -> 3472222.2 | E15: =IF(C15=0,N14,IF(C15>1,L15)) -> 4248477.8 | F15: =IF(C15=0,N14,IF(C15>1,M15)) -> 7720700 | G15: =B15-B14 -> 28 | H15: =DATE(YEAR(B15),12,31)-DATE(YEAR(B15),1,1)+1 -> 365 | I15: =IF($L$5=A15,K15,IF($L$5>A15,I14)) -> 3472222.2 | J15: =SUM($I$8:I14) -> 24305556 | K15: =$J$12-J15 -> 1.0069444e+08 | L15: =ROUND(C15*malumot!$B$85/H15,2)*G15 -> 4248477.8 | M15: =D15+E15 -> 7720700 | O15: =TEXT(R15,"ддд") -> Пн | P15: =IF(O15=$U$8,2,IF(O15=$V$8,1,0)) -> 0 | Q15: =DAY(malumot!$B$79)+P15 -> 1 | R15: =IF(A15<=malumot!$B$82,DATE(YEAR($B$8),MONTH($B$8)+A14,DAY(malumot!$B$79)),0) -> 45992
A16: 9 | B16: =IF(A16<=malumot!$B$82,DATE(YEAR(R16),MONTH(R16),DAY(IF(A16=malumot!$B$82,malumot!$B$67,IF(A16<malumot!$B$82,(Q16),IF(A16>malumot!$B$82,$H$56,0)))))) -> 46023 | C16: =C15-D15 -> 97222222 | D16: =IF(C16=0,L16,IF(C16>1,I16)) -> 3472222.2 | E16: =IF(C16=0,N15,IF(C16>1,L16)) -> 4541476.4 | F16: =IF(C16=0,N15,IF(C16>1,M16)) -> 8013698.7 | G16: =B16-B15 -> 31 | H16: =DATE(YEAR(B16),12,31)-DATE(YEAR(B16),1,1)+1 -> 365 | I16: =IF($L$5=A16,K16,IF($L$5>A16,I15)) -> 3472222.2 | J16: =SUM($I$8:I15) -> 27777778 | K16: =$J$12-J16 -> 97222222 | L16: =ROUND(C16*malumot!$B$85/H16,2)*G16 -> 4541476.4 | M16: =D16+E16 -> 8013698.7 | O16: =TEXT(R16,"ддд") -> Чт | P16: =IF(O16=$U$8,2,IF(O16=$V$8,1,0)) -> 0 | Q16: =DAY(malumot!$B$79)+P16 -> 1 | R16: =IF(A16<=malumot!$B$82,DATE(YEAR($B$8),MONTH($B$8)+A15,DAY(malumot!$B$79)),0) -> 46023
A17: 10 | B17: =IF(A17<=malumot!$B$82,DATE(YEAR(R17),MONTH(R17),DAY(IF(A17=malumot!$B$82,malumot!$B$67,IF(A17<malumot!$B$82,(Q17),IF(A17>malumot!$B$82,$H$56,0)))))) -> 46055 | C17: =C16-D16 -> 93750000 | D17: =IF(C17=0,L17,IF(C17>1,I17)) -> 3472222.2 | E17: =IF(C17=0,N16,IF(C17>1,L17)) -> 4520547.8 | F17: =IF(C17=0,N16,IF(C17>1,M17)) -> 7992770.1 | G17: =B17-B16 -> 32 | H17: =DATE(YEAR(B17),12,31)-DATE(YEAR(B17),1,1)+1 -> 365 | I17: =IF($L$5=A17,K17,IF($L$5>A17,I16)) -> 3472222.2 | J17: =SUM($I$8:I16) -> 31250000 | K17: =$J$12-J17 -> 93750000 | L17: =ROUND(C17*malumot!$B$85/H17,2)*G17 -> 4520547.8 | M17: =D17+E17 -> 7992770.1 | O17: =TEXT(R17,"ддд") -> Вс | P17: =IF(O17=$U$8,2,IF(O17=$V$8,1,0)) -> 1 | Q17: =DAY(malumot!$B$79)+P17 -> 2 | R17: =IF(A17<=malumot!$B$82,DATE(YEAR($B$8),MONTH($B$8)+A16,DAY(malumot!$B$79)),0) -> 46054
A18: 11 | B18: =IF(A18<=malumot!$B$82,DATE(YEAR(R18),MONTH(R18),DAY(IF(A18=malumot!$B$82,malumot!$B$67,IF(A18<malumot!$B$82,(Q18),IF(A18>malumot!$B$82,$H$56,0)))))) -> 46083 | C18: =C17-D17 -> 90277778 | D18: =IF(C18=0,L18,IF(C18>1,I18)) -> 3472222.2 | E18: =IF(C18=0,N17,IF(C18>1,L18)) -> 3808980.3 | F18: =IF(C18=0,N17,IF(C18>1,M18)) -> 7281202.5 | G18: =B18-B17 -> 28 | H18: =DATE(YEAR(B18),12,31)-DATE(YEAR(B18),1,1)+1 -> 365 | I18: =IF($L$5=A18,K18,IF($L$5>A18,I17)) -> 3472222.2 | J18: =SUM($I$8:I17) -> 34722222 | K18: =$J$12-J18 -> 90277778 | L18: =ROUND(C18*malumot!$B$85/H18,2)*G18 -> 3808980.3 | M18: =D18+E18 -> 7281202.5 | O18: =TEXT(R18,"ддд") -> Вс | P18: =IF(O18=$U$8,2,IF(O18=$V$8,1,0)) -> 1 | Q18: =DAY(malumot!$B$79)+P18 -> 2 | R18: =IF(A18<=malumot!$B$82,DATE(YEAR($B$8),MONTH($B$8)+A17,DAY(malumot!$B$79)),0) -> 46082
A19: 12 | B19: =IF(A19<=malumot!$B$82,DATE(YEAR(R19),MONTH(R19),DAY(IF(A19=malumot!$B$82,malumot!$B$67,IF(A19<malumot!$B$82,(Q19),IF(A19>malumot!$B$82,$H$56,0)))))) -> 46113 | C19: =C18-D18 -> 86805556 | D19: =IF(C19=0,L19,IF(C19>1,I19)) -> 3472222.2 | E19: =IF(C19=0,N18,IF(C19>1,L19)) -> 3924086.7 | F19: =IF(C19=0,N18,IF(C19>1,M19)) -> 7396308.9 | G19: =B19-B18 -> 30 | H19: =DATE(YEAR(B19),12,31)-DATE(YEAR(B19),1,1)+1 -> 365 | I19: =IF($L$5=A19,K19,IF($L$5>A19,I18)) -> 3472222.2 | J19: =SUM($I$8:I18) -> 38194444 | K19: =$J$12-J19 -> 86805556 | L19: =ROUND(C19*malumot!$B$85/H19,2)*G19 -> 3924086.7 | M19: =D19+E19 -> 7396308.9 | O19: =TEXT(R19,"ддд") -> Ср | P19: =IF(O19=$U$8,2,IF(O19=$V$8,1,0)) -> 0 | Q19: =DAY(malumot!$B$79)+P19 -> 1 | R19: =IF(A19<=malumot!$B$82,DATE(YEAR($B$8),MONTH($B$8)+A18,DAY(malumot!$B$79)),0) -> 46113
A20: 13 | B20: =IF(A20<=malumot!$B$82,DATE(YEAR(R20),MONTH(R20),DAY(IF(A20=malumot!$B$82,malumot!$B$67,IF(A20<malumot!$B$82,(Q20),IF(A20>malumot!$B$82,$H$56,0)))))) -> 46143 | C20: =C19-D19 -> 83333333 | D20: =IF(C20=0,L20,IF(C20>1,I20)) -> 3472222.2 | E20: =IF(C20=0,N19,IF(C20>1,L20)) -> 3767123.4 | F20: =IF(C20=0,N19,IF(C20>1,M20)) -> 7239345.6 | G20: =B20-B19 -> 30 | H20: =DATE(YEAR(B20),12,31)-DATE(YEAR(B20),1,1)+1 -> 365 | I20: =IF($L$5=A20,K20,IF($L$5>A20,I19)) -> 3472222.2 | J20: =SUM($I$8:I19) -> 41666667 | K20: =$J$12-J20 -> 83333333 | L20: =ROUND(C20*malumot!$B$85/H20,2)*G20 -> 3767123.4 | M20: =D20+E20 -> 7239345.6 | O20: =TEXT(R20,"ддд") -> Пт | P20: =IF(O20=$U$8,2,IF(O20=$V$8,1,0)) -> 0 | Q20: =DAY(malumot!$B$79)+P20 -> 1 | R20: =IF(A20<=malumot!$B$82,DATE(YEAR($B$8),MONTH($B$8)+A19,DAY(malumot!$B$79)),0) -> 46143
A21: 14 | B21: =IF(A21<=malumot!$B$82,DATE(YEAR(R21),MONTH(R21),DAY(IF(A21=malumot!$B$82,malumot!$B$67,IF(A21<malumot!$B$82,(Q21),IF(A21>malumot!$B$82,$H$56,0)))))) -> 46174 | C21: =C20-D20 -> 79861111 | D21: =IF(C21=0,L21,IF(C21>1,I21)) -> 3472222.2 | E21: =IF(C21=0,N20,IF(C21>1,L21)) -> 3730498.5 | F21: =IF(C21=0,N20,IF(C21>1,M21)) -> 7202720.7 | G21: =B21-B20 -> 31 | H21: =DATE(YEAR(B21),12,31)-DATE(YEAR(B21),1,1)+1 -> 365 | I21: =IF($L$5=A21,K21,IF($L$5>A21,I20)) -> 3472222.2 | J21: =SUM($I$8:I20) -> 45138889 | K21: =$J$12-J21 -> 79861111 | L21: =ROUND(C21*malumot!$B$85/H21,2)*G21 -> 3730498.5 | M21: =D21+E21 -> 7202720.7 | O21: =TEXT(R21,"ддд") -> Пн | P21: =IF(O21=$U$8,2,IF(O21=$V$8,1,0)) -> 0 | Q21: =DAY(malumot!$B$79)+P21 -> 1 | R21: =IF(A21<=malumot!$B$82,DATE(YEAR($B$8),MONTH($B$8)+A20,DAY(malumot!$B$79)),0) -> 46174
A22: 15 | B22: =IF(A22<=malumot!$B$82,DATE(YEAR(R22),MONTH(R22),DAY(IF(A22=malumot!$B$82,malumot!$B$67,IF(A22<malumot!$B$82,(Q22),IF(A22>malumot!$B$82,$H$56,0)))))) -> 46204 | C22: =C21-D21 -> 76388889 | D22: =IF(C22=0,L22,IF(C22>1,I22)) -> 3472222.2 | E22: =IF(C22=0,N21,IF(C22>1,L22)) -> 3453196.2 | F22: =IF(C22=0,N21,IF(C22>1,M22)) -> 6925418.4 | G22: =B22-B21 -> 30 | H22: =DATE(YEAR(B22),12,31)-DATE(YEAR(B22),1,1)+1 -> 365 | I22: =IF($L$5=A22,K22,IF($L$5>A22,I21)) -> 3472222.2 | J22: =SUM($I$8:I21) -> 48611111 | K22: =$J$12-J22 -> 76388889 | L22: =ROUND(C22*malumot!$B$85/H22,2)*G22 -> 3453196.2 | M22: =D22+E22 -> 6925418.4 | O22: =TEXT(R22,"ддд") -> Ср | P22: =IF(O22=$U$8,2,IF(O22=$V$8,1,0)) -> 0 | Q22: =DAY(malumot!$B$79)+P22 -> 1 | R22: =IF(A22<=malumot!$B$82,DATE(YEAR($B$8),MONTH($B$8)+A21,DAY(malumot!$B$79)),0) -> 46204
A23: 16 | B23: =IF(A23<=malumot!$B$82,DATE(YEAR(R23),MONTH(R23),DAY(IF(A23=malumot!$B$82,malumot!$B$67,IF(A23<malumot!$B$82,(Q23),IF(A23>malumot!$B$82,$H$56,0)))))) -> 46237 | C23: =C22-D22 -> 72916667 | D23: =IF(C23=0,L23,IF(C23>1,I23)) -> 3472222.2 | E23: =IF(C23=0,N22,IF(C23>1,L23)) -> 3625856.2 | F23: =IF(C23=0,N22,IF(C23>1,M23)) -> 7098078.4 | G23: =B23-B22 -> 33 | H23: =DATE(YEAR(B23),12,31)-DATE(YEAR(B23),1,1)+1 -> 365 | I23: =IF($L$5=A23,K23,IF($L$5>A23,I22)) -> 3472222.2 | J23: =SUM($I$8:I22) -> 52083333 | K23: =$J$12-J23 -> 72916667 | L23: =ROUND(C23*malumot!$B$85/H23,2)*G23 -> 3625856.2 | M23: =D23+E23 -> 7098078.4 | O23: =TEXT(R23,"ддд") -> Сб | P23: =IF(O23=$U$8,2,IF(O23=$V$8,1,0)) -> 2 | Q23: =DAY(malumot!$B$79)+P23 -> 3 | R23: =IF(A23<=malumot!$B$82,DATE(YEAR($B$8),MONTH($B$8)+A22,DAY(malumot!$B$79)),0) -> 46235
A24: 17 | B24: =IF(A24<=malumot!$B$82,DATE(YEAR(R24),MONTH(R24),DAY(IF(A24=malumot!$B$82,malumot!$B$67,IF(A24<malumot!$B$82,(Q24),IF(A24>malumot!$B$82,$H$56,0)))))) -> 46266 | C24: =C23-D23 -> 69444444 | D24: =IF(C24=0,L24,IF(C24>1,I24)) -> 3472222.2 | E24: =IF(C24=0,N23,IF(C24>1,L24)) -> 3034627 | F24: =IF(C24=0,N23,IF(C24>1,M24)) -> 6506849.2 | G24: =B24-B23 -> 29 | H24: =DATE(YEAR(B24),12,31)-DATE(YEAR(B24),1,1)+1 -> 365 | I24: =IF($L$5=A24,K24,IF($L$5>A24,I23)) -> 3472222.2 | J24: =SUM($I$8:I23) -> 55555556 | K24: =$J$12-J24 -> 69444444 | L24: =ROUND(C24*malumot!$B$85/H24,2)*G24 -> 3034627 | M24: =D24+E24 -> 6506849.2 | O24: =TEXT(R24,"ддд") -> Вт | P24: =IF(O24=$U$8,2,IF(O24=$V$8,1,0)) -> 0 | Q24: =DAY(malumot!$B$79)+P24 -> 1 | R24: =IF(A24<=malumot!$B$82,DATE(YEAR($B$8),MONTH($B$8)+A23,DAY(malumot!$B$79)),0) -> 46266
A25: 18 | B25: =IF(A25<=malumot!$B$82,DATE(YEAR(R25),MONTH(R25),DAY(IF(A25=malumot!$B$82,malumot!$B$67,IF(A25<malumot!$B$82,(Q25),IF(A25>malumot!$B$82,$H$56,0)))))) -> 46296 | C25: =C24-D24 -> 65972222 | D25: =IF(C25=0,L25,IF(C25>1,I25)) -> 3472222.2 | E25: =IF(C25=0,N24,IF(C25>1,L25)) -> 2982306 | F25: =IF(C25=0,N24,IF(C25>1,M25)) -> 6454528.2 | G25: =B25-B24 -> 30 | H25: =DATE(YEAR(B25),12,31)-DATE(YEAR(B25),1,1)+1 -> 365 | I25: =IF($L$5=A25,K25,IF($L$5>A25,I24)) -> 3472222.2 | J25: =SUM($I$8:I24) -> 59027778 | K25: =$J$12-J25 -> 65972222 | L25: =ROUND(C25*malumot!$B$85/H25,2)*G25 -> 2982306 | M25: =D25+E25 -> 6454528.2 | O25: =TEXT(R25,"ддд") -> Чт | P25: =IF(O25=$U$8,2,IF(O25=$V$8,1,0)) -> 0 | Q25: =DAY(malumot!$B$79)+P25 -> 1 | R25: =IF(A25<=malumot!$B$82,DATE(YEAR($B$8),MONTH($B$8)+A24,DAY(malumot!$B$79)),0) -> 46296
... A31: 24 | B31: =IF(A31<=malumot!$B$82,DATE(YEAR(R31),MONTH(R31),DAY(IF(A31=malumot!$B$82,malumot!$B$67,IF(A31<malumot!$B$82,(Q31),IF(A31>malumot!$B$82,$H$56,0)))))) -> 46478 | C31: =C30-D30 -> 45138889 | D31: =IF(C31=0,L31,IF(C31>1,I31)) -> 3472222.2 | E31: =IF(C31=0,N30,IF(C31>1,L31)) -> 2108542.5 | F31: =IF(C31=0,N30,IF(C31>1,M31)) -> 5580764.7 | G31: =B31-B30 -> 31 | H31: =DATE(YEAR(B31),12,31)-DATE(YEAR(B31),1,1)+1 -> 365 | I31: =IF($L$5=A31,K31,IF($L$5>A31,I30)) -> 3472222.2 | J31: =SUM($I$8:I30) -> 79861111 | K31: =$J$12-J31 -> 45138889 | L31: =ROUND(C31*malumot!$B$85/H31,2)*G31 -> 2108542.5 | M31: =D31+E31 -> 5580764.7 | O31: =TEXT(R31,"ддд") -> Чт | P31: =IF(O31=$U$8,2,IF(O31=$V$8,1,0)) -> 0 | Q31: =DAY(malumot!$B$79)+P31 -> 1 | R31: =IF(A31<=malumot!$B$82,DATE(YEAR($B$8),MONTH($B$8)+A30,DAY(malumot!$B$79)),0) -> 46478
A32: =1+A31 -> 25 | B32: =IF(A32<=malumot!$B$82,DATE(YEAR(R32),MONTH(R32),DAY(IF(A32=malumot!$B$82,malumot!$B$67,IF(A32<malumot!$B$82,(Q32),IF(A32>malumot!$B$82,$H$56,0)))))) -> 46510 | C32: =C31-D31 -> 41666667 | D32: =IF(C32=0,L32,IF(C32>1,I32)) -> 3472222.2 | E32: =IF(C32=0,N31,IF(C32>1,L32)) -> 2009132.5 | F32: =IF(C32=0,N31,IF(C32>1,M32)) -> 5481354.7 | G32: =B32-B31 -> 32 | H32: =DATE(YEAR(B32),12,31)-DATE(YEAR(B32),1,1)+1 -> 365 | I32: =IF($L$5=A32,K32,IF($L$5>A32,I31)) -> 3472222.2 | J32: =SUM($I$8:I31) -> 83333333 | K32: =$J$12-J32 -> 41666667 | L32: =ROUND(C32*malumot!$B$85/H32,2)*G32 -> 2009132.5 | M32: =D32+E32 -> 5481354.7 | O32: =TEXT(R32,"ддд") -> Сб | P32: =IF(O32=$U$8,2,IF(O32=$V$8,1,0)) -> 2 | Q32: =DAY(malumot!$B$79)+P32 -> 3 | R32: =IF(A32<=malumot!$B$82,DATE(YEAR($B$8),MONTH($B$8)+A31,DAY(malumot!$B$79)),0) -> 46508
A33: =1+A32 -> 26 | B33: =IF(A33<=malumot!$B$82,DATE(YEAR(R33),MONTH(R33),DAY(IF(A33=malumot!$B$82,malumot!$B$67,IF(A33<malumot!$B$82,(Q33),IF(A33>malumot!$B$82,$H$56,0)))))) -> 46539 | C33: =C32-D32 -> 38194445 | D33: =IF(C33=0,L33,IF(C33>1,I33)) -> 3472222.2 | E33: =IF(C33=0,N32,IF(C33>1,L33)) -> 1669044.8 | F33: =IF(C33=0,N32,IF(C33>1,M33)) -> 5141267 | G33: =B33-B32 -> 29 | H33: =DATE(YEAR(B33),12,31)-DATE(YEAR(B33),1,1)+1 -> 365 | I33: =IF($L$5=A33,K33,IF($L$5>A33,I32)) -> 3472222.2 | J33: =SUM($I$8:I32) -> 86805555 | K33: =$J$12-J33 -> 38194445 | L33: =ROUND(C33*malumot!$B$85/H33,2)*G33 -> 1669044.8 | M33: =D33+E33 -> 5141267 | O33: =TEXT(R33,"ддд") -> Вт | P33: =IF(O33=$U$8,2,IF(O33=$V$8,1,0)) -> 0 | Q33: =DAY(malumot!$B$79)+P33 -> 1 | R33: =IF(A33<=malumot!$B$82,DATE(YEAR($B$8),MONTH($B$8)+A32,DAY(malumot!$B$79)),0) -> 46539
A34: =1+A33 -> 27 | B34: =IF(A34<=malumot!$B$82,DATE(YEAR(R34),MONTH(R34),DAY(IF(A34=malumot!$B$82,malumot!$B$67,IF(A34<malumot!$B$82,(Q34),IF(A34>malumot!$B$82,$H$56,0)))))) -> 46569 | C34: =C33-D33 -> 34722222 | D34: =IF(C34=0,L34,IF(C34>1,I34)) -> 3472222.2 | E34: =IF(C34=0,N33,IF(C34>1,L34)) -> 1569634.8 | F34: =IF(C34=0,N33,IF(C34>1,M34)) -> 5041857 | G34: =B34-B33 -> 30 | H34: =DATE(YEAR(B34),12,31)-DATE(YEAR(B34),1,1)+1 -> 365 | I34: =IF($L$5=A34,K34,IF($L$5>A34,I33)) -> 3472222.2 | J34: =SUM($I$8:I33) -> 90277778 | K34: =$J$12-J34 -> 34722222 | L34: =ROUND(C34*malumot!$B$85/H34,2)*G34 -> 1569634.8 | M34: =D34+E34 -> 5041857 | O34: =TEXT(R34,"ддд") -> Чт | P34: =IF(O34=$U$8,2,IF(O34=$V$8,1,0)) -> 0 | Q34: =DAY(malumot!$B$79)+P34 -> 1 | R34: =IF(A34<=malumot!$B$82,DATE(YEAR($B$8),MONTH($B$8)+A33,DAY(malumot!$B$79)),0) -> 46569
A35: =1+A34 -> 28 | B35: =IF(A35<=malumot!$B$82,DATE(YEAR(R35),MONTH(R35),DAY(IF(A35=malumot!$B$82,malumot!$B$67,IF(A35<malumot!$B$82,(Q35),IF(A35>malumot!$B$82,$H$56,0)))))) -> 46601 | C35: =C34-D34 -> 31250000 | D35: =IF(C35=0,L35,IF(C35>1,I35)) -> 3472222.2 | E35: =IF(C35=0,N34,IF(C35>1,L35)) -> 1506849.3 | F35: =IF(C35=0,N34,IF(C35>1,M35)) -> 4979071.5 | G35: =B35-B34 -> 32 | H35: =DATE(YEAR(B35),12,31)-DATE(YEAR(B35),1,1)+1 -> 365 | I35: =IF($L$5=A35,K35,IF($L$5>A35,I34)) -> 3472222.2 | J35: =SUM($I$8:I34) -> 93750000 | K35: =$J$12-J35 -> 31250000 | L35: =ROUND(C35*malumot!$B$85/H35,2)*G35 -> 1506849.3 | M35: =D35+E35 -> 4979071.5 | O35: =TEXT(R35,"ддд") -> Вс | P35: =IF(O35=$U$8,2,IF(O35=$V$8,1,0)) -> 1 | Q35: =DAY(malumot!$B$79)+P35 -> 2 | R35: =IF(A35<=malumot!$B$82,DATE(YEAR($B$8),MONTH($B$8)+A34,DAY(malumot!$B$79)),0) -> 46600
A36: =1+A35 -> 29 | B36: =IF(A36<=malumot!$B$82,DATE(YEAR(R36),MONTH(R36),DAY(IF(A36=malumot!$B$82,malumot!$B$67,IF(A36<malumot!$B$82,(Q36),IF(A36>malumot!$B$82,$H$56,0)))))) -> 46631 | C36: =C35-D35 -> 27777778 | D36: =IF(C36=0,L36,IF(C36>1,I36)) -> 3472222.2 | E36: =IF(C36=0,N35,IF(C36>1,L36)) -> 1255707.9 | F36: =IF(C36=0,N35,IF(C36>1,M36)) -> 4727930.1 | G36: =B36-B35 -> 30 | H36: =DATE(YEAR(B36),12,31)-DATE(YEAR(B36),1,1)+1 -> 365 | I36: =IF($L$5=A36,K36,IF($L$5>A36,I35)) -> 3472222.2 | J36: =SUM($I$8:I35) -> 97222222 | K36: =$J$12-J36 -> 27777778 | L36: =ROUND(C36*malumot!$B$85/H36,2)*G36 -> 1255707.9 | M36: =D36+E36 -> 4727930.1 | O36: =TEXT(R36,"ддд") -> Ср | P36: =IF(O36=$U$8,2,IF(O36=$V$8,1,0)) -> 0 | Q36: =DAY(malumot!$B$79)+P36 -> 1 | R36: =IF(A36<=malumot!$B$82,DATE(YEAR($B$8),MONTH($B$8)+A35,DAY(malumot!$B$79)),0) -> 46631
A37: =1+A36 -> 30 | B37: =IF(A37<=malumot!$B$82,DATE(YEAR(R37),MONTH(R37),DAY(IF(A37=malumot!$B$82,malumot!$B$67,IF(A37<malumot!$B$82,(Q37),IF(A37>malumot!$B$82,$H$56,0)))))) -> 46661 | C37: =C36-D36 -> 24305556 | D37: =IF(C37=0,L37,IF(C37>1,I37)) -> 3472222.2 | E37: =IF(C37=0,N36,IF(C37>1,L37)) -> 1098744.3 | F37: =IF(C37=0,N36,IF(C37>1,M37)) -> 4570966.5 | G37: =B37-B36 -> 30 | H37: =DATE(YEAR(B37),12,31)-DATE(YEAR(B37),1,1)+1 -> 365 | I37: =IF($L$5=A37,K37,IF($L$5>A37,I36)) -> 3472222.2 | J37: =SUM($I$8:I36) -> 1.0069444e+08 | K37: =$J$12-J37 -> 24305556 | L37: =ROUND(C37*malumot!$B$85/H37,2)*G37 -> 1098744.3 | M37: =D37+E37 -> 4570966.5 | O37: =TEXT(R37,"ддд") -> Пт | P37: =IF(O37=$U$8,2,IF(O37=$V$8,1,0)) -> 0 | Q37: =DAY(malumot!$B$79)+P37 -> 1 | R37: =IF(A37<=malumot!$B$82,DATE(YEAR($B$8),MONTH($B$8)+A36,DAY(malumot!$B$79)),0) -> 46661
A38: =1+A37 -> 31 | B38: =IF(A38<=malumot!$B$82,DATE(YEAR(R38),MONTH(R38),DAY(IF(A38=malumot!$B$82,malumot!$B$67,IF(A38<malumot!$B$82,(Q38),IF(A38>malumot!$B$82,$H$56,0)))))) -> 46692 | C38: =C37-D37 -> 20833333 | D38: =IF(C38=0,L38,IF(C38>1,I38)) -> 3472222.2 | E38: =IF(C38=0,N37,IF(C38>1,L38)) -> 973173.39 | F38: =IF(C38=0,N37,IF(C38>1,M38)) -> 4445395.6 | G38: =B38-B37 -> 31 | H38: =DATE(YEAR(B38),12,31)-DATE(YEAR(B38),1,1)+1 -> 365 | I38: =IF($L$5=A38,K38,IF($L$5>A38,I37)) -> 3472222.2 | J38: =SUM($I$8:I37) -> 1.0416667e+08 | K38: =$J$12-J38 -> 20833333 | L38: =ROUND(C38*malumot!$B$85/H38,2)*G38 -> 973173.39 | M38: =D38+E38 -> 4445395.6 | O38: =TEXT(R38,"ддд") -> Пн | P38: =IF(O38=$U$8,2,IF(O38=$V$8,1,0)) -> 0 | Q38: =DAY(malumot!$B$79)+P38 -> 1 | R38: =IF(A38<=malumot!$B$82,DATE(YEAR($B$8),MONTH($B$8)+A37,DAY(malumot!$B$79)),0) -> 46692
A39: =1+A38 -> 32 | B39: =IF(A39<=malumot!$B$82,DATE(YEAR(R39),MONTH(R39),DAY(IF(A39=malumot!$B$82,malumot!$B$67,IF(A39<malumot!$B$82,(Q39),IF(A39>malumot!$B$82,$H$56,0)))))) -> 46722 | C39: =C38-D38 -> 17361111 | D39: =IF(C39=0,L39,IF(C39>1,I39)) -> 3472222.2 | E39: =IF(C39=0,N38,IF(C39>1,L39)) -> 784817.4 | F39: =IF(C39=0,N38,IF(C39>1,M39)) -> 4257039.6 | G39: =B39-B38 -> 30 | H39: =DATE(YEAR(B39),12,31)-DATE(YEAR(B39),1,1)+1 -> 365 | I39: =IF($L$5=A39,K39,IF($L$5>A39,I38)) -> 3472222.2 | J39: =SUM($I$8:I38) -> 1.0763889e+08 | K39: =$J$12-J39 -> 17361111 | L39: =ROUND(C39*malumot!$B$85/H39,2)*G39 -> 784817.4 | M39: =D39+E39 -> 4257039.6 | O39: =TEXT(R39,"ддд") -> Ср | P39: =IF(O39=$U$8,2,IF(O39=$V$8,1,0)) -> 0 | Q39: =DAY(malumot!$B$79)+P39 -> 1 | R39: =IF(A39<=malumot!$B$82,DATE(YEAR($B$8),MONTH($B$8)+A38,DAY(malumot!$B$79)),0) -> 46722
A40: =1+A39 -> 33 | B40: =IF(A40<=malumot!$B$82,DATE(YEAR(R40),MONTH(R40),DAY(IF(A40=malumot!$B$82,malumot!$B$67,IF(A40<malumot!$B$82,(Q40),IF(A40>malumot!$B$82,$H$56,0)))))) -> 46755 | C40: =C39-D39 -> 13888889 | D40: =IF(C40=0,L40,IF(C40>1,I40)) -> 3472222.2 | E40: =IF(C40=0,N39,IF(C40>1,L40)) -> 688752.24 | F40: =IF(C40=0,N39,IF(C40>1,M40)) -> 4160974.5 | G40: =B40-B39 -> 33 | H40: =DATE(YEAR(B40),12,31)-DATE(YEAR(B40),1,1)+1 -> 366 | I40: =IF($L$5=A40,K40,IF($L$5>A40,I39)) -> 3472222.2 | J40: =SUM($I$8:I39) -> 1.1111111e+08 | K40: =$J$12-J40 -> 13888889 | L40: =ROUND(C40*malumot!$B$85/H40,2)*G40 -> 688752.24 | M40: =D40+E40 -> 4160974.5 | O40: =TEXT(R40,"ддд") -> Сб | P40: =IF(O40=$U$8,2,IF(O40=$V$8,1,0)) -> 2 | Q40: =DAY(malumot!$B$79)+P40 -> 3 | R40: =IF(A40<=malumot!$B$82,DATE(YEAR($B$8),MONTH($B$8)+A39,DAY(malumot!$B$79)),0) -> 46753
A41: =1+A40 -> 34 | B41: =IF(A41<=malumot!$B$82,DATE(YEAR(R41),MONTH(R41),DAY(IF(A41=malumot!$B$82,malumot!$B$67,IF(A41<malumot!$B$82,(Q41),IF(A41>malumot!$B$82,$H$56,0)))))) -> 46784 | C41: =C40-D40 -> 10416667 | D41: =IF(C41=0,L41,IF(C41>1,I41)) -> 3472222.2 | E41: =IF(C41=0,N40,IF(C41>1,L41)) -> 453950.34 | F41: =IF(C41=0,N40,IF(C41>1,M41)) -> 3926172.6 | G41: =B41-B40 -> 29 | H41: =DATE(YEAR(B41),12,31)-DATE(YEAR(B41),1,1)+1 -> 366 | I41: =IF($L$5=A41,K41,IF($L$5>A41,I40)) -> 3472222.2 | J41: =SUM($I$8:I40) -> 1.1458333e+08 | K41: =$J$12-J41 -> 10416667 | L41: =ROUND(C41*malumot!$B$85/H41,2)*G41 -> 453950.34 | M41: =D41+E41 -> 3926172.6 | O41: =TEXT(R41,"ддд") -> Вт | P41: =IF(O41=$U$8,2,IF(O41=$V$8,1,0)) -> 0 | Q41: =DAY(malumot!$B$79)+P41 -> 1 | R41: =IF(A41<=malumot!$B$82,DATE(YEAR($B$8),MONTH($B$8)+A40,DAY(malumot!$B$79)),0) -> 46784
A42: =1+A41 -> 35 | B42: =IF(A42<=malumot!$B$82,DATE(YEAR(R42),MONTH(R42),DAY(IF(A42=malumot!$B$82,malumot!$B$67,IF(A42<malumot!$B$82,(Q42),IF(A42>malumot!$B$82,$H$56,0)))))) -> 46813 | C42: =C41-D41 -> 6944444.5 | D42: =IF(C42=0,L42,IF(C42>1,I42)) -> 3472222.2 | E42: =IF(C42=0,N41,IF(C42>1,L42)) -> 302633.56 | F42: =IF(C42=0,N41,IF(C42>1,M42)) -> 3774855.8 | G42: =B42-B41 -> 29 | H42: =DATE(YEAR(B42),12,31)-DATE(YEAR(B42),1,1)+1 -> 366 | I42: =IF($L$5=A42,K42,IF($L$5>A42,I41)) -> 3472222.2 | J42: =SUM($I$8:I41) -> 1.1805556e+08 | K42: =$J$12-J42 -> 6944444.5 | L42: =ROUND(C42*malumot!$B$85/H42,2)*G42 -> 302633.56 | M42: =D42+E42 -> 3774855.8 | O42: =TEXT(R42,"ддд") -> Ср | P42: =IF(O42=$U$8,2,IF(O42=$V$8,1,0)) -> 0 | Q42: =DAY(malumot!$B$79)+P42 -> 1 | R42: =IF(A42<=malumot!$B$82,DATE(YEAR($B$8),MONTH($B$8)+A41,DAY(malumot!$B$79)),0) -> 46813
A43: =1+A42 -> 36 | B43: =IF(A43<=malumot!$B$82,DATE(YEAR(R43),MONTH(R43),DAY(IF(A43=malumot!$B$82,malumot!$B$67,IF(A43<malumot!$B$82,(Q43),IF(A43>malumot!$B$82,$H$56,0)))))) -> 46850 | C43: =C42-D42 -> 3472222.3 | D43: =IF(C43=0,L43,IF(C43>1,I43)) -> 3472222.3 | E43: =IF(C43=0,N42,IF(C43>1,L43)) -> 193059.34 | F43: =IF(C43=0,N42,IF(C43>1,M43)) -> 3665281.6 | G43: =B43-B42 -> 37 | H43: =DATE(YEAR(B43),12,31)-DATE(YEAR(B43),1,1)+1 -> 366 | I43: =IF($L$5=A43,K43,IF($L$5>A43,I42)) -> 3472222.3 | J43: =SUM($I$8:I42) -> 1.2152778e+08 | K43: =$J$12-J43 -> 3472222.3 | L43: =ROUND(C43*malumot!$B$85/H43,2)*G43 -> 193059.34 | M43: =D43+E43 -> 3665281.6 | O43: =TEXT(R43,"ддд") -> Сб | P43: =IF(O43=$U$8,2,IF(O43=$V$8,1,0)) -> 2 | Q43: =DAY(malumot!$B$79)+P43 -> 3 | R43: =IF(A43<=malumot!$B$82,DATE(YEAR($B$8),MONTH($B$8)+A42,DAY(malumot!$B$79)),0) -> 46844
... A55: =1+A54 -> 48 | B55: =IF(A55<=malumot!$B$82,DATE(YEAR(R55),MONTH(R55),DAY(IF(A55=malumot!$B$82,malumot!$B$67,IF(A55<malumot!$B$82,(Q55),IF(A55>malumot!$B$82,$H$56,0)))))) -> FALSE | C55: =C54-D54 -> 7.9162419e-09 | D55: =IF(C55=0,L55,IF(C55>1,I55)) -> FALSE | E55: =IF(C55=0,N54,IF(C55>1,L55)) -> FALSE | F55: =IF(C55=0,N54,IF(C55>1,M55)) -> FALSE | G55: =B55-B54 -> 0 | H55: =DATE(YEAR(B55),12,31)-DATE(YEAR(B55),1,1)+1 -> 366 | I55: =IF($L$5=A55,K55,IF($L$5>A55,I54)) -> FALSE | J55: =SUM($I$8:I54) -> 125000000 | K55: =$J$12-J55 -> 0 | L55: =ROUND(C55*malumot!$B$85/H55,2)*G55 -> 0 | M55: =D55+E55 -> 0 | O55: =TEXT(R55,"ддд") -> Сб | P55: =IF(O55=$U$8,2,IF(O55=$V$8,1,0)) -> 2 | Q55: =DAY(malumot!$B$79)+P55 -> 3 | R55: =IF(A55<=malumot!$B$82,DATE(YEAR($B$8),MONTH($B$8)+A54,DAY(malumot!$B$79)),0) -> 0
B56: ИТОГО | D56: =SUM(D8:D55) -> 125000000 | E56: =SUM(E8:E55) -> 1.0505116e+08 | F56: =SUM(F8:F55) -> 2.3005116e+08
A58: *В случае осуществления погашения платежей по кредиту в даты, отличные от указанных в графике погашения, сумма платежа меняется на сумму процентов, которые начисляются на сумму остатка долга по микрозайму в соответствии с п.п. 2.2. настоящего договора.
A60: =#REF! -> #REF! | D60: =#REF! -> #REF!
A62: =#REF! -> #REF! | D62: =#REF! -> #REF!
A63: =#REF! -> #REF! | D63: =#REF! -> #REF!
A64: =#REF! -> #REF! | D64: ="паспорт серии "&malumot!B16&", "&malumot!B20&"" -> паспорт серии AC 2074678, XORAZM VILOYATI SHOVOT TUMANI IIB tomonidan 17.07.2019 yilda berilgan
A65: =#REF! -> #REF!
A66: =#REF! -> #REF! | D66: =#REF! -> #REF!
A67: =#REF! -> #REF! | D67: =#REF! -> #REF!
A68: =#REF! -> #REF! | D68: =#REF! -> #REF!
A70: =#REF! -> #REF! | D70: =#REF! -> #REF!
A72: =#REF! -> #REF! | D72: =#REF! -> #REF!
D74: =#REF! -> #REF!

Sheet Данные для послед. Залога
A1: № | B1: - | E1: ФИО | F1: дата | L1: № договора | M1: Сог. Сумма | N1: сог. Сумма (пропис.)
A2: 1 | B2: ha | C2: yoq | D2: ha | E2: TULYAGANOV XODJIAKBAR IRGASHEVICH | F2: 44207 | G2: =MONTH(F2) -> 1 | H2: =IF(G2=$A$26,$A$28,IF(G2=$B$26,$B$28,IF(G2=$C$26,$C$28,IF(G2=$D$26,$D$28,IF(G2=$E$26,$E$28,IF(G2=$F$26,$F$28,IF(G2=$K$26,$K$28,IF(G2=$L$26,$L$28,IF(G2=$M$26,$M$28,IF(G2=$N$26,$N$28,IF(G2=$O$26,$O$28,IF(G2=$P$26,$P$28,0)))))))))))) -> yanvar | I2: =DAY(F2) -> 11 | J2: =YEAR(F2) -> 2021 | K2: =""&I2&" "&H2&" "&J2&" г." -> 11 yanvar 2021 г. | L2: 5 | M2: 15000000 | N2: on besh million | O2: ="- №"&L2&" от "&K2&", заключенного с ООО «Clever Mikrokredit Tashkiloti» и "&E2&", по согласованной залоговой стоимость - "&FIXED(M2)&" ("&N2&") сум." -> - №5 от 11 yanvar 2021 г., заключенного с ООО «Clever Mikrokredit Tashkiloti» и TULYAGANOV XODJIAKBAR IRGASHEVICH, по согласованной залоговой стоимость - 15 000 000,00 (on besh million) сум. | P2: =IF(D2=$B$2,O2,IF(D2=$C$2,$B$1)) -> - №5 от 11 yanvar 2021 г., заключенного с ООО «Clever Mikrokredit Tashkiloti» и TULYAGANOV XODJIAKBAR IRGASHEVICH, по согласованной залоговой стоимость - 15 000 000,00 (on besh million) сум. | W2: =""&P2&" "&P3&" "&P4&" "&P5&" "&P6&" "&P7&" "&P8&" "&P9&" "&P10&" "&P11&" "&P12&" "&P13&" "&P14&" "&P15&" "&P16&" "&P17&" "&P18&" "&P19&" "&P20&" "&P21&"" -> - №5 от 11 yanvar 2021 г., заключенного с ООО «Clever Mikrokredit Tashkiloti» и TULYAGANOV XODJIAKBAR IRGASHEVICH, по согласованной залоговой стоимость - 15 000 000,00 (on besh million) сум. - №386 от 6 noyabr 2019 г., заключенного с ООО «Clever Mikrokredit Tashkiloti» и YUNUSOVA ZALOXAT MIRSULTANOVNA, по согласованной залоговой стоимость - 15 000 000,00 (on besh million) сум. - №33 от 21 yanvar 2021 г., заключенного с ООО «Clever Mikrokredit Tashkiloti» и YUNUSOVA ZALOXAT MIRSULTANOVNA, по согласованной залоговой стоимость - 15 000 000,00 (on besh million) сум. 0 0 0 0 0 0 0 0 0 0 0 0 0 0 0 0 0
A3: 2 | D3: ha | E3: YUNUSOVA ZALOXAT MIRSULTANOVNA | F3: 43775 | G3: =MONTH(F3) -> 11 | H3: =IF(G3=$A$26,$A$28,IF(G3=$B$26,$B$28,IF(G3=$C$26,$C$28,IF(G3=$D$26,$D$28,IF(G3=$E$26,$E$28,IF(G3=$F$26,$F$28,IF(G3=$K$26,$K$28,IF(G3=$L$26,$L$28,IF(G3=$M$26,$M$28,IF(G3=$N$26,$N$28,IF(G3=$O$26,$O$28,IF(G3=$P$26,$P$28,0)))))))))))) -> noyabr | I3: =DAY(F3) -> 6 | J3: =YEAR(F3) -> 2019 | K3: =""&I3&" "&H3&" "&J3&" г." -> 6 noyabr 2019 г. | L3: 386 | M3: 15000000 | N3: on besh million | O3: ="- №"&L3&" от "&K3&", заключенного с ООО «Clever Mikrokredit Tashkiloti» и "&E3&", по согласованной залоговой стоимость - "&FIXED(M3)&" ("&N3&") сум." -> - №386 от 6 noyabr 2019 г., заключенного с ООО «Clever Mikrokredit Tashkiloti» и YUNUSOVA ZALOXAT MIRSULTANOVNA, по согласованной залоговой стоимость - 15 000 000,00 (on besh million) сум. | P3: =IF(D3=$B$2,O3,IF(D3=$C$2,$B$1)) -> - №386 от 6 noyabr 2019 г., заключенного с ООО «Clever Mikrokredit Tashkiloti» и YUNUSOVA ZALOXAT MIRSULTANOVNA, по согласованной залоговой стоимость - 15 000 000,00 (on besh million) сум.
A4: 3 | D4: ha | E4: YUNUSOVA ZALOXAT MIRSULTANOVNA | F4: 44217 | G4: =MONTH(F4) -> 1 | H4: =IF(G4=$A$26,$A$28,IF(G4=$B$26,$B$28,IF(G4=$C$26,$C$28,IF(G4=$D$26,$D$28,IF(G4=$E$26,$E$28,IF(G4=$F$26,$F$28,IF(G4=$K$26,$K$28,IF(G4=$L$26,$L$28,IF(G4=$M$26,$M$28,IF(G4=$N$26,$N$28,IF(G4=$O$26,$O$28,IF(G4=$P$26,$P$28,0)))))))))))) -> yanvar | I4: =DAY(F4) -> 21 | J4: =YEAR(F4) -> 2021 | K4: =""&I4&" "&H4&" "&J4&" г." -> 21 yanvar 2021 г. | L4: 33 | M4: 15000000 | N4: on besh million | O4: ="- №"&L4&" от "&K4&", заключенного с ООО «Clever Mikrokredit Tashkiloti» и "&E4&", по согласованной залоговой стоимость - "&FIXED(M4)&" ("&N4&") сум." -> - №33 от 21 yanvar 2021 г., заключенного с ООО «Clever Mikrokredit Tashkiloti» и YUNUSOVA ZALOXAT MIRSULTANOVNA, по согласованной залоговой стоимость - 15 000 000,00 (on besh million) сум. | P4: =IF(D4=$B$2,O4,IF(D4=$C$2,$B$1)) -> - №33 от 21 yanvar 2021 г., заключенного с ООО «Clever Mikrokredit Tashkiloti» и YUNUSOVA ZALOXAT MIRSULTANOVNA, по согласованной залоговой стоимость - 15 000 000,00 (on besh million) сум.
A5: 4 | D5: ha | G5: =MONTH(F5) -> 1 | H5: =IF(G5=$A$26,$A$28,IF(G5=$B$26,$B$28,IF(G5=$C$26,$C$28,IF(G5=$D$26,$D$28,IF(G5=$E$26,$E$28,IF(G5=$F$26,$F$28,IF(G5=$K$26,$K$28,IF(G5=$L$26,$L$28,IF(G5=$M$26,$M$28,IF(G5=$N$26,$N$28,IF(G5=$O$26,$O$28,IF(G5=$P$26,$P$28,0)))))))))))) -> yanvar | I5: =DAY(F5) -> 0 | J5: =YEAR(F5) -> 1900 | K5: =""&I5&" "&H5&" "&J5&" г." -> 0 yanvar 1900 г. | P5: =IF(D5=$B$2,O5,IF(D5=$C$2,$B$1)) -> 0
A6: 5 | D6: ha | G6: =MONTH(F6) -> 1 | H6: =IF(G6=$A$26,$A$28,IF(G6=$B$26,$B$28,IF(G6=$C$26,$C$28,IF(G6=$D$26,$D$28,IF(G6=$E$26,$E$28,IF(G6=$F$26,$F$28,IF(G6=$K$26,$K$28,IF(G6=$L$26,$L$28,IF(G6=$M$26,$M$28,IF(G6=$N$26,$N$28,IF(G6=$O$26,$O$28,IF(G6=$P$26,$P$28,0)))))))))))) -> yanvar | I6: =DAY(F6) -> 0 | J6: =YEAR(F6) -> 1900 | K6: =""&I6&" "&H6&" "&J6&" г." -> 0 yanvar 1900 г. | P6: =IF(D6=$B$2,O6,IF(D6=$C$2,$B$1)) -> 0
A7: 6 | D7: ha | G7: =MONTH(F7) -> 1 | H7: =IF(G7=$A$26,$A$28,IF(G7=$B$26,$B$28,IF(G7=$C$26,$C$28,IF(G7=$D$26,$D$28,IF(G7=$E$26,$E$28,IF(G7=$F$26,$F$28,IF(G7=$K$26,$K$28,IF(G7=$L$26,$L$28,IF(G7=$M$26,$M$28,IF(G7=$N$26,$N$28,IF(G7=$O$26,$O$28,IF(G7=$P$26,$P$28,0)))))))))))) -> yanvar | I7: =DAY(F7) -> 0 | J7: =YEAR(F7) -> 1900 | K7: =""&I7&" "&H7&" "&J7&" г." -> 0 yanvar 1900 г. | P7: =IF(D7=$B$2,O7,IF(D7=$C$2,$B$1)) -> 0
A8: 7 | D8: ha | G8: =MONTH(F8) -> 1 | H8: =IF(G8=$A$26,$A$28,IF(G8=$B$26,$B$28,IF(G8=$C$26,$C$28,IF(G8=$D$26,$D$28,IF(G8=$E$26,$E$28,IF(G8=$F$26,$F$28,IF(G8=$K$26,$K$28,IF(G8=$L$26,$L$28,IF(G8=$M$26,$M$28,IF(G8=$N$26,$N$28,IF(G8=$O$26,$O$28,IF(G8=$P$26,$P$28,0)))))))))))) -> yanvar | I8: =DAY(F8) -> 0 | J8: =YEAR(F8) -> 1900 | K8: =""&I8&" "&H8&" "&J8&" г." -> 0 yanvar 1900 г. | P8: =IF(D8=$B$2,O8,IF(D8=$C$2,$B$1)) -> 0
A9: 8 | D9: ha | G9: =MONTH(F9) -> 1 | H9: =IF(G9=$A$26,$A$28,IF(G9=$B$26,$B$28,IF(G9=$C$26,$C$28,IF(G9=$D$26,$D$28,IF(G9=$E$26,$E$28,IF(G9=$F$26,$F$28,IF(G9=$K$26,$K$28,IF(G9=$L$26,$L$28,IF(G9=$M$26,$M$28,IF(G9=$N$26,$N$28,IF(G9=$O$26,$O$28,IF(G9=$P$26,$P$28,0)))))))))))) -> yanvar | I9: =DAY(F9) -> 0 | J9: =YEAR(F9) -> 1900 | K9: =""&I9&" "&H9&" "&J9&" г." -> 0 yanvar 1900 г. | P9: =IF(D9=$B$2,O9,IF(D9=$C$2,$B$1)) -> 0
A10: 9 | D10: ha | G10: =MONTH(F10) -> 1 | H10: =IF(G10=$A$26,$A$28,IF(G10=$B$26,$B$28,IF(G10=$C$26,$C$28,IF(G10=$D$26,$D$28,IF(G10=$E$26,$E$28,IF(G10=$F$26,$F$28,IF(G10=$K$26,$K$28,IF(G10=$L$26,$L$28,IF(G10=$M$26,$M$28,IF(G10=$N$26,$N$28,IF(G10=$O$26,$O$28,IF(G10=$P$26,$P$28,0)))))))))))) -> yanvar | I10: =DAY(F10) -> 0 | J10: =YEAR(F10) -> 1900 | K10: =""&I10&" "&H10&" "&J10&" г." -> 0 yanvar 1900 г. | P10: =IF(D10=$B$2,O10,IF(D10=$C$2,$B$1)) -> 0
A11: 10 | D11: ha | G11: =MONTH(F11) -> 1 | H11: =IF(G11=$A$26,$A$28,IF(G11=$B$26,$B$28,IF(G11=$C$26,$C$28,IF(G11=$D$26,$D$28,IF(G11=$E$26,$E$28,IF(G11=$F$26,$F$28,IF(G11=$K$26,$K$28,IF(G11=$L$26,$L$28,IF(G11=$M$26,$M$28,IF(G11=$N$26,$N$28,IF(G11=$O$26,$O$28,IF(G11=$P$26,$P$28,0)))))))))))) -> yanvar | I11: =DAY(F11) -> 0 | J11: =YEAR(F11) -> 1900 | K11: =""&I11&" "&H11&" "&J11&" г." -> 0 yanvar 1900 г. | P11: =IF(D11=$B$2,O11,IF(D11=$C$2,$B$1)) -> 0
A12: 11 | D12: ha | G12: =MONTH(F12) -> 1 | H12: =IF(G12=$A$26,$A$28,IF(G12=$B$26,$B$28,IF(G12=$C$26,$C$28,IF(G12=$D$26,$D$28,IF(G12=$E$26,$E$28,IF(G12=$F$26,$F$28,IF(G12=$K$26,$K$28,IF(G12=$L$26,$L$28,IF(G12=$M$26,$M$28,IF(G12=$N$26,$N$28,IF(G12=$O$26,$O$28,IF(G12=$P$26,$P$28,0)))))))))))) -> yanvar | I12: =DAY(F12) -> 0 | J12: =YEAR(F12) -> 1900 | K12: =""&I12&" "&H12&" "&J12&" г." -> 0 yanvar 1900 г. | P12: =IF(D12=$B$2,O12,IF(D12=$C$2,$B$1)) -> 0
A13: 12 | D13: ha | G13: =MONTH(F13) -> 1 | H13: =IF(G13=$A$26,$A$28,IF(G13=$B$26,$B$28,IF(G13=$C$26,$C$28,IF(G13=$D$26,$D$28,IF(G13=$E$26,$E$28,IF(G13=$F$26,$F$28,IF(G13=$K$26,$K$28,IF(G13=$L$26,$L$28,IF(G13=$M$26,$M$28,IF(G13=$N$26,$N$28,IF(G13=$O$26,$O$28,IF(G13=$P$26,$P$28,0)))))))))))) -> yanvar | I13: =DAY(F13) -> 0 | J13: =YEAR(F13) -> 1900 | K13: =""&I13&" "&H13&" "&J13&" г." -> 0 yanvar 1900 г. | P13: =IF(D13=$B$2,O13,IF(D13=$C$2,$B$1)) -> 0
A14: 13 | D14: ha | G14: =MONTH(F14) -> 1 | H14: =IF(G14=$A$26,$A$28,IF(G14=$B$26,$B$28,IF(G14=$C$26,$C$28,IF(G14=$D$26,$D$28,IF(G14=$E$26,$E$28,IF(G14=$F$26,$F$28,IF(G14=$K$26,$K$28,IF(G14=$L$26,$L$28,IF(G14=$M$26,$M$28,IF(G14=$N$26,$N$28,IF(G14=$O$26,$O$28,IF(G14=$P$26,$P$28,0)))))))))))) -> yanvar | I14: =DAY(F14) -> 0 | J14: =YEAR(F14) -> 1900 | K14: =""&I14&" "&H14&" "&J14&" г." -> 0 yanvar 1900 г. | P14: =IF(D14=$B$2,O14,IF(D14=$C$2,$B$1)) -> 0
A15: 14 | D15: ha | G15: =MONTH(F15) -> 1 | H15: =IF(G15=$A$26,$A$28,IF(G15=$B$26,$B$28,IF(G15=$C$26,$C$28,IF(G15=$D$26,$D$28,IF(G15=$E$26,$E$28,IF(G15=$F$26,$F$28,IF(G15=$K$26,$K$28,IF(G15=$L$26,$L$28,IF(G15=$M$26,$M$28,IF(G15=$N$26,$N$28,IF(G15=$O$26,$O$28,IF(G15=$P$26,$P$28,0)))))))))))) -> yanvar | I15: =DAY(F15) -> 0 | J15: =YEAR(F15) -> 1900 | K15: =""&I15&" "&H15&" "&J15&" г." -> 0 yanvar 1900 г. | P15: =IF(D15=$B$2,O15,IF(D15=$C$2,$B$1)) -> 0
A16: 15 | D16: ha | G16: =MONTH(F16) -> 1 | H16: =IF(G16=$A$26,$A$28,IF(G16=$B$26,$B$28,IF(G16=$C$26,$C$28,IF(G16=$D$26,$D$28,IF(G16=$E$26,$E$28,IF(G16=$F$26,$F$28,IF(G16=$K$26,$K$28,IF(G16=$L$26,$L$28,IF(G16=$M$26,$M$28,IF(G16=$N$26,$N$28,IF(G16=$O$26,$O$28,IF(G16=$P$26,$P$28,0)))))))))))) -> yanvar | I16: =DAY(F16) -> 0 | J16: =YEAR(F16) -> 1900 | K16: =""&I16&" "&H16&" "&J16&" г." -> 0 yanvar 1900 г. | P16: =IF(D16=$B$2,O16,IF(D16=$C$2,$B$1)) -> 0
... A21: 20 | D21: ha | G21: =MONTH(F21) -> 1 | H21: =IF(G21=$A$26,$A$28,IF(G21=$B$26,$B$28,IF(G21=$C$26,$C$28,IF(G21=$D$26,$D$28,IF(G21=$E$26,$E$28,IF(G21=$F$26,$F$28,IF(G21=$K$26,$K$28,IF(G21=$L$26,$L$28,IF(G21=$M$26,$M$28,IF(G21=$N$26,$N$28,IF(G21=$O$26,$O$28,IF(G21=$P$26,$P$28,0)))))))))))) -> yanvar | I21: =DAY(F21) -> 0 | J21: =YEAR(F21) -> 1900 | K21: =""&I21&" "&H21&" "&J21&" г." -> 0 yanvar 1900 г. | P21: =IF(D21=$B$2,O21,IF(D21=$C$2,$B$1)) -> 0
M22: =SUM(M2:M21)+malumot!B143 -> 210000000 | Q22: ottiz yetti million besh yuz ming
A25: =MONTH(F2) -> 1 | B25: =IF(A25=A26,A28,IF(A25=B26,B28,IF(A25=C26,C28,IF(A25=D26,D28,IF(A25=E26,E28,IF(A25=F26,F28,IF(A25=K26,K28,IF(A25=L26,L28,IF(A25=M26,M28,IF(A25=N26,N28,IF(A25=O26,O28,IF(A25=#REF!,#REF!,)))))))))))) -> yanvar | C25: =DAY(F2) -> 11 | D25: =YEAR(F2) -> 2021
A26: 1 | B26: 2 | C26: 3 | D26: 4 | E26: 5 | F26: 6 | K26: 7 | L26: 8 | M26: 9 | N26: 10 | O26: 11 | P26: 12
A28: yanvar | B28: fevral | C28: mart | D28: aprel | E28: may | F28: iyun | K28: июля | L28: avgust | M28: sentyabr | N28: oktyabr | O28: noyabr | P28: dekabr
A29: yanvar | B29: fevral | C29: mart | D29: aprel | E29: may | F29: iyun | K29: июль | L29: avgust | M29: sentyabr | N29: oktyabr | O29: noyabr | P29: dekabr

Sheet График аннуитет.
E1: Приложение №1
F2: ="к договору микрозайма "&malumot!B74&"" -> к договору микрозайма 7 aprel 2025 y.dan №717-XMS
A4: График погашения
A6: № | B6: Дата погашения | C6: Остаток основного долга | D6: Сумма погашения, сум
D7: основного долга | E7: процентов* | F7: всего*
A8: 1 | B8: ='График дифференц'!B8 -> 45778 | C8: =malumot!B76 -> 125000000 | D8: =IF(A8<malumot!$B$82,'График аннуитет.'!F8-'График аннуитет.'!E8,'График аннуитет.'!C8) -> 2634452.2 | E8: =ROUND(C8*malumot!$B$85/H8,2)*'График аннуитет.'!G8 -> 4520547.8 | F8: =malumot!B91 -> 7155000 | G8: =B8-malumot!B67 -> 24 | H8: =DATE(YEAR(B8),12,31)-DATE(YEAR(B8),1,1)+1 -> 365
A9: 2 | B9: ='График дифференц'!B9 -> 45810 | C9: =C8-D8 -> 1.2236555e+08 | D9: =IF(A9<malumot!$B$82,'График аннуитет.'!F9-'График аннуитет.'!E9,'График аннуитет.'!C9) -> 1254633.9 | E9: =ROUND(C9*malumot!$B$85/H9,2)*'График аннуитет.'!G9 -> 5900366.1 | F9: =IF(A9<malumot!$B$82,'График аннуитет.'!F8,'График аннуитет.'!D9+'График аннуитет.'!E9) -> 7155000 | G9: =B9-B8 -> 32 | H9: =DATE(YEAR(B9),12,31)-DATE(YEAR(B9),1,1)+1 -> 365
A10: 3 | B10: ='График дифференц'!B10 -> 45839 | C10: =C9-D9 -> 1.2111091e+08 | D10: =IF(A10<malumot!$B$82,'График аннуитет.'!F10-'График аннуитет.'!E10,'График аннуитет.'!C10) -> 1862618.9 | E10: =ROUND(C10*malumot!$B$85/H10,2)*'График аннуитет.'!G10 -> 5292381.1 | F10: =IF(A10<malumot!$B$82,'График аннуитет.'!F9,'График аннуитет.'!D10+'График аннуитет.'!E10) -> 7155000 | G10: =B10-B9 -> 29 | H10: =DATE(YEAR(B10),12,31)-DATE(YEAR(B10),1,1)+1 -> 365
A11: 4 | B11: ='График дифференц'!B11 -> 45870 | C11: =C10-D10 -> 1.192483e+08 | D11: =IF(A11<malumot!$B$82,'График аннуитет.'!F11-'График аннуитет.'!E11,'График аннуитет.'!C11) -> 1584634.5 | E11: =ROUND(C11*malumot!$B$85/H11,2)*'График аннуитет.'!G11 -> 5570365.5 | F11: =IF(A11<malumot!$B$82,'График аннуитет.'!F10,'График аннуитет.'!D11+'График аннуитет.'!E11) -> 7155000 | G11: =B11-B10 -> 31 | H11: =DATE(YEAR(B11),12,31)-DATE(YEAR(B11),1,1)+1 -> 365
A12: 5 | B12: ='График дифференц'!B12 -> 45901 | C12: =C11-D11 -> 1.1766366e+08 | D12: =IF(A12<malumot!$B$82,'График аннуитет.'!F12-'График аннуитет.'!E12,'График аннуитет.'!C12) -> 1658656.3 | E12: =ROUND(C12*malumot!$B$85/H12,2)*'График аннуитет.'!G12 -> 5496343.7 | F12: =IF(A12<malumot!$B$82,'График аннуитет.'!F11,'График аннуитет.'!D12+'График аннуитет.'!E12) -> 7155000 | G12: =B12-B11 -> 31 | H12: =DATE(YEAR(B12),12,31)-DATE(YEAR(B12),1,1)+1 -> 365
A13: 6 | B13: ='График дифференц'!B13 -> 45931 | C13: =C12-D12 -> 1.16005e+08 | D13: =IF(A13<malumot!$B$82,'График аннуитет.'!F13-'График аннуитет.'!E13,'График аннуитет.'!C13) -> 1910938.2 | E13: =ROUND(C13*malumot!$B$85/H13,2)*'График аннуитет.'!G13 -> 5244061.8 | F13: =IF(A13<malumot!$B$82,'График аннуитет.'!F12,'График аннуитет.'!D13+'График аннуитет.'!E13) -> 7155000 | G13: =B13-B12 -> 30 | H13: =DATE(YEAR(B13),12,31)-DATE(YEAR(B13),1,1)+1 -> 365
A14: 7 | B14: ='График дифференц'!B14 -> 45964 | C14: =C13-D13 -> 1.1409407e+08 | D14: =IF(A14<malumot!$B$82,'График аннуитет.'!F14-'График аннуитет.'!E14,'График аннуитет.'!C14) -> 1481555.2 | E14: =ROUND(C14*malumot!$B$85/H14,2)*'График аннуитет.'!G14 -> 5673444.8 | F14: =IF(A14<malumot!$B$82,'График аннуитет.'!F13,'График аннуитет.'!D14+'График аннуитет.'!E14) -> 7155000 | G14: =B14-B13 -> 33 | H14: =DATE(YEAR(B14),12,31)-DATE(YEAR(B14),1,1)+1 -> 365
A15: 8 | B15: ='График дифференц'!B15 -> 45992 | C15: =C14-D14 -> 1.1261251e+08 | D15: =IF(A15<malumot!$B$82,'График аннуитет.'!F15-'График аннуитет.'!E15,'График аннуитет.'!C15) -> 2403677.8 | E15: =ROUND(C15*malumot!$B$85/H15,2)*'График аннуитет.'!G15 -> 4751322.2 | F15: =IF(A15<malumot!$B$82,'График аннуитет.'!F14,'График аннуитет.'!D15+'График аннуитет.'!E15) -> 7155000 | G15: =B15-B14 -> 28 | H15: =DATE(YEAR(B15),12,31)-DATE(YEAR(B15),1,1)+1 -> 365
A16: 9 | B16: ='График дифференц'!B16 -> 46023 | C16: =C15-D15 -> 1.1020883e+08 | D16: =IF(A16<malumot!$B$82,'График аннуитет.'!F16-'График аннуитет.'!E16,'График аннуитет.'!C16) -> 2006888.9 | E16: =ROUND(C16*malumot!$B$85/H16,2)*'График аннуитет.'!G16 -> 5148111.1 | F16: =IF(A16<malumot!$B$82,'График аннуитет.'!F15,'График аннуитет.'!D16+'График аннуитет.'!E16) -> 7155000 | G16: =B16-B15 -> 31 | H16: =DATE(YEAR(B16),12,31)-DATE(YEAR(B16),1,1)+1 -> 365
A17: 10 | B17: ='График дифференц'!B17 -> 46055 | C17: =C16-D16 -> 1.0820194e+08 | D17: =IF(A17<malumot!$B$82,'График аннуитет.'!F17-'График аннуитет.'!E17,'График аннуитет.'!C17) -> 1937591 | E17: =ROUND(C17*malumot!$B$85/H17,2)*'График аннуитет.'!G17 -> 5217409 | F17: =IF(A17<malumot!$B$82,'График аннуитет.'!F16,'График аннуитет.'!D17+'График аннуитет.'!E17) -> 7155000 | G17: =B17-B16 -> 32 | H17: =DATE(YEAR(B17),12,31)-DATE(YEAR(B17),1,1)+1 -> 365
A18: 11 | B18: ='График дифференц'!B18 -> 46083 | C18: =C17-D17 -> 1.0626435e+08 | D18: =IF(A18<malumot!$B$82,'График аннуитет.'!F18-'График аннуитет.'!E18,'График аннуитет.'!C18) -> 2671517.6 | E18: =ROUND(C18*malumot!$B$85/H18,2)*'График аннуитет.'!G18 -> 4483482.4 | F18: =IF(A18<malumot!$B$82,'График аннуитет.'!F17,'График аннуитет.'!D18+'График аннуитет.'!E18) -> 7155000 | G18: =B18-B17 -> 28 | H18: =DATE(YEAR(B18),12,31)-DATE(YEAR(B18),1,1)+1 -> 365
A19: 12 | B19: ='График дифференц'!B19 -> 46113 | C19: =C18-D18 -> 1.0359284e+08 | D19: =IF(A19<malumot!$B$82,'График аннуитет.'!F19-'График аннуитет.'!E19,'График аннуитет.'!C19) -> 2472036.3 | E19: =ROUND(C19*malumot!$B$85/H19,2)*'График аннуитет.'!G19 -> 4682963.7 | F19: =IF(A19<malumot!$B$82,'График аннуитет.'!F18,'График аннуитет.'!D19+'График аннуитет.'!E19) -> 7155000 | G19: =B19-B18 -> 30 | H19: =DATE(YEAR(B19),12,31)-DATE(YEAR(B19),1,1)+1 -> 365
A20: 13 | B20: ='График дифференц'!B20 -> 46143 | C20: =C19-D19 -> 1.011208e+08 | D20: =IF(A20<malumot!$B$82,'График аннуитет.'!F20-'График аннуитет.'!E20,'График аннуитет.'!C20) -> 2583785.7 | E20: =ROUND(C20*malumot!$B$85/H20,2)*'График аннуитет.'!G20 -> 4571214.3 | F20: =IF(A20<malumot!$B$82,'График аннуитет.'!F19,'График аннуитет.'!D20+'График аннуитет.'!E20) -> 7155000 | G20: =B20-B19 -> 30 | H20: =DATE(YEAR(B20),12,31)-DATE(YEAR(B20),1,1)+1 -> 365
... A31: 24 | B31: ='График дифференц'!B31 -> 46478 | C31: =C30-D30 -> 66132501 | D31: =IF(A31<malumot!$B$82,'График аннуитет.'!F31-'График аннуитет.'!E31,'График аннуитет.'!C31) -> 4065797 | E31: =ROUND(C31*malumot!$B$85/H31,2)*'График аннуитет.'!G31 -> 3089203 | F31: =IF(A31<malumot!$B$82,'График аннуитет.'!F30,'График аннуитет.'!D31+'График аннуитет.'!E31) -> 7155000 | G31: =B31-B30 -> 31 | H31: =DATE(YEAR(B31),12,31)-DATE(YEAR(B31),1,1)+1 -> 365
A32: =1+A31 -> 25 | B32: ='График дифференц'!B32 -> 46510 | C32: =C31-D31 -> 62066704 | D32: =IF(A32<malumot!$B$82,'График аннуитет.'!F32-'График аннуитет.'!E32,'График аннуитет.'!C32) -> 4162194.6 | E32: =ROUND(C32*malumot!$B$85/H32,2)*'График аннуитет.'!G32 -> 2992805.4 | F32: =IF(A32<malumot!$B$82,'График аннуитет.'!F31,'График аннуитет.'!D32+'График аннуитет.'!E32) -> 7155000 | G32: =B32-B31 -> 32 | H32: =DATE(YEAR(B32),12,31)-DATE(YEAR(B32),1,1)+1 -> 365
A33: =1+A32 -> 26 | B33: ='График дифференц'!B33 -> 46539 | C33: =C32-D32 -> 57904509 | D33: =IF(A33<malumot!$B$82,'График аннуитет.'!F33-'График аннуитет.'!E33,'График аннуитет.'!C33) -> 4624652.3 | E33: =ROUND(C33*malumot!$B$85/H33,2)*'График аннуитет.'!G33 -> 2530347.7 | F33: =IF(A33<malumot!$B$82,'График аннуитет.'!F32,'График аннуитет.'!D33+'График аннуитет.'!E33) -> 7155000 | G33: =B33-B32 -> 29 | H33: =DATE(YEAR(B33),12,31)-DATE(YEAR(B33),1,1)+1 -> 365
A34: =1+A33 -> 27 | B34: ='График дифференц'!B34 -> 46569 | C34: =C33-D33 -> 53279857 | D34: =IF(A34<malumot!$B$82,'График аннуитет.'!F34-'График аннуитет.'!E34,'График аннуитет.'!C34) -> 4746458.4 | E34: =ROUND(C34*malumot!$B$85/H34,2)*'График аннуитет.'!G34 -> 2408541.6 | F34: =IF(A34<malumot!$B$82,'График аннуитет.'!F33,'График аннуитет.'!D34+'График аннуитет.'!E34) -> 7155000 | G34: =B34-B33 -> 30 | H34: =DATE(YEAR(B34),12,31)-DATE(YEAR(B34),1,1)+1 -> 365
A35: =1+A34 -> 28 | B35: ='График дифференц'!B35 -> 46601 | C35: =C34-D34 -> 48533398 | D35: =IF(A35<malumot!$B$82,'График аннуитет.'!F35-'График аннуитет.'!E35,'График аннуитет.'!C35) -> 4814759.4 | E35: =ROUND(C35*malumot!$B$85/H35,2)*'График аннуитет.'!G35 -> 2340240.6 | F35: =IF(A35<malumot!$B$82,'График аннуитет.'!F34,'График аннуитет.'!D35+'График аннуитет.'!E35) -> 7155000 | G35: =B35-B34 -> 32 | H35: =DATE(YEAR(B35),12,31)-DATE(YEAR(B35),1,1)+1 -> 365
A36: =1+A35 -> 29 | B36: ='График дифференц'!B36 -> 46631 | C36: =C35-D35 -> 43718639 | D36: =IF(A36<malumot!$B$82,'График аннуитет.'!F36-'График аннуитет.'!E36,'График аннуитет.'!C36) -> 5178678 | E36: =ROUND(C36*malumot!$B$85/H36,2)*'График аннуитет.'!G36 -> 1976322 | F36: =IF(A36<malumot!$B$82,'График аннуитет.'!F35,'График аннуитет.'!D36+'График аннуитет.'!E36) -> 7155000 | G36: =B36-B35 -> 30 | H36: =DATE(YEAR(B36),12,31)-DATE(YEAR(B36),1,1)+1 -> 365
A37: =1+A36 -> 30 | B37: ='График дифференц'!B37 -> 46661 | C37: =C36-D36 -> 38539961 | D37: =IF(A37<malumot!$B$82,'График аннуитет.'!F37-'График аннуитет.'!E37,'График аннуитет.'!C37) -> 5412782.7 | E37: =ROUND(C37*malumot!$B$85/H37,2)*'График аннуитет.'!G37 -> 1742217.3 | F37: =IF(A37<malumot!$B$82,'График аннуитет.'!F36,'График аннуитет.'!D37+'График аннуитет.'!E37) -> 7155000 | G37: =B37-B36 -> 30 | H37: =DATE(YEAR(B37),12,31)-DATE(YEAR(B37),1,1)+1 -> 365
A38: =1+A37 -> 31 | B38: ='График дифференц'!B38 -> 46692 | C38: =C37-D37 -> 33127178 | D38: =IF(A38<malumot!$B$82,'График аннуитет.'!F38-'График аннуитет.'!E38,'График аннуитет.'!C38) -> 5607552.2 | E38: =ROUND(C38*malumot!$B$85/H38,2)*'График аннуитет.'!G38 -> 1547447.8 | F38: =IF(A38<malumot!$B$82,'График аннуитет.'!F37,'График аннуитет.'!D38+'График аннуитет.'!E38) -> 7155000 | G38: =B38-B37 -> 31 | H38: =DATE(YEAR(B38),12,31)-DATE(YEAR(B38),1,1)+1 -> 365
A39: =1+A38 -> 32 | B39: ='График дифференц'!B39 -> 46722 | C39: =C38-D38 -> 27519626 | D39: =IF(A39<malumot!$B$82,'График аннуитет.'!F39-'График аннуитет.'!E39,'График аннуитет.'!C39) -> 5910962.1 | E39: =ROUND(C39*malumot!$B$85/H39,2)*'График аннуитет.'!G39 -> 1244037.9 | F39: =IF(A39<malumot!$B$82,'График аннуитет.'!F38,'График аннуитет.'!D39+'График аннуитет.'!E39) -> 7155000 | G39: =B39-B38 -> 30 | H39: =DATE(YEAR(B39),12,31)-DATE(YEAR(B39),1,1)+1 -> 365
A40: =1+A39 -> 33 | B40: ='График дифференц'!B40 -> 46755 | C40: =C39-D39 -> 21608664 | D40: =IF(A40<malumot!$B$82,'График аннуитет.'!F40-'График аннуитет.'!E40,'График аннуитет.'!C40) -> 6083422.7 | E40: =ROUND(C40*malumot!$B$85/H40,2)*'График аннуитет.'!G40 -> 1071577.3 | F40: =IF(A40<malumot!$B$82,'График аннуитет.'!F39,'График аннуитет.'!D40+'График аннуитет.'!E40) -> 7155000 | G40: =B40-B39 -> 33 | H40: =DATE(YEAR(B40),12,31)-DATE(YEAR(B40),1,1)+1 -> 366
A41: =1+A40 -> 34 | B41: ='График дифференц'!B41 -> 46784 | C41: =C40-D40 -> 15525241 | D41: =IF(A41<malumot!$B$82,'График аннуитет.'!F41-'График аннуитет.'!E41,'График аннуитет.'!C41) -> 6478421.9 | E41: =ROUND(C41*malumot!$B$85/H41,2)*'График аннуитет.'!G41 -> 676578.12 | F41: =IF(A41<malumot!$B$82,'График аннуитет.'!F40,'График аннуитет.'!D41+'График аннуитет.'!E41) -> 7155000 | G41: =B41-B40 -> 29 | H41: =DATE(YEAR(B41),12,31)-DATE(YEAR(B41),1,1)+1 -> 366
A42: =1+A41 -> 35 | B42: ='График дифференц'!B42 -> 46813 | C42: =C41-D41 -> 9046819.4 | D42: =IF(A42<malumot!$B$82,'График аннуитет.'!F42-'График аннуитет.'!E42,'График аннуитет.'!C42) -> 6760746.5 | E42: =ROUND(C42*malumot!$B$85/H42,2)*'График аннуитет.'!G42 -> 394253.55 | F42: =IF(A42<malumot!$B$82,'График аннуитет.'!F41,'График аннуитет.'!D42+'График аннуитет.'!E42) -> 7155000 | G42: =B42-B41 -> 29 | H42: =DATE(YEAR(B42),12,31)-DATE(YEAR(B42),1,1)+1 -> 366
A43: =1+A42 -> 36 | B43: ='График дифференц'!B43 -> 46850 | C43: =C42-D42 -> 2286073 | D43: =IF(A43<malumot!$B$82,'График аннуитет.'!F43-'График аннуитет.'!E43,'График аннуитет.'!C43) -> 2286073 | E43: =ROUND(C43*malumot!$B$85/H43,2)*'График аннуитет.'!G43 -> 127108.32 | F43: =IF(A43<malumot!$B$82,'График аннуитет.'!F42,'График аннуитет.'!D43+'График аннуитет.'!E43) -> 2413181.3 | G43: =B43-B42 -> 37 | H43: =DATE(YEAR(B43),12,31)-DATE(YEAR(B43),1,1)+1 -> 366
... A55: =1+A54 -> 48 | B55: ='График дифференц'!B55 -> FALSE | C55: =C54-D54 -> 0 | D55: =IF(A55<malumot!$B$82,'График аннуитет.'!F55-'График аннуитет.'!E55,'График аннуитет.'!C55) -> 0 | E55: =ROUND(C55*malumot!$B$85/H55,2)*'График аннуитет.'!G55 -> 0 | F55: =IF(A55<malumot!$B$82,'График аннуитет.'!F54,'График аннуитет.'!D55+'График аннуитет.'!E55) -> 0 | G55: =B55-B54 -> 0 | H55: =DATE(YEAR(B55),12,31)-DATE(YEAR(B55),1,1)+1 -> 366
B56: ИТОГО | D56: =SUM(D8:D55) -> 1.25e+08 | E56: =SUM(E8:E55) -> 1.2783818e+08 | F56: =SUM(F8:F55) -> 2.5283818e+08
A58: *В случае осуществления погашения платежей по кредиту в даты, отличные от указанных в графике погашения, сумма платежа меняется на сумму процентов, которые начисляются на сумму остатка долга по микрозайму в соответствии с п.п. 2.2. настоящего договора.
A60: =#REF! -> #REF! | D60: =#REF! -> #REF!
A62: =#REF! -> #REF! | D62: =#REF! -> #REF!
A63: =#REF! -> #REF! | D63: =#REF! -> #REF!
A64: =#REF! -> #REF! | D64: ="паспорт серии "&malumot!B16&", "&malumot!B20&"" -> паспорт серии AC 2074678, XORAZM VILOYATI SHOVOT TUMANI IIB tomonidan 17.07.2019 yilda berilgan
A65: =#REF! -> #REF!
A66: =#REF! -> #REF! | D66: =#REF! -> #REF!
A67: =#REF! -> #REF! | D67: =#REF! -> #REF!
A68: =#REF! -> #REF! | D68: =#REF! -> #REF!
A70: =#REF! -> #REF! | D70: =#REF! -> #REF!
A72: =#REF! -> #REF! | D72: =#REF! -> #REF!

Sheet xulosa
A1: =""&malumot!B157&" mikromoliya tashkilotining Xulosasi" -> «CLEVER MIKROMOLIYA TASHKILOTI» MChJ mikromoliya tashkilotining Xulosasi
A3: MIJOZ HAQIDA MA'LUMOTLAR
A4: ="Mijozning to'liq ismi sharifi: "&malumot!B5&"" -> Mijozning to'liq ismi sharifi: MATCHANOVA AZIZA BEKTURDIYEVNA
A5: ="Tug'ilgan sanasi: "&malumot!B15&"" -> Tug'ilgan sanasi: 09.04.1990 y
A6: ="Pasport seriyasi "&malumot!B16&" "&malumot!B20&", amal qilish muddati - "&malumot!B21&"" -> Pasport seriyasi AC 2074678 XORAZM VILOYATI SHOVOT TUMANI IIB tomonidan 17.07.2019 yilda berilgan, amal qilish muddati - 16.07.2029 y.
A7: ="Ro‘yxatdan o‘tgan manzili: "&malumot!B28&", mo'ljal: "&malumot!B26&"" -> Ro‘yxatdan o‘tgan manzili: XORAZM VILOYATI SHOVOT TUMANI BOYRACHI QFY BOBORAXIM KO'CHASI 4-UY, mo'ljal: SHOVOT TUMANI BOYRACH QFY MADANIYAT MARKAZI
A8: ="Ish joyi: "&malumot!B52&" lavozimi "&malumot!B49&"da "&malumot!B44&"" -> Ish joyi: lavozimi TIKISH-BICHISHda O'Z O'ZINI BAND QILGAN FUQARO
A10: ="Mijoz tomonidan so’ralgan "&malumot!B65&" shartlari:" -> Mijoz tomonidan so’ralgan mikrokredit shartlari:
A11: =kredit_ariza!A13:D13 -> Mikrokredit summasi: 125 000 000,00 (yuz yigirma besh million so'm) so'm.
A12: =kredit_ariza!A14:D14 -> Mikrokredit muddati: 36 (O'ttiz olti ) oy.
A13: =kredit_ariza!A15:D15 -> Mikrokreditdan foydalanganlik uchun foiz stavkasi: yillik 55% (Ellik besh ) foiz
A14: =kredit_ariza!A16:D16 -> Mikrokredit bo'yicha asosiy qarz va foizlarni to'lash:
A15: =kredit_ariza!A19:D19 -> - mikrokredit shartnomasi bo'yicha har oy annuitet to'lovlari amalga oshiriladi
A16: =kredit_ariza!A20:D20
A17: =kredit_ariza!A21:D21 -> Mikrokredit ta’minoti::
A18: =kredit_ariza!A22:D22 -> 1. Egalik huquqi BEKOV OTABEK BAXODIROVICHga tegishli bo'lgan garovga olingan avtomobil markasi JAC M3, rangi - QORA CHERNIY, ishlab chiqarilgan yili - 2023, davlat raqam belgisi 90C477ZA, kuzov turi - YENGIL MINIVEN, kuzov raqami P08461541, dvigatel raqami LJ166A33XP2208188, shassi raqami - Rakamsiz
A19: Mijozning moliyaviy holati
A20: ="Anketaga muvofiq "&malumot!B9&"ning o‘rtacha oylik daromadi "&FIXED(malumot!B60)&" so‘mni tashkil etdi." -> Anketaga muvofiq MATCHANOVA A.B.ning o‘rtacha oylik daromadi 12 000 000,00 so‘mni tashkil etdi.
A21: ="Mijozning o'rtacha oylik xarajatlari "&FIXED(mijoz_anketasi!F27)&" so'mni tashkil etdi" -> Mijozning o'rtacha oylik xarajatlari 1 700 000,00 so'mni tashkil etdi
A22: =IF(malumot!B78=malumot!C78,xulosa!A23:E23,xulosa!A24:E24) -> Mikrokredit bo‘yicha oylik annuitet to‘lovi miqdori 7 155 000,00 so‘mni tashkil etadi.
A23: =""&malumot!C64&" shartnomasi bo'yicha birinchi oy uchun to'lov "&FIXED(malumot!B91)&" so'mni tashkil etadi." -> Mikrokredit shartnomasi bo'yicha birinchi oy uchun to'lov 7 155 000,00 so'mni tashkil etadi.
A24: =""&malumot!C64&" bo‘yicha oylik "&malumot!B78&" to‘lovi miqdori "&FIXED(malumot!B91)&" so‘mni tashkil etadi." -> Mikrokredit bo‘yicha oylik annuitet to‘lovi miqdori 7 155 000,00 so‘mni tashkil etadi.
A25: Mijoz quyidagi majburiyatlarga ega: AT Xalq banki bosh amaliyotlar boshqarmasi 806 751 so'm. Alif Moliya 920 000 so'm. Ayni paytda muddati o'tgan qarzdorligi mavjud emas. O‘rtacha oylik to‘lov 1 125 884.02 so‘mni tashkil qiladi
A26: =""&malumot!C64&" bo’yicha ta’minot:" -> Mikrokredit bo’yicha ta’minot:
A27: =" - "&malumot!B124&" ga mulk huquqi asosida tegishli avtotransport vositasi "&malumot!B132&" , quyidagi tafsilotlarga muvofiq:" -> - BEKOV OTABEK BAXODIROVICH ga mulk huquqi asosida tegishli avtotransport vositasi JAC M3 , quyidagi tafsilotlarga muvofiq:
A28: =" - "&malumot!C124&" ga mulk huquqi asosida tegishli ko'chmas mulk shaklida "&malumot!C133&", manzili: "&malumot!C130&", quyidagi tafsilotlarga muvofiq:" -> - 0 ga mulk huquqi asosida tegishli ko'chmas mulk shaklida 0, manzili: , quyidagi tafsilotlarga muvofiq:
A29: =IF(malumot!B110="Avtotransport",xulosa!A27:E27,xulosa!A28:E28) -> - BEKOV OTABEK BAXODIROVICH ga mulk huquqi asosida tegishli avtotransport vositasi JAC M3 , quyidagi tafsilotlarga muvofiq:
A30: =dalolatnoma!A29 -> Nomi | B30: =dalolatnoma!B29 -> Kuzov turi va kuzov raqami* | C30: =dalolatnoma!C29 -> Dvigatel va shassi raqami* | D30: =dalolatnoma!D29 -> Ishlab chiqarilgan yili va rangi* | E30: =dalolatnoma!E29 -> Kelishilgan garov qiymati, so'm
A31: =dalolatnoma!A30 -> JAC M3 | B31: =dalolatnoma!B30 -> kuzov turi - YENGIL MINIVEN, kuzov raqami P08461541 | C31: =dalolatnoma!C30 -> dvigatel raqami LJ166A33XP2208188, shassi raqami - Rakamsiz | D31: =dalolatnoma!D30 -> rangi - QORA CHERNIY, ishlab chiqarilgan yili - 2023 | E31: =dalolatnoma!E30 -> 165 000 000,00 (yuz oltmish besh million so'm)
A32: =dalolatnoma!A22 -> -* avtotransport egasi: BEKOV OTABEK BAXODIROVICH
A33: =dalolatnoma!A23 -> -* texnik pasport: AAG 5923045 28.03.2025y.
A34: =dalolatnoma!A24 -> -* roʻyxatdan oʻtgan manzili/garaj manzili: XORAZM VILOYATI URGANCH TUMANI GOYBU QFY OQ MAKTAB MFY
A35: =dalolatnoma!A25 -> -* davlat raqami: 90C477ZA
A36: =""&malumot!B157&" mikromoliya tashkilotining Xulosasi" -> «CLEVER MIKROMOLIYA TASHKILOTI» MChJ mikromoliya tashkilotining Xulosasi
A37: =""&malumot!B157&" kredit qo‘mitasining xulosasiga quyidagi shartlarda "&malumot!B10&"ga "&malumot!B65&" berish masalasi kiritiladi:" -> «CLEVER MIKROMOLIYA TASHKILOTI» MChJ kredit qo‘mitasining xulosasiga quyidagi shartlarda MATCHANOVA AZIZA BEKTURDIYEVNAga mikrokredit berish masalasi kiritiladi:
A38: =A11 -> Mikrokredit summasi: 125 000 000,00 (yuz yigirma besh million so'm) so'm.
A39: =A12 -> Mikrokredit muddati: 36 (O'ttiz olti ) oy.
A40: =A13 -> Mikrokreditdan foydalanganlik uchun foiz stavkasi: yillik 55% (Ellik besh ) foiz
A41: =A14 -> Mikrokredit bo'yicha asosiy qarz va foizlarni to'lash:
A42: =A15 -> - mikrokredit shartnomasi bo'yicha har oy annuitet to'lovlari amalga oshiriladi
A43: =A16
A44: =A17 -> Mikrokredit ta’minoti::
A45: =A18 -> 1. Egalik huquqi BEKOV OTABEK BAXODIROVICHga tegishli bo'lgan garovga olingan avtomobil markasi JAC M3, rangi - QORA CHERNIY, ishlab chiqarilgan yili - 2023, davlat raqam belgisi 90C477ZA, kuzov turi - YENGIL MINIVEN, kuzov raqami P08461541, dvigatel raqami LJ166A33XP2208188, shassi raqami - Rakamsiz
A47: =""&malumot!B157&" mikromoliya tashkilotining xulosasi "&TEXT(malumot!B2,"ДД.ММ.ГГГГ")&" y. tayyorlangan" -> «CLEVER MIKROMOLIYA TASHKILOTI» MChJ mikromoliya tashkilotining xulosasi 07.04.2025 y. tayyorlangan
A52: =""&malumot!B157&" mikromoliya tashkilotining Kredit qo‘mitasi a’zolari "&malumot!B157&" mikromoliya tashkilotining xulosasi va Mijoz tomonidan taqdim etilgan ma’lumotlar bilan tanishdilar:" -> «CLEVER MIKROMOLIYA TASHKILOTI» MChJ mikromoliya tashkilotining Kredit qo‘mitasi a’zolari «CLEVER MIKROMOLIYA TASHKILOTI» MChJ mikromoliya tashkilotining xulosasi va Mijoz tomonidan taqdim etilgan ma’lumotlar bilan tanishdilar:
A53: Imzolaganlar ro'yxati:
A55: =malumot!A160 -> Xorazm filiali boshlig'i | D55: =malumot!B160 -> M.Sharipov
A59: =malumot!A169 -> Kreditlash bo’limi boshlig’i | D59: =malumot!B169 -> B. Mominov
A63: =malumot!A170 -> Monitoring bo’limi boshlig’i | D63: =malumot!B170 -> B. Jumanazarov
A67: Ijrochi direktor | D67: N. Abduraximov

Sheet dalolatnoma
A2: ="GAROV PREDMETI QIYMATINI KELISHISH №"&malumot!B148&" SONLI DALOLATNOMASI " -> GAROV PREDMETI QIYMATINI KELISHISH №1 SONLI DALOLATNOMASI
A4: Toshkent shahri | E4: =malumot!B149 -> 7 aprel 2025 y.
A6: =IF(malumot!B110="avtotransport",dalolatnoma!A10:E10,dalolatnoma!A7:E7) -> «CLEVER MIKROMOLIYA TASHKILOTI» MChJning (1-tomon) vakili bo‘lgan Xorazm filiali boshlig'i M.Sharipov, O‘zbekiston Respublikasi fuqarosi MATCHANOVA AZIZA BEKTURDIYEVNA (2-tomon) va garovga beruvchi O‘zbekiston Respublikasi fuqarosi BEKOV OTABEK BAXODIROVICH (3-tomon) o’rtalarida, 7 aprel 2025 y.dan №717-XMS-sonli Mikrokredit shartnomasiga muvofiq 1-tomon 2-tomonga berilgan mikrokredit bo‘yicha ta’minot sifatida taqdim etilgan, 3-tomonga mulk huquqi asosida tegishli bo‘lgan mulkning garov qiymatini kelishish muzokaralari o’tkazildi.
A7: =IF(malumot!B100="ha",dalolatnoma!A9:E9,dalolatnoma!A8:E8) -> «CLEVER MIKROMOLIYA TASHKILOTI» MChJning (1-tomon) vakili bo‘lgan Xorazm filiali boshlig'i M.Sharipov, va O‘zbekiston Respublikasi fuqarosi MATCHANOVA AZIZA BEKTURDIYEVNA (2-tomon) va garov egasi 0 (3-tomon) 7 aprel 2025 y.dan №717-XMS Mikrokredit shartnomasiga muvofiq 1-tomon 2-tomonga berilgan mikrokredit bo‘yicha ta’minot sifatida taqdim etilgan, 2-tomonga mulk huquqi asosida tegishli bo‘lgan mulkning garov qiymatini kelishish muzokaralari o’tkazildi.
A8: =""&malumot!B157&"ning (1-tomon) vakili bo‘lgan "&malumot!A160&" "&malumot!B160&", va O‘zbekiston Respublikasi fuqarosi "&malumot!B5&" (2-tomon) va garov egasi "&malumot!C124&" (3-tomon) "&malumot!B74&" "&malumot!C64&" shartnomasiga muvofiq 1-tomon 2-tomonga berilgan "&malumot!B65&" bo‘yicha ta’minot sifatida taqdim etilgan, 2-tomonga mulk huquqi asosida tegishli bo‘lgan mulkning garov qiymatini kelishish muzokaralari o’tkazildi. " -> «CLEVER MIKROMOLIYA TASHKILOTI» MChJning (1-tomon) vakili bo‘lgan Xorazm filiali boshlig'i M.Sharipov, va O‘zbekiston Respublikasi fuqarosi MATCHANOVA AZIZA BEKTURDIYEVNA (2-tomon) va garov egasi 0 (3-tomon) 7 aprel 2025 y.dan №717-XMS Mikrokredit shartnomasiga muvofiq 1-tomon 2-tomonga berilgan mikrokredit bo‘yicha ta’minot sifatida taqdim etilgan, 2-tomonga mulk huquqi asosida tegishli bo‘lgan mulkning garov qiymatini kelishish muzokaralari o’tkazildi.
A9: =""&malumot!B157&"ning (1-tomon) vakili bo‘lgan "&malumot!A160&" "&malumot!B160&", va O‘zbekiston Respublikasi fuqarosi "&malumot!B5&" (2-tomon) va garov egasi "&malumot!C124&" (3-tomon) "&malumot!B74&" "&malumot!C64&" shartnomasiga muvofiq 1-tomon 2-tomonga berilgan "&malumot!B65&" bo‘yicha ta’minot sifatida taqdim etilgan, 2-tomonga mulk huquqi asosida tegishli bo‘lgan mulkning garov qiymatini kelishish muzokaralari o’tkazildi. " -> «CLEVER MIKROMOLIYA TASHKILOTI» MChJning (1-tomon) vakili bo‘lgan Xorazm filiali boshlig'i M.Sharipov, va O‘zbekiston Respublikasi fuqarosi MATCHANOVA AZIZA BEKTURDIYEVNA (2-tomon) va garov egasi 0 (3-tomon) 7 aprel 2025 y.dan №717-XMS Mikrokredit shartnomasiga muvofiq 1-tomon 2-tomonga berilgan mikrokredit bo‘yicha ta’minot sifatida taqdim etilgan, 2-tomonga mulk huquqi asosida tegishli bo‘lgan mulkning garov qiymatini kelishish muzokaralari o’tkazildi.
A10: =IF(malumot!B100="ha",dalolatnoma!A12:E12,dalolatnoma!A11:E11) -> «CLEVER MIKROMOLIYA TASHKILOTI» MChJning (1-tomon) vakili bo‘lgan Xorazm filiali boshlig'i M.Sharipov, O‘zbekiston Respublikasi fuqarosi MATCHANOVA AZIZA BEKTURDIYEVNA (2-tomon) va garovga beruvchi O‘zbekiston Respublikasi fuqarosi BEKOV OTABEK BAXODIROVICH (3-tomon) o’rtalarida, 7 aprel 2025 y.dan №717-XMS-sonli Mikrokredit shartnomasiga muvofiq 1-tomon 2-tomonga berilgan mikrokredit bo‘yicha ta’minot sifatida taqdim etilgan, 3-tomonga mulk huquqi asosida tegishli bo‘lgan mulkning garov qiymatini kelishish muzokaralari o’tkazildi.
A11: =""&malumot!B157&"ning (1-tomon) vakili bo‘lgan "&malumot!A160&" "&malumot!B160&", O‘zbekiston Respublikasi fuqarosi "&malumot!B5&" (2-tomon) va garovga beruvchi O‘zbekiston Respublikasi fuqarosi "&malumot!B124&" (3-tomon) o’rtalarida, "&malumot!B74&"-sonli "&malumot!C64&" shartnomasiga muvofiq 1-tomon 2-tomonga berilgan "&malumot!B65&" bo‘yicha ta’minot sifatida taqdim etilgan, 3-tomonga mulk huquqi asosida tegishli bo‘lgan mulkning garov qiymatini kelishish muzokaralari o’tkazildi." -> «CLEVER MIKROMOLIYA TASHKILOTI» MChJning (1-tomon) vakili bo‘lgan Xorazm filiali boshlig'i M.Sharipov, O‘zbekiston Respublikasi fuqarosi MATCHANOVA AZIZA BEKTURDIYEVNA (2-tomon) va garovga beruvchi O‘zbekiston Respublikasi fuqarosi BEKOV OTABEK BAXODIROVICH (3-tomon) o’rtalarida, 7 aprel 2025 y.dan №717-XMS-sonli Mikrokredit shartnomasiga muvofiq 1-tomon 2-tomonga berilgan mikrokredit bo‘yicha ta’minot sifatida taqdim etilgan, 3-tomonga mulk huquqi asosida tegishli bo‘lgan mulkning garov qiymatini kelishish muzokaralari o’tkazildi.
A12: =""&malumot!B157&"ning (1-tomon) vakili bo‘lgan "&malumot!A160&" "&malumot!B160&", O‘zbekiston Respublikasi fuqarosi va garovga beruvchi "&malumot!B5&" (2-tomon) o’rtalarida, "&malumot!B74&"-sonli "&malumot!C64&" shartnomasiga muvofiq 1-tomon 2-tomonga berilgan "&malumot!B65&" bo‘yicha ta’minot sifatida taqdim etilgan, 2-tomonga mulk huquqi asosida tegishli bo‘lgan mulkning garov qiymatini kelishish muzokaralari o’tkazildi." -> «CLEVER MIKROMOLIYA TASHKILOTI» MChJning (1-tomon) vakili bo‘lgan Xorazm filiali boshlig'i M.Sharipov, O‘zbekiston Respublikasi fuqarosi va garovga beruvchi MATCHANOVA AZIZA BEKTURDIYEVNA (2-tomon) o’rtalarida, 7 aprel 2025 y.dan №717-XMS-sonli Mikrokredit shartnomasiga muvofiq 1-tomon 2-tomonga berilgan mikrokredit bo‘yicha ta’minot sifatida taqdim etilgan, 2-tomonga mulk huquqi asosida tegishli bo‘lgan mulkning garov qiymatini kelishish muzokaralari o’tkazildi.
A13: ="Garov predmeti sifatida "&malumot!B132&", 3-tomonga egalik huquqi tegishli bo'lgan, quyidagi tafsilotlarga ega avtotransport vositasi taqdim etiladi:" -> Garov predmeti sifatida JAC M3, 3-tomonga egalik huquqi tegishli bo'lgan, quyidagi tafsilotlarga ega avtotransport vositasi taqdim etiladi:
A14: ="Garov predmeti sifatida "&malumot!B132&", 2-tomonga egalik huquqi tegishli bo'lgan, quyidagi tafsilotlarga ega avtotransport vositasi taqdim etiladi:" -> Garov predmeti sifatida JAC M3, 2-tomonga egalik huquqi tegishli bo'lgan, quyidagi tafsilotlarga ega avtotransport vositasi taqdim etiladi:
A15: =IF(malumot!B100="ha",dalolatnoma!A14:E14,dalolatnoma!A13:E13) -> Garov predmeti sifatida JAC M3, 3-tomonga egalik huquqi tegishli bo'lgan, quyidagi tafsilotlarga ega avtotransport vositasi taqdim etiladi:
A16: ="Garov predmeti sifatida "&malumot!C133&", 2-tomonga egalik huquqi tegishli bo'lgan, quyidagi tafsilotlarga ega ko'chmas mulk taqdim etiladi:" -> Garov predmeti sifatida 0, 2-tomonga egalik huquqi tegishli bo'lgan, quyidagi tafsilotlarga ega ko'chmas mulk taqdim etiladi:
A17: ="Garov predmeti sifatida "&malumot!C133&", 3-tomonga egalik huquqi tegishli bo'lgan, quyidagi tafsilotlarga ega ko'chmas mulk taqdim etiladi:" -> Garov predmeti sifatida 0, 3-tomonga egalik huquqi tegishli bo'lgan, quyidagi tafsilotlarga ega ko'chmas mulk taqdim etiladi:
A18: =IF(malumot!B100="ha",dalolatnoma!A16:E16,dalolatnoma!A17:E17) -> Garov predmeti sifatida 0, 3-tomonga egalik huquqi tegishli bo'lgan, quyidagi tafsilotlarga ega ko'chmas mulk taqdim etiladi:
A19: =IF(malumot!B110="Avtotransport",dalolatnoma!A15:E15,dalolatnoma!A18:E18) -> Garov predmeti sifatida JAC M3, 3-tomonga egalik huquqi tegishli bo'lgan, quyidagi tafsilotlarga ega avtotransport vositasi taqdim etiladi:
A20: Nomi | B20: =IF(malumot!B110=malumot!C110,"Kuzov turi va kuzov raqami*","Foydali maydoni") -> Kuzov turi va kuzov raqami* | D20: =IF(malumot!B110=malumot!C110,"Dvigatel va shassi raqami*","Yashash maydoni") -> Dvigatel va shassi raqami* | E20: =IF(malumot!B110=malumot!C110,"Ishlab chiqarilgan yili va rangi**","Umumiy maydoni") -> Ishlab chiqarilgan yili va rangi**
A21: =IF(malumot!B110=malumot!C110,malumot!B132,malumot!C132) -> JAC M3 | B21: =IF(malumot!B110=malumot!C110,malumot!B134,CONCATENATE(malumot!F137," ","kv.m")) -> kuzov turi - YENGIL MINIVEN, kuzov raqami P08461541 | D21: =IF(malumot!B110=malumot!C110,malumot!B137,malumot!E140) -> dvigatel raqami LJ166A33XP2208188, shassi raqami - Rakamsiz | E21: =IF(malumot!B110=malumot!C110,malumot!B140,malumot!E137) -> rangi - QORA CHERNIY, ishlab chiqarilgan yili - 2023
A22: ="-* "&IF(malumot!B110=malumot!C110,"avtotransport "&"egasi: "&malumot!B124&"","ko'chmas mulk"&" egasi: "&malumot!B124&"") -> -* avtotransport egasi: BEKOV OTABEK BAXODIROVICH
A23: =IF(malumot!B110=malumot!C110,"-* texnik pasport: "&malumot!B131&"","-* reest raqami: "&malumot!C131&"") -> -* texnik pasport: AAG 5923045 28.03.2025y.
A24: =IF(malumot!B110=malumot!C110,"-* roʻyxatdan oʻtgan manzili/garaj manzili: "&malumot!B129&"","-* kadastr raqami: "&malumot!C134&"") -> -* roʻyxatdan oʻtgan manzili/garaj manzili: XORAZM VILOYATI URGANCH TUMANI GOYBU QFY OQ MAKTAB MFY
A25: =IF(malumot!B110=malumot!C110,"-* davlat raqami: "&malumot!B133&"","-* manzili: "&malumot!C130&"") -> -* davlat raqami: 90C477ZA
A26: =IF(malumot!B100="ha",dalolatnoma!A28:E28,dalolatnoma!A27:E27) -> Tomonlar o’rtasida o’tkazilgan muzokaralar natijalariga ko‘ra, 2-tomon ta’minot sifatida quyidagi tafsilotlarga ega bo’lgan garov predmetini taqdim etadi, 1-tomon esa ushbu garov predmetini 7 aprel 2025 y.dan №717-XMS mikrokredit shartnomasi bo‘yicha berilgan mikrokredit bo‘yicha 165 000 000,00 (yuz oltmish besh million so'm) so’m bo‘lgan kelishilgan garov qiymatida qabul qiladi::
A27: ="Tomonlar o’rtasida o’tkazilgan muzokaralar natijalariga ko‘ra, 2-tomon ta’minot sifatida quyidagi tafsilotlarga ega bo’lgan garov predmetini taqdim etadi, 1-tomon esa ushbu garov predmetini "&malumot!B74&" "&malumot!B65&" shartnomasi bo‘yicha berilgan "&malumot!B65&" bo‘yicha "&FIXED(malumot!B143,2)&" ("&malumot!B144&") so’m bo‘lgan kelishilgan garov qiymatida qabul qiladi::" -> Tomonlar o’rtasida o’tkazilgan muzokaralar natijalariga ko‘ra, 2-tomon ta’minot sifatida quyidagi tafsilotlarga ega bo’lgan garov predmetini taqdim etadi, 1-tomon esa ushbu garov predmetini 7 aprel 2025 y.dan №717-XMS mikrokredit shartnomasi bo‘yicha berilgan mikrokredit bo‘yicha 165 000 000,00 (yuz oltmish besh million so'm) so’m bo‘lgan kelishilgan garov qiymatida qabul qiladi::
A28: ="Tomonlar o’rtasida o’tkazilgan muzokaralar natijalariga ko‘ra, 2-tomon ta’minot sifatida quyidagi tafsilotlarga ega bo’lgan garov predmetini taqdim etadi, 1-tomon esa ushbu garov predmetini "&malumot!B74&" "&malumot!C64&" shartnomasi bo‘yicha berilgan "&malumot!B65&" bo‘yicha "&FIXED(malumot!B143,2)&" ("&malumot!B144&") so’m bo‘lgan kelishilgan garov qiymatida qabul qiladi::" -> Tomonlar o’rtasida o’tkazilgan muzokaralar natijalariga ko‘ra, 2-tomon ta’minot sifatida quyidagi tafsilotlarga ega bo’lgan garov predmetini taqdim etadi, 1-tomon esa ushbu garov predmetini 7 aprel 2025 y.dan №717-XMS Mikrokredit shartnomasi bo‘yicha berilgan mikrokredit bo‘yicha 165 000 000,00 (yuz oltmish besh million so'm) so’m bo‘lgan kelishilgan garov qiymatida qabul qiladi::
A29: Nomi | B29: =B20 -> Kuzov turi va kuzov raqami* | C29: =D20 -> Dvigatel va shassi raqami* | D29: =IF(malumot!B110=malumot!C110,"Ishlab chiqarilgan yili va rangi*","Foydalanishga topshirilgan sanasi") -> Ishlab chiqarilgan yili va rangi* | E29: Kelishilgan garov qiymati, so'm
A30: =A21 -> JAC M3 | B30: =B21 -> kuzov turi - YENGIL MINIVEN, kuzov raqami P08461541 | C30: =D21 -> dvigatel raqami LJ166A33XP2208188, shassi raqami - Rakamsiz | D30: =IF(malumot!B110=malumot!C110,E21,TEXT(malumot!C142,"ДД.ММ.ГГГГ")) -> rangi - QORA CHERNIY, ishlab chiqarilgan yili - 2023 | E30: =""&FIXED(malumot!B143,2)&" ("&malumot!B144&")" -> 165 000 000,00 (yuz oltmish besh million so'm)
A32: Наименование | B32: Полезная площадь | C32: Жилая площадь | D32: Общая площадь | E32: Согласованная залоговая стоимость, сум
A33: =#REF! -> #REF! | B33: =#REF! -> #REF! | C33: =#REF! -> #REF! | D33: =#REF! -> #REF! | E33: =""&FIXED(malumot!C143,2)&" ("&malumot!B144&")" -> 165 000 000,00 (yuz oltmish besh million so'm)
A35: =#REF! -> #REF! | B35: =#REF! -> #REF! | C35: =#REF! -> #REF! | D35: =#REF! -> #REF!
A36: =#REF! -> #REF! | B36: =#REF! -> #REF! | C36: =#REF! -> #REF! | D36: =#REF! -> #REF!
A37: =#REF! -> #REF! | B37: =#REF! -> #REF! | C37: =#REF! -> #REF! | D37: =#REF! -> #REF!
A38: =#REF! -> #REF! | B38: =#REF! -> #REF! | C38: =#REF! -> #REF! | D38: =#REF! -> #REF!
A39: =#REF! -> #REF! | B39: =#REF! -> #REF! | C39: =#REF! -> #REF! | D39: =#REF! -> #REF!
A40: =#REF! -> #REF! | B40: =#REF! -> #REF! | C40: =#REF! -> #REF! | D40: =#REF! -> #REF!
A41: =#REF! -> #REF! | B41: =#REF! -> #REF! | C41: =#REF! -> #REF! | D41: =#REF! -> #REF!
A42: =#REF! -> #REF! | B42: =#REF! -> #REF! | C42: =#REF! -> #REF! | D42: =#REF! -> #REF!
A43: =#REF! -> #REF! | B43: =#REF! -> #REF! | C43: =#REF! -> #REF! | D43: =#REF! -> #REF!
A44: =#REF! -> #REF! | B44: =#REF! -> #REF! | C44: =#REF! -> #REF! | D44: =#REF! -> #REF! | E44: =FIXED(malumot!C143,2) -> 165 000 000,00
A46: ="“Birinchi talabga ko‘ra, yuqoridagi avtomobil Mikrokredit shartnomasi bo‘yicha garovga qo‘yilgan edi:: "&'Данные для послед. Залога'!W2&"" -> “Birinchi talabga ko‘ra, yuqoridagi avtomobil Mikrokredit shartnomasi bo‘yicha garovga qo‘yilgan edi:: - №5 от 11 yanvar 2021 г., заключенного с ООО «Clever Mikrokredit Tashkiloti» и TULYAGANOV XODJIAKBAR IRGASHEVICH, по согласованной залоговой стоимость - 15 000 000,00 (on besh million) сум. - №386 от 6 noyabr 2019 г., заключенного с ООО «Clever Mikrokredit Tashkiloti» и YUNUSOVA ZALOXAT MIRSULTANOVNA, по согласованной залоговой стоимость - 15 000 000,00 (on besh million) сум. - №33 от 21 yanvar 2021 г., заключенного с ООО «Clever Mikrokredit Tashkiloti» и YUNUSOVA ZALOXAT MIRSULTANOVNA, по согласованной залоговой стоимость - 15 000 000,00 (on besh million) сум. 0 0 0 0 0 0 0 0 0 0 0 0 0 0 0 0 0
A47: Shu bilan birga, garov predmetining kelishilgan garov qiymati deganda ushbu mulk garov sifatida taqdim etilgan/qabul qilingan qiymati tushuniladi.
A48: ="Shunday qilib, garov predmetining kelishilgan garov qiymati "&FIXED(malumot!B143)&" ("&malumot!B144&") so‘mni tashkil etadi." -> Shunday qilib, garov predmetining kelishilgan garov qiymati 165 000 000,00 (yuz oltmish besh million so'm) so‘mni tashkil etadi.
D49: =IF(malumot!B99=malumot!C99,malumot!C143,IF(malumot!B99=malumot!D99,'Данные для послед. Залога'!M22,0)) -> 165000000 | E49: =IF(malumot!B99=malumot!C99,malumot!B144,IF(malumot!B99=malumot!D99,'Данные для послед. Залога'!Q22,0)) -> yuz oltmish besh million so'm
A50: 1-tomondan:
A51: =malumot!B158 -> «CLEVER MIKROMOLIYA TASHKILOTI» MChJ
A52: =""&malumot!A160&"" -> Xorazm filiali boshlig'i | E52: =malumot!B160 -> M.Sharipov
A55: Начальник отдела кредитования
A56: =malumot!B158 -> «CLEVER MIKROMOLIYA TASHKILOTI» MChJ | D56: ="_______________ "&malumot!B169&"" -> _______________ B. Mominov
A58: 2-tomondan:
A59: O'zbekiston Respublikasi fuqarosi | D59: ="_______________ "&malumot!B7&"" -> _______________ MATCHANOVA A.B.
D60: =IF(malumot!B100="да","",malumot!B125) -> BEKOV O.B.
A61: =+IF(malumot!B100="ha"," ","3-tomondan:") -> 3-tomondan: | D61: ="_______________ "&malumot!B113&"" -> _______________ BEKOV O.B. | F61: =IF(malumot!B101=malumot!D101,B7,"")
A62: =+IF(malumot!B100="ha"," ","O'zbekiston Respublikasi fuqarosi") -> O'zbekiston Respublikasi fuqarosi | D62: ="_______________ "&malumot!B103 -> _______________

Sheet grafik
E3: =""&malumot!B74&" "&malumot!B65&" shartnomasiga 1 sonli ilova" -> 7 aprel 2025 y.dan №717-XMS mikrokredit shartnomasiga 1 sonli ilova
A5: To'lov jadvali
A7: № | B7: To'lov muddati | C7: Asosiy qarz qoldig'i | D7: To'lov miqdori, so'm
D8: asosiy qarz | E8: foizlar | F8: jami*
A9: 1 | B9: ='График аннуитет.'!B8 -> 45778 | C9: =IF(malumot!$B$78=malumot!$C$78,'График дифференц'!C8,IF(malumot!$B$78=malumot!$D$78,'График аннуитет.'!C8)) -> 125000000 | D9: =IF(malumot!$B$78=malumot!$C$78,'График дифференц'!D8,IF(malumot!$B$78=malumot!$D$78,'График аннуитет.'!D8)) -> 2634452.2 | E9: =IF(malumot!$B$78=malumot!$C$78,'График дифференц'!E8,IF(malumot!$B$78=malumot!$D$78,'График аннуитет.'!E8)) -> 4520547.8 | F9: =IF(malumot!$B$78=malumot!$C$78,'График дифференц'!F8,IF(malumot!$B$78=malumot!$D$78,'График аннуитет.'!F8)) -> 7155000
A10: 2 | B10: ='График аннуитет.'!B9 -> 45810 | C10: =IF(malumot!$B$78=malumot!$C$78,'График дифференц'!C9,IF(malumot!$B$78=malumot!$D$78,'График аннуитет.'!C9)) -> 1.2236555e+08 | D10: =IF(malumot!$B$78=malumot!$C$78,'График дифференц'!D9,IF(malumot!$B$78=malumot!$D$78,'График аннуитет.'!D9)) -> 1254633.9 | E10: =IF(malumot!$B$78=malumot!$C$78,'График дифференц'!E9,IF(malumot!$B$78=malumot!$D$78,'График аннуитет.'!E9)) -> 5900366.1 | F10: =IF(malumot!$B$78=malumot!$C$78,'График дифференц'!F9,IF(malumot!$B$78=malumot!$D$78,'График аннуитет.'!F9)) -> 7155000
A11: 3 | B11: ='График аннуитет.'!B10 -> 45839 | C11: =IF(malumot!$B$78=malumot!$C$78,'График дифференц'!C10,IF(malumot!$B$78=malumot!$D$78,'График аннуитет.'!C10)) -> 1.2111091e+08 | D11: =IF(malumot!$B$78=malumot!$C$78,'График дифференц'!D10,IF(malumot!$B$78=malumot!$D$78,'График аннуитет.'!D10)) -> 1862618.9 | E11: =IF(malumot!$B$78=malumot!$C$78,'График дифференц'!E10,IF(malumot!$B$78=malumot!$D$78,'График аннуитет.'!E10)) -> 5292381.1 | F11: =IF(malumot!$B$78=malumot!$C$78,'График дифференц'!F10,IF(malumot!$B$78=malumot!$D$78,'График аннуитет.'!F10)) -> 7155000
A12: 4 | B12: ='График аннуитет.'!B11 -> 45870 | C12: =IF(malumot!$B$78=malumot!$C$78,'График дифференц'!C11,IF(malumot!$B$78=malumot!$D$78,'График аннуитет.'!C11)) -> 1.192483e+08 | D12: =IF(malumot!$B$78=malumot!$C$78,'График дифференц'!D11,IF(malumot!$B$78=malumot!$D$78,'График аннуитет.'!D11)) -> 1584634.5 | E12: =IF(malumot!$B$78=malumot!$C$78,'График дифференц'!E11,IF(malumot!$B$78=malumot!$D$78,'График аннуитет.'!E11)) -> 5570365.5 | F12: =IF(malumot!$B$78=malumot!$C$78,'График дифференц'!F11,IF(malumot!$B$78=malumot!$D$78,'График аннуитет.'!F11)) -> 7155000 | H12: GRAFIKTA BO'SH JOY BO'LSA SKRIT' QILIB TASHLANG!!!
A13: 5 | B13: ='График аннуитет.'!B12 -> 45901 | C13: =IF(malumot!$B$78=malumot!$C$78,'График дифференц'!C12,IF(malumot!$B$78=malumot!$D$78,'График аннуитет.'!C12)) -> 1.1766366e+08 | D13: =IF(malumot!$B$78=malumot!$C$78,'График дифференц'!D12,IF(malumot!$B$78=malumot!$D$78,'График аннуитет.'!D12)) -> 1658656.3 | E13: =IF(malumot!$B$78=malumot!$C$78,'График дифференц'!E12,IF(malumot!$B$78=malumot!$D$78,'График аннуитет.'!E12)) -> 5496343.7 | F13: =IF(malumot!$B$78=malumot!$C$78,'График дифференц'!F12,IF(malumot!$B$78=malumot!$D$78,'График аннуитет.'!F12)) -> 7155000
A14: 6 | B14: ='График аннуитет.'!B13 -> 45931 | C14: =IF(malumot!$B$78=malumot!$C$78,'График дифференц'!C13,IF(malumot!$B$78=malumot!$D$78,'График аннуитет.'!C13)) -> 1.16005e+08 | D14: =IF(malumot!$B$78=malumot!$C$78,'График дифференц'!D13,IF(malumot!$B$78=malumot!$D$78,'График аннуитет.'!D13)) -> 1910938.2 | E14: =IF(malumot!$B$78=malumot!$C$78,'График дифференц'!E13,IF(malumot!$B$78=malumot!$D$78,'График аннуитет.'!E13)) -> 5244061.8 | F14: =IF(malumot!$B$78=malumot!$C$78,'График дифференц'!F13,IF(malumot!$B$78=malumot!$D$78,'График аннуитет.'!F13)) -> 7155000
A15: 7 | B15: ='График аннуитет.'!B14 -> 45964 | C15: =IF(malumot!$B$78=malumot!$C$78,'График дифференц'!C14,IF(malumot!$B$78=malumot!$D$78,'График аннуитет.'!C14)) -> 1.1409407e+08 | D15: =IF(malumot!$B$78=malumot!$C$78,'График дифференц'!D14,IF(malumot!$B$78=malumot!$D$78,'График аннуитет.'!D14)) -> 1481555.2 | E15: =IF(malumot!$B$78=malumot!$C$78,'График дифференц'!E14,IF(malumot!$B$78=malumot!$D$78,'График аннуитет.'!E14)) -> 5673444.8 | F15: =IF(malumot!$B$78=malumot!$C$78,'График дифференц'!F14,IF(malumot!$B$78=malumot!$D$78,'График аннуитет.'!F14)) -> 7155000
A16: 8 | B16: ='График аннуитет.'!B15 -> 45992 | C16: =IF(malumot!$B$78=malumot!$C$78,'График дифференц'!C15,IF(malumot!$B$78=malumot!$D$78,'График аннуитет.'!C15)) -> 1.1261251e+08 | D16: =IF(malumot!$B$78=malumot!$C$78,'График дифференц'!D15,IF(malumot!$B$78=malumot!$D$78,'График аннуитет.'!D15)) -> 2403677.8 | E16: =IF(malumot!$B$78=malumot!$C$78,'График дифференц'!E15,IF(malumot!$B$78=malumot!$D$78,'График аннуитет.'!E15)) -> 4751322.2 | F16: =IF(malumot!$B$78=malumot!$C$78,'График дифференц'!F15,IF(malumot!$B$78=malumot!$D$78,'График аннуитет.'!F15)) -> 7155000
A17: 9 | B17: ='График аннуитет.'!B16 -> 46023 | C17: =IF(malumot!$B$78=malumot!$C$78,'График дифференц'!C16,IF(malumot!$B$78=malumot!$D$78,'График аннуитет.'!C16)) -> 1.1020883e+08 | D17: =IF(malumot!$B$78=malumot!$C$78,'График дифференц'!D16,IF(malumot!$B$78=malumot!$D$78,'График аннуитет.'!D16)) -> 2006888.9 | E17: =IF(malumot!$B$78=malumot!$C$78,'График дифференц'!E16,IF(malumot!$B$78=malumot!$D$78,'График аннуитет.'!E16)) -> 5148111.1 | F17: =IF(malumot!$B$78=malumot!$C$78,'График дифференц'!F16,IF(malumot!$B$78=malumot!$D$78,'График аннуитет.'!F16)) -> 7155000
A18: 10 | B18: ='График аннуитет.'!B17 -> 46055 | C18: =IF(malumot!$B$78=malumot!$C$78,'График дифференц'!C17,IF(malumot!$B$78=malumot!$D$78,'График аннуитет.'!C17)) -> 1.0820194e+08 | D18: =IF(malumot!$B$78=malumot!$C$78,'График дифференц'!D17,IF(malumot!$B$78=malumot!$D$78,'График аннуитет.'!D17)) -> 1937591 | E18: =IF(malumot!$B$78=malumot!$C$78,'График дифференц'!E17,IF(malumot!$B$78=malumot!$D$78,'График аннуитет.'!E17)) -> 5217409 | F18: =IF(malumot!$B$78=malumot!$C$78,'График дифференц'!F17,IF(malumot!$B$78=malumot!$D$78,'График аннуитет.'!F17)) -> 7155000
A19: 11 | B19: ='График аннуитет.'!B18 -> 46083 | C19: =IF(malumot!$B$78=malumot!$C$78,'График дифференц'!C18,IF(malumot!$B$78=malumot!$D$78,'График аннуитет.'!C18)) -> 1.0626435e+08 | D19: =IF(malumot!$B$78=malumot!$C$78,'График дифференц'!D18,IF(malumot!$B$78=malumot!$D$78,'График аннуитет.'!D18)) -> 2671517.6 | E19: =IF(malumot!$B$78=malumot!$C$78,'График дифференц'!E18,IF(malumot!$B$78=malumot!$D$78,'График аннуитет.'!E18)) -> 4483482.4 | F19: =IF(malumot!$B$78=malumot!$C$78,'График дифференц'!F18,IF(malumot!$B$78=malumot!$D$78,'График аннуитет.'!F18)) -> 7155000
A20: 12 | B20: ='График аннуитет.'!B19 -> 46113 | C20: =IF(malumot!$B$78=malumot!$C$78,'График дифференц'!C19,IF(malumot!$B$78=malumot!$D$78,'График аннуитет.'!C19)) -> 1.0359284e+08 | D20: =IF(malumot!$B$78=malumot!$C$78,'График дифференц'!D19,IF(malumot!$B$78=malumot!$D$78,'График аннуитет.'!D19)) -> 2472036.3 | E20: =IF(malumot!$B$78=malumot!$C$78,'График дифференц'!E19,IF(malumot!$B$78=malumot!$D$78,'График аннуитет.'!E19)) -> 4682963.7 | F20: =IF(malumot!$B$78=malumot!$C$78,'График дифференц'!F19,IF(malumot!$B$78=malumot!$D$78,'График аннуитет.'!F19)) -> 7155000
A21: 13 | B21: ='График аннуитет.'!B20 -> 46143 | C21: =IF(malumot!$B$78=malumot!$C$78,'График дифференц'!C20,IF(malumot!$B$78=malumot!$D$78,'График аннуитет.'!C20)) -> 1.011208e+08 | D21: =IF(malumot!$B$78=malumot!$C$78,'График дифференц'!D20,IF(malumot!$B$78=malumot!$D$78,'График аннуитет.'!D20)) -> 2583785.7 | E21: =IF(malumot!$B$78=malumot!$C$78,'График дифференц'!E20,IF(malumot!$B$78=malumot!$D$78,'График аннуитет.'!E20)) -> 4571214.3 | F21: =IF(malumot!$B$78=malumot!$C$78,'График дифференц'!F20,IF(malumot!$B$78=malumot!$D$78,'График аннуитет.'!F20)) -> 7155000
A22: 14 | B22: ='График аннуитет.'!B21 -> 46174 | C22: =IF(malumot!$B$78=malumot!$C$78,'График дифференц'!C21,IF(malumot!$B$78=malumot!$D$78,'График аннуитет.'!C21)) -> 98537014 | D22: =IF(malumot!$B$78=malumot!$C$78,'График дифференц'!D21,IF(malumot!$B$78=malumot!$D$78,'График аннуитет.'!D21)) -> 2552106.7 | E22: =IF(malumot!$B$78=malumot!$C$78,'График дифференц'!E21,IF(malumot!$B$78=malumot!$D$78,'График аннуитет.'!E21)) -> 4602893.3 | F22: =IF(malumot!$B$78=malumot!$C$78,'График дифференц'!F21,IF(malumot!$B$78=malumot!$D$78,'График аннуитет.'!F21)) -> 7155000
A23: 15 | B23: ='График аннуитет.'!B22 -> 46204 | C23: =IF(malumot!$B$78=malumot!$C$78,'График дифференц'!C22,IF(malumot!$B$78=malumot!$D$78,'График аннуитет.'!C22)) -> 95984907 | D23: =IF(malumot!$B$78=malumot!$C$78,'График дифференц'!D22,IF(malumot!$B$78=malumot!$D$78,'График аннуитет.'!D22)) -> 2815956.3 | E23: =IF(malumot!$B$78=malumot!$C$78,'График дифференц'!E22,IF(malumot!$B$78=malumot!$D$78,'График аннуитет.'!E22)) -> 4339043.7 | F23: =IF(malumot!$B$78=malumot!$C$78,'График дифференц'!F22,IF(malumot!$B$78=malumot!$D$78,'График аннуитет.'!F22)) -> 7155000
A24: 16 | B24: ='График аннуитет.'!B23 -> 46237 | C24: =IF(malumot!$B$78=malumot!$C$78,'График дифференц'!C23,IF(malumot!$B$78=malumot!$D$78,'График аннуитет.'!C23)) -> 93168951 | D24: =IF(malumot!$B$78=malumot!$C$78,'График дифференц'!D23,IF(malumot!$B$78=malumot!$D$78,'График аннуитет.'!D23)) -> 2522078.2 | E24: =IF(malumot!$B$78=malumot!$C$78,'График дифференц'!E23,IF(malumot!$B$78=malumot!$D$78,'График аннуитет.'!E23)) -> 4632921.8 | F24: =IF(malumot!$B$78=malumot!$C$78,'График дифференц'!F23,IF(malumot!$B$78=malumot!$D$78,'График аннуитет.'!F23)) -> 7155000
... A26: 18 | B26: ='График аннуитет.'!B25 -> 46296 | C26: =IF(malumot!$B$78=malumot!$C$78,'График дифференц'!C25,IF(malumot!$B$78=malumot!$D$78,'График аннуитет.'!C25)) -> 87453017 | D26: =IF(malumot!$B$78=malumot!$C$78,'График дифференц'!D25,IF(malumot!$B$78=malumot!$D$78,'График аннуитет.'!D25)) -> 3201644.4 | E26: =IF(malumot!$B$78=malumot!$C$78,'График дифференц'!E25,IF(malumot!$B$78=malumot!$D$78,'График аннуитет.'!E25)) -> 3953355.6 | F26: =IF(malumot!$B$78=malumot!$C$78,'График дифференц'!F25,IF(malumot!$B$78=malumot!$D$78,'График аннуитет.'!F25)) -> 7155000
A27: =1+A26 -> 19 | B27: ='График аннуитет.'!B26 -> 46328 | C27: =IF(malumot!$B$78=malumot!$C$78,'График дифференц'!C26,IF(malumot!$B$78=malumot!$D$78,'График аннуитет.'!C26)) -> 84251372 | D27: =IF(malumot!$B$78=malumot!$C$78,'График дифференц'!D26,IF(malumot!$B$78=malumot!$D$78,'График аннуитет.'!D26)) -> 3092468.2 | E27: =IF(malumot!$B$78=malumot!$C$78,'График дифференц'!E26,IF(malumot!$B$78=malumot!$D$78,'График аннуитет.'!E26)) -> 4062531.8 | F27: =IF(malumot!$B$78=malumot!$C$78,'График дифференц'!F26,IF(malumot!$B$78=malumot!$D$78,'График аннуитет.'!F26)) -> 7155000
A28: =1+A27 -> 20 | B28: ='График аннуитет.'!B27 -> 46357 | C28: =IF(malumot!$B$78=malumot!$C$78,'График дифференц'!C27,IF(malumot!$B$78=malumot!$D$78,'График аннуитет.'!C27)) -> 81158904 | D28: =IF(malumot!$B$78=malumot!$C$78,'График дифференц'!D27,IF(malumot!$B$78=malumot!$D$78,'График аннуитет.'!D27)) -> 3608467 | E28: =IF(malumot!$B$78=malumot!$C$78,'График дифференц'!E27,IF(malumot!$B$78=malumot!$D$78,'График аннуитет.'!E27)) -> 3546533 | F28: =IF(malumot!$B$78=malumot!$C$78,'График дифференц'!F27,IF(malumot!$B$78=malumot!$D$78,'График аннуитет.'!F27)) -> 7155000
A29: =1+A28 -> 21 | B29: ='График аннуитет.'!B28 -> 46388 | C29: =IF(malumot!$B$78=malumot!$C$78,'График дифференц'!C28,IF(malumot!$B$78=malumot!$D$78,'График аннуитет.'!C28)) -> 77550437 | D29: =IF(malumot!$B$78=malumot!$C$78,'График дифференц'!D28,IF(malumot!$B$78=malumot!$D$78,'График аннуитет.'!D28)) -> 3532438.6 | E29: =IF(malumot!$B$78=malumot!$C$78,'График дифференц'!E28,IF(malumot!$B$78=malumot!$D$78,'График аннуитет.'!E28)) -> 3622561.4 | F29: =IF(malumot!$B$78=malumot!$C$78,'График дифференц'!F28,IF(malumot!$B$78=malumot!$D$78,'График аннуитет.'!F28)) -> 7155000
A30: =1+A29 -> 22 | B30: ='График аннуитет.'!B29 -> 46419 | C30: =IF(malumot!$B$78=malumot!$C$78,'График дифференц'!C29,IF(malumot!$B$78=malumot!$D$78,'График аннуитет.'!C29)) -> 74017998 | D30: =IF(malumot!$B$78=malumot!$C$78,'График дифференц'!D29,IF(malumot!$B$78=malumot!$D$78,'График аннуитет.'!D29)) -> 3697446.9 | E30: =IF(malumot!$B$78=malumot!$C$78,'График дифференц'!E29,IF(malumot!$B$78=malumot!$D$78,'График аннуитет.'!E29)) -> 3457553.1 | F30: =IF(malumot!$B$78=malumot!$C$78,'График дифференц'!F29,IF(malumot!$B$78=malumot!$D$78,'График аннуитет.'!F29)) -> 7155000
A31: =1+A30 -> 23 | B31: ='График аннуитет.'!B30 -> 46447 | C31: =IF(malumot!$B$78=malumot!$C$78,'График дифференц'!C30,IF(malumot!$B$78=malumot!$D$78,'График аннуитет.'!C30)) -> 70320551 | D31: =IF(malumot!$B$78=malumot!$C$78,'График дифференц'!D30,IF(malumot!$B$78=malumot!$D$78,'График аннуитет.'!D30)) -> 4188050.8 | E31: =IF(malumot!$B$78=malumot!$C$78,'График дифференц'!E30,IF(malumot!$B$78=malumot!$D$78,'График аннуитет.'!E30)) -> 2966949.2 | F31: =IF(malumot!$B$78=malumot!$C$78,'График дифференц'!F30,IF(malumot!$B$78=malumot!$D$78,'График аннуитет.'!F30)) -> 7155000
A32: =1+A31 -> 24 | B32: ='График аннуитет.'!B31 -> 46478 | C32: =IF(malumot!$B$78=malumot!$C$78,'График дифференц'!C31,IF(malumot!$B$78=malumot!$D$78,'График аннуитет.'!C31)) -> 66132501 | D32: =IF(malumot!$B$78=malumot!$C$78,'График дифференц'!D31,IF(malumot!$B$78=malumot!$D$78,'График аннуитет.'!D31)) -> 4065797 | E32: =IF(malumot!$B$78=malumot!$C$78,'График дифференц'!E31,IF(malumot!$B$78=malumot!$D$78,'График аннуитет.'!E31)) -> 3089203 | F32: =IF(malumot!$B$78=malumot!$C$78,'График дифференц'!F31,IF(malumot!$B$78=malumot!$D$78,'График аннуитет.'!F31)) -> 7155000
A33: =1+A32 -> 25 | B33: =IF('График аннуитет.'!B32=FALSE,"",'График аннуитет.'!B32) -> 46510 | C33: =IF(malumot!$B$78=malumot!$C$78,'График дифференц'!C32,IF(malumot!$B$78=malumot!$D$78,'График аннуитет.'!C32)) -> 62066704 | D33: =IF(malumot!$B$78=malumot!$C$78,'График дифференц'!D32,IF(malumot!$B$78=malumot!$D$78,'График аннуитет.'!D32)) -> 4162194.6 | E33: =IF(malumot!$B$78=malumot!$C$78,'График дифференц'!E32,IF(malumot!$B$78=malumot!$D$78,'График аннуитет.'!E32)) -> 2992805.4 | F33: =IF(malumot!$B$78=malumot!$C$78,'График дифференц'!F32,IF(malumot!$B$78=malumot!$D$78,'График аннуитет.'!F32)) -> 7155000
A34: =1+A33 -> 26 | B34: =IF('График аннуитет.'!B33=FALSE,"",'График аннуитет.'!B33) -> 46539 | C34: =IF(malumot!$B$78=malumot!$C$78,'График дифференц'!C33,IF(malumot!$B$78=malumot!$D$78,'График аннуитет.'!C33)) -> 57904509 | D34: =IF(malumot!$B$78=malumot!$C$78,'График дифференц'!D33,IF(malumot!$B$78=malumot!$D$78,'График аннуитет.'!D33)) -> 4624652.3 | E34: =IF(malumot!$B$78=malumot!$C$78,'График дифференц'!E33,IF(malumot!$B$78=malumot!$D$78,'График аннуитет.'!E33)) -> 2530347.7 | F34: =IF(malumot!$B$78=malumot!$C$78,'График дифференц'!F33,IF(malumot!$B$78=malumot!$D$78,'График аннуитет.'!F33)) -> 7155000
A35: =1+A34 -> 27 | B35: =IF('График аннуитет.'!B34=FALSE,"",'График аннуитет.'!B34) -> 46569 | C35: =IF(malumot!$B$78=malumot!$C$78,'График дифференц'!C34,IF(malumot!$B$78=malumot!$D$78,'График аннуитет.'!C34)) -> 53279857 | D35: =IF(malumot!$B$78=malumot!$C$78,'График дифференц'!D34,IF(malumot!$B$78=malumot!$D$78,'График аннуитет.'!D34)) -> 4746458.4 | E35: =IF(malumot!$B$78=malumot!$C$78,'График дифференц'!E34,IF(malumot!$B$78=malumot!$D$78,'График аннуитет.'!E34)) -> 2408541.6 | F35: =IF(malumot!$B$78=malumot!$C$78,'График дифференц'!F34,IF(malumot!$B$78=malumot!$D$78,'График аннуитет.'!F34)) -> 7155000
A36: =1+A35 -> 28 | B36: =IF('График аннуитет.'!B35=FALSE,"",'График аннуитет.'!B35) -> 46601 | C36: =IF(malumot!$B$78=malumot!$C$78,'График дифференц'!C35,IF(malumot!$B$78=malumot!$D$78,'График аннуитет.'!C35)) -> 48533398 | D36: =IF(malumot!$B$78=malumot!$C$78,'График дифференц'!D35,IF(malumot!$B$78=malumot!$D$78,'График аннуитет.'!D35)) -> 4814759.4 | E36: =IF(malumot!$B$78=malumot!$C$78,'График дифференц'!E35,IF(malumot!$B$78=malumot!$D$78,'График аннуитет.'!E35)) -> 2340240.6 | F36: =IF(malumot!$B$78=malumot!$C$78,'График дифференц'!F35,IF(malumot!$B$78=malumot!$D$78,'График аннуитет.'!F35)) -> 7155000
A37: =1+A36 -> 29 | B37: =IF('График аннуитет.'!B36=FALSE,"",'График аннуитет.'!B36) -> 46631 | C37: =IF(malumot!$B$78=malumot!$C$78,'График дифференц'!C36,IF(malumot!$B$78=malumot!$D$78,'График аннуитет.'!C36)) -> 43718639 | D37: =IF(malumot!$B$78=malumot!$C$78,'График дифференц'!D36,IF(malumot!$B$78=malumot!$D$78,'График аннуитет.'!D36)) -> 5178678 | E37: =IF(malumot!$B$78=malumot!$C$78,'График дифференц'!E36,IF(malumot!$B$78=malumot!$D$78,'График аннуитет.'!E36)) -> 1976322 | F37: =IF(malumot!$B$78=malumot!$C$78,'График дифференц'!F36,IF(malumot!$B$78=malumot!$D$78,'График аннуитет.'!F36)) -> 7155000
A38: =1+A37 -> 30 | B38: =IF('График аннуитет.'!B37=FALSE,"",'График аннуитет.'!B37) -> 46661 | C38: =IF(malumot!$B$78=malumot!$C$78,'График дифференц'!C37,IF(malumot!$B$78=malumot!$D$78,'График аннуитет.'!C37)) -> 38539961 | D38: =IF(malumot!$B$78=malumot!$C$78,'График дифференц'!D37,IF(malumot!$B$78=malumot!$D$78,'График аннуитет.'!D37)) -> 5412782.7 | E38: =IF(malumot!$B$78=malumot!$C$78,'График дифференц'!E37,IF(malumot!$B$78=malumot!$D$78,'График аннуитет.'!E37)) -> 1742217.3 | F38: =IF(malumot!$B$78=malumot!$C$78,'График дифференц'!F37,IF(malumot!$B$78=malumot!$D$78,'График аннуитет.'!F37)) -> 7155000
A39: =1+A38 -> 31 | B39: =IF('График аннуитет.'!B38=FALSE,"",'График аннуитет.'!B38) -> 46692 | C39: =IF(malumot!$B$78=malumot!$C$78,'График дифференц'!C38,IF(malumot!$B$78=malumot!$D$78,'График аннуитет.'!C38)) -> 33127178 | D39: =IF(malumot!$B$78=malumot!$C$78,'График дифференц'!D38,IF(malumot!$B$78=malumot!$D$78,'График аннуитет.'!D38)) -> 5607552.2 | E39: =IF(malumot!$B$78=malumot!$C$78,'График дифференц'!E38,IF(malumot!$B$78=malumot!$D$78,'График аннуитет.'!E38)) -> 1547447.8 | F39: =IF(malumot!$B$78=malumot!$C$78,'График дифференц'!F38,IF(malumot!$B$78=malumot!$D$78,'График аннуитет.'!F38)) -> 7155000
A40: =1+A39 -> 32 | B40: =IF('График аннуитет.'!B39=FALSE,"",'График аннуитет.'!B39) -> 46722 | C40: =IF(malumot!$B$78=malumot!$C$78,'График дифференц'!C39,IF(malumot!$B$78=malumot!$D$78,'График аннуитет.'!C39)) -> 27519626 | D40: =IF(malumot!$B$78=malumot!$C$78,'График дифференц'!D39,IF(malumot!$B$78=malumot!$D$78,'График аннуитет.'!D39)) -> 5910962.1 | E40: =IF(malumot!$B$78=malumot!$C$78,'График дифференц'!E39,IF(malumot!$B$78=malumot!$D$78,'График аннуитет.'!E39)) -> 1244037.9 | F40: =IF(malumot!$B$78=malumot!$C$78,'График дифференц'!F39,IF(malumot!$B$78=malumot!$D$78,'График аннуитет.'!F39)) -> 7155000
A41: =1+A40 -> 33 | B41: =IF('График аннуитет.'!B40=FALSE,"",'График аннуитет.'!B40) -> 46755 | C41: =IF(malumot!$B$78=malumot!$C$78,'График дифференц'!C40,IF(malumot!$B$78=malumot!$D$78,'График аннуитет.'!C40)) -> 21608664 | D41: =IF(malumot!$B$78=malumot!$C$78,'График дифференц'!D40,IF(malumot!$B$78=malumot!$D$78,'График аннуитет.'!D40)) -> 6083422.7 | E41: =IF(malumot!$B$78=malumot!$C$78,'График дифференц'!E40,IF(malumot!$B$78=malumot!$D$78,'График аннуитет.'!E40)) -> 1071577.3 | F41: =IF(malumot!$B$78=malumot!$C$78,'График дифференц'!F40,IF(malumot!$B$78=malumot!$D$78,'График аннуитет.'!F40)) -> 7155000
A42: =1+A41 -> 34 | B42: =IF('График аннуитет.'!B41=FALSE,"",'График аннуитет.'!B41) -> 46784 | C42: =IF(malumot!$B$78=malumot!$C$78,'График дифференц'!C41,IF(malumot!$B$78=malumot!$D$78,'График аннуитет.'!C41)) -> 15525241 | D42: =IF(malumot!$B$78=malumot!$C$78,'График дифференц'!D41,IF(malumot!$B$78=malumot!$D$78,'График аннуитет.'!D41)) -> 6478421.9 | E42: =IF(malumot!$B$78=malumot!$C$78,'График дифференц'!E41,IF(malumot!$B$78=malumot!$D$78,'График аннуитет.'!E41)) -> 676578.12 | F42: =IF(malumot!$B$78=malumot!$C$78,'График дифференц'!F41,IF(malumot!$B$78=malumot!$D$78,'График аннуитет.'!F41)) -> 7155000
A43: =1+A42 -> 35 | B43: =IF('График аннуитет.'!B42=FALSE,"",'График аннуитет.'!B42) -> 46813 | C43: =IF(malumot!$B$78=malumot!$C$78,'График дифференц'!C42,IF(malumot!$B$78=malumot!$D$78,'График аннуитет.'!C42)) -> 9046819.4 | D43: =IF(malumot!$B$78=malumot!$C$78,'График дифференц'!D42,IF(malumot!$B$78=malumot!$D$78,'График аннуитет.'!D42)) -> 6760746.5 | E43: =IF(malumot!$B$78=malumot!$C$78,'График дифференц'!E42,IF(malumot!$B$78=malumot!$D$78,'График аннуитет.'!E42)) -> 394253.55 | F43: =IF(malumot!$B$78=malumot!$C$78,'График дифференц'!F42,IF(malumot!$B$78=malumot!$D$78,'График аннуитет.'!F42)) -> 7155000
A44: =1+A43 -> 36 | B44: =IF('График аннуитет.'!B43=FALSE,"",'График аннуитет.'!B43) -> 46850 | C44: =IF(malumot!$B$78=malumot!$C$78,'График дифференц'!C43,IF(malumot!$B$78=malumot!$D$78,'График аннуитет.'!C43)) -> 2286073 | D44: =IF(malumot!$B$78=malumot!$C$78,'График дифференц'!D43,IF(malumot!$B$78=malumot!$D$78,'График аннуитет.'!D43)) -> 2286073 | E44: =IF(malumot!$B$78=malumot!$C$78,'График дифференц'!E43,IF(malumot!$B$78=malumot!$D$78,'График аннуитет.'!E43)) -> 127108.32 | F44: =IF(malumot!$B$78=malumot!$C$78,'График дифференц'!F43,IF(malumot!$B$78=malumot!$D$78,'График аннуитет.'!F43)) -> 2413181.3
... A56: =1+A55 -> 48 | B56: =IF('График аннуитет.'!B55=FALSE,"",'График аннуитет.'!B55) | C56: =IF(malumot!$B$78=malumot!$C$78,'График дифференц'!C55,IF(malumot!$B$78=malumot!$D$78,'График аннуитет.'!C55)) -> 0 | D56: =IF(malumot!$B$78=malumot!$C$78,'График дифференц'!D55,IF(malumot!$B$78=malumot!$D$78,'График аннуитет.'!D55)) -> 0 | E56: =IF(malumot!$B$78=malumot!$C$78,'График дифференц'!E55,IF(malumot!$B$78=malumot!$D$78,'График аннуитет.'!E55)) -> 0 | F56: =IF(malumot!$B$78=malumot!$C$78,'График дифференц'!F55,IF(malumot!$B$78=malumot!$D$78,'График аннуитет.'!F55)) -> 0
B57: JAMI | D57: =SUM(D9:D56) -> 1.25e+08 | E57: =SUM(E9:E56) -> 1.2783818e+08 | F57: =SUM(F9:F56) -> 2.5283818e+08
A59: ="*"&malumot!C64&" bo‘yicha to‘lovlar to‘lov jadvalida ko‘rsatilmagan sanalarda to‘langan taqdirda, to‘lov summasi mikroqarz shartnomasining 2.2.-bandiga muvofiq "&malumot!B65&" qoldig‘iga hisoblangan foizlar summasiga o‘zgartiriladi." -> *Mikrokredit bo‘yicha to‘lovlar to‘lov jadvalida ko‘rsatilmagan sanalarda to‘langan taqdirda, to‘lov summasi mikroqarz shartnomasining 2.2.-bandiga muvofiq mikrokredit qoldig‘iga hisoblangan foizlar summasiga o‘zgartiriladi.
A61: «Mikromoliya tashkiloti » | D61: «Qarz oluvchi»
A63: =shartnoma!A117 -> «CLEVER MIKROMOLIYA TASHKILOTI» MChJ | D63: =shartnoma!B117 -> MATCHANOVA AZIZA BEKTURDIYEVNA
A64: =shartnoma!A119 -> Manzil: Toshkent shahri, Olmazor tumani, Sagbon ko'chasi, 30 boshi berk, 6-uy | D64: =shartnoma!B119 -> Manzil: XORAZM VILOYATI SHOVOT TUMANI BOYRACHI QFY BOBORAXIM KO'CHASI 4-UY
A65: =shartnoma!A120 -> h/r: №20216000705068380001 | D65: =shartnoma!B121 -> Pasport: AC 2074678, XORAZM VILOYATI SHOVOT TUMANI IIB tomonidan 17.07.2019 yilda berilgan
A66: =shartnoma!A121 -> MFO: №01042 в ATB “Kapitalbank” Sergeli filiali
A67: =shartnoma!A122 -> STIR: 306365847 | D67: =shartnoma!B122 -> Tel: 91 860-86-87 O'ZI
A68: =shartnoma!A123 -> Tel: (78) 113 31 33 | D68: =shartnoma!B123 -> 33 381-86-87 Ayoli
A69: =shartnoma!A124 -> (78) 113 31 34 | D69: =shartnoma!B124 -> 99-187-10-62 Otasi
D70: =IF(shartnoma!B125=0,"",shartnoma!B125)
A71: =malumot!A171 -> Xorazm filiali boshlig'i | D71: =shartnoma!B126 -> MATCHANOVA A.B. __________________
A72: =malumot!B160 -> M.Sharipov

Sheet garov_ariza
C6: =malumot!B157 -> «CLEVER MIKROMOLIYA TASHKILOTI» MChJ
C7: =malumot!A160&" "&malumot!B171 &"ga" -> Xorazm filiali boshlig'i M.Sharipovga
C8: =malumot!B5 & "dan" -> MATCHANOVA AZIZA BEKTURDIYEVNAdan
C9: =[2]malumot!B119 -> FAYZIYEV JAMSHID KURBONOVICH
C10: =[2]malumot!C119 -> 0
C11: dan
B12: ARIZA
A13: =IF(malumot!B110="Avtotransport",A14,A15) -> MATCHANOVA AZIZA BEKTURDIYEVNA tomonidan so’ralayotgan O'ttiz olti (36) oy muddatga, 110 000 000 (yuz yigirma besh million so'm) miqdoridagi mikrokreditning ta’minoti sifatida menga mulk huquqi asosida tegishli bo’lgan 90C477ZA, YENGIL MINIVEN, LJ166A33XP2208188, QORA CHERNIY, avtotransport vositasini qabul qilishingizni so’rayman:
A14: =""&malumot!B12&" tomonidan so’ralayotgan "&malumot!B83&" ("&malumot!B82&") oy muddatga, "&FIXED(malumot!B75,0)&" ("&malumot!B77&") miqdoridagi "&malumot!B65&"ning ta’minoti sifatida menga mulk huquqi asosida tegishli bo’lgan "&malumot!B133&", "&malumot!B135&", "&malumot!B138&", "&malumot!B141&", avtotransport vositasini qabul qilishingizni so’rayman:" -> MATCHANOVA AZIZA BEKTURDIYEVNA tomonidan so’ralayotgan O'ttiz olti (36) oy muddatga, 110 000 000 (yuz yigirma besh million so'm) miqdoridagi mikrokreditning ta’minoti sifatida menga mulk huquqi asosida tegishli bo’lgan 90C477ZA, YENGIL MINIVEN, LJ166A33XP2208188, QORA CHERNIY, avtotransport vositasini qabul qilishingizni so’rayman:
A15: =""&[2]malumot!B12&" tomonidan so’ralayotgan "&[2]malumot!B81&" ("&[2]malumot!B82&") oy muddatga, "&FIXED([2]malumot!B75,0)&" ("&[2]malumot!B76&") miqdoridagi "&[2]malumot!B65&"ning ta’minoti sifatida menga mulk huquqi asosida tegishli bo’lgan "&[2]malumot!C134&", umumiy maydoni "&[2]malumot!C138&" va yashash maydoni "&[2]malumot!C141&" "&[2]malumot!C131&" manzilda joylashgan ko'chmas mulkni qabul qilishingizni so’rayman:" -> XAYATOV OTABEK KURBANOVICH tomonidan so’ralayotgan 48 (Qirq sakkiz ) oy muddatga, 26 000 000 (yigirma olti million so'm) miqdoridagi mikroqarzning ta’minoti sifatida menga mulk huquqi asosida tegishli bo’lgan 3 - xonali yakka tartibdagi uy-joy, umumiy maydoni 72,13 va yashash maydoni 37,39 SAMARQAND VILOYATI TAYLOQ TUMANI CHAROG'BON MFY YANGI TAYLOQ QISHLOG'I 6 TURAR JOY 12 QAVAT 58 XONADON manzilda joylashgan ko'chmas mulkni qabul qilishingizni so’rayman:
C18: Sana:
C19: =malumot!B2 -> 07.04.2025
A23: =malumot!A171 -> Xorazm filiali boshlig'i | C23: =malumot!B171 -> M.Sharipov
A27: =" xususiy faoliyat ko'rsatuvchi notarius tomonidan "&[2]malumot!B104&" "&[2]malumot!B105&" berilgan ishonchnomaga asosan " -> xususiy faoliyat ko'rsatuvchi notarius tomonidan BUXORO VILOYATI BUXORO SHAHRI ASHXOBOD KO'CHASI 1/3-UY SHARIPOV ZAFAR JO'RABOYEVICH berilgan ishonchnomaga asosan
A29: ="№"&[2]malumot!B106& "" -> №202502386001856
A30: =[2]malumot!B108 -> 01.04.2025
A31: =TEXT(A30,"ДД.ММ.ГГГГ") -> 01.04.2025
A32: sanasidan
A33: =CONCATENATE(A31,A32) -> 01.04.2025 sanasidan

Sheet ariza
C1: =malumot!B157&" Ijrochi direktori" -> «CLEVER MIKROMOLIYA TASHKILOTI» MChJ Ijrochi direktori
C2: N.Abduraximovga
C4: =malumot!B22&" manzilida istiqomat qiluvchi" -> XORAZM VILOYATI SHOVOT TUMANI BOYRACHI QFY BOBORAXIM KO'CHASI 4-UY manzilida istiqomat qiluvchi
C5: =malumot!B5&" tomonidan" -> MATCHANOVA AZIZA BEKTURDIYEVNA tomonidan
C6: ="Pasport: "&malumot!B16&", "&malumot!B20 -> Pasport: AC 2074678, XORAZM VILOYATI SHOVOT TUMANI IIB tomonidan 17.07.2019 yilda berilgan
A8: ARIZA
A9: =" Men, " & malumot!B5 & " sizdan " & malumot!B2 & " yildagi " & malumot!B1 & "-sonli kredit shartnomasiga asosan " & malumot!B76 & "(" & malumot!B77 & ")" & "so'm pul mablag'larini quyidagi rekvizitlar asosida o'tkazib berishingizni so'rayman: " -> Men, MATCHANOVA AZIZA BEKTURDIYEVNA sizdan 07.04.2025 yildagi №717-XMS-sonli kredit shartnomasiga asosan 125000000(yuz yigirma besh million so'm)so'm pul mablag'larini quyidagi rekvizitlar asosida o'tkazib berishingizni so'rayman:
A10: =malumot!A93 -> Bank nomi: | B10: =malumot!B93 -> «HAMKOR BANK» AJ
A11: =malumot!A94 -> H/r: | B11: =malumot!B94 -> 2312 0000 6000 1143 7200
A12: =malumot!A95 -> MFO: | B12: =malumot!B95 -> 00083
A13: =malumot!A96 -> STIR: | B13: =malumot!B96 -> 200242936
A14: =malumot!A97 -> Karta raqami: | B14: =malumot!B97 -> 9860 1678 4680 5015
A16: =malumot!B5 -> MATCHANOVA AZIZA BEKTURDIYEVNA | D16: ________________
D17: (imzo)
A20: =malumot!B157&" ijrochi direktori" -> «CLEVER MIKROMOLIYA TASHKILOTI» MChJ ijrochi direktori | D20: N. Abduraximov
A23: sana | B23: _______________

Sheet muqova
B2: =malumot!B158 -> «CLEVER MIKROMOLIYA TASHKILOTI» MChJ
B12: =malumot!B5 -> MATCHANOVA AZIZA BEKTURDIYEVNA
B19: =""&malumot!C64&" shartnoma "&malumot!B74&"" -> Mikrokredit shartnoma 7 aprel 2025 y.dan №717-XMS
B24: =" Foiz stavkasi: "&malumot!B86&"%" -> Foiz stavkasi: 55%
B25: =" "&malumot!C64&" muddati: "&malumot!B82&" oy" -> Mikrokredit muddati: 36 oy
B26: =" "&malumot!C64&" miqdori: "&FIXED(malumot!B76,2)&" so'm" -> Mikrokredit miqdori: 125 000 000,00 so'm
B40: ="Toshkent sh., "&malumot!B70&"" -> Toshkent sh., 7 aprel 2025 y.

Sheet mijoz_anketasi
A1: MIJOZNING ANKETASI
A2: Anketa kredit menejeri tomonidan mijozning javoblarini kiritish orqali to'ldiriladi, kerak bo'lganda, Mijoz tomonidan tanlangan javob variantlarini belgilash orqali amalga oshiriladi
A3: 1. MIJOZ HAQIDA MA'LUMOTLAR:
A4: =xulosa!A4:E4 -> Mijozning to'liq ismi sharifi: MATCHANOVA AZIZA BEKTURDIYEVNA
A5: =xulosa!A5:E5 -> Tug'ilgan sanasi: 09.04.1990 y
A6: =xulosa!A6:E6 -> Pasport seriyasi AC 2074678 XORAZM VILOYATI SHOVOT TUMANI IIB tomonidan 17.07.2019 yilda berilgan, amal qilish muddati - 16.07.2029 y.
A7: ="Fuqaroligi: "&malumot!B32&"" -> Fuqaroligi: O’zbekiston Respublikasi
A8: =xulosa!A7:E7 -> Ro‘yxatdan o‘tgan manzili: XORAZM VILOYATI SHOVOT TUMANI BOYRACHI QFY BOBORAXIM KO'CHASI 4-UY, mo'ljal: SHOVOT TUMANI BOYRACH QFY MADANIYAT MARKAZI
A9: =IF(malumot!B23="mos keladi"," ",mijoz_anketasi!A10:F10)
A10: ="Haqiqatdan yashash joy manzili: "&malumot!B28&"" -> Haqiqatdan yashash joy manzili: XORAZM VILOYATI SHOVOT TUMANI BOYRACHI QFY BOBORAXIM KO'CHASI 4-UY
A11: =xulosa!A8:E8 -> Ish joyi: lavozimi TIKISH-BICHISHda O'Z O'ZINI BAND QILGAN FUQARO
A12: 2. Mijoz bilan ulanich uchun aloqa ma'lumotlari:
A13: ="Uy telefoni raqami: "&malumot!B40&"" -> Uy telefoni raqami: 91 860-86-87 O'ZI
A14: ="Uyali telefon raqami: "&malumot!B41&"" -> Uyali telefon raqami: 33 381-86-87 Ayoli
A15: ="Uyali telefon raqami: "&malumot!B42&"" -> Uyali telefon raqami: 99-187-10-62 Otasi
A16: ="Uyali telefon raqami: "&malumot!B42&"" -> Uyali telefon raqami: 99-187-10-62 Otasi
A17: ="Ish telefoni raqami: "&malumot!B43&"" -> Ish telefoni raqami:
A18: 3. MIJOZNING ISH JOYI HAQIDA MA'LUMOT:
A19: ="Muassasa nomlanishi:"&malumot!B58&"" -> Muassasa nomlanishi:O'Z O'ZINI BAND QILGAN FUQARO № MALUMOTNOMA № 0009500363
A20: ="Ro‘yxatdan o‘tish manzili:"&malumot!B50&"" -> Ro‘yxatdan o‘tish manzili:
A21: ="Lavozimi: "&malumot!B59&"" -> Lavozimi: TIKISH-BICHISH
A22: 4. MIJOZNING OYLIK DAROMADLARI VA XARAJATLARI HAQIDA MA'LUMOT
A23: Daromad manbalari | B23: Mijoz | C23: Turmush o'rtog'i | D23: Boshqa oila a'zolari | E23: Xarajatlar | F23: Мiqdori
A24: ish haqi (asosiy ish) | B24: =malumot!B60 -> 12000000 | C24: 0 | D24: 0 | E24: uy-joy va kommunal xizmatlar uchun to'lov | F24: 700000
A25: ish haqi (o‘rindoshlik) | B25: 0 | C25: 0 | D25: 0 | E25: oilaviy xarajatlar | F25: 500000
A26: boshqa daromadlar | B26: =malumot!B61 -> 0 | C26: 0 | D26: 0 | E26: boshqa xarajatlar | F26: 500000
A27: JAMI | B27: =B24+B25+B26 -> 12000000 | C27: =SUM(C24:C26) -> 0 | D27: =SUM(D24:D26) -> 0 | F27: =SUM(F24:F26) -> 1700000
A28: ="Men, "&malumot!B5&", ushbu anketada ko‘rsatilgan barcha ma'lumotlar anketa to'ldirilgan sanada to'g'ri va aniq ekanligini tasdiqlayman." -> Men, MATCHANOVA AZIZA BEKTURDIYEVNA, ushbu anketada ko‘rsatilgan barcha ma'lumotlar anketa to'ldirilgan sanada to'g'ri va aniq ekanligini tasdiqlayman.
A29: ="Men, "&malumot!B5&", quyidagilarni tan olaman va roziman::" -> Men, MATCHANOVA AZIZA BEKTURDIYEVNA, quyidagilarni tan olaman va roziman::
A30: ="1. Ushbu anketada ko‘rsatilgan har qanday ma’lumot "&malumot!B157&", uning xodimlari va huquqiy vorislari tomonidan istalgan manbaa va ma’lumotlardan foydalangan holda istalgan vaqtda tekshirilishi va qayta tekshirilishi mumkin." -> 1. Ushbu anketada ko‘rsatilgan har qanday ma’lumot «CLEVER MIKROMOLIYA TASHKILOTI» MChJ, uning xodimlari va huquqiy vorislari tomonidan istalgan manbaa va ma’lumotlardan foydalangan holda istalgan vaqtda tekshirilishi va qayta tekshirilishi mumkin.
A31: ="2. Mazkur anketaning "&malumot!B157&" tomonidan qabul qilinishi “Clever Mikromoliya Tashkiloti” MChJ tomonidan menga "&malumot!B65&" berish majburiyatini yuklamaydi." -> 2. Mazkur anketaning «CLEVER MIKROMOLIYA TASHKILOTI» MChJ tomonidan qabul qilinishi “Clever Mikromoliya Tashkiloti” MChJ tomonidan menga mikrokredit berish majburiyatini yuklamaydi.
A32: Men, _________________________________________________________________ (to'liq ismi sharifi), ushbu anketadagi barcha ma'lumotlar anketa to'ldirilgan sanada to'g'ri ekanligini tasdiqlayman va ushbu anketaning 1- va 2-bandlarini tan olaman va ularga rozilik bildiraman. Mazkur anketaning 4-bo'limida ko'rsatilgan daromadlarim haqidagi ma'lumotlarni qabul qilishingizni va moliyaviy tahlilda foydalanishingizni so’rayman.
A34: Mijozning to'liq ismi sharifi | D34: Sana | E34: Imzo
D35: =malumot!B2 -> 07.04.2025

Sheet majburiyatnoma
A3: MAJBURIYATNOMA
A4: =" Men, fuqaro "&malumot!B5&" "&malumot!B159&" bilan "&malumot!B69&" sanasidagi "&malumot!B66&"-sonli shartnomaning garov ta'minoti sifatida taqdim etilayotgan mulk "&malumot!B132&" rusumli avtotransport vositasini qonunga xilof ravishda o‘zlashtirmaslikka, yashirmaslikka, nobud qilmaslikka yoki unga shikast yetkazmaslik majburiyatini olaman." -> Men, fuqaro MATCHANOVA AZIZA BEKTURDIYEVNA «CLEVER MIKROMOLIYA TASHKILOTI» MChJ bilan 7 aprel 2025 y. sanasidagi №717-XMS-sonli shartnomaning garov ta'minoti sifatida taqdim etilayotgan mulk JAC M3 rusumli avtotransport vositasini qonunga xilof ravishda o‘zlashtirmaslikka, yashirmaslikka, nobud qilmaslikka yoki unga shikast yetkazmaslik majburiyatini olaman.
A5: Ushbu majburiyatlarimni bajarmagan taqdirimda O'zbekiston Respublikasi jinoyat kodeksining 233-moddasi talablari asosida javobgarlik tog'risida ogohlantrildim.
A7: =malumot!B5 -> MATCHANOVA AZIZA BEKTURDIYEVNA | B7: Imzo_____________
A11: ="sana: "&TEXT(malumot!B2,"ДД.ММ.ГГГГ")&" y." -> sana: 07.04.2025 y.

Sheet kredit_ariza
C1: =""&malumot!B157&"ning "&malumot!A160&"" -> «CLEVER MIKROMOLIYA TASHKILOTI» MChJning Xorazm filiali boshlig'i
D2: =""&malumot!B160&"ga" -> M.Sharipovga
A4: =""&malumot!C64&" olish uchun Ariza" -> Mikrokredit olish uchun Ariza
A6: =""&malumot!B28&".-da yashovchi O‘zbekiston Respublikasi fuqarosi "&malumot!B8&"dan. " -> XORAZM VILOYATI SHOVOT TUMANI BOYRACHI QFY BOBORAXIM KO'CHASI 4-UY.-da yashovchi O‘zbekiston Respublikasi fuqarosi MATCHANOVA AZIZA BEKTURDIYEVNAdan.
A7: ="Tug'ilgan kuni: "&malumot!B15&"" -> Tug'ilgan kuni: 09.04.1990 y
A8: ="Pasport seriyasi: "&malumot!B16&" "&malumot!B20&"" -> Pasport seriyasi: AC 2074678 XORAZM VILOYATI SHOVOT TUMANI IIB tomonidan 17.07.2019 yilda berilgan
A9: ="Asosiy ish joyi : "&malumot!B58&"" -> Asosiy ish joyi : O'Z O'ZINI BAND QILGAN FUQARO № MALUMOTNOMA № 0009500363
A10: ="Lavozimi: "&malumot!B59&"" -> Lavozimi: TIKISH-BICHISH
A11: ="O’rtacha oylik daromadi: "&FIXED(malumot!B60,2)&" so'm." -> O’rtacha oylik daromadi: 12 000 000,00 so'm.
A12: ="Menga quyidagi shartlarda "&malumot!B65&" berishingizni so’rayman:" -> Menga quyidagi shartlarda mikrokredit berishingizni so’rayman:
A13: =""&malumot!C64&" summasi: "&FIXED(malumot!B76,2)&" ("&malumot!B77&") so'm." -> Mikrokredit summasi: 125 000 000,00 (yuz yigirma besh million so'm) so'm.
A14: =""&malumot!C64&" muddati: "&malumot!B82&" ("&malumot!B83&") oy." -> Mikrokredit muddati: 36 (O'ttiz olti ) oy.
A15: =""&malumot!C64&"dan foydalanganlik uchun foiz stavkasi: yillik "&malumot!B86&"% ("&malumot!B87&") foiz" -> Mikrokreditdan foydalanganlik uchun foiz stavkasi: yillik 55% (Ellik besh ) foiz
A16: =""&malumot!C64&" bo'yicha asosiy qarz va foizlarni to'lash:" -> Mikrokredit bo'yicha asosiy qarz va foizlarni to'lash:
A17: =" - "&malumot!B65&" shartnomasi bo'yicha har oy differensial to'lovlari amalga oshiriladi" -> - mikrokredit shartnomasi bo'yicha har oy differensial to'lovlari amalga oshiriladi
A18: =" - "&malumot!B65&" shartnomasi bo'yicha har oy annuitet to'lovlari amalga oshiriladi" -> - mikrokredit shartnomasi bo'yicha har oy annuitet to'lovlari amalga oshiriladi
A19: =IF(malumot!B78=malumot!C78,kredit_ariza!A17:D17,IF(malumot!B78=malumot!D78,kredit_ariza!A18:D18)) -> - mikrokredit shartnomasi bo'yicha har oy annuitet to'lovlari amalga oshiriladi
A20: =IF(DAY(malumot!E67)<15," "," Oxirgi yakuniy to'lov "&malumot!B65&" shartnomasi tuzilgan kundan boshlab oxirgi oyning oxirgi kunida amalga oshiriladi")
A21: =""&malumot!C64&" ta’minoti::" -> Mikrokredit ta’minoti::
A22: ="1. "&IF(malumot!B110="Avtotransport",A26,A23)&"" -> 1. Egalik huquqi BEKOV OTABEK BAXODIROVICHga tegishli bo'lgan garovga olingan avtomobil markasi JAC M3, rangi - QORA CHERNIY, ishlab chiqarilgan yili - 2023, davlat raqam belgisi 90C477ZA, kuzov turi - YENGIL MINIVEN, kuzov raqami P08461541, dvigatel raqami LJ166A33XP2208188, shassi raqami - Rakamsiz
A23: =IF(malumot!B99=malumot!C99,A25,IF(malumot!B99=malumot!D99,A24,0)) -> Egalik huquqi 0ga tegishli bo'lgan umumiy maydoni - va yashash maydoni - 0,
A24: =" - Navbatdagi garov (ipoteka) Egalik huquqi asosida "&malumot!C124&"ga "&malumot!C133&", umumiy maydoni - "&malumot!C137&" va yashash maydoni - "&malumot!C140&", manzili: "&malumot!C130&"." -> - Navbatdagi garov (ipoteka) Egalik huquqi asosida 0ga 0, umumiy maydoni - va yashash maydoni - , manzili: .
A25: =" Egalik huquqi "&malumot!C124&"ga tegishli bo'lgan umumiy maydoni - "&malumot!C137&" va yashash maydoni - "&malumot!C140&" "&malumot!C133&", "&malumot!C130&" " -> Egalik huquqi 0ga tegishli bo'lgan umumiy maydoni - va yashash maydoni - 0,
A26: =IF(malumot!B99=malumot!C99,kredit_ariza!A28:D28,IF(malumot!B99=malumot!D99,kredit_ariza!A27:D27,0)) -> Egalik huquqi BEKOV OTABEK BAXODIROVICHga tegishli bo'lgan garovga olingan avtomobil markasi JAC M3, rangi - QORA CHERNIY, ishlab chiqarilgan yili - 2023, davlat raqam belgisi 90C477ZA, kuzov turi - YENGIL MINIVEN, kuzov raqami P08461541, dvigatel raqami LJ166A33XP2208188, shassi raqami - Rakamsiz
