Workbook
Name mos: '[1]Общие данные'!$C$23:$D$23
Name mulk: '[1]Общие данные'!$C$24:$W$24

Sheet malumot
A1: =CONCATENATE(B65," olish uchun ariza") -> mikroqarz olish uchun ariza | B1: №659-SR
A2: =CONCATENATE(B65," olish uchun ariza sanasi QO’L BILAN KIRITILADI") -> mikroqarz olish uchun ariza sanasi QO’L BILAN KIRITILADI | B2: 24.03.2025 | D2: =180+B2 -> 45920
A4: Qarz oluvchi bo’yicha ma’lumotlar
A5: Ariza beruvchining FISh (kim? – Ibragimov Rustam Sadikovich) | B5: SHAYMARDANOVA SABOXAT YULDASHEVNA | C5: yu
A6: agar o’zgarishlar bo’lgan bo’lsa oldingi FISh (Sadikov Rustam Sadikovich yoki yo’q) | B6: yo’q | C6: ha | D6: yo’q
A7: Ariza beruvchining FISh (kim? – Ibragimov R.S.) | B7: SHAYMARDANOVA S.Y.
A8: FISh (ariza kimdan? – Ibragimov Rustam Sadikovichdan) | B8: =B5 -> SHAYMARDANOVA SABOXAT YULDASHEVNA
A9: FISh (kimdan? – Ibragimov R.S.dan) | B9: =B7 -> SHAYMARDANOVA S.Y.
A10: FISh (kimga? – Ibragimov Rustam Sadikovichga) | B10: =B8 -> SHAYMARDANOVA SABOXAT YULDASHEVNA
A11: FISh (kimga? – Ibragimov R.S.ga) | B11: =B9 -> SHAYMARDANOVA S.Y.
A12: FISh (kim bilan? – Ibragimov Rustam Sadikovich bilan) | B12: =B10 -> SHAYMARDANOVA SABOXAT YULDASHEVNA
A13: FISh (kim bilan? – Ibragimov R.S. bilan) | B13: =B11 -> SHAYMARDANOVA S.Y.
A14: Fuqaroligi (O’zbekiston Respublikasi) | B14: O’zbekiston Respublikasi
A15: Tug’ilgan sanasi (01.10.2011 yil) | B15: 09.11.1976 yil
A16: Pasport seriyasi (СА №1234567) | B16: AC 1659096
B17: SURXONDARYO VILOYATI JARQO'RG'ON TUMANI IIB | D17: =TEXT(C17,"ДД.ММ.ГГГГ") -> 00.01.1900
B18: 43517 | C18: =TEXT(B18,"ДД.ММ.ГГГГ") -> 21.02.2019
B19: 47169 | C19: =TEXT(B19,"ДД.ММ.ГГГГ") -> 20.02.2029
A20: Kim va qachon berilgan (Toshkent shahri Chilonzor IIB tomonidan 2011 yil __.____) | B20: =""&B17&" tomonidan "&C18&" yilda berilgan" -> SURXONDARYO VILOYATI JARQO'RG'ON TUMANI IIB tomonidan 21.02.2019 yilda berilgan | C20: =""&B17&" tomonidan "&C18&" yilda berilgan" -> SURXONDARYO VILOYATI JARQO'RG'ON TUMANI IIB tomonidan 21.02.2019 yilda berilgan
A21: Pasportni amal qilish muddati (01.10.2011 yilgacha / yoki muddatsiz) | B21: =""&C19&" y." -> 20.02.2029 y. | C21: =""&C19&" yilgacha" -> 20.02.2029 yilgacha
A22: doimiy ro’yhatdan o’tgan joyi (Toshkent sh., Mirobod tumani, Nukus ko’chasi, 1 uy, 1 honadon) | B22: SURXONDAEYO VILOYATU JARQO'RG'ON TUMANI QORAYONTOQ MFY IBN SINO KO'CHASI 114-UY | C22: =TEXT(B19,"ДД.ММ.ГГГГ") -> 20.02.2029
A23: doimiy ro’yhatdan o’tgan joyi haqiqatdagi turar joyi bilan mos keladi/mos kelmaydi | B23: mos keladi | C23: mos keladi | D23: mos kelmaydi
A24: Ro’yhatdan o’tish joyida yashash asosi | B24: Mulk huquqi | C24: Mulk huquqi | D24: ijara | E24: служебная | F24: другое | G24: -
A25: Telefon raqami kod bilan ((99871) 277 77 77) | B25: 93-763-00-67 MIJOZ
A26: Mo’ljal | B26: QORAYONTOQ BEKAT
B27: =IF(B23="mos keladi",B22,B28) -> SURXONDAEYO VILOYATU JARQO'RG'ON TUMANI QORAYONTOQ MFY IBN SINO KO'CHASI 114-UY
A28: Haqiqatdagi yashash joyi (Toshkent sh., Mirobod tumani, Nukus ko’chasi, 1 uy, 1 honadon) | B28: SURXONDARYO VILOYATI JARQO'RG'ON TUMANI QORAYONTOQ MFY IBN SINO KO'CHASI 114-UY
A29: Haqiqatdagi yashash joyida turish asosi | B29: Mulk huquqi | C29: Mulk huquqi | D29: ijara | E29: xizmat | F29: boshqa | G29: -
A30: Mijozning jinsi | B30: ayol | C30: erkak | D30: ayol
A31: Tug’ilgan joyi (Toshkent) | B31: JARQO'RG'ON TUMANI | C31: i
A32: Fuqaroligi (O’zbekiston Respublikasi) | B32: O’zbekiston Respublikasi
A33: Telefon raqami kod bilan ((99871) 277 77 77) | B33: 93-761-09-76 TURMUSH O'RTOG'I
B34: =IF(B23="mos keladi",B26,B35) -> QORAYONTOQ BEKAT
A35: Mo’ljal
A36: Oilaviy ahvoli
A37: Oila a'zolari soni (jami):
A38: Ma’lumoti
A39: Mutaxassisligi | B39: {=+A39:B102} -> Mutaxassisligi
A40: Ish telefoni raqami kod bilan ((99890) 3270000) | B40: 94-706-67-09 UY RAQAMI
A41: Mobil telefon raqami kod bilan ((99890) 3270000) | B41: 93-763-00-67 MIJOZ
A42: Ish telefoni raqami kod bilan ((99890) 3270000) | B42: 93-761-09-76 TURMUSH O'RTOG'I
A43: Mobil telefon raqami kod bilan ((99890) 3270000)
A44: Asosiy ish joyi | B44: Yakka tartibdagi tadbirkor | C44: Yakka tartibdagi tadbirkor | D44: O'Z O'ZINI BAND QILGAN FUQARO
B45: =IF(B44=D44,CONCATENATE("MA'LUMOTNOMA ",B47,B46),C44) -> Yakka tartibdagi tadbirkor
A46: O'Z O'ZINI BAND QILGAN BO'LSA, MA'LUMOTNOMA KIRITING
C47: №
A48: AGAR O'Z O'ZINI BAND QILGAN FUQARO BO'LSA FAOLIYAT TURINI KIRITING
A49: Lavozimi | B49: =IF(B44=C44,C44,B48) -> Yakka tartibdagi tadbirkor
A50: Tashkilotning haqiqiy manzili (Toshkent sh., Mirobod tumani, Nukus ko’chasi, 1 uy, 1 honadon)
A51: Mo’ljal
A52: Ish staji, sanasidan (01.10.2011 yildan)
A53: Umumiy mehnat staji (3 yil/ 5 yil)
A54: Ish joyi telefon raqami
A55: Mijozning STIRi
A56: Mijozning unikal kodi | B56: 990000__
A57: QARZ OLUVCHINING ISH JOYI, LAVOZIMI VA O'RTACHA OYLIK DAROMADI
A58: Ish joyi | B58: =IF(B44=C44,C44,CONCATENATE(B44," ",B47)) -> Yakka tartibdagi tadbirkor
A59: Lavozimi | B59: =B49 -> Yakka tartibdagi tadbirkor
A60: O’rtacha oylik daromadi | B60: 14000000 | C60: =C63/B75 -> 0.47242009
A61: Mijozning boshqa daromadlari | B61: 0 | C61: Йиллик фойз 50 фойздан утиб кетмаслиги керак
A62: Ishning davomiyligi | B62: =B53 -> 0
A63: Ish joyidan ma’lumotnomaning raqami va sanasi | C63: =SUM(grafik!E9:E20) -> 24565845
A64: Kredit bo’yicha parametrlar | C64: =PROPER(B65) -> Mikroqarz | D64: =UPPER(B65) -> MIKROQARZ
A65: Kredit turi | B65: =IF(B75>100000001,"mikrokredit",IF(B75<100000001,"mikroqarz",0)) -> mikroqarz | C65: =DATE(YEAR(B67),MONTH(B67)+B81,DAY(B67)) -> 46836
A66: Kredit shartnomasi raqami | B66: =B1 -> №659-SR | C66: =MONTH(C65) -> 3 | D66: =IF(C66=C68,C70,IF(C66=D68,D70,IF(C66=E68,E70,IF(C66=F68,F70,IF(C66=G68,G70,IF(C66=H68,H70,IF(C66=I68,I70,IF(C66=J68,J70,IF(C66=K68,K70,IF(C66=L68,L70,IF(C66=M68,M70,IF(C66=N68,N70,)))))))))))) -> mart | E66: =DAY(C65) -> 24 | F66: =YEAR(C65) -> 2028 | G66: =MONTH(C65) -> 3 | H66: =IF(C66=C68,C71,IF(C66=D68,D71,IF(C66=E68,E71,IF(C66=F68,F71,IF(C66=G68,G71,IF(C66=H68,H71,IF(C66=I68,I71,IF(C66=J68,J71,IF(C66=K68,K71,IF(C66=L68,L71,IF(C66=M68,M71,IF(C66=N68,N71,)))))))))))) -> mart | I66: =YEAR(C65) -> 2028
A67: Kredit shartnomasi sanasi (14.10.2011) | B67: =B2 -> 24.03.2025 | C67: =MONTH(B67) -> 3 | D67: =IF(C67=C68,C70,IF(C67=D68,D70,IF(C67=E68,E70,IF(C67=F68,F70,IF(C67=G68,G70,IF(C67=H68,H70,IF(C67=I68,I70,IF(C67=J68,J70,IF(C67=K68,K70,IF(C67=L68,L70,IF(C67=M68,M70,IF(C67=N68,N70,)))))))))))) -> mart | E67: =DAY(B67) -> 24 | F67: =YEAR(B67) -> 2025 | G67: =MONTH(B67) -> 3 | H67: =IF(C67=C68,C71,IF(C67=D68,D71,IF(C67=E68,E71,IF(C67=F68,F71,IF(C67=G68,G71,IF(C67=H68,H71,IF(C67=I68,I71,IF(C67=J68,J71,IF(C67=K68,K71,IF(C67=L68,L71,IF(C67=M68,M71,IF(C67=N68,N71,)))))))))))) -> mart | I67: =YEAR(B67) -> 2025
A68: Kredit shartnomasi sanasi (14.10.2011 y.) | B68: =""&E67&" "&D67&" "&F67&" y." -> 24 mart 2025 y. | C68: 1 | D68: 2 | E68: 3 | F68: 4 | G68: 5 | H68: 6 | I68: 7 | J68: 8 | K68: 9 | L68: 10 | M68: 11 | N68: 12
B69: =""&E67&" "&H67&" "&F67&" y." -> 24 mart 2025 y.
B70: =B68 -> 24 mart 2025 y. | C70: yanvar | D70: fevral | E70: mart | F70: aprel | G70: may | H70: iyun | I70: iyul | J70: avgust | K70: sentabr | L70: oktabr | M70: noyabr | N70: dekabr
B71: =B69 -> 24 mart 2025 y. | C71: yanvar | D71: fevral | E71: mart | F71: aprel | G71: may | H71: iyun | I71: iyul | J71: avgust | K71: sentabr | L71: oktabr | M71: noyabr | N71: dekabr
A72: Tugash sanasi QO’L BILAN KIRITILADI | B72: =""&E66&" "&D66&" "&F66&" y." -> 24 mart 2028 y.
B73: =""&E66&" "&H66&" "&F66&" y." -> 24 mart 2028 y.
A74: Kredit shartnomasi raqami va sanasi | B74: =""&B68&"dan "&B66&"" -> 24 mart 2025 y.dan №659-SR
A75: =CONCATENATE(B65," miqdori (summasi)") -> mikroqarz miqdori (summasi) | B75: 52000000 | C75: Uzbek tilida
A76: QO’L BILAN KIRITILADI | B76: =""&SUBSTITUTE(SUBSTITUTE(SUBSTITUTE(TRIM(SUBSTITUTE(SUBSTITUTE(SUBSTITUTE(SUBSTITUTE(SUBSTITUTE(SUBSTITUTE(SUBSTITUTE(SUBSTITUTE(SUBSTITUTE(SUBSTITUTE(SUBSTITUTE(SUBSTITUTE(SUBSTITUTE(SUBSTITUTE(SUBSTITUTE(SUBSTITUTE(SUBSTITUTE(SUBSTITUTE(SUBSTITUTE(SUBSTITUTE(SUBSTITUTE(SUBSTITUTE(SUBSTITUTE(SUBSTITUTE(SUBSTITUTE(SUBSTITUTE(SUBSTITUTE(SUBSTITUTE(SUBSTITUTE(SUBSTITUTE(SUBSTITUTE(SUBSTITUTE(SUBSTITUTE(SUBSTITUTE(SUBSTITUTE(SUBSTITUTE(SUBSTITUTE(SUBSTITUTE(SUBSTITUTE(SUBSTITUTE(SUBSTITUTE(SUBSTITUTE(SUBSTITUTE(SUBSTITUTE(IF(LEN(INT(B75))>6,ROMAN(MID(INT(B75),1,LEN(INT(B75))-6)+0)&" million "&ROMAN(MID(INT(B75),LEN(INT(B75))-5,3)+0)&" ming "&ROMAN(MID(INT(B75),LEN(INT(B75))-2,3)+0),IF(LEN(INT(B75))>3,ROMAN(MID(INT(B75),1,LEN(INT(B75))-3)+0)&" ming "&ROMAN(MID(INT(B75),LEN(INT(B75))-2,3)+0),ROMAN(INT(B75)))),"DCCC"," sakkiz yuz"),"DCC"," yetti yuz"),"DC"," olti yuz"),"CD"," to'rt yuz"),"XC"," to'qson"),"CCC"," uch yuz"),"CC"," ikki yuz"),"D"," besh yuz"),"CM"," to'qqiz yuz"),"C"," yuz"),"XL"," qirq"),"LXXX"," sakson"),"LXX"," yetmish"),"LX"," oltmish"),"L"," ellik"),"XXX"," o'ttiz"),"XX"," yigirma"),"XIX"," o'n toqqiz"),"XVIII"," o'n sakkiz"),"XVII"," o'n yetti"),"XVI"," o'n olti"),"XV"," o'n besh"),"XIV"," o'n to'rt"),"XIII"," o'n uch"),"XII"," o'n ikki"),"XI"," o'n bir"),"IX"," to'qqiz"),"X"," o'n"),"VIII"," sakkiz"),"VII"," yetti"),"VI"," olti"),"IV"," to'rt"),"V"," besh"),"III"," uch"),"II"," ikki"),"I"," bir"),"bir ming","bir ming"),"ikki ming","ikki ming"),"uch ming","uch ming"),"to'rt ming","to'rt ming"),"bir million","bir million"),"ikki million","ikki million"),"uch million","uch million"),"to'rt million","to'rt million")),"million ming","million"),"million ming","million"),"million ming","million")&" so'm" -> ellik ikki million so'm | C76: =UPPER(LEFT(SUBSTITUTE(SUBSTITUTE(SUBSTITUTE(TRIM(SUBSTITUTE(SUBSTITUTE(SUBSTITUTE(SUBSTITUTE(SUBSTITUTE(SUBSTITUTE(SUBSTITUTE(SUBSTITUTE(SUBSTITUTE(SUBSTITUTE(SUBSTITUTE(SUBSTITUTE(SUBSTITUTE(SUBSTITUTE(SUBSTITUTE(SUBSTITUTE(SUBSTITUTE(SUBSTITUTE(SUBSTITUTE(SUBSTITUTE(SUBSTITUTE(SUBSTITUTE(SUBSTITUTE(SUBSTITUTE(SUBSTITUTE(SUBSTITUTE(SUBSTITUTE(SUBSTITUTE(SUBSTITUTE(SUBSTITUTE(SUBSTITUTE(SUBSTITUTE(SUBSTITUTE(SUBSTITUTE(SUBSTITUTE(SUBSTITUTE(SUBSTITUTE(SUBSTITUTE(SUBSTITUTE(SUBSTITUTE(SUBSTITUTE(SUBSTITUTE(SUBSTITUTE(SUBSTITUTE(SUBSTITUTE(SUBSTITUTE(SUBSTITUTE(SUBSTITUTE(IF(LEN(ROUNDDOWN(B75,0))>6,ROMAN(MID(ROUNDDOWN(B75,0),1,LEN(ROUNDDOWN(B75,0))-6)+0)&" million "&ROMAN(MID(ROUNDDOWN(B75,0),LEN(ROUNDDOWN(B75,0))-5,3)+0)&" ming "&ROMAN(MID(ROUNDDOWN(B75,0),LEN(ROUNDDOWN(B75,0))-2,3)+0)&" so'm",IF(LEN(ROUNDDOWN(B75,0))>3,ROMAN(MID(ROUNDDOWN(B75,0),1,LEN(ROUNDDOWN(B75,0))-3)+0)&" ming "&ROMAN(MID(ROUNDDOWN(B75,0),LEN(ROUNDDOWN(B75,0))-2,3)+0)&" so'm",ROMAN(ROUNDDOWN(B75,0))&" so'm")),"DCCC"," sakkiz yuz"),"DCC"," yetti yuz"),"DC"," olti yuz"),"CD"," to'rt yuz"),"XC"," to'qson"),"CCC"," uch yuz"),"CC"," ikki yuz"),"D"," besh yuz"),"CM"," to'qqiz yuz"),"C"," yuz"),"XL"," qiriq"),"LXXX"," sakson"),"LXX"," yetmish"),"LX"," oltmish"),"L"," ellik"),"XXX"," o'ttiz"),"XX"," yigirma"),"XIX"," o'n tiqqiz"),"XVIII"," o'n sakkiz"),"XVII"," o'n yetti"),"XVI"," o'n olti"),"XV"," o'n besh"),"XIV"," o'n to'rt"),"XIII"," o'n uch"),"XII"," o'n ikki"),"XI"," o'n bir"),"IX"," to'qqiz"),"X"," o'n"),"VIII"," sakkiz"),"VII"," yetti"),"VI"," olti"),"IV"," to'rt"),"V"," besh"),"III"," uch"),"II"," ikki"),"I"," bir"),"bir ming","bir ming"),"ikki ming","ikki ming"),"uch ming","uch ming"),"to'rt ming","to'rt ming"),"bir million","bir million"),"ikki million","ikki million"),"uch million","uch million"),"to'rt million","to'rt million"),"bir so'm","bir so'm"),"ikki so'm","ikki so'm"),"uch so'm","uch so'm"),"to'rt so'm","to'rt so'm")),"ming million","million"),"ming million","million"),"ming million","million"),1))&MID(SUBSTITUTE(SUBSTITUTE(SUBSTITUTE(TRIM(SUBSTITUTE(SUBSTITUTE(SUBSTITUTE(SUBSTITUTE(SUBSTITUTE(SUBSTITUTE(SUBSTITUTE(SUBSTITUTE(SUBSTITUTE(SUBSTITUTE(SUBSTITUTE(SUBSTITUTE(SUBSTITUTE(SUBSTITUTE(SUBSTITUTE(SUBSTITUTE(SUBSTITUTE(SUBSTITUTE(SUBSTITUTE(SUBSTITUTE(SUBSTITUTE(SUBSTITUTE(SUBSTITUTE(SUBSTITUTE(SUBSTITUTE(SUBSTITUTE(SUBSTITUTE(SUBSTITUTE(SUBSTITUTE(SUBSTITUTE(SUBSTITUTE(SUBSTITUTE(SUBSTITUTE(SUBSTITUTE(SUBSTITUTE(SUBSTITUTE(SUBSTITUTE(SUBSTITUTE(SUBSTITUTE(SUBSTITUTE(SUBSTITUTE(SUBSTITUTE(SUBSTITUTE(SUBSTITUTE(SUBSTITUTE(SUBSTITUTE(SUBSTITUTE(SUBSTITUTE(IF(LEN(ROUNDDOWN(B75,0))>6,ROMAN(MID(ROUNDDOWN(B75,0),1,LEN(ROUNDDOWN(B75,0))-6)+0)&" million "&ROMAN(MID(ROUNDDOWN(B75,0),LEN(ROUNDDOWN(B75,0))-5,3)+0)&" "&ROMAN(MID(ROUNDDOWN(B75,0),LEN(ROUNDDOWN(B75,0))-2,3)+0)&" so'm",IF(LEN(ROUNDDOWN(B75,0))>3,ROMAN(MID(ROUNDDOWN(B75,0),1,LEN(ROUNDDOWN(B75,0))-3)+0)&" ming "&ROMAN(MID(ROUNDDOWN(B75,0),LEN(ROUNDDOWN(B75,0))-2,3)+0)&" so'm",ROMAN(ROUNDDOWN(B75,0))&" so'm")),"DCCC"," sakkiz yuz"),"DCC"," yetti yuz"),"DC"," olti yuz"),"CD"," to'rt yuz"),"XC"," to'qson"),"CCC"," uch yuz"),"CC"," ikki yuz"),"D"," besh yuz"),"CM"," to'qqiz yuz"),"C"," yuz"),"XL"," qirq"),"LXXX"," sakson"),"LXX"," yetmish"),"LX"," oltmish"),"L"," ellik"),"XXX"," o'ttiz"),"XX"," yigirma"),"XIX"," o'n to'qqiz"),"XVIII"," o'n sakkiz"),"XVII"," o'n yetti"),"XVI"," o'n olti"),"XV"," o'n besh"),"XIV"," o'n to'rt"),"XIII"," o'n uch"),"XII"," o'n ikki"),"XI"," o'n bir"),"IX"," to'qqiz"),"X"," o'n"),"VIII"," sakkiz"),"VII"," yetti"),"VI"," olti"),"IV"," to'rt"),"V"," besh"),"III"," uch"),"II"," ikki"),"I"," bir"),"bir ming","bir ming"),"ikki ming","ikki ming"),"uch ming","uch ming"),"to'rt ming","to'rt ming"),"bir million","bir million"),"ikki million","ikki million"),"uch million","uch million"),"to'rt million","to'rt million"),"bir so'm","bir so'm"),"ikki so'm","ikki so'm"),"uch so'm","uch so'm"),"to'rt so'm","to'rt so'm")),"ming million","million"),"ming million","million"),"ming million","million"),2,200)&"" -> Ellik ikki million so'm
A77: Grafik turi | B77: differensial | C77: differensial | D77: annuitet
A78: =CONCATENATE(B65,"ni to'lash sanasi (14.10.2011)") -> mikroqarzni to'lash sanasi (14.10.2011) | B78: 1 | C78: =DATE(YEAR(B67),MONTH(B67)+1,DAY(B78)) -> 45748 | D78: Пн | E78: Вт | F78: Ср | G78: Чт | H78: Пт | I78: Сб | J78: Вс
A79: =CONCATENATE(B65,"ni to'lash sanasi (14.10.2011 y.) QO’L BILAN KIRITILADI") -> mikroqarzni to'lash sanasi (14.10.2011 y.) QO’L BILAN KIRITILADI | B79: =DATE(YEAR(B67),MONTH(B67)+1,DAY(B78+C80)) -> 45748 | C79: =TEXT(C78,"ддд") -> Вт | D79: Пн | E79: Вт | F79: Ср | G79: Чт | H79: Пт | I79: Сб | J79: Вс
A80: Mikroqarzni to'lash sanasi (14.10.2011 y.) QO’L BILAN KIRITILADI | B80: =B79 -> 45748 | C80: =IF(C79=I79,2,IF(C79=J79,1,0)) -> 0
A81: =CONCATENATE(B65," muddati") -> mikroqarz muddati | B81: 36 | C81: 6 | D81: 12 | E81: 18 | F81: 24 | G81: 36
A82: =CONCATENATE(B65," muddati QO’L BILAN KIRITILADI") -> mikroqarz muddati QO’L BILAN KIRITILADI | B82: o'ttiz olti
A83: Imtiyozli davr | B83: 0 | BJ83: 1 | BK83: 0
A84: =CONCATENATE(B65," stavkasi") -> mikroqarz stavkasi | B84: 0.6
A85: =CONCATENATE(B65," stavkasi") -> mikroqarz stavkasi | B85: 60
A86: =CONCATENATE(B65," stavkasi (so’z bilan)") -> mikroqarz stavkasi (so’z bilan) | B86: Oltmish | C86: Oltmish
A87: =CONCATENATE("Muddati o'tgan ",B65," bo’yicha stavka") -> Muddati o'tgan mikroqarz bo’yicha stavka | B87: 1
A88: QO’L BILAN KIRITILADI | B88: 100
A89: =CONCATENATE("Muddati o'tgan ",B65," bo’yicha stavka") -> Muddati o'tgan mikroqarz bo’yicha stavka | B89: bir yuz | C89: bir yuz
A90: Oylik to'lov | B90: =IF(B77=C77,LARGE(grafik!F9:F26,1),ROUND(PMT(B84/12,B81,-B75,0),-3)) -> 4027823.3
A91: Mijoz plastik kartasi parametrlari
A92: Bank nomi: | B92: «Davr bank»
A93: H/r: | B93: 2312 0000 1000 0112 1001
A94: MFO: | B94: 01121
A95: STIR: | B95: 207212359
A96: Karta raqami: | B96: 6262 7300 8771 9516
A97: GAROV BO’YICHA MA’LUMOTLAR
B98: Birlamchi | C98: Birlamchi | D98: navbatdagi garov
A99: Garovga beruvchi mulkdormi? | B99: yo’q | C99: Ha | D99: yo’q
A100: Agar garovga beruvchi qarz oluvchi bo'lmasa, garovga kim qo'yganligini ko'rsating | B100: Garovga beruvchining o’zi | C100: Garovga beruvchining o’zi | D100: Bosh ishonchnoma bo’yicha boshqa shaxs
A101: Bosh ishonchnoma bo’yicha bo’lsa FIShni ko’rsating
...

Sheet shartnoma
A1: =""&malumot!C64&" shartnoma "&malumot!B66&"" -> Mikroqarz shartnoma №659-SR
A3: ="Toshkent shahri "&malumot!B70&"" -> Toshkent shahri 24 mart 2025 y.
A5: =""&malumot!B153&", bundan buyon «Mikromoliya tashkiloti» deb nomlanuvchi, ishonchnoma asosida xarakat qiluvchi "&malumot!A156&" "&malumot!B156&" bir tomondan va o‘z manfaati yo‘lida hamda o‘z nomidan harakat qiluvchi O‘zbekiston Respublikasi fuqarosi "&malumot!B5&" (pasport raqami "&malumot!B16&", "&malumot!C20&" ), bundan buyon «Qarz oluvchi» deb nomlanuvchi, boshqa tomondan, birgalikda “Tomonlar” yoki alohida “Tomon” deb nomlanuvchilar, Qarz oluvchi tomonidan "&TEXT(malumot!B2,"ДД.ММ.ГГГГ")&" yil,"&malumot!B65&" olish uchun ariza berilganligini hisobga olib, ushbu "&malumot!C64&" shartnomasini (bundan keyin – «Shartnoma») quyidagilar haqida tuzdilar:" -> «CLEVER MIKROMOLIYA TASHKILOTI» MChJ, bundan buyon «Mikromoliya tashkiloti» deb nomlanuvchi, ishonchnoma asosida xarakat qiluvchi Surxondaryo filiali boshlig'i A.PARDAYEV bir tomondan va o‘z manfaati yo‘lida hamda o‘z nomidan harakat qiluvchi O‘zbekiston Respublikasi fuqarosi SHAYMARDANOVA SABOXAT YULDASHEVNA (pasport raqami AC 1659096, SURXONDARYO VILOYATI JARQO'RG'ON TUMANI IIB tomonidan 21.02.2019 yilda berilgan ), bundan buyon «Qarz oluvchi» deb nomlanuvchi, boshqa tomondan, birgalikda “Tomonlar” yoki alohida “Tomon” deb nomlanuvchilar, Qarz oluvchi tomonidan 24.03.2025 yil,mikroqarz olish uchun ariza berilganligini hisobga olib, ushbu Mikroqarz shartnomasini (bundan keyin – «Shartnoma») quyidagilar haqida tuzdilar:
A7: 1. SHARTNOMA PREDMETI
A8: ="1.1. Mikromoliya tashkiloti Qarz oluvchiga umumiy miqdori "&FIXED(malumot!B75,2)&" ("&malumot!C76&") bo‘lgan "&malumot!B65&"ni "&malumot!B71&" dan "&malumot!B73&" gacha bo'lgan muddatga naqd pul va/yoki o'tkazmasi shaklida ajratadi." -> 1.1. Mikromoliya tashkiloti Qarz oluvchiga umumiy miqdori 52 000 000,00 (Ellik ikki million so'm) bo‘lgan mikroqarzni 24 mart 2025 y. dan 24 mart 2028 y. gacha bo'lgan muddatga naqd pul va/yoki o'tkazmasi shaklida ajratadi.
A9: ="1.2. Qarz oluvchi to‘lovlilik, muddatlilik va ta’minlanganlik tamoyillariga amal qilgan holda "&malumot!B65&"dan foydalanish majburiyatini o‘z zimmasiga oladi." -> 1.2. Qarz oluvchi to‘lovlilik, muddatlilik va ta’minlanganlik tamoyillariga amal qilgan holda mikroqarzdan foydalanish majburiyatini o‘z zimmasiga oladi.
A11: ="2. "&malumot!D64&" BERISH VA QAYTARISH TARTIBI" -> 2. MIKROQARZ BERISH VA QAYTARISH TARTIBI
A12: ="2.1. Ushbu Shartnomaning 1.1.-bandida ko‘rsatilgan summa miqdoridagi "&malumot!B65&" Mikromoliya tashkiloti kassasidan naqd pul shaklida va/yoki plastik kartaga o‘tkazish yuli bilan beriladi." -> 2.1. Ushbu Shartnomaning 1.1.-bandida ko‘rsatilgan summa miqdoridagi mikroqarz Mikromoliya tashkiloti kassasidan naqd pul shaklida va/yoki plastik kartaga o‘tkazish yuli bilan beriladi.
A13: ="2.2. "&malumot!C64&" berish ushbu Shartnoma tuzilgan va Qarz oluvchi tomonidan ushbu shartnomaning 3-bo‘limiga muvofiq garov ta'minoti ta'minlangandan so‘ng 10 kalendar kundan kechiktirmay amalga oshiriladi." -> 2.2. Mikroqarz berish ushbu Shartnoma tuzilgan va Qarz oluvchi tomonidan ushbu shartnomaning 3-bo‘limiga muvofiq garov ta'minoti ta'minlangandan so‘ng 10 kalendar kundan kechiktirmay amalga oshiriladi.
A14: ="2.3. "&malumot!C64&" Qarz oluvchi tomonidan ushbu Shartnomaning ajralmas qismi hisoblanadigan 1-ilovasida ko‘rsatilgan to‘lov jadvalida (bundan keyin - To‘lov jadvali) belgilangan miqdor, tartib va muddatlarda qaytariladi." -> 2.3. Mikroqarz Qarz oluvchi tomonidan ushbu Shartnomaning ajralmas qismi hisoblanadigan 1-ilovasida ko‘rsatilgan to‘lov jadvalida (bundan keyin - To‘lov jadvali) belgilangan miqdor, tartib va muddatlarda qaytariladi.
A15: ="2.4. Mikromoliya tashkiloti, "&malumot!B65&" berilgan vaqtdan boshlab, "&malumot!B65&" miqdorining qoldiq summasiga "&malumot!B85&"% ("&malumot!C86&") foiz yillik va yiliga 365/366 kunlik hisobidan foizlar hisoblaydi. To'lov jadvaliga muvofiq asosiy qarz bo'yicha navbatdagi to'lov buzilgan hollarda, "&"foiz stavkasi oshiriladi va Mikromoliya tashkiloti "&malumot!B65&"ning muddati o'tgan asosiy qarz summasiga yillik "&malumot!B88&" ("&malumot!B89&") foiz miqdorida foizlar hisoblaydi." -> 2.4. Mikromoliya tashkiloti, mikroqarz berilgan vaqtdan boshlab, mikroqarz miqdorining qoldiq summasiga 60% (Oltmish) foiz yillik va yiliga 365/366 kunlik hisobidan foizlar hisoblaydi. To'lov jadvaliga muvofiq asosiy qarz bo'yicha navbatdagi to'lov buzilgan hollarda, foiz stavkasi oshiriladi va Mikromoliya tashkiloti mikroqarzning muddati o'tgan asosiy qarz summasiga yillik 100 (bir yuz) foiz miqdorida foizlar hisoblaydi.
A16: 2.4.1 Qarz oluvchining xisob raqamlaridan shartnomaning 4.1.2 bandida ko‘rsatilgan tartibda yechib olingan pul mablag‘lari yechib olinganidan so‘ng mijoz tomonidan kredit qarzdorligini so‘ndirish uchun bank kassalari orqali to‘langan pul mablag‘lari yoki mijoz tomonidan kredit qarzdorligini so‘ndirish uchun bank kassalari orqali to‘langandan so‘ng qarz oluvchining xisob raqamlaridan shartnomaning 4.1.2 bandida ko‘rsatilgan tartibda yechib olingan pul mablag‘larining bir oylik kredit to‘lovini so‘ndirishga yo‘naltirilgan miqdoridan ortiqcha qismi qarz oluvchining to‘lov amalga oshirilgan kundan boshlab 3 bank ish kuni ichida yo‘llagan arizasiga asosan qarz oluvchiga qaytarilishi mumkun. 2.5. Foizlar To‘lov jadvaliga muvofiq asosiy qarzni qaytarish uchun belgilangan sanada to‘lanadi. 2.5.1 Qarz oluvchi tomonidan shartnomaning 2.4 bandida ko‘rsatilgan muddatda ortiqcha to‘langan pul mablag‘larini qaytarish to‘g‘risida ariza berilmagan taqdirda to‘langan ortiqcha pul mablag‘lari mijozning asosiy qarzdorligini so‘ndirishga yo‘naltiriladi.
A17: =CONCATENATE(C17,H17,I17) -> 2.6 Qarz oluvchi tomonidan to‘lov jadvalida ko‘rsatilgan muddatdan oldin xamda to‘lov jadvalida ko‘rsatilgan oylik kredit qarzdorligini so‘ndirish miqdoridan ko‘p miqdorda to‘lovni amalga oshirib, to‘langan pul mablag‘larini asosiy kredit qarzdorligini so‘ndirishga yo‘naltirilishini so‘ralganda qarz oluvchining kredit qarzdorligini so‘ndirish uchun to‘lagan pul mablag‘laridan kredit qarzdorligi to‘langan oy uchun to‘lov jadvali bo‘yicha so‘ndirilishi lozim bo‘lgan foiz qarzdorligi summasi, to‘lov jadvalida foiz qarzdorligi so‘ndirilishi ko‘rsatilgan muddatga qadar tashkilotning xisob raqamida saqlanib to‘lov jadvalida ko‘rsatilgan sanada oylik foiz qarzdorligini so‘ndirishga yo‘naltiriladi. 2.6.1. Qarz oluvchi tomonidan olingan mikroqarzni va undan foydalanganlik uchun foizlarni qaytarish bo‘yicha muddati o‘tgan qarzdorlik hosil bo‘lganda Qarz oluvchi tomonidan ko‘rsatilgan qarzdorlikni to‘lash hisobiga to‘lanadigan summalar quyidagi tartibda hisobga olinadi: | C17: 2.6 Qarz oluvchi tomonidan to‘lov jadvalida ko‘rsatilgan muddatdan oldin xamda to‘lov jadvalida ko‘rsatilgan oylik kredit qarzdorligini so‘ndirish miqdoridan ko‘p miqdorda to‘lovni amalga oshirib, to‘langan pul mablag‘larini asosiy kredit qarzdorligini so‘ndirishga yo‘naltirilishini so‘ralganda qarz oluvchining kredit qarzdorligini so‘ndirish uchun to‘lagan pul mablag‘laridan kredit qarzdorligi to‘langan oy uchun to‘lov jadvali bo‘yicha so‘ndirilishi lozim bo‘lgan foiz qarzdorligi summasi, to‘lov jadvalida foiz qarzdorligi so‘ndirilishi ko‘rsatilgan muddatga qadar tashkilotning xisob raqamida saqlanib to‘lov jadvalida ko‘rsatilgan sanada oylik foiz qarzdorligini so‘ndirishga yo‘naltiriladi. 2.6.1. Qarz oluvchi tomonidan olingan | H17: =malumot!B65 -> mikroqarz | I17: ni va undan foydalanganlik uchun foizlarni qaytarish bo‘yicha muddati o‘tgan qarzdorlik hosil bo‘lganda Qarz oluvchi tomonidan ko‘rsatilgan qarzdorlikni to‘lash hisobiga to‘lanadigan summalar quyidagi tartibda hisobga olinadi:
A18: - jarima sanksiyalarni to‘lash; - to‘lov muddati o‘tgan foizlarni to‘lash; - to‘lov muddati o‘tgan asosiy qarzni to‘lash; - muddatli qarz bo‘yicha hisoblangan foizlarni to‘lash; - muddatli asosiy qarzni to‘lash; - Mikromoliya tashkilotning boshqa zararlarini qoplash.
A19: ="2.7. Qarz oluvchi Mikromoliya tashkilotining "&malumot!B65&" bo‘yicha asosiy summasi, hisoblangan foizlarni, penya va boshqa moliyaviy talablarini ham naqd pul shaklida, ham naqdsiz shaklda qaytarib beradi." -> 2.7. Qarz oluvchi Mikromoliya tashkilotining mikroqarz bo‘yicha asosiy summasi, hisoblangan foizlarni, penya va boshqa moliyaviy talablarini ham naqd pul shaklida, ham naqdsiz shaklda qaytarib beradi.
A20: ="2.8. Qarz oluvchi "&malumot!B65&" miqdorini muddatidan oldin qaytarish, shuningdek, bu haqida Mikromoliya tashkilotini albatta ogohlantirgan holda ulardan aniq foydalangan muddat uchun hisoblangan foizlarni to‘lash huquqiga ega." -> 2.8. Qarz oluvchi mikroqarz miqdorini muddatidan oldin qaytarish, shuningdek, bu haqida Mikromoliya tashkilotini albatta ogohlantirgan holda ulardan aniq foydalangan muddat uchun hisoblangan foizlarni to‘lash huquqiga ega.
A21: =CONCATENATE(C21,H21,I21) -> 2.9. Qarz oluvchi jismoniy shaxslarning kreditlar (mikroqarzlar) bo‘yicha qarz yukini hisoblash tartibi, qarz yukining ruxsat etilgan miqdori, shuningdek qarz yuki o‘sishini cheklash to‘g‘risidagi Nizomga muvofiq (O’zbekiston Respublikasi Adliya vazirligi tomonidan 19.12.2019 y. 3205-son bilan ro‘yxatga olingan Markaziy bank Boshqaruvining 28.09.2019 y. 24/5-son qarori bilan tasdiqlangan), qarz yuki ko‘rsatkichi har bir qarz oluvchiga qarz beruvchi tomonidan mikroqarz ajratishda uning summasi va qarz oluvchining amaldagi kredit (mikroqarz) shartnomalari bo‘yicha asosiy qarz qoldig‘i yig‘indisi bazaviy hisoblash miqdorining 50 baravaridan oshganda hisoblanadi. | C21: ="2.9. Qarz oluvchi jismoniy shaxslarning kreditlar ("&malumot!B65&"lar) bo‘yicha qarz yukini hisoblash tartibi, qarz yukining ruxsat etilgan miqdori, shuningdek qarz yuki o‘sishini cheklash to‘g‘risidagi Nizomga muvofiq (O’zbekiston Respublikasi Adliya vazirligi tomonidan 19.12.2019 y. 3205-son bilan ro‘yxatga " -> 2.9. Qarz oluvchi jismoniy shaxslarning kreditlar (mikroqarzlar) bo‘yicha qarz yukini hisoblash tartibi, qarz yukining ruxsat etilgan miqdori, shuningdek qarz yuki o‘sishini cheklash to‘g‘risidagi Nizomga muvofiq (O’zbekiston Respublikasi Adliya vazirligi tomonidan 19.12.2019 y. 3205-son bilan ro‘yxatga | H21: ="olingan Markaziy bank Boshqaruvining 28.09.2019 y. 24/5-son qarori bilan tasdiqlangan), qarz yuki ko‘rsatkichi har bir qarz oluvchiga qarz beruvchi tomonidan "&malumot!B65&" ajratishda uning summasi va " -> olingan Markaziy bank Boshqaruvining 28.09.2019 y. 24/5-son qarori bilan tasdiqlangan), qarz yuki ko‘rsatkichi har bir qarz oluvchiga qarz beruvchi tomonidan mikroqarz ajratishda uning summasi va | I21: ="qarz oluvchining amaldagi kredit ("&malumot!B65&") shartnomalari bo‘yicha asosiy qarz qoldig‘i yig‘indisi bazaviy hisoblash miqdorining 50 baravaridan oshganda hisoblanadi." -> qarz oluvchining amaldagi kredit (mikroqarz) shartnomalari bo‘yicha asosiy qarz qoldig‘i yig‘indisi bazaviy hisoblash miqdorining 50 baravaridan oshganda hisoblanadi.
A22: ="3. "&malumot!D64&" TA'MINOTI BO‘YICHA " -> 3. MIKROQARZ TA'MINOTI BO‘YICHA
A23: ="3.1. Ushbu Shartnoma bo‘yicha taqdim etilgan "&malumot!C64&" quyidagi garov bilan ta'minlanadi:" -> 3.1. Ushbu Shartnoma bo‘yicha taqdim etilgan Mikroqarz quyidagi garov bilan ta'minlanadi:
A24: =IF(malumot!B109=malumot!C109,shartnoma!A28,IF(malumot!B109=malumot!D109,shartnoma!A25,0)) -> 3.1.1. Mikromoliya tashkiloti, Qarz oluvchi va XUDOYKULOV ALMURAT KURBONAZAROVICH tomonidan 2025 yil 24 martda imzolangan 1-sonli garov predmeti qiymatini tasdiqlash dalolatnomasiga muvofiq SARIQ JELTO- ORANJEVIY rangli, ishlab chiqarilgan yili – 2019 yil, dvigatel raqami 3977458, shassi - RAKAMSIZ, kuzov turi - YENGIL SEDAN, kuzov raqami №XTAGFL110KY258232, davlat raqam belgisi 75M497WA bo'lgan LADA VESTA rusumli avtomashinasi (bundan keyin “Garov predmeti”), egalik huquqiga ega XUDOYKULOV ALMURAT KURBONAZAROVICHga tegishli va kelishilgan garov qiymati 2025 yil 24 martda imzolangan 1-sonli Garov predmeti qiymatini tasdiqlash dalolatnomasiga muvifiq 78 000 000,00 (yetmish sakkiz million so'm) so'mni tashkil qiladi. Garov garovining aniq shartlari tegishli notarial rasmiylashtirilgan garov shartnomasi bilan belgilanadi.
A25: =IF(malumot!B98=malumot!C98,shartnoma!A27,IF(malumot!B98=malumot!D98,shartnoma!A26,0)) -> 3.1.1. Mikromoliya tashkiloti, Qarz oluvchi va XUDOYKULOV ALMURAT KURBONAZAROVICH tomonidan 2025 yil 24 martda imzolangan 1-sonli Garov predmeti qiymatini tasdiqlash dalolatnomasiga muvofiq SAMARQAND VILOYATI TAYLOQ TUMANI CHAROG'BON MFY YANGI TAYLOQ QISHLOG'I 6 TURAR JOY 12 QAVAT 58 XONADON manzilida joylashgan, yer uchastkasi maydoni - , umumiy maydoni - 72,13, yashash maydoni - 37,39 bo'lgan, 3 - xonali yakka tartibdagi uy-joy ko'rinishidagi ko'chmas mulk (bundan keyin “Garov predmeti”), egalik huquqiga ko'ra 0ga tegishli va kelishilgan garov qiymati 2025 yil 24 martda imzolangan 1-sonli Garov predmeti qiymatini tasdiqlash dalolatnomasiga muvofiq 78 000 000,00 (yetmish sakkiz million so'm) so'mni tashkil qiladi. Garovning aniq shartlari tegishli tarzda notarial tasdiqlangan garov shartnomasi bilan belgilangan.
A26: ="3.1.1. "&malumot!N132&" tomonidan "&malumot!B149&" yil "&malumot!B151&" "&malumot!B150&"da imzolangan 1-sonli navbatdagi garov predmeti qiymatini tasdiqlash dalolatnomasiga muvofiq "&malumot!C129&" manzilida joylashgan, "&malumot!E132&" bo'lgan, "&malumot!E131&" ko'rinishidagi ko'chmas mulk (bundan keyin “navbatdagi garov predmeti”), egalik huquqiga ko'ra "&malumot!C123&"ga tegishli va kelishilgan garov qiymati "&malumot!B149&" yil "&malumot!B151&" "&malumot!B150&"da imzolangan 1-sonli Garov predmeti qiymatini tasdiqlash dalolatnomasiga muvofiq "&FIXED(malumot!B142,2)&" ("&malumot!B144&") so'mni tashkil qiladi. Garovning aniq shartlari tegishli tarzda notarial tasdiqlangan garov shartnomasi bilan belgilangan." -> 3.1.1. Mikromoliya tashkiloti, Qarz oluvchi va XUDOYKULOV ALMURAT KURBONAZAROVICH tomonidan 2025 yil 24 martda imzolangan 1-sonli navbatdagi garov predmeti qiymatini tasdiqlash dalolatnomasiga muvofiq SAMARQAND VILOYATI TAYLOQ TUMANI CHAROG'BON MFY YANGI TAYLOQ QISHLOG'I 6 TURAR JOY 12 QAVAT 58 XONADON manzilida joylashgan, yer uchastkasi maydoni - , umumiy maydoni - 72,13, yashash maydoni - 37,39 bo'lgan, 3 - xonali yakka tartibdagi uy-joy ko'rinishidagi ko'chmas mulk (bundan keyin “navbatdagi garov predmeti”), egalik huquqiga ko'ra 0ga tegishli va kelishilgan garov qiymati 2025 yil 24 martda imzolangan 1-sonli Garov predmeti qiymatini tasdiqlash dalolatnomasiga muvofiq 78 000 000,00 (yetmish sakkiz million so'm) so'mni tashkil qiladi. Garovning aniq shartlari tegishli tarzda notarial tasdiqlangan garov shartnomasi bilan belgilangan.
A27: ="3.1.1. "&malumot!N132&" tomonidan "&malumot!B149&" yil "&malumot!B151&" "&malumot!B150&"da imzolangan 1-sonli Garov predmeti qiymatini tasdiqlash dalolatnomasiga muvofiq "&malumot!C129&" manzilida joylashgan, "&malumot!E132&" bo'lgan, "&malumot!E131&" ko'rinishidagi ko'chmas mulk (bundan keyin “Garov predmeti”), egalik huquqiga ko'ra "&malumot!C123&"ga tegishli va kelishilgan garov qiymati "&malumot!B149&" yil "&malumot!B151&" "&malumot!B150&"da imzolangan 1-sonli Garov predmeti qiymatini tasdiqlash dalolatnomasiga muvofiq "&FIXED(malumot!B142,2)&" ("&malumot!B144&") so'mni tashkil qiladi. Garovning aniq shartlari tegishli tarzda notarial tasdiqlangan garov shartnomasi bilan belgilangan." -> 3.1.1. Mikromoliya tashkiloti, Qarz oluvchi va XUDOYKULOV ALMURAT KURBONAZAROVICH tomonidan 2025 yil 24 martda imzolangan 1-sonli Garov predmeti qiymatini tasdiqlash dalolatnomasiga muvofiq SAMARQAND VILOYATI TAYLOQ TUMANI CHAROG'BON MFY YANGI TAYLOQ QISHLOG'I 6 TURAR JOY 12 QAVAT 58 XONADON manzilida joylashgan, yer uchastkasi maydoni - , umumiy maydoni - 72,13, yashash maydoni - 37,39 bo'lgan, 3 - xonali yakka tartibdagi uy-joy ko'rinishidagi ko'chmas mulk (bundan keyin “Garov predmeti”), egalik huquqiga ko'ra 0ga tegishli va kelishilgan garov qiymati 2025 yil 24 martda imzolangan 1-sonli Garov predmeti qiymatini tasdiqlash dalolatnomasiga muvofiq 78 000 000,00 (yetmish sakkiz million so'm) so'mni tashkil qiladi. Garovning aniq shartlari tegishli tarzda notarial tasdiqlangan garov shartnomasi bilan belgilangan.
A28: =IF(malumot!B98=malumot!C98,A29,IF(malumot!B98=malumot!D98,A30,0)) -> 3.1.1. Mikromoliya tashkiloti, Qarz oluvchi va XUDOYKULOV ALMURAT KURBONAZAROVICH tomonidan 2025 yil 24 martda imzolangan 1-sonli garov predmeti qiymatini tasdiqlash dalolatnomasiga muvofiq SARIQ JELTO- ORANJEVIY rangli, ishlab chiqarilgan yili – 2019 yil, dvigatel raqami 3977458, shassi - RAKAMSIZ, kuzov turi - YENGIL SEDAN, kuzov raqami №XTAGFL110KY258232, davlat raqam belgisi 75M497WA bo'lgan LADA VESTA rusumli avtomashinasi (bundan keyin “Garov predmeti”), egalik huquqiga ega XUDOYKULOV ALMURAT KURBONAZAROVICHga tegishli va kelishilgan garov qiymati 2025 yil 24 martda imzolangan 1-sonli Garov predmeti qiymatini tasdiqlash dalolatnomasiga muvifiq 78 000 000,00 (yetmish sakkiz million so'm) so'mni tashkil qiladi. Garov garovining aniq shartlari tegishli notarial rasmiylashtirilgan garov shartnomasi bilan belgilanadi.
A29: ="3.1.1. "&malumot!N132&" tomonidan "&malumot!B149&" yil "&malumot!B151&" "&malumot!B150&"da imzolangan 1-sonli garov predmeti qiymatini tasdiqlash dalolatnomasiga muvofiq "&malumot!B140&" rangli, ishlab chiqarilgan yili – "&malumot!B141&" yil, dvigatel raqami "&malumot!B137&", shassi - "&malumot!B138&", kuzov turi - "&malumot!B134&", kuzov raqami №"&malumot!B135&", davlat raqam belgisi "&malumot!B132&" bo'lgan "&malumot!B131&" rusumli avtomashinasi (bundan keyin “Garov predmeti”), egalik huquqiga ega "&malumot!B123&"ga tegishli va kelishilgan garov qiymati "&malumot!B149&" yil "&malumot!B151&" "&malumot!B150&"da imzolangan 1-sonli Garov predmeti qiymatini tasdiqlash dalolatnomasiga muvifiq "&FIXED(malumot!B142,2)&" ("&malumot!B144&") so'mni tashkil qiladi. Garov garovining aniq shartlari tegishli notarial rasmiylashtirilgan garov shartnomasi bilan belgilanadi." -> 3.1.1. Mikromoliya tashkiloti, Qarz oluvchi va XUDOYKULOV ALMURAT KURBONAZAROVICH tomonidan 2025 yil 24 martda imzolangan 1-sonli garov predmeti qiymatini tasdiqlash dalolatnomasiga muvofiq SARIQ JELTO- ORANJEVIY rangli, ishlab chiqarilgan yili – 2019 yil, dvigatel raqami 3977458, shassi - RAKAMSIZ, kuzov turi - YENGIL SEDAN, kuzov raqami №XTAGFL110KY258232, davlat raqam belgisi 75M497WA bo'lgan LADA VESTA rusumli avtomashinasi (bundan keyin “Garov predmeti”), egalik huquqiga ega XUDOYKULOV ALMURAT KURBONAZAROVICHga tegishli va kelishilgan garov qiymati 2025 yil 24 martda imzolangan 1-sonli Garov predmeti qiymatini tasdiqlash dalolatnomasiga muvifiq 78 000 000,00 (yetmish sakkiz million so'm) so'mni tashkil qiladi. Garov garovining aniq shartlari tegishli notarial rasmiylashtirilgan garov shartnomasi bilan belgilanadi.
A30: ="3.1.1. "&malumot!N132&" tomonidan "&malumot!B149&" yil "&malumot!B151&" "&malumot!B150&"da imzolangan 1-sonli navbatdagi garov predmeti qiymatini tasdiqlash dalolatnomasiga muvofiq "&malumot!B140&" rangli, ishlab chiqarilgan yili – "&malumot!B141&" yil, dvigatel raqami "&malumot!B137&", shassi - "&malumot!B138&", kuzov turi - "&malumot!B134&", kuzov raqami №"&malumot!B135&", davlat raqam belgisi "&malumot!B132&" bo'lgan "&malumot!B131&" rusumli avtomashinasi (bundan keyin “navbatdagi garov predmeti”), egalik huquqiga ega "&malumot!B123&"ga tegishli va kelishilgan garov qiymati "&malumot!B149&" yil "&malumot!B151&" "&malumot!B150&"da imzolangan 1-sonli Garov predmeti qiymatini tasdiqlash dalolatnomasiga muvifiq "&FIXED(malumot!B142,2)&" ("&malumot!B144&") so'mni tashkil qiladi. Garov garovining aniq shartlari tegishli notarial rasmiylashtirilgan garov shartnomasi bilan belgilanadi." -> 3.1.1. Mikromoliya tashkiloti, Qarz oluvchi va XUDOYKULOV ALMURAT KURBONAZAROVICH tomonidan 2025 yil 24 martda imzolangan 1-sonli navbatdagi garov predmeti qiymatini tasdiqlash dalolatnomasiga muvofiq SARIQ JELTO- ORANJEVIY rangli, ishlab chiqarilgan yili – 2019 yil, dvigatel raqami 3977458, shassi - RAKAMSIZ, kuzov turi - YENGIL SEDAN, kuzov raqami №XTAGFL110KY258232, davlat raqam belgisi 75M497WA bo'lgan LADA VESTA rusumli avtomashinasi (bundan keyin “navbatdagi garov predmeti”), egalik huquqiga ega XUDOYKULOV ALMURAT KURBONAZAROVICHga tegishli va kelishilgan garov qiymati 2025 yil 24 martda imzolangan 1-sonli Garov predmeti qiymatini tasdiqlash dalolatnomasiga muvifiq 78 000 000,00 (yetmish sakkiz million so'm) so'mni tashkil qiladi. Garov garovining aniq shartlari tegishli notarial rasmiylashtirilgan garov shartnomasi bilan belgilanadi.
A31: =CONCATENATE(A32,B32) -> 3.2. Qonun hujjatlariga muvofiq rasmiylashtirilgan, “Garov predmeti” hisoblangan notarial tasdiqlangan garov shartnomasi, shu jumladan “Garov predmeti”ga taʼqiq quyilganligi tasdiqlovchi xujjat Qarz oluvchi tomonidan ushbu shartnoma tuzilgandan so‘ng 10 bank kuni mobaynida Mikromoliya tashkilotiga taqdim etilishi lozim. Garov shartnomasi belgilangan muddatda taqdim etilmagan hollarda, Mikromoliya tashkiloti Qarz oluvchining manziliga yozma bildirishnoma yuborish orqali mikroqarz berishni rad etish va / yoki ushbu shartnomani bir tomonlama bekor qilish huquqiga egadir. Bunda ushbu shartnoma Qarz oluvchi tomonidan talabnoma olingan vaqtda yoki talabnoma pochta xizmati orqali yuborilgandan keyin uchinchi kuni bekor qilingan hisoblanadi.
A32: 3.2. Qonun hujjatlariga muvofiq rasmiylashtirilgan, “Garov predmeti” hisoblangan notarial tasdiqlangan garov shartnomasi, shu jumladan “Garov predmeti”ga taʼqiq quyilganligi tasdiqlovchi xujjat Qarz oluvchi tomonidan ushbu shartnoma tuzilgandan so‘ng 10 bank kuni mobaynida | B32: =CONCATENATE(A33,B33) -> Mikromoliya tashkilotiga taqdim etilishi lozim. Garov shartnomasi belgilangan muddatda taqdim etilmagan hollarda, Mikromoliya tashkiloti Qarz oluvchining manziliga yozma bildirishnoma yuborish orqali mikroqarz berishni rad etish va / yoki ushbu shartnomani bir tomonlama bekor qilish huquqiga egadir. Bunda ushbu shartnoma Qarz oluvchi tomonidan talabnoma olingan vaqtda yoki talabnoma pochta xizmati orqali yuborilgandan keyin uchinchi kuni bekor qilingan hisoblanadi.
A33: =" Mikromoliya tashkilotiga taqdim etilishi lozim. Garov shartnomasi belgilangan muddatda taqdim etilmagan hollarda, Mikromoliya tashkiloti Qarz oluvchining manziliga yozma bildirishnoma yuborish orqali "&malumot!B65&"" -> Mikromoliya tashkilotiga taqdim etilishi lozim. Garov shartnomasi belgilangan muddatda taqdim etilmagan hollarda, Mikromoliya tashkiloti Qarz oluvchining manziliga yozma bildirishnoma yuborish orqali mikroqarz | B33: berishni rad etish va / yoki ushbu shartnomani bir tomonlama bekor qilish huquqiga egadir. Bunda ushbu shartnoma Qarz oluvchi tomonidan talabnoma olingan vaqtda yoki talabnoma pochta xizmati orqali yuborilgandan keyin uchinchi kuni bekor qilingan hisoblanadi.
A34: 3.3. Asosiy qarzni, foizlar yoki ushbu shartnoma bo‘yicha belgilangan muddatdan kechiktirilganligi bo‘yicha penyalarni qaytarish muddati kechiktirilishi yuzaga kelganda va/yoki ushbu shartnoma bo‘yicha boshqa majburiyatlar buzilishi holatlarida Mikromoliya tashkiloti O‘zbekiston Respublikasining amaldagi qonunchiligiga muvofiq qarzni undirish uchun qaytarib olinmaydigan va muqarrar tartibda unidirishni garov ob'ektiga qaratish huquqiga ega bo‘ladi.
A35: 3.4. O‘zbekiston Respublikasi "Garov to‘g‘risida" gi Qonunining 27-moddasiga muvofiq Garov predmeti sug‘urtalanmaydi. Lekin Mikromoliya tashkiloti Qarz oluvchidan Mikromoliya tashkiloti foydasiga Garov obʼektini ushbu Shartnomaning to‘liq amal qilish muddatiga har turli xavflardan sug‘urta qilishni talab qilish huquqiga ega. Bunda, sug‘urta xavflari ro‘yxati, shuningdek, sug‘urta kompaniyasi Mikromoliya tashkilotining xohishiga ko‘ra belgilanadi. Sug‘urta hodisasi yuz berganda Foyda oluvchi Mikromoliya tashkiloti bo‘lishi kerak.
A37: 4. MIKROMOLIYA TASHKILOTINING HUQUQ VA MAJBURIYATLARI
A38: 4.1. Mikromoliya tashkiloti quyidagi huquqlarga ega:
A39: =CONCATENATE(C39,H39) -> 4.1.1. Ushbu Shartnomada ko‘rsatilgan asoslar bo‘yicha Qarz oluvchiga Shartnomada ko‘zda tutilgan mikroqarz summasini berilishini to‘liq yoki qisman rad etish. 4.1.2 “Mikromoliya Tashkiloti” qarz oluvchining nomidagi barcha plastik kartalaridan, xozirgi kunda mavjud va bundan so‘ng ochiladigan barcha xisob raqamlaridan (talab qilib olguncha, depozit jamg‘arib boriladigan plastik va boshqa istalgan xisob raqamlaridan) kredit to‘lovini kredit qaytarish jadvaliga asosan oyning kredit qarzdorligi qaytarilishi ko‘rsatilgan kuni akseptsiz tarzda yechib olish xuquqiga ega.Usbu bandda belgilangan harakatlarni amalga oshirish uchun bo‘lgan barcha xarajatlar Qarz oluvchi xisobidan qoplanadi | C39: ="4.1.1. Ushbu Shartnomada ko‘rsatilgan asoslar bo‘yicha Qarz oluvchiga Shartnomada ko‘zda tutilgan "&malumot!B65&"" -> 4.1.1. Ushbu Shartnomada ko‘rsatilgan asoslar bo‘yicha Qarz oluvchiga Shartnomada ko‘zda tutilgan mikroqarz | H39: summasini berilishini to‘liq yoki qisman rad etish. 4.1.2 “Mikromoliya Tashkiloti” qarz oluvchining nomidagi barcha plastik kartalaridan, xozirgi kunda mavjud va bundan so‘ng ochiladigan barcha xisob raqamlaridan (talab qilib olguncha, depozit jamg‘arib boriladigan plastik va boshqa istalgan xisob raqamlaridan) kredit to‘lovini kredit qaytarish jadvaliga asosan oyning kredit qarzdorligi qaytarilishi ko‘rsatilgan kuni akseptsiz tarzda yechib olish xuquqiga ega.Usbu bandda belgilangan harakatlarni amalga oshirish uchun bo‘lgan barcha xarajatlar Qarz oluvchi xisobidan qoplanadi
A40: ="4.1.2.1. "&malumot!C64&" bo‘yicha qolgan barcha qarzdorlik, foiz to‘lovlarining muddatidan oldin qaytarilishini talab qilish, shuningdek, quyidagi holatlardan biri yuzaga kelganda undirishni garov ta'minotiga qaratish:" -> 4.1.2.1. Mikroqarz bo‘yicha qolgan barcha qarzdorlik, foiz to‘lovlarining muddatidan oldin qaytarilishini talab qilish, shuningdek, quyidagi holatlardan biri yuzaga kelganda undirishni garov ta'minotiga qaratish:
A41: a) ta'minotisiz qarzdorlik yuzaga kelganda;
A42: ="b) "&malumot!B65&" summasiga hisoblanadigan asosiy qarz bo‘yicha muddati o‘tgan qarzdorlik va/yoki foizlarning yuzaga kelishi;" -> b) mikroqarz summasiga hisoblanadigan asosiy qarz bo‘yicha muddati o‘tgan qarzdorlik va/yoki foizlarning yuzaga kelishi;
A43: с) Qarz oluvchini qonun hujjatlarida belgilangan tartibda to‘lov qobiliyatiga ega emas, muomalaga layoqatli emas yoki muomalaga layoqati cheklangan deb e'lon qilish;
A44: d) Mikromoliya tashkilotiga ushbu Shartnomaning 3.1.-bandida ko‘zda tutilgan hisobotlar, axborotlar va boshqa ma'lumotlarni o‘z vaqtida taqdim etmaslik, shuningdek, moliya-xo‘jalik faoliyat va daromad to‘g‘risidagi hisobotning ishonchsizligi holatlari aniqlanganda;
A45: e) Qarz oluvchi tomonidan ushbu shartnoma shartlariga amal qilmaslik;
A46: ="f) Qarz oluvchi "&malumot!B65&" summasini olish uchun Mikromoliya tashkilotiga "&malumot!B65&" taqdim etilishi to‘g‘risida ijobiy qaror qabul qilinishi uchun muhim hisoblangan masalalar bo‘yicha yolg‘on yoki to‘liq bo‘lmagan ma'lumotlarni taqdim etganligi aniqlanganda." -> f) Qarz oluvchi mikroqarz summasini olish uchun Mikromoliya tashkilotiga mikroqarz taqdim etilishi to‘g‘risida ijobiy qaror qabul qilinishi uchun muhim hisoblangan masalalar bo‘yicha yolg‘on yoki to‘liq bo‘lmagan ma'lumotlarni taqdim etganligi aniqlanganda.
A47: 4.1.3. Ushbu shartnomaning amal qilish jarayonida Qarz oluvchining moliyaviy holatini tekshirish va Qarz oluvchi tomonidan o‘z zimmasiga olgan majburiyatlarning bajarilishini nazorat qilish.
A48: 4.1.4. Qarz oluvchi tomonidan yoki ushbu Shartnoma bo‘yicha uchinchi shaxs tomonidan ta'minot sifatida garovga qo‘yilgan mol-mulkning tegishli holatdaligi va ulardan foydalanish bo‘yicha tekshiruvlar o‘tkazish.
A49: 4.1.5. Garovga qo‘yuvchi tomonidan garovga qo‘yilgan mol-mulk buzilgan yoki belgilangan maqsadda foydalanish uchun yaroqsiz holga kelganda, bu esa Mikromoliya tashkilotining ushbu Shartnoma bo‘yicha moliyaviy talablarini qondirishga qodir bo‘lgan bozor qiymatiga ma'lum darajada ta'sir ko‘rsatganda, yoki uchinchi shaxsning (kafil) moliyaviy holatining yomonlashuvi sababli ushbu Shartnomadan kelib chiqqan majburiyatlar bo‘yicha javob berish qobiliyatiga ega bo‘lmay qolgan holatlarda Qarz oluvchidan ta'minotning qo‘shimcha turini taqdim etish yoki almashtirishni talab qilish.
A50: 4.1.6. Qonun hujjatlariga muvofiq, Qarz oluvchi tomonidan ushbu Shartnoma bo‘yicha asosiy qarz, foizlar, penya va boshqa pul majburiyatlarini o‘z vaqtida to‘lamaslik holatlarida Qarz oluvchining bank hisobvaraqlaridagi pul mablag‘larini akseptsiz tartibda yechib olish to‘g‘risida to‘lov talabnomasini berish va bunga Qarz oluvchi qaytarib olinmaydigan va so‘zsiz rozilik bildiradi.
A51: ="4.1.7. Qarz oluvchini oldindan ogohlantirmasdan "&malumot!B65&"ni qaytarish uchun haqiqatdan ham garov ta'minoti mavjudligini tekshirishni amalga oshirish." -> 4.1.7. Qarz oluvchini oldindan ogohlantirmasdan mikroqarzni qaytarish uchun haqiqatdan ham garov ta'minoti mavjudligini tekshirishni amalga oshirish.
A52: 4.1.8. Ushbu shartnoma doirasida o‘z majburiyatlarini bajarish uchun uchinchi shaxslarga barcha zarur ma'lumotlarni yetkazish.
A53: 4.1.9. Istalgan vaqtda Qarz oluvchining avvaldan roziligini olmasdan turib ushbu Shartnoma bo‘yicha uchinchi tomonga da'vo qilish huquqini berish yoki uning foydasiga voz kechish.
A54: =CONCATENATE(C54,H54) -> 4.1.10. Qarz oluvchi taqdim etilgan mikroqarzdan Shartnoma tuzilgan kundan boshlab 1 (bir) oy davomida foydalanmagan holatlarda, bu haqda Qarz oluvchini yozma ravishda xabardor qilib, Shartnoma bir tomonlama bekor qilish. Yozma xabarni jo‘natish sanasi uni taqdim etish yoki pochta orqali jo‘natish sanasi hisoblanadi. | C54: ="4.1.10. Qarz oluvchi taqdim etilgan "&malumot!B65&"dan Shartnoma tuzilgan kundan boshlab 1 (bir) oy davomida foydalanmagan" -> 4.1.10. Qarz oluvchi taqdim etilgan mikroqarzdan Shartnoma tuzilgan kundan boshlab 1 (bir) oy davomida foydalanmagan | H54: holatlarda, bu haqda Qarz oluvchini yozma ravishda xabardor qilib, Shartnoma bir tomonlama bekor qilish. Yozma xabarni jo‘natish sanasi uni taqdim etish yoki pochta orqali jo‘natish sanasi hisoblanadi.
A55: ="4.1.11. Oldingi "&malumot!B65&" to‘liq to‘lanmagunga qadar yangi "&malumot!B65&" berishni rad etish." -> 4.1.11. Oldingi mikroqarz to‘liq to‘lanmagunga qadar yangi mikroqarz berishni rad etish.
A57: 5. QARZ OLUVCHINING HUQUQ VA MAJBURIYATLARI
A58: 5.1. Qarz oluvchi quyidagi huquqlarga ega:
A59: ="5.1.1. Ushbu shartnomada nazarda tutilgan shartlar bo‘yicha "&malumot!B65&" olish, shuningdek, Mikromoliya tashkiloti tomonidan ko‘rsatiladigan pullik xizmatlardan foydalanish." -> 5.1.1. Ushbu shartnomada nazarda tutilgan shartlar bo‘yicha mikroqarz olish, shuningdek, Mikromoliya tashkiloti tomonidan ko‘rsatiladigan pullik xizmatlardan foydalanish.
A60: ="5.1.2. Shartnoma tuzilgan kundan boshlab 2 (ikki) hafta mobaynida Mikromoliya tashkilotiga bu haqda yozma xabarnoma yo‘llash orqali "&malumot!B65&"ning foydalanilmagan summasidan voz kechish." -> 5.1.2. Shartnoma tuzilgan kundan boshlab 2 (ikki) hafta mobaynida Mikromoliya tashkilotiga bu haqda yozma xabarnoma yo‘llash orqali mikroqarzning foydalanilmagan summasidan voz kechish.
A61: ="5.1.3. "&malumot!C64&" xizmatlari ko‘rsatish qoidalari bilan tanishish." -> 5.1.3. Mikroqarz xizmatlari ko‘rsatish qoidalari bilan tanishish.
A62: ="5.1.4. O‘z huquq va majburiyatlari, shu jumladan "&malumot!B65&" xizmatlari ko‘rsatish bilan bog‘liq barcha xarajatlar haqida aniq va to‘liq ma'lumot olish." -> 5.1.4. O‘z huquq va majburiyatlari, shu jumladan mikroqarz xizmatlari ko‘rsatish bilan bog‘liq barcha xarajatlar haqida aniq va to‘liq ma'lumot olish.
A63: 5.1.5. Shartnoma bo‘yicha Mikromoliya tashkilotining majburiyatlarini bajarmaslik yoki tegishli darajada bajarmaslik natijasida yuzaga kelgan zararlarni qoplashni talab qilish.
A64: 5.2. Qarz oluvchining majburiyatlari:
A65: ="5.2.1. Mikromoliya tashkilotining birinchi talabi bilan zarur hujjatlar, shuningdek "&malumot!B65&"dan foydalanishning butun davri davomida uning moliyaviy holati va to‘lash qobiliyatiga tegishli bo‘lgan ma'lumotlarni taqdim etish." -> 5.2.1. Mikromoliya tashkilotining birinchi talabi bilan zarur hujjatlar, shuningdek mikroqarzdan foydalanishning butun davri davomida uning moliyaviy holati va to‘lash qobiliyatiga tegishli bo‘lgan ma'lumotlarni taqdim etish.
A66: 5.2.2. Ushbu shartnomada nazarda tutilgan hollarda garov ta'minotini almashtirish yoki qo‘shimcha ta'minot turini taqdim etish bo‘yicha Mikromoliya tashkiloti talablarini bajarish.
A67: ="5.2.3. To‘lov jadvaliga muvofiq "&malumot!B65&", shuningdek hisoblangan foizlar to‘lovlarini amalga oshirish." -> 5.2.3. To‘lov jadvaliga muvofiq mikroqarz, shuningdek hisoblangan foizlar to‘lovlarini amalga oshirish.
A68: =CONCATENATE(C68,H68) -> 5.2.4. Mikromoliya tashkiloti vakillariga o‘zlarining moliyaviy holati, yashash joyini tekshirishga, Mikromoliya tashkiloti foydasiga garovga qo‘yilgan mol-mulk saqlanishini tekshirishga ruxsat berish, shuningdek Qarz oluvchi ob'ektlaridan istalganiga tashrif buyurish va har qanday bino, inshoot, mol-mulk, asbob-uskunalar, tovarlar va xizmatlar, shuningdek ularning mikroqarz mablag‘lari hisobiga moliyalashtirilgan hujjatlarni ko‘zdan kechirish va Mikromoliya tashkiloti tomonidan ushbu huquqni amalga oshirishga to‘sqinlik qilmaslik majburiyatini oladi. | C68: 5.2.4. Mikromoliya tashkiloti vakillariga o‘zlarining moliyaviy holati, yashash joyini tekshirishga, Mikromoliya tashkiloti foydasiga garovga qo‘yilgan mol-mulk saqlanishini tekshirishga ruxsat berish, shuningdek Qarz oluvchi ob'ektlaridan istalganiga tashrif buyurish va har qanday bino, inshoot, mol-mulk, asbob-uskunalar, tovarlar va xizmatlar, shuningdek ularning | H68: =" "&malumot!B65&" mablag‘lari hisobiga moliyalashtirilgan hujjatlarni ko‘zdan kechirish va Mikromoliya tashkiloti tomonidan ushbu huquqni amalga oshirishga to‘sqinlik qilmaslik majburiyatini oladi." -> mikroqarz mablag‘lari hisobiga moliyalashtirilgan hujjatlarni ko‘zdan kechirish va Mikromoliya tashkiloti tomonidan ushbu huquqni amalga oshirishga to‘sqinlik qilmaslik majburiyatini oladi.
A69: 5.2.5. Qarz oluvchining moliyaviy ahvoli yomonlashuvi va ushbu shartnoma bo‘yicha Qarz oluvchining Mikromoliya tashkiloti oldidagi majburiyatlarining bajarilmasligi va/yoki tegishli darajada bajarilmaslik xavfi yuzaga kelishiga olib keluvchi hech qanday majburiyat va choralarni o‘z zimmasiga olmaslik;
A70: ="5.2.6. Quyidagi holatlarda Mikromoliya tashkilotning birinchi talabi bilan "&malumot!B65&" qaytarilishi bo‘yicha qo‘shimcha garov ta'minotini taqdim etish: " -> 5.2.6. Quyidagi holatlarda Mikromoliya tashkilotning birinchi talabi bilan mikroqarz qaytarilishi bo‘yicha qo‘shimcha garov ta'minotini taqdim etish:
A71: - Qarz oluvchining moliyaviy holatining yomonlashuvi; - Garov ob'ekti va/yoki uning bir qismining yo‘q qilinishi, qiymatining pasayishi, qisman yoki to‘liq yo‘qotilishi; - qarz qaytarilmaslik xavfini ko‘paytiruvchi boshqa omillarning paydo bo‘lishi;
A72: ="5.2.7. Sud qarori asosida Qarz oluvchi – jismoniy shaxsning muomalaga layoqatsizligi yoki muomalaga layoqati cheklangan yoxud to‘lash qobiliyatiga ega emasligi (bankrotligi) tan olinganda, uning vasiysi yoki homiysi "&malumot!B65&"ning asosiy summa bo‘yicha qarzdorlikni "&malumot!B65&"dan aniq foydalanish muddati uchun foizlar bilan kechiktirmasdan to‘liq to‘lashi shart." -> 5.2.7. Sud qarori asosida Qarz oluvchi – jismoniy shaxsning muomalaga layoqatsizligi yoki muomalaga layoqati cheklangan yoxud to‘lash qobiliyatiga ega emasligi (bankrotligi) tan olinganda, uning vasiysi yoki homiysi mikroqarzning asosiy summa bo‘yicha qarzdorlikni mikroqarzdan aniq foydalanish muddati uchun foizlar bilan kechiktirmasdan to‘liq to‘lashi shart.
A73: ="5.2.8. Mikromoliya tashkilotining "&malumot!B65&" umumiy summasi va hisoblangan foizlarni muddatidan oldin qaytarish to‘g‘risidagi talabini kechiktirmasdan bajarish." -> 5.2.8. Mikromoliya tashkilotining mikroqarz umumiy summasi va hisoblangan foizlarni muddatidan oldin qaytarish to‘g‘risidagi talabini kechiktirmasdan bajarish. | H73: "&'Общие данные'!B59&"
A74: =CONCATENATE(C74,H74) -> 5.2.9. Mikromoliya tashkilotining talabi bo‘yicha Mikromoliya tashkiloti ko‘rgan, shu jumladan mikroqarz bo‘yicha (asosiy qarz, foizlar va boshqalar) qarzdorlikni majburiy va/yoki muddatidan oldin qaytarish bo‘yicha qabul qilingan choralar bilan bog‘liq bo‘lgan barcha xarajatlari va zararlarni qoplash, shuningdek ushbu shartnoma doirasida unidruvni taqdim etilgan garov ta'minotiga qaratish. | C74: ="5.2.9. Mikromoliya tashkilotining talabi bo‘yicha Mikromoliya tashkiloti ko‘rgan, shu jumladan "&malumot!B65&" bo‘yicha (asosiy qarz, foizlar va boshqalar)" -> 5.2.9. Mikromoliya tashkilotining talabi bo‘yicha Mikromoliya tashkiloti ko‘rgan, shu jumladan mikroqarz bo‘yicha (asosiy qarz, foizlar va boshqalar) | H74: qarzdorlikni majburiy va/yoki muddatidan oldin qaytarish bo‘yicha qabul qilingan choralar bilan bog‘liq bo‘lgan barcha xarajatlari va zararlarni qoplash, shuningdek ushbu shartnoma doirasida unidruvni taqdim etilgan garov ta'minotiga qaratish.
A76: 6. TOMONLARNING JAVOBGARLIGI
A77: =CONCATENATE(C77,H77) -> 6.1. Mikromoliya tashkiloti tomonidan Qarz oluvchiga pul mablag‘larini ajratib berish bo‘yicha o‘z zimmasiga olgan majburiyatlarning Shartnomaning 1.1.-bandida keltirilgan summa va muddatlarda bajarilmaslik yoki tegishli tarzda bajarilmaslik holatlarida Mikromoliya tashkiloti muddatidan o‘tgan har bir kalendar kun uchun kechiktirilgan to‘lov summasining 0,1% miqdorida, biroq ushbu Shartnomaning 1.1.-bandida ko‘rsatilgan mikroqarz miqdori umumiy summasining 50% dan ko‘p bo‘lmagan miqdorda penya ko‘rinishidagi neustoyka to‘lash majburiyatini o‘z zimmasiga oladi. | C77: 6.1. Mikromoliya tashkiloti tomonidan Qarz oluvchiga pul mablag‘larini ajratib berish bo‘yicha o‘z zimmasiga olgan majburiyatlarning Shartnomaning 1.1.-bandida keltirilgan summa va muddatlarda bajarilmaslik yoki tegishli tarzda bajarilmaslik holatlarida Mikromoliya tashkiloti muddatidan o‘tgan har bir kalendar kun uchun kechiktirilgan to‘lov summasining 0,1% miqdorida, biroq ushbu Shartnomaning 1.1.-bandida ko‘rsatilgan | H77: =""&malumot!B65&" miqdori umumiy summasining 50% dan ko‘p bo‘lmagan miqdorda penya ko‘rinishidagi neustoyka to‘lash majburiyatini o‘z zimmasiga oladi." -> mikroqarz miqdori umumiy summasining 50% dan ko‘p bo‘lmagan miqdorda penya ko‘rinishidagi neustoyka to‘lash majburiyatini o‘z zimmasiga oladi.
A78: 6.2. Jarima sanksiyalarni to‘lash Tomonlarni ushbu Shartnomada ko‘zda tutilgan zimmalaridagi majburiyatlarini bajarishdan ozod qilmaydi.
A79: 6.3. Tomonlarning ushbu Shartnomada nazarda tutilmagan javobgarligi O‘zbekiston Respublikasining amaldagi qonunchiligiga muvofiq belgilanadi.
A80: 6.4. Tomonlar O‘zbekiston Respublikasi Fuqarolik kodeksining 325-moddasiga muvofiq aybdor tomondan yetkazilgan zararni neustoykadan tashqari to‘la hajmda undirish huquqiga egadirlar.
A82: 7. FORS-MAJOR
A83: 7.1. Agar Tomonlar ular zimmasidagi majburiyatlarni tegishli darajada bajarishi yengib bo‘lmas kuch (fors-major) oqibatida mumkin bo‘lmay qolgan bo‘lsa, ya'ni aniq vaqt davri davomida aniq sharoitlarda favqulodda va oldini olib bo‘lmaydigan holatlar ekanligini isbotlay olmasalar, Shartnoma bo‘yicha o‘z majburiyatlarini bajarmagan yoki tegishli darajada bajarmagan Tomon uning shartlarini bajarishda javobgar hisoblanadi. Ushbu Shartnoma Tomonlari yengilmas kuch holatlariga quyidagilarni kiritadi: tabiiy ofat (zilzila, suv toshqini, chaqmoq chaqishi, vulqon otilishi, sel kelishi, ko‘chki, sunami va hokazo), Shartnoma bo‘yicha majburiyatlar bajarilish joyida temperatura – harorat, shamol kuchi va yog‘ingarchilik darajasining inson hayotiy faoliyati normasidan ortiq bo‘lishi; hokimiyat va boshqaruv organlari moratoriysi; qonuniy belgilangan tartibda tashkil etilgan ish tashlashlar va majburiyatlarning tegishli darajada bajarilishi uchun Shartnoma Tomonlari tarafidan yengib bo‘lmas kuch sifatida belgilangan boshqa holatlar.
A84: 7.2. Fors-major holati ta'sirida qolgan Tomon, bunday holatlar yuzaga kelgan kundan boshlab 7 (etti) kalendar kundan kechiktirmasdan boshqa Tomonni xabardor qilishi shart.
A85: 7.3. Fors-major holati boshlanganligi to‘g‘risida xabar qilmaslik yoki o‘z vaqtida xabar bermaslik fors-major holati boshlanganda Shartnoma bo‘yicha o‘z majburiyatlarini bajarish imkoniyatiga vaj qilib keltirish huquqiga ega emas.
A86: 7.4. Fors-major holati boshlanganligini vaj qilib ko‘rsatish huquqidan mahrum etilgan Tomon amaldagi qonun hujjatlariga muvofiq javobgar bo‘ladi.
A88: 8. NIZOLARNI HAL QILISH TARTIBI
A89: 8.1. Ushbu Shartnomadan kelib chiqadigan tomonlar o‘rtasidagi barcha nizolar va undan kelib chiqadigan majburiyatlar, shu jumladan shartnoma bajarilmasligi oqibatida yuzaga kelgan bajarilishi, o‘zgartirilishi, bekor qilinishi, tugatilishi Mikromoliya tashkilot joylashgan yerdagi taalluqli sudda yoki «CONSILIO» Mas'uliyati cheklangan jamiyat qoshidagi Hakamlik sudida, O‘zbekiston Respublikasining amaldagi qonun hujjatlari va uning reglamentiga muvofiq Hakamlik sudi raisi tomonidan tayinlangan, yakka tartibdagi hakamlik sudyasi tomonidan, sud ishlarini sud majlisi bayonnomasi tuzmasdan ko‘rib chiqilishi kerak bo‘ladi. U yoki bu sudga murojaat qilish huquqi da'vogarda qoladi.
A90: Qarzni undirish va garovdagi mol-mulkiga qaratish ham sud tartibida, ham suddan tashqari tartibda, shu jumladan notariusning ijro yozuvini olish yo‘li bilan amalga oshirilishi mumkin.
A91: ="8.2. Mikromoliya tashkiloti sud organlariga murojaat qilganidan keyin Qarz oluvchi tomonidan "&malumot!B65&" bo‘yicha muddati o‘tgan qarzdorlikning to‘lanishi Mikromoliya tashkilotning "&malumot!B65&" bo‘yicha qarzdorlikni muddatidan avval undirish, shu jumladan undiruvni garovdagi mol-mulkka qaratish yo‘li bilan undirish huquqidan mahrum qilmaydi." -> 8.2. Mikromoliya tashkiloti sud organlariga murojaat qilganidan keyin Qarz oluvchi tomonidan mikroqarz bo‘yicha muddati o‘tgan qarzdorlikning to‘lanishi Mikromoliya tashkilotning mikroqarz bo‘yicha qarzdorlikni muddatidan avval undirish, shu jumladan undiruvni garovdagi mol-mulkka qaratish yo‘li bilan undirish huquqidan mahrum qilmaydi.
A93: 9. SHARTNOMA SHARTLARI VA AMAL QILISH MUDDATI
A94: 9.1. Ushbu Shartnoma Tomonlar tarafidan imzolangandan keyin kuchga kiradi.
A95: ="9.2. Shartnomaning amal qilish muddati Qarz oluvchi "&malumot!B65&"ni to‘liq qaytargan, hisoblangan foizlar, penya va boshqa pul majburiyatlarini to‘lagan kunda yakunlanadi." -> 9.2. Shartnomaning amal qilish muddati Qarz oluvchi mikroqarzni to‘liq qaytargan, hisoblangan foizlar, penya va boshqa pul majburiyatlarini to‘lagan kunda yakunlanadi.
A96: 9.3. Ushbu Shartnomaga kiritiladigan barcha o‘zgartirish va qo‘shimchalar, ushbu Shartnomada kelishilgan holatlardan tashqari, ikkala Tomon tarafidan qo‘shimcha bitimni yozma shaklda imzolagan holda amalga oshiriladi.
A98: 10. SHAXSIY MA'LUMOTLARNI QAYTA ISHLASH
A99: 10.1. Ushbu shartnomani tuzish bilan, Qarz oluvchi Mikromoliya tashkilotiga uning shaxsiy ma'lumotlari, shu jumladan, familiyasi, ismi, otasining ismi, pasport ma'lumotlari (shu jumladan, pasport raqami, berilgan vaqti va sanasi, ro‘yxatdan o‘tgan manzili va boshqalar); aloqaga chiqish uchun ma'lumotlar (shu jumladan, telefon raqami, e-mail, pochta manzili va boshqalar); STIR, ushbu shartnoma maqsadiga tegishli bo‘lgan boshqa ma'lumotlarni har qanday maqsadda ishlov berishga rozilik beradi.
A100: 10.2. Rozilik, shu jumladan shahsiy ma'lumotlar bilan quyidagi harakatlarni amalga oshirishga beriladi: yig‘ish, tizimlashtirish, to‘plash, saqlash, aniqlashtirish (yangilash, o‘zgartirish), foydalanish; O‘zbekiston Respublikasi qonun hujjatlarida nazarda tutilgan hollar va darajada tarqatish, shu jumladan davlat organlari va boshqa tashkilotlarga taqdim etish, shaxsiy ma'lumotlarning egasizlantirish, blokirovka va yo‘q qilish.
A101: 10.3. Qarz oluvchi, shuningdek, Mikromoliya tashkiloti shartnoma doirasida olingan ma'lumotlarni kredit byurosi va garov reestri, skoring kompaniyasi, uyali aloqa operatori, sug‘urta kompaniyasi, reklama ishlab chiqaruvchilari va tarqatuvchilari, shuningdek Mikromoliya tashkilotining boshqa hamkorlariga taqdim etishga roziligini bildiradi.
A103: 11. BOSHQA SHARTLAR
A104: 11.1. Ushbu shartnoma kuchga kirganidan keyin, o‘zaro munosabatlarga aloqador barcha yozishmalar yoki kelishuvlar, o‘z kuchini yo‘qotadi.
A105: 11.2. Ushbu shartnomani bajarish, o‘zgartirish va bekor qilish bilan bog‘liq barcha yozishma va xabarnomalar Tomonlarning ushbu shartnomaning yakuniy qismida ko‘rsatilgan pochta manzillariga yuboriladi.
A106: 11.3. Ushbu shartnomani bajarish uchun zarur bo‘lgan ismi (nomlanishi), ro‘yxatdan o‘tgan joyi, haqiqiy yashash joyi, manzili (joylashgan yeri), bank rekvizitlari va boshqa ma'lumotlar o‘zgargan holatlarda, Tomonlarning har biri bunday o‘zgarishlar amalga oshgan kundan boshlab 5 (besh) kalendar kun ichida boshqa Tomonni bunday o‘zgarishlar haqida yozma ravishda xabardor qilishi shart.
A107: 11.4. Ushbu bitimni amalga oshirish bilan, Qarz oluvchi kelishuvning muhimligi va uni tuzishning yuridik oqibatlarini to‘liq tushunib yetishi, shu sababli Shartnomani tuzish yanglishishlar, aldov, zo‘ravonlik, tahdidlar, yomon niyatli bitim yoki murakkab holatlar (tutqinlik) ta'sirida emasligini tasdiqlaydi.
A108: 11.5. Ushbu shartnomada ko‘zda tutilmagan holatlarda Tomonlar O‘zbekiston Respublikasining amaldagi qonunchiligiga amal qiladilar.
A109: 11.6. Qarz oluvchi Mikromoliya tashkilotining oldindan yozma roziligini olmasdan turib o‘z majburiyatlari yoki huquqlarini uchinchi shaxslarga o‘tkaza olmaydi.
... A113: 12. TOMONLARNING YURIDIK MANZILLARI VA REKVIZITLARI:
A115: «Mikromoliya tashkiloti» | B115: «Qarz oluvchi»
A117: =malumot!B154 -> «CLEVER MIKROMOLIYA TASHKILOTI» MChJ | B117: =malumot!B5 -> SHAYMARDANOVA SABOXAT YULDASHEVNA
...

Sheet buyruq
A4: =""&malumot!B153&" ijrochi direktorining "&malumot!B171&"dagi "&malumot!B170&"-sonli buyrug‘i" -> «CLEVER MIKROMOLIYA TASHKILOTI» MChJ ijrochi direktorining 24 mart 2025 y.dagi №659-SR-sonli buyrug‘i
A8: ="Men, Abduraximov Nadirbek Kamilevich "&malumot!B153&" ijrochi direktori, jismoniy shaxs "&malumot!B10&"ga quyidagi shartlarda "&malumot!B65&" berishni buyuraman:" -> Men, Abduraximov Nadirbek Kamilevich «CLEVER MIKROMOLIYA TASHKILOTI» MChJ ijrochi direktori, jismoniy shaxs SHAYMARDANOVA SABOXAT YULDASHEVNAga quyidagi shartlarda mikroqarz berishni buyuraman:
A9: ='Кредитная заявка'!A13:D13 -> Mikroqarz summasi: 52 000 000,00 (ellik ikki million so'm) so'm.
A10: ='Кредитная заявка'!A14:D14 -> Mikroqarz muddati: 36 (o'ttiz olti) oy.
A11: ='Кредитная заявка'!A15:D15 -> Mikroqarzdan foydalanganlik uchun foiz stavkasi: yillik 60% (Oltmish) foiz
A12: ='Кредитная заявка'!A16:D16 -> Mikroqarz bo'yicha asosiy qarz va foizlarni to'lash:
A13: ='Кредитная заявка'!A17:D17 -> - mikroqarz shartnomasi bo'yicha har oy differensial to'lovlari amalga oshiriladi
A14: ='Кредитная заявка'!A19:D19 -> - mikroqarz shartnomasi bo'yicha har oy differensial to'lovlari amalga oshiriladi
A15: =IF(malumot!B109="Avtotransport",buyruq!A14:E14,buyruq!A13:E13) -> - mikroqarz shartnomasi bo'yicha har oy differensial to'lovlari amalga oshiriladi
A16: =IF(malumot!B109=malumot!D109,""&malumot!C123&"ga tegishli "&malumot!C132&" ko'rinishidagi ko'chmas mulkni quyidagi ma'lumotlarga muvofiq garovga qabul qilinsin:",""&malumot!B123&"ga tegishli "&malumot!B131&" ko'rinishidagi transport vositasini quyidagi ma'lumotlarga muvofiq garovga qabul qilinsin:") -> XUDOYKULOV ALMURAT KURBONAZAROVICHga tegishli LADA VESTA ko'rinishidagi transport vositasini quyidagi ma'lumotlarga muvofiq garovga qabul qilinsin:
A17: =""&malumot!C123&"ga tegishli "&malumot!C132&" ko'rinishidagi ko'chmas mulkni quyidagi ma'lumotlarga muvofiq garovga qabul qilinsin:" -> 0ga tegishli 3 - xonali yakka tartibdagi uy-joy ko'rinishidagi ko'chmas mulkni quyidagi ma'lumotlarga muvofiq garovga qabul qilinsin:
A18: =""&malumot!B123&"ga tegishli "&malumot!B131&" ko'rinishidagi transport vositasini quyidagi ma'lumotlarga muvofiq garovga qabul qilinsin:" -> XUDOYKULOV ALMURAT KURBONAZAROVICHga tegishli LADA VESTA ko'rinishidagi transport vositasini quyidagi ma'lumotlarga muvofiq garovga qabul qilinsin:
A19: =dalolatnoma!A29 -> Nomi | B19: =dalolatnoma!B29 -> Kuzov turi va kuzov raqami* | C19: =dalolatnoma!C29 -> Dvigatel va shassi raqami* | D19: =dalolatnoma!D29 -> Ishlab chiqarilgan yili va rangi* | E19: =dalolatnoma!E29 -> Kelishilgan garov qiymati, so'm
A20: =dalolatnoma!A30 -> LADA VESTA | B20: =dalolatnoma!B30 -> kuzov turi - YENGIL SEDAN, kuzov raqami XTAGFL110KY258232 | C20: =dalolatnoma!C30 -> dvigatel raqami 3977458, shassi raqami - RAKAMSIZ | D20: =dalolatnoma!D30 -> rangi - SARIQ JELTO- ORANJEVIY, ishlab chiqarilgan yili - 2019 | E20: =dalolatnoma!E30 -> 78 000 000,00 (yetmish sakkiz million so'm)
A21: =dalolatnoma!A22:E22 -> -* avtotransport egasi: XUDOYKULOV ALMURAT KURBONAZAROVICH
A22: =dalolatnoma!A23:E23 -> -* texnik pasport: AAG 3367573 24.01.2024 y.
A23: =dalolatnoma!A24:E24 -> -* roʻyxatdan oʻtgan manzili/garaj manzili: SURXONDARYO VILOYATI JARQO'RG'ON TUMANI OQQURG'ON QFY QORAYONTOQ MFY IBN SINO KO'CHASI 114-UY
A24: =dalolatnoma!A25:E25 -> -* davlat raqami: 75M497WA
B25: «CLEVER MIKROMOLIYA TASHKILOTI» MChJ
B26: Ijrochi direktori
B27: N. Abduraximov

Sheet bayonnoma
A1: =""&malumot!B153&" mikromoliya tashkiloti Kredit qo‘mitasining yig‘ilishi" -> «CLEVER MIKROMOLIYA TASHKILOTI» MChJ mikromoliya tashkiloti Kredit qo‘mitasining yig‘ilishi
A2: =""&H7&" protokolidan ko'chirma" -> №659-SR protokolidan ko'chirma
A3: Toshkent shahri | E3: =malumot!B68 -> 24 mart 2025 y.
B4: KUN TARTIBI:
A5: =" "&H8&"."&malumot!B5&" ga "&malumot!B65&" berish masalasini ko‘rib chiqish to‘g‘risida." -> 1.SHAYMARDANOVA SABOXAT YULDASHEVNA ga mikroqarz berish masalasini ko‘rib chiqish to‘g‘risida.
A7: =" "&H9&" masala yuzasidan: «Clever Mikromoliya Tashkiloti» MChJ mikromoliya tashkiloti kredit bo‘yicha menejeri "&malumot!B5&"ga "&FIXED(malumot!B75)&" ("&malumot!B76&") so‘m miqdorida, muddati "&malumot!B81&" ("&malumot!B82&") oyga va yillik 60 (Oltmish) foiz miqdorida "&malumot!B65&" berich bo‘yicha "&malumot!B5&"ning kredit arizasi va "&malumot!B153&"ning xulosasi bilan ishtirokchilarni tanishtirdi." -> Birinchi masala yuzasidan: «Clever Mikromoliya Tashkiloti» MChJ mikromoliya tashkiloti kredit bo‘yicha menejeri SHAYMARDANOVA SABOXAT YULDASHEVNAga 52 000 000,00 (ellik ikki million so'm) so‘m miqdorida, muddati 36 (o'ttiz olti) oyga va yillik 60 (Oltmish) foiz miqdorida mikroqarz berich bo‘yicha SHAYMARDANOVA SABOXAT YULDASHEVNAning kredit arizasi va «CLEVER MIKROMOLIYA TASHKILOTI» MChJning xulosasi bilan ishtirokchilarni tanishtirdi. | G7: Protokol raqami | H7: =malumot!B1 -> №659-SR
G8: Savol raqami | H8: 1 | I8: 1 | J8: 2 | K8: 3 | L8: 4 | M8: 5 | N8: 6 | O8: 7 | P8: 8 | Q8: 9 | R8: 10 | S8: 11 | T8: 12 | U8: 13 | V8: 14 | W8: 15 | X8: 16 | Y8: 17 | Z8: 18 | AA8: 19 | AB8: 20 | AC8: 21 | AD8: 22 | AE8: 23 | AF8: 24 | AG8: 25
G9: Savol raqami qol bilan | H9: =IF(H8=I8,I9,IF(H8=J8,J9,IF(H8=K8,K9,IF(H8=L8,L9,IF(H8=M8,M9,IF(H8=N8,N9,IF(H8=O8,O9,IF(H8=P8,P9,IF(H8=Q8,Q9,IF(H8=R8,R9,IF(H8=S8,S9,IF(H8=T8,T9,IF(H8=U8,U9,IF(H8=V8,V9,IF(H8=W8,W9,IF(H8=X8,X9,IF(H8=Y8,Y9,IF(H8=Z8,Z9,IF(H8=AA8,AA9,IF(H8=AB8,AB9,IF(H8=AC8,AC9,IF(H8=AD8,AD9,IF(H8=AE8,AE9,IF(H8=AF8,AF9,IF(H8=AG8,AG9))))))))))))))))))))))))) -> Birinchi | I9: Birinchi | J9: Ikkinchi | K9: Uchinchi | L9: To'rtinchi | M9: Beshinchi | N9: O'ltinchi | O9: Yettinchi | P9: Sakkizinchi | Q9: Tuqqizinchi | R9: O'ninchi | S9: O'n birinchi | T9: O'n ikkinchi | U9: O'n uchinchi | V9: O'n to'rtinchi | W9: O'n beshinchi | X9: O'n oltinchi | Y9: O'n yettinchi | Z9: O'n sakkizinchi | AA9: O'n tuqqizinchi | AB9: Yigirmanchi | AC9: Yigirma birinchi | AD9: Yigizma ikkinchi | AE9: Yigirma uchinchi | AF9: Yigirma to'rtinchi | AG9: Yigirma beshinchi
A14: =""&malumot!C64&" ta’minoti:" -> Mikroqarz ta’minoti:
A16: =xulosa!A18:E18 -> Egalik huquqi XUDOYKULOV ALMURAT KURBONAZAROVICHga tegishli bo'lgan garovga olingan avtomobil markasi LADA VESTA, rangi - SARIQ JELTO- ORANJEVIY, ishlab chiqarilgan yili - 2019, davlat raqam belgisi 75M497WA, kuzov turi - YENGIL SEDAN, kuzov raqami XTAGFL110KY258232, dvigatel raqami 3977458, shassi raqami - RAKAMSIZ
C17: masala yuzasidan berilgan ma’lumotlarni muhokama qilib, Kredit qo‘mitasi a’zolariga taqdim etilgan zarur hujjatlarni o‘rganib, majlisda ishtirok etgan Kredit qo‘mitasi a’zolarining taklif va mulohazalarini inobatga olgan holda | D17: =""&malumot!B153&" kredit qo‘mitasi" -> «CLEVER MIKROMOLIYA TASHKILOTI» MChJ kredit qo‘mitasi | E17: =CONCATENATE(C17,D17) -> masala yuzasidan berilgan ma’lumotlarni muhokama qilib, Kredit qo‘mitasi a’zolariga taqdim etilgan zarur hujjatlarni o‘rganib, majlisda ishtirok etgan Kredit qo‘mitasi a’zolarining taklif va mulohazalarini inobatga olgan holda «CLEVER MIKROMOLIYA TASHKILOTI» MChJ kredit qo‘mitasi
A18: =CONCATENATE(H9,E17) -> Birinchi masala yuzasidan berilgan ma’lumotlarni muhokama qilib, Kredit qo‘mitasi a’zolariga taqdim etilgan zarur hujjatlarni o‘rganib, majlisda ishtirok etgan Kredit qo‘mitasi a’zolarining taklif va mulohazalarini inobatga olgan holda «CLEVER MIKROMOLIYA TASHKILOTI» MChJ kredit qo‘mitasi
A19: QAROR QILADI:
A20: =" "&malumot!B5&"ga quyidagi shartlarda "&malumot!B65&" berish masalasi ma’qullansin:" -> SHAYMARDANOVA SABOXAT YULDASHEVNAga quyidagi shartlarda mikroqarz berish masalasi ma’qullansin:
A21: ="1. "&malumot!C64&" summasi: "&FIXED(malumot!B75)&" ("&malumot!B76&") so'm." -> 1. Mikroqarz summasi: 52 000 000,00 (ellik ikki million so'm) so'm.
A22: ="2. "&malumot!C64&" muddati: "&malumot!B81&" ("&malumot!B82&") oy " -> 2. Mikroqarz muddati: 36 (o'ttiz olti) oy
A23: ="3. "&malumot!C64&"dan foydalanganlik uchun foiz stavkasi:yillik "&malumot!B85&"% ("&malumot!B86&") foiz." -> 3. Mikroqarzdan foydalanganlik uchun foiz stavkasi:yillik 60% (Oltmish) foiz.
A24: ="4. "&malumot!C64&" bo‘yicha asosiy qarz va foizlarni to‘lash:" -> 4. Mikroqarz bo‘yicha asosiy qarz va foizlarni to‘lash:
A25: ='Кредитная заявка'!A19:D19 -> - mikroqarz shartnomasi bo'yicha har oy differensial to'lovlari amalga oshiriladi
A26: ="5. "&malumot!C64&" bo‘yicha garov "&xulosa!A29:E29&"" -> 5. Mikroqarz bo‘yicha garov - XUDOYKULOV ALMURAT KURBONAZAROVICH ga mulk huquqi asosida tegishli avtotransport vositasi LADA VESTA , quyidagi tafsilotlarga muvofiq:
A27: =dalolatnoma!A29 -> Nomi | B27: =dalolatnoma!B29 -> Kuzov turi va kuzov raqami* | C27: =dalolatnoma!C29 -> Dvigatel va shassi raqami* | D27: =dalolatnoma!D29 -> Ishlab chiqarilgan yili va rangi* | E27: =dalolatnoma!E29 -> Kelishilgan garov qiymati, so'm
A28: =dalolatnoma!A30 -> LADA VESTA | B28: =dalolatnoma!B30 -> kuzov turi - YENGIL SEDAN, kuzov raqami XTAGFL110KY258232 | C28: =dalolatnoma!C30 -> dvigatel raqami 3977458, shassi raqami - RAKAMSIZ | D28: =dalolatnoma!D30 -> rangi - SARIQ JELTO- ORANJEVIY, ishlab chiqarilgan yili - 2019 | E28: =dalolatnoma!E30 -> 78 000 000,00 (yetmish sakkiz million so'm)
A29: =dalolatnoma!A22:E22 -> -* avtotransport egasi: XUDOYKULOV ALMURAT KURBONAZAROVICH
A30: =dalolatnoma!A23:E23 -> -* texnik pasport: AAG 3367573 24.01.2024 y.
A31: =dalolatnoma!A24:E24 -> -* roʻyxatdan oʻtgan manzili/garaj manzili: SURXONDARYO VILOYATI JARQO'RG'ON TUMANI OQQURG'ON QFY QORAYONTOQ MFY IBN SINO KO'CHASI 114-UY
A32: =dalolatnoma!A25:E25 -> -* davlat raqami: 75M497WA
A34: ="6. Boshqa shartlar – "&IF(malumot!B109=malumot!B110,"avtotransport vositasi",IF(malumot!B109=malumot!C110,"ko'chmas mulk",0))&" shaklida garov ta'minlangandan keyin "&malumot!B65&" berish." -> 6. Boshqa shartlar – 0 shaklida garov ta'minlangandan keyin mikroqarz berish.
A36: Qaror bir ovozdan qabul qilindi.
B37: =malumot!B153&" ijrochi direktori" -> «CLEVER MIKROMOLIYA TASHKILOTI» MChJ ijrochi direktori | D37: N. Abduraximov
B38: =malumot!A165 -> Kreditlash bo’limi boshlig’i | D38: =malumot!B165 -> B. Mominov
B39: =malumot!A166 -> Monitoring bo’limi boshlig’i | D39: =malumot!B166 -> B. Jumanazarov

Sheet График дифференц
E1: Приложение №1
F2: ="к договору микрозайма "&malumot!B74&"" -> к договору микрозайма 24 mart 2025 y.dan №659-SR
A4: График погашения
L5: =malumot!B81 -> 36
A6: № | B6: Дата погашения | C6: Остаток основного долга | D6: Сумма погашения, сум
D7: основного долга | E7: процентов* | F7: всего*
A8: 1 | B8: =malumot!B79 -> 45748 | C8: =malumot!B75 -> 52000000 | D8: =IF(IF(C8=0,L8,IF(C8>1,I8))="",0,(IF(C8=0,L8,IF(C8>1,I8)))) -> 1444444.4 | E8: =IF(C8=0,N6,IF(C8>1,L8)) -> 683835.6 | F8: =IF(C8=0,O6,IF(C8>1,M8)) -> 2128280 | G8: =B8-malumot!B67 -> 8 | H8: =DATE(YEAR(B8),12,31)-DATE(YEAR(B8),1,1)+1 -> 365 | I8: =IF(malumot!B83=0,ROUND(C8/L5,2),"") -> 1444444.4 | L8: =ROUND(C8*malumot!$B$84/H8,2)*G8 -> 683835.6 | M8: =D8+E8 -> 2128280 | O8: =TEXT(B8,"ддд") -> Вт | P8: =IF(O8=$U$8,2,IF(O8=$V$8,1,0)) -> 0 | Q8: =DAY(malumot!$B$78)+P8 -> 1 | S8: Чт | T8: Пт | U8: Сб | V8: Вс
A9: 2 | B9: =IF(A9<=malumot!$B$81,DATE(YEAR(R9),MONTH(R9),DAY(IF(A9=malumot!$B$81,malumot!$B$67,IF(A9<malumot!$B$81,(Q9),IF(A9>malumot!$B$81,$H$44,0)))))) -> 45778 | C9: =C8-D8 -> 50555556 | D9: =IF(C9=0,L9,IF(C9>1,I9)) -> 1444444.4 | E9: =IF(C9=0,N8,IF(C9>1,L9)) -> 2493150.6 | F9: =IF(C9=0,N8,IF(C9>1,M9)) -> 3937595 | G9: =B9-B8 -> 30 | H9: =DATE(YEAR(B9),12,31)-DATE(YEAR(B9),1,1)+1 -> 365 | I9: =IF(I8="",ROUND(C8/(L5-1),2),I8) -> 1444444.4 | L9: =ROUND(C9*malumot!$B$84/H9,2)*G9 -> 2493150.6 | M9: =D9+E9 -> 3937595 | O9: =TEXT(R9,"ддд") -> Чт | P9: =IF(O9=$U$8,2,IF(O9=$V$8,1,0)) -> 0 | Q9: =DAY(malumot!$B$78)+P9 -> 1 | R9: =IF(A9<=malumot!$B$81,DATE(YEAR($B$8),MONTH($B$8)+A8,DAY(malumot!$B$78)),0) -> 45778
A10: 3 | B10: =IF(A10<=malumot!$B$81,DATE(YEAR(R10),MONTH(R10),DAY(IF(A10=malumot!$B$81,malumot!$B$67,IF(A10<malumot!$B$81,(Q10),IF(A10>malumot!$B$81,$H$44,0)))))) -> 45810 | C10: =C9-D9 -> 49111111 | D10: =IF(C10=0,L10,IF(C10>1,I10)) -> 1444444.4 | E10: =IF(C10=0,N9,IF(C10>1,L10)) -> 2583378.9 | F10: =IF(C10=0,N9,IF(C10>1,M10)) -> 4027823.3 | G10: =B10-B9 -> 32 | H10: =DATE(YEAR(B10),12,31)-DATE(YEAR(B10),1,1)+1 -> 365 | I10: =I9 -> 1444444.4 | L10: =ROUND(C10*malumot!$B$84/H10,2)*G10 -> 2583378.9 | M10: =D10+E10 -> 4027823.3 | O10: =TEXT(R10,"ддд") -> Вс | P10: =IF(O10=$U$8,2,IF(O10=$V$8,1,0)) -> 1 | Q10: =DAY(malumot!$B$78)+P10 -> 2 | R10: =IF(A10<=malumot!$B$81,DATE(YEAR($B$8),MONTH($B$8)+A9,DAY(malumot!$B$78)),0) -> 45809
A11: 4 | B11: =IF(A11<=malumot!$B$81,DATE(YEAR(R11),MONTH(R11),DAY(IF(A11=malumot!$B$81,malumot!$B$67,IF(A11<malumot!$B$81,(Q11),IF(A11>malumot!$B$81,$H$44,0)))))) -> 45839 | C11: =C10-D10 -> 47666667 | D11: =IF(C11=0,L11,IF(C11>1,I11)) -> 1444444.4 | E11: =IF(C11=0,N10,IF(C11>1,L11)) -> 2272328.6 | F11: =IF(C11=0,N10,IF(C11>1,M11)) -> 3716773.1 | G11: =B11-B10 -> 29 | H11: =DATE(YEAR(B11),12,31)-DATE(YEAR(B11),1,1)+1 -> 365 | I11: =I10 -> 1444444.4 | L11: =ROUND(C11*malumot!$B$84/H11,2)*G11 -> 2272328.6 | M11: =D11+E11 -> 3716773.1 | O11: =TEXT(R11,"ддд") -> Вт | P11: =IF(O11=$U$8,2,IF(O11=$V$8,1,0)) -> 0 | Q11: =DAY(malumot!$B$78)+P11 -> 1 | R11: =IF(A11<=malumot!$B$81,DATE(YEAR($B$8),MONTH($B$8)+A10,DAY(malumot!$B$78)),0) -> 45839
A12: 5 | B12: =IF(A12<=malumot!$B$81,DATE(YEAR(R12),MONTH(R12),DAY(IF(A12=malumot!$B$81,malumot!$B$67,IF(A12<malumot!$B$81,(Q12),IF(A12>malumot!$B$81,$H$44,0)))))) -> 45870 | C12: =C11-D11 -> 46222222 | D12: =IF(C12=0,L12,IF(C12>1,I12)) -> 1444444.4 | E12: =IF(C12=0,N11,IF(C12>1,L12)) -> 2355433.9 | F12: =IF(C12=0,N11,IF(C12>1,M12)) -> 3799878.4 | G12: =B12-B11 -> 31 | H12: =DATE(YEAR(B12),12,31)-DATE(YEAR(B12),1,1)+1 -> 365 | I12: =I11 -> 1444444.4 | J12: =malumot!B75 -> 52000000 | L12: =ROUND(C12*malumot!$B$84/H12,2)*G12 -> 2355433.9 | M12: =D12+E12 -> 3799878.4 | O12: =TEXT(R12,"ддд") -> Пт | P12: =IF(O12=$U$8,2,IF(O12=$V$8,1,0)) -> 0 | Q12: =DAY(malumot!$B$78)+P12 -> 1 | R12: =IF(A12<=malumot!$B$81,DATE(YEAR($B$8),MONTH($B$8)+A11,DAY(malumot!$B$78)),0) -> 45870
A13: 6 | B13: =IF(A13<=malumot!$B$81,DATE(YEAR(R13),MONTH(R13),DAY(IF(A13=malumot!$B$81,malumot!$B$67,IF(A13<malumot!$B$81,(Q13),IF(A13>malumot!$B$81,$H$44,0)))))) -> 45901 | C13: =C12-D12 -> 44777778 | D13: =IF(C13=0,L13,IF(C13>1,I13)) -> 1444444.4 | E13: =IF(C13=0,N12,IF(C13>1,L13)) -> 2281826.6 | F13: =IF(C13=0,N12,IF(C13>1,M13)) -> 3726271 | G13: =B13-B12 -> 31 | H13: =DATE(YEAR(B13),12,31)-DATE(YEAR(B13),1,1)+1 -> 365 | I13: =IF(L5=H1,K13,IF(L5>H1,I12)) -> 1444444.4 | J13: =SUM($I$8:I12) -> 7222222.2 | K13: =$J$12-J13 -> 44777778 | L13: =ROUND(C13*malumot!$B$84/H13,2)*G13 -> 2281826.6 | M13: =D13+E13 -> 3726271 | O13: =TEXT(R13,"ддд") -> Пн | P13: =IF(O13=$U$8,2,IF(O13=$V$8,1,0)) -> 0 | Q13: =DAY(malumot!$B$78)+P13 -> 1 | R13: =IF(A13<=malumot!$B$81,DATE(YEAR($B$8),MONTH($B$8)+A12,DAY(malumot!$B$78)),0) -> 45901
A14: 7 | B14: =IF(A14<=malumot!$B$81,DATE(YEAR(R14),MONTH(R14),DAY(IF(A14=malumot!$B$81,malumot!$B$67,IF(A14<malumot!$B$81,(Q14),IF(A14>malumot!$B$81,$H$44,0)))))) -> 45931 | C14: =C13-D13 -> 43333333 | D14: =IF(C14=0,L14,IF(C14>1,I14)) -> 1444444.4 | E14: =IF(C14=0,N13,IF(C14>1,L14)) -> 2136986.4 | F14: =IF(C14=0,N13,IF(C14>1,M14)) -> 3581430.8 | G14: =B14-B13 -> 30 | H14: =DATE(YEAR(B14),12,31)-DATE(YEAR(B14),1,1)+1 -> 365 | I14: =IF($L$5=A14,K14,IF($L$5>A14,I13)) -> 1444444.4 | J14: =SUM($I$8:I13) -> 8666666.6 | K14: =$J$12-J14 -> 43333333 | L14: =ROUND(C14*malumot!$B$84/H14,2)*G14 -> 2136986.4 | M14: =D14+E14 -> 3581430.8 | O14: =TEXT(R14,"ддд") -> Ср | P14: =IF(O14=$U$8,2,IF(O14=$V$8,1,0)) -> 0 | Q14: =DAY(malumot!$B$78)+P14 -> 1 | R14: =IF(A14<=malumot!$B$81,DATE(YEAR($B$8),MONTH($B$8)+A13,DAY(malumot!$B$78)),0) -> 45931
A15: 8 | B15: =IF(A15<=malumot!$B$81,DATE(YEAR(R15),MONTH(R15),DAY(IF(A15=malumot!$B$81,malumot!$B$67,IF(A15<malumot!$B$81,(Q15),IF(A15>malumot!$B$81,$H$44,0)))))) -> 45964 | C15: =C14-D14 -> 41888889 | D15: =IF(C15=0,L15,IF(C15>1,I15)) -> 1444444.4 | E15: =IF(C15=0,N14,IF(C15>1,L15)) -> 2272328.9 | F15: =IF(C15=0,N14,IF(C15>1,M15)) -> 3716773.3 | G15: =B15-B14 -> 33 | H15: =DATE(YEAR(B15),12,31)-DATE(YEAR(B15),1,1)+1 -> 365 | I15: =IF($L$5=A15,K15,IF($L$5>A15,I14)) -> 1444444.4 | J15: =SUM($I$8:I14) -> 10111111 | K15: =$J$12-J15 -> 41888889 | L15: =ROUND(C15*malumot!$B$84/H15,2)*G15 -> 2272328.9 | M15: =D15+E15 -> 3716773.3 | O15: =TEXT(R15,"ддд") -> Сб | P15: =IF(O15=$U$8,2,IF(O15=$V$8,1,0)) -> 2 | Q15: =DAY(malumot!$B$78)+P15 -> 3 | R15: =IF(A15<=malumot!$B$81,DATE(YEAR($B$8),MONTH($B$8)+A14,DAY(malumot!$B$78)),0) -> 45962
A16: 9 | B16: =IF(A16<=malumot!$B$81,DATE(YEAR(R16),MONTH(R16),DAY(IF(A16=malumot!$B$81,malumot!$B$67,IF(A16<malumot!$B$81,(Q16),IF(A16>malumot!$B$81,$H$44,0)))))) -> 45992 | C16: =C15-D15 -> 40444444 | D16: =IF(C16=0,L16,IF(C16>1,I16)) -> 1444444.4 | E16: =IF(C16=0,N15,IF(C16>1,L16)) -> 1861552.6 | F16: =IF(C16=0,N15,IF(C16>1,M16)) -> 3305997 | G16: =B16-B15 -> 28 | H16: =DATE(YEAR(B16),12,31)-DATE(YEAR(B16),1,1)+1 -> 365 | I16: =IF($L$5=A16,K16,IF($L$5>A16,I15)) -> 1444444.4 | J16: =SUM($I$8:I15) -> 11555556 | K16: =$J$12-J16 -> 40444444 | L16: =ROUND(C16*malumot!$B$84/H16,2)*G16 -> 1861552.6 | M16: =D16+E16 -> 3305997 | O16: =TEXT(R16,"ддд") -> Пн | P16: =IF(O16=$U$8,2,IF(O16=$V$8,1,0)) -> 0 | Q16: =DAY(malumot!$B$78)+P16 -> 1 | R16: =IF(A16<=malumot!$B$81,DATE(YEAR($B$8),MONTH($B$8)+A15,DAY(malumot!$B$78)),0) -> 45992
A17: 10 | B17: =IF(A17<=malumot!$B$81,DATE(YEAR(R17),MONTH(R17),DAY(IF(A17=malumot!$B$81,malumot!$B$67,IF(A17<malumot!$B$81,(Q17),IF(A17>malumot!$B$81,$H$44,0)))))) -> 46023 | C17: =C16-D16 -> 39000000 | D17: =IF(C17=0,L17,IF(C17>1,I17)) -> 1444444.4 | E17: =IF(C17=0,N16,IF(C17>1,L17)) -> 1987397.3 | F17: =IF(C17=0,N16,IF(C17>1,M17)) -> 3431841.7 | G17: =B17-B16 -> 31 | H17: =DATE(YEAR(B17),12,31)-DATE(YEAR(B17),1,1)+1 -> 365 | I17: =IF($L$5=A17,K17,IF($L$5>A17,I16)) -> 1444444.4 | J17: =SUM($I$8:I16) -> 13000000 | K17: =$J$12-J17 -> 39000000 | L17: =ROUND(C17*malumot!$B$84/H17,2)*G17 -> 1987397.3 | M17: =D17+E17 -> 3431841.7 | O17: =TEXT(R17,"ддд") -> Чт | P17: =IF(O17=$U$8,2,IF(O17=$V$8,1,0)) -> 0 | Q17: =DAY(malumot!$B$78)+P17 -> 1 | R17: =IF(A17<=malumot!$B$81,DATE(YEAR($B$8),MONTH($B$8)+A16,DAY(malumot!$B$78)),0) -> 46023
A18: 11 | B18: =IF(A18<=malumot!$B$81,DATE(YEAR(R18),MONTH(R18),DAY(IF(A18=malumot!$B$81,malumot!$B$67,IF(A18<malumot!$B$81,(Q18),IF(A18>malumot!$B$81,$H$44,0)))))) -> 46055 | C18: =C17-D17 -> 37555556 | D18: =IF(C18=0,L18,IF(C18>1,I18)) -> 1444444.4 | E18: =IF(C18=0,N17,IF(C18>1,L18)) -> 1975525.1 | F18: =IF(C18=0,N17,IF(C18>1,M18)) -> 3419969.6 | G18: =B18-B17 -> 32 | H18: =DATE(YEAR(B18),12,31)-DATE(YEAR(B18),1,1)+1 -> 365 | I18: =IF($L$5=A18,K18,IF($L$5>A18,I17)) -> 1444444.4 | J18: =SUM($I$8:I17) -> 14444444 | K18: =$J$12-J18 -> 37555556 | L18: =ROUND(C18*malumot!$B$84/H18,2)*G18 -> 1975525.1 | M18: =D18+E18 -> 3419969.6 | O18: =TEXT(R18,"ддд") -> Вс | P18: =IF(O18=$U$8,2,IF(O18=$V$8,1,0)) -> 1 | Q18: =DAY(malumot!$B$78)+P18 -> 2 | R18: =IF(A18<=malumot!$B$81,DATE(YEAR($B$8),MONTH($B$8)+A17,DAY(malumot!$B$78)),0) -> 46054
A19: 12 | B19: =IF(A19<=malumot!$B$81,DATE(YEAR(R19),MONTH(R19),DAY(IF(A19=malumot!$B$81,malumot!$B$67,IF(A19<malumot!$B$81,(Q19),IF(A19>malumot!$B$81,$H$44,0)))))) -> 46083 | C19: =C18-D18 -> 36111111 | D19: =IF(C19=0,L19,IF(C19>1,I19)) -> 1444444.4 | E19: =IF(C19=0,N18,IF(C19>1,L19)) -> 1662100.4 | F19: =IF(C19=0,N18,IF(C19>1,M19)) -> 3106544.9 | G19: =B19-B18 -> 28 | H19: =DATE(YEAR(B19),12,31)-DATE(YEAR(B19),1,1)+1 -> 365 | I19: =IF($L$5=A19,K19,IF($L$5>A19,I18)) -> 1444444.4 | J19: =SUM($I$8:I18) -> 15888889 | K19: =$J$12-J19 -> 36111111 | L19: =ROUND(C19*malumot!$B$84/H19,2)*G19 -> 1662100.4 | M19: =D19+E19 -> 3106544.9 | O19: =TEXT(R19,"ддд") -> Вс | P19: =IF(O19=$U$8,2,IF(O19=$V$8,1,0)) -> 1 | Q19: =DAY(malumot!$B$78)+P19 -> 2 | R19: =IF(A19<=malumot!$B$81,DATE(YEAR($B$8),MONTH($B$8)+A18,DAY(malumot!$B$78)),0) -> 46082
A20: 13 | B20: =IF(A20<=malumot!$B$81,DATE(YEAR(R20),MONTH(R20),DAY(IF(A20=malumot!$B$81,malumot!$B$67,IF(A20<malumot!$B$81,(Q20),IF(A20>malumot!$B$81,$H$44,0)))))) -> 46113 | C20: =C19-D19 -> 34666667 | D20: =IF(C20=0,L20,IF(C20>1,I20)) -> 1444444.4 | E20: =IF(C20=0,N19,IF(C20>1,L20)) -> 1709589 | F20: =IF(C20=0,N19,IF(C20>1,M20)) -> 3154033.4 | G20: =B20-B19 -> 30 | H20: =DATE(YEAR(B20),12,31)-DATE(YEAR(B20),1,1)+1 -> 365 | I20: =IF($L$5=A20,K20,IF($L$5>A20,I19)) -> 1444444.4 | J20: =SUM($I$8:I19) -> 17333333 | K20: =$J$12-J20 -> 34666667 | L20: =ROUND(C20*malumot!$B$84/H20,2)*G20 -> 1709589 | M20: =D20+E20 -> 3154033.4 | O20: =TEXT(R20,"ддд") -> Ср | P20: =IF(O20=$U$8,2,IF(O20=$V$8,1,0)) -> 0 | Q20: =DAY(malumot!$B$78)+P20 -> 1 | R20: =IF(A20<=malumot!$B$81,DATE(YEAR($B$8),MONTH($B$8)+A19,DAY(malumot!$B$78)),0) -> 46113
A21: 14 | B21: =IF(A21<=malumot!$B$81,DATE(YEAR(R21),MONTH(R21),DAY(IF(A21=malumot!$B$81,malumot!$B$67,IF(A21<malumot!$B$81,(Q21),IF(A21>malumot!$B$81,$H$44,0)))))) -> 46143 | C21: =C20-D20 -> 33222222 | D21: =IF(C21=0,L21,IF(C21>1,I21)) -> 1444444.4 | E21: =IF(C21=0,N20,IF(C21>1,L21)) -> 1638356.1 | F21: =IF(C21=0,N20,IF(C21>1,M21)) -> 3082800.5 | G21: =B21-B20 -> 30 | H21: =DATE(YEAR(B21),12,31)-DATE(YEAR(B21),1,1)+1 -> 365 | I21: =IF($L$5=A21,K21,IF($L$5>A21,I20)) -> 1444444.4 | J21: =SUM($I$8:I20) -> 18777778 | K21: =$J$12-J21 -> 33222222 | L21: =ROUND(C21*malumot!$B$84/H21,2)*G21 -> 1638356.1 | M21: =D21+E21 -> 3082800.5 | O21: =TEXT(R21,"ддд") -> Пт | P21: =IF(O21=$U$8,2,IF(O21=$V$8,1,0)) -> 0 | Q21: =DAY(malumot!$B$78)+P21 -> 1 | R21: =IF(A21<=malumot!$B$81,DATE(YEAR($B$8),MONTH($B$8)+A20,DAY(malumot!$B$78)),0) -> 46143
A22: 15 | B22: =IF(A22<=malumot!$B$81,DATE(YEAR(R22),MONTH(R22),DAY(IF(A22=malumot!$B$81,malumot!$B$67,IF(A22<malumot!$B$81,(Q22),IF(A22>malumot!$B$81,$H$44,0)))))) -> 46174 | C22: =C21-D21 -> 31777778 | D22: =IF(C22=0,L22,IF(C22>1,I22)) -> 1444444.4 | E22: =IF(C22=0,N21,IF(C22>1,L22)) -> 1619360.6 | F22: =IF(C22=0,N21,IF(C22>1,M22)) -> 3063805.1 | G22: =B22-B21 -> 31 | H22: =DATE(YEAR(B22),12,31)-DATE(YEAR(B22),1,1)+1 -> 365 | I22: =IF($L$5=A22,K22,IF($L$5>A22,I21)) -> 1444444.4 | J22: =SUM($I$8:I21) -> 20222222 | K22: =$J$12-J22 -> 31777778 | L22: =ROUND(C22*malumot!$B$84/H22,2)*G22 -> 1619360.6 | M22: =D22+E22 -> 3063805.1 | O22: =TEXT(R22,"ддд") -> Пн | P22: =IF(O22=$U$8,2,IF(O22=$V$8,1,0)) -> 0 | Q22: =DAY(malumot!$B$78)+P22 -> 1 | R22: =IF(A22<=malumot!$B$81,DATE(YEAR($B$8),MONTH($B$8)+A21,DAY(malumot!$B$78)),0) -> 46174
A23: 16 | B23: =IF(A23<=malumot!$B$81,DATE(YEAR(R23),MONTH(R23),DAY(IF(A23=malumot!$B$81,malumot!$B$67,IF(A23<malumot!$B$81,(Q23),IF(A23>malumot!$B$81,$H$44,0)))))) -> 46204 | C23: =C22-D22 -> 30333333 | D23: =IF(C23=0,L23,IF(C23>1,I23)) -> 1444444.4 | E23: =IF(C23=0,N22,IF(C23>1,L23)) -> 1495890.3 | F23: =IF(C23=0,N22,IF(C23>1,M23)) -> 2940334.7 | G23: =B23-B22 -> 30 | H23: =DATE(YEAR(B23),12,31)-DATE(YEAR(B23),1,1)+1 -> 365 | I23: =IF($L$5=A23,K23,IF($L$5>A23,I22)) -> 1444444.4 | J23: =SUM($I$8:I22) -> 21666667 | K23: =$J$12-J23 -> 30333333 | L23: =ROUND(C23*malumot!$B$84/H23,2)*G23 -> 1495890.3 | M23: =D23+E23 -> 2940334.7 | O23: =TEXT(R23,"ддд") -> Ср | P23: =IF(O23=$U$8,2,IF(O23=$V$8,1,0)) -> 0 | Q23: =DAY(malumot!$B$78)+P23 -> 1 | R23: =IF(A23<=malumot!$B$81,DATE(YEAR($B$8),MONTH($B$8)+A22,DAY(malumot!$B$78)),0) -> 46204
A24: 17 | B24: =IF(A24<=malumot!$B$81,DATE(YEAR(R24),MONTH(R24),DAY(IF(A24=malumot!$B$81,malumot!$B$67,IF(A24<malumot!$B$81,(Q24),IF(A24>malumot!$B$81,$H$44,0)))))) -> 46237 | C24: =C23-D23 -> 28888889 | D24: =IF(C24=0,L24,IF(C24>1,I24)) -> 1444444.4 | E24: =IF(C24=0,N23,IF(C24>1,L24)) -> 1567123.1 | F24: =IF(C24=0,N23,IF(C24>1,M24)) -> 3011567.6 | G24: =B24-B23 -> 33 | H24: =DATE(YEAR(B24),12,31)-DATE(YEAR(B24),1,1)+1 -> 365 | I24: =IF($L$5=A24,K24,IF($L$5>A24,I23)) -> 1444444.4 | J24: =SUM($I$8:I23) -> 23111111 | K24: =$J$12-J24 -> 28888889 | L24: =ROUND(C24*malumot!$B$84/H24,2)*G24 -> 1567123.1 | M24: =D24+E24 -> 3011567.6 | O24: =TEXT(R24,"ддд") -> Сб | P24: =IF(O24=$U$8,2,IF(O24=$V$8,1,0)) -> 2 | Q24: =DAY(malumot!$B$78)+P24 -> 3 | R24: =IF(A24<=malumot!$B$81,DATE(YEAR($B$8),MONTH($B$8)+A23,DAY(malumot!$B$78)),0) -> 46235
A25: 18 | B25: =IF(A25<=malumot!$B$81,DATE(YEAR(R25),MONTH(R25),DAY(IF(A25=malumot!$B$81,malumot!$B$67,IF(A25<malumot!$B$81,(Q25),IF(A25>malumot!$B$81,$H$44,0)))))) -> 46266 | C25: =C24-D24 -> 27444445 | D25: =IF(C25=0,L25,IF(C25>1,I25)) -> 1444444.4 | E25: =IF(C25=0,N24,IF(C25>1,L25)) -> 1308310.6 | F25: =IF(C25=0,N24,IF(C25>1,M25)) -> 2752755.1 | G25: =B25-B24 -> 29 | H25: =DATE(YEAR(B25),12,31)-DATE(YEAR(B25),1,1)+1 -> 365 | I25: =IF($L$5=A25,K25,IF($L$5>A25,I24)) -> 1444444.4 | J25: =SUM($I$8:I24) -> 24555555 | K25: =$J$12-J25 -> 27444445 | L25: =ROUND(C25*malumot!$B$84/H25,2)*G25 -> 1308310.6 | M25: =D25+E25 -> 2752755.1 | O25: =TEXT(R25,"ддд") -> Вт | P25: =IF(O25=$U$8,2,IF(O25=$V$8,1,0)) -> 0 | Q25: =DAY(malumot!$B$78)+P25 -> 1 | R25: =IF(A25<=malumot!$B$81,DATE(YEAR($B$8),MONTH($B$8)+A24,DAY(malumot!$B$78)),0) -> 46266
... A31: 24 | B31: =IF(A31<=malumot!$B$81,DATE(YEAR(R31),MONTH(R31),DAY(IF(A31=malumot!$B$81,malumot!$B$67,IF(A31<malumot!$B$81,(Q31),IF(A31>malumot!$B$81,$H$44,0)))))) -> 46447 | C31: =C30-D30 -> 18777778 | D31: =IF(C31=0,L31,IF(C31>1,I31)) -> 1444444.4 | E31: =IF(C31=0,N30,IF(C31>1,L31)) -> 864292.24 | F31: =IF(C31=0,N30,IF(C31>1,M31)) -> 2308736.7 | G31: =B31-B30 -> 28 | H31: =DATE(YEAR(B31),12,31)-DATE(YEAR(B31),1,1)+1 -> 365 | I31: =IF($L$5=A31,K31,IF($L$5>A31,I30)) -> 1444444.4 | J31: =SUM($I$8:I30) -> 33222222 | K31: =$J$12-J31 -> 18777778 | L31: =ROUND(C31*malumot!$B$84/H31,2)*G31 -> 864292.24 | M31: =D31+E31 -> 2308736.7 | O31: =TEXT(R31,"ддд") -> Пн | P31: =IF(O31=$U$8,2,IF(O31=$V$8,1,0)) -> 0 | Q31: =DAY(malumot!$B$78)+P31 -> 1 | R31: =IF(A31<=malumot!$B$81,DATE(YEAR($B$8),MONTH($B$8)+A30,DAY(malumot!$B$78)),0) -> 46447
A32: =1+A31 -> 25 | B32: =IF(A32<=malumot!$B$81,DATE(YEAR(R32),MONTH(R32),DAY(IF(A32=malumot!$B$81,malumot!$B$67,IF(A32<malumot!$B$81,(Q32),IF(A32>malumot!$B$81,$H$44,0)))))) -> 46478 | C32: =C31-D31 -> 17333333 | D32: =IF(C32=0,L32,IF(C32>1,I32)) -> 1444444.4 | E32: =IF(C32=0,N31,IF(C32>1,L32)) -> 883287.65 | F32: =IF(C32=0,N31,IF(C32>1,M32)) -> 2327732.1 | G32: =B32-B31 -> 31 | H32: =DATE(YEAR(B32),12,31)-DATE(YEAR(B32),1,1)+1 -> 365 | I32: =IF($L$5=A32,K32,IF($L$5>A32,I31)) -> 1444444.4 | J32: =SUM($I$8:I31) -> 34666667 | K32: =$J$12-J32 -> 17333333 | L32: =ROUND(C32*malumot!$B$84/H32,2)*G32 -> 883287.65 | M32: =D32+E32 -> 2327732.1 | O32: =TEXT(R32,"ддд") -> Чт | P32: =IF(O32=$U$8,2,IF(O32=$V$8,1,0)) -> 0 | Q32: =DAY(malumot!$B$78)+P32 -> 1 | R32: =IF(A32<=malumot!$B$81,DATE(YEAR($B$8),MONTH($B$8)+A31,DAY(malumot!$B$78)),0) -> 46478
A33: =1+A32 -> 26 | B33: =IF(A33<=malumot!$B$81,DATE(YEAR(R33),MONTH(R33),DAY(IF(A33=malumot!$B$81,malumot!$B$67,IF(A33<malumot!$B$81,(Q33),IF(A33>malumot!$B$81,$H$44,0)))))) -> 46510 | C33: =C32-D32 -> 15888889 | D33: =IF(C33=0,L33,IF(C33>1,I33)) -> 1444444.4 | E33: =IF(C33=0,N32,IF(C33>1,L33)) -> 835799.04 | F33: =IF(C33=0,N32,IF(C33>1,M33)) -> 2280243.5 | G33: =B33-B32 -> 32 | H33: =DATE(YEAR(B33),12,31)-DATE(YEAR(B33),1,1)+1 -> 365 | I33: =IF($L$5=A33,K33,IF($L$5>A33,I32)) -> 1444444.4 | J33: =SUM($I$8:I32) -> 36111111 | K33: =$J$12-J33 -> 15888889 | L33: =ROUND(C33*malumot!$B$84/H33,2)*G33 -> 835799.04 | M33: =D33+E33 -> 2280243.5 | O33: =TEXT(R33,"ддд") -> Сб | P33: =IF(O33=$U$8,2,IF(O33=$V$8,1,0)) -> 2 | Q33: =DAY(malumot!$B$78)+P33 -> 3 | R33: =IF(A33<=malumot!$B$81,DATE(YEAR($B$8),MONTH($B$8)+A32,DAY(malumot!$B$78)),0) -> 46508
A34: =1+A33 -> 27 | B34: =IF(A34<=malumot!$B$81,DATE(YEAR(R34),MONTH(R34),DAY(IF(A34=malumot!$B$81,malumot!$B$67,IF(A34<malumot!$B$81,(Q34),IF(A34>malumot!$B$81,$H$44,0)))))) -> 46539 | C34: =C33-D33 -> 14444445 | D34: =IF(C34=0,L34,IF(C34>1,I34)) -> 1444444.4 | E34: =IF(C34=0,N33,IF(C34>1,L34)) -> 688584.41 | F34: =IF(C34=0,N33,IF(C34>1,M34)) -> 2133028.9 | G34: =B34-B33 -> 29 | H34: =DATE(YEAR(B34),12,31)-DATE(YEAR(B34),1,1)+1 -> 365 | I34: =IF($L$5=A34,K34,IF($L$5>A34,I33)) -> 1444444.4 | J34: =SUM($I$8:I33) -> 37555555 | K34: =$J$12-J34 -> 14444445 | L34: =ROUND(C34*malumot!$B$84/H34,2)*G34 -> 688584.41 | M34: =D34+E34 -> 2133028.9 | O34: =TEXT(R34,"ддд") -> Вт | P34: =IF(O34=$U$8,2,IF(O34=$V$8,1,0)) -> 0 | Q34: =DAY(malumot!$B$78)+P34 -> 1 | R34: =IF(A34<=malumot!$B$81,DATE(YEAR($B$8),MONTH($B$8)+A33,DAY(malumot!$B$78)),0) -> 46539
A35: =1+A34 -> 28 | B35: =IF(A35<=malumot!$B$81,DATE(YEAR(R35),MONTH(R35),DAY(IF(A35=malumot!$B$81,malumot!$B$67,IF(A35<malumot!$B$81,(Q35),IF(A35>malumot!$B$81,$H$44,0)))))) -> 46569 | C35: =C34-D34 -> 13000000 | D35: =IF(C35=0,L35,IF(C35>1,I35)) -> 1444444.4 | E35: =IF(C35=0,N34,IF(C35>1,L35)) -> 641095.8 | F35: =IF(C35=0,N34,IF(C35>1,M35)) -> 2085540.2 | G35: =B35-B34 -> 30 | H35: =DATE(YEAR(B35),12,31)-DATE(YEAR(B35),1,1)+1 -> 365 | I35: =IF($L$5=A35,K35,IF($L$5>A35,I34)) -> 1444444.4 | J35: =SUM($I$8:I34) -> 39000000 | K35: =$J$12-J35 -> 13000000 | L35: =ROUND(C35*malumot!$B$84/H35,2)*G35 -> 641095.8 | M35: =D35+E35 -> 2085540.2 | O35: =TEXT(R35,"ддд") -> Чт | P35: =IF(O35=$U$8,2,IF(O35=$V$8,1,0)) -> 0 | Q35: =DAY(malumot!$B$78)+P35 -> 1 | R35: =IF(A35<=malumot!$B$81,DATE(YEAR($B$8),MONTH($B$8)+A34,DAY(malumot!$B$78)),0) -> 46569
A36: =1+A35 -> 29 | B36: =IF(A36<=malumot!$B$81,DATE(YEAR(R36),MONTH(R36),DAY(IF(A36=malumot!$B$81,malumot!$B$67,IF(A36<malumot!$B$81,(Q36),IF(A36>malumot!$B$81,$H$44,0)))))) -> 46601 | C36: =C35-D35 -> 11555556 | D36: =IF(C36=0,L36,IF(C36>1,I36)) -> 1444444.4 | E36: =IF(C36=0,N35,IF(C36>1,L36)) -> 607853.76 | F36: =IF(C36=0,N35,IF(C36>1,M36)) -> 2052298.2 | G36: =B36-B35 -> 32 | H36: =DATE(YEAR(B36),12,31)-DATE(YEAR(B36),1,1)+1 -> 365 | I36: =IF($L$5=A36,K36,IF($L$5>A36,I35)) -> 1444444.4 | J36: =SUM($I$8:I35) -> 40444444 | K36: =$J$12-J36 -> 11555556 | L36: =ROUND(C36*malumot!$B$84/H36,2)*G36 -> 607853.76 | M36: =D36+E36 -> 2052298.2 | O36: =TEXT(R36,"ддд") -> Вс | P36: =IF(O36=$U$8,2,IF(O36=$V$8,1,0)) -> 1 | Q36: =DAY(malumot!$B$78)+P36 -> 2 | R36: =IF(A36<=malumot!$B$81,DATE(YEAR($B$8),MONTH($B$8)+A35,DAY(malumot!$B$78)),0) -> 46600
A37: =1+A36 -> 30 | B37: =IF(A37<=malumot!$B$81,DATE(YEAR(R37),MONTH(R37),DAY(IF(A37=malumot!$B$81,malumot!$B$67,IF(A37<malumot!$B$81,(Q37),IF(A37>malumot!$B$81,$H$44,0)))))) -> 46631 | C37: =C36-D36 -> 10111111 | D37: =IF(C37=0,L37,IF(C37>1,I37)) -> 1444444.4 | E37: =IF(C37=0,N36,IF(C37>1,L37)) -> 498630 | F37: =IF(C37=0,N36,IF(C37>1,M37)) -> 1943074.4 | G37: =B37-B36 -> 30 | H37: =DATE(YEAR(B37),12,31)-DATE(YEAR(B37),1,1)+1 -> 365 | I37: =IF($L$5=A37,K37,IF($L$5>A37,I36)) -> 1444444.4 | J37: =SUM($I$8:I36) -> 41888889 | K37: =$J$12-J37 -> 10111111 | L37: =ROUND(C37*malumot!$B$84/H37,2)*G37 -> 498630 | M37: =D37+E37 -> 1943074.4 | O37: =TEXT(R37,"ддд") -> Ср | P37: =IF(O37=$U$8,2,IF(O37=$V$8,1,0)) -> 0 | Q37: =DAY(malumot!$B$78)+P37 -> 1 | R37: =IF(A37<=malumot!$B$81,DATE(YEAR($B$8),MONTH($B$8)+A36,DAY(malumot!$B$78)),0) -> 46631
A38: =1+A37 -> 31 | B38: =IF(A38<=malumot!$B$81,DATE(YEAR(R38),MONTH(R38),DAY(IF(A38=malumot!$B$81,malumot!$B$67,IF(A38<malumot!$B$81,(Q38),IF(A38>malumot!$B$81,$H$44,0)))))) -> 46661 | C38: =C37-D37 -> 8666666.8 | D38: =IF(C38=0,L38,IF(C38>1,I38)) -> 1444444.4 | E38: =IF(C38=0,N37,IF(C38>1,L38)) -> 427397.4 | F38: =IF(C38=0,N37,IF(C38>1,M38)) -> 1871841.8 | G38: =B38-B37 -> 30 | H38: =DATE(YEAR(B38),12,31)-DATE(YEAR(B38),1,1)+1 -> 365 | I38: =IF($L$5=A38,K38,IF($L$5>A38,I37)) -> 1444444.4 | J38: =SUM($I$8:I37) -> 43333333 | K38: =$J$12-J38 -> 8666666.8 | L38: =ROUND(C38*malumot!$B$84/H38,2)*G38 -> 427397.4 | M38: =D38+E38 -> 1871841.8 | O38: =TEXT(R38,"ддд") -> Пт | P38: =IF(O38=$U$8,2,IF(O38=$V$8,1,0)) -> 0 | Q38: =DAY(malumot!$B$78)+P38 -> 1 | R38: =IF(A38<=malumot!$B$81,DATE(YEAR($B$8),MONTH($B$8)+A37,DAY(malumot!$B$78)),0) -> 46661
A39: =1+A38 -> 32 | B39: =IF(A39<=malumot!$B$81,DATE(YEAR(R39),MONTH(R39),DAY(IF(A39=malumot!$B$81,malumot!$B$67,IF(A39<malumot!$B$81,(Q39),IF(A39>malumot!$B$81,$H$44,0)))))) -> 46692 | C39: =C38-D38 -> 7222222.4 | D39: =IF(C39=0,L39,IF(C39>1,I39)) -> 1444444.4 | E39: =IF(C39=0,N38,IF(C39>1,L39)) -> 368036.65 | F39: =IF(C39=0,N38,IF(C39>1,M39)) -> 1812481.1 | G39: =B39-B38 -> 31 | H39: =DATE(YEAR(B39),12,31)-DATE(YEAR(B39),1,1)+1 -> 365 | I39: =IF($L$5=A39,K39,IF($L$5>A39,I38)) -> 1444444.4 | J39: =SUM($I$8:I38) -> 44777778 | K39: =$J$12-J39 -> 7222222.4 | L39: =ROUND(C39*malumot!$B$84/H39,2)*G39 -> 368036.65 | M39: =D39+E39 -> 1812481.1 | O39: =TEXT(R39,"ддд") -> Пн | P39: =IF(O39=$U$8,2,IF(O39=$V$8,1,0)) -> 0 | Q39: =DAY(malumot!$B$78)+P39 -> 1 | R39: =IF(A39<=malumot!$B$81,DATE(YEAR($B$8),MONTH($B$8)+A38,DAY(malumot!$B$78)),0) -> 46692
A40: =1+A39 -> 33 | B40: =IF(A40<=malumot!$B$81,DATE(YEAR(R40),MONTH(R40),DAY(IF(A40=malumot!$B$81,malumot!$B$67,IF(A40<malumot!$B$81,(Q40),IF(A40>malumot!$B$81,$H$44,0)))))) -> 46722 | C40: =C39-D39 -> 5777777.9 | D40: =IF(C40=0,L40,IF(C40>1,I40)) -> 1444444.4 | E40: =IF(C40=0,N39,IF(C40>1,L40)) -> 284931.6 | F40: =IF(C40=0,N39,IF(C40>1,M40)) -> 1729376 | G40: =B40-B39 -> 30 | H40: =DATE(YEAR(B40),12,31)-DATE(YEAR(B40),1,1)+1 -> 365 | I40: =IF($L$5=A40,K40,IF($L$5>A40,I39)) -> 1444444.4 | J40: =SUM($I$8:I39) -> 46222222 | K40: =$J$12-J40 -> 5777777.9 | L40: =ROUND(C40*malumot!$B$84/H40,2)*G40 -> 284931.6 | M40: =D40+E40 -> 1729376 | O40: =TEXT(R40,"ддд") -> Ср | P40: =IF(O40=$U$8,2,IF(O40=$V$8,1,0)) -> 0 | Q40: =DAY(malumot!$B$78)+P40 -> 1 | R40: =IF(A40<=malumot!$B$81,DATE(YEAR($B$8),MONTH($B$8)+A39,DAY(malumot!$B$78)),0) -> 46722
A41: =1+A40 -> 34 | B41: =IF(A41<=malumot!$B$81,DATE(YEAR(R41),MONTH(R41),DAY(IF(A41=malumot!$B$81,malumot!$B$67,IF(A41<malumot!$B$81,(Q41),IF(A41>malumot!$B$81,$H$44,0)))))) -> 46755 | C41: =C40-D40 -> 4333333.5 | D41: =IF(C41=0,L41,IF(C41>1,I41)) -> 1444444.4 | E41: =IF(C41=0,N40,IF(C41>1,L41)) -> 234426.39 | F41: =IF(C41=0,N40,IF(C41>1,M41)) -> 1678870.8 | G41: =B41-B40 -> 33 | H41: =DATE(YEAR(B41),12,31)-DATE(YEAR(B41),1,1)+1 -> 366 | I41: =IF($L$5=A41,K41,IF($L$5>A41,I40)) -> 1444444.4 | J41: =SUM($I$8:I40) -> 47666667 | K41: =$J$12-J41 -> 4333333.5 | L41: =ROUND(C41*malumot!$B$84/H41,2)*G41 -> 234426.39 | M41: =D41+E41 -> 1678870.8 | O41: =TEXT(R41,"ддд") -> Сб | P41: =IF(O41=$U$8,2,IF(O41=$V$8,1,0)) -> 2 | Q41: =DAY(malumot!$B$78)+P41 -> 3 | R41: =IF(A41<=malumot!$B$81,DATE(YEAR($B$8),MONTH($B$8)+A40,DAY(malumot!$B$78)),0) -> 46753
A42: =1+A41 -> 35 | B42: =IF(A42<=malumot!$B$81,DATE(YEAR(R42),MONTH(R42),DAY(IF(A42=malumot!$B$81,malumot!$B$67,IF(A42<malumot!$B$81,(Q42),IF(A42>malumot!$B$81,$H$44,0)))))) -> 46784 | C42: =C41-D41 -> 2888889 | D42: =IF(C42=0,L42,IF(C42>1,I42)) -> 1444444.4 | E42: =IF(C42=0,N41,IF(C42>1,L42)) -> 137340.52 | F42: =IF(C42=0,N41,IF(C42>1,M42)) -> 1581785 | G42: =B42-B41 -> 29 | H42: =DATE(YEAR(B42),12,31)-DATE(YEAR(B42),1,1)+1 -> 366 | I42: =IF($L$5=A42,K42,IF($L$5>A42,I41)) -> 1444444.4 | J42: =SUM($I$8:I41) -> 49111111 | K42: =$J$12-J42 -> 2888889 | L42: =ROUND(C42*malumot!$B$84/H42,2)*G42 -> 137340.52 | M42: =D42+E42 -> 1581785 | O42: =TEXT(R42,"ддд") -> Вт | P42: =IF(O42=$U$8,2,IF(O42=$V$8,1,0)) -> 0 | Q42: =DAY(malumot!$B$78)+P42 -> 1 | R42: =IF(A42<=malumot!$B$81,DATE(YEAR($B$8),MONTH($B$8)+A41,DAY(malumot!$B$78)),0) -> 46784
A43: =1+A42 -> 36 | B43: =IF(A43<=malumot!$B$81,DATE(YEAR(R43),MONTH(R43),DAY(IF(A43=malumot!$B$81,malumot!$B$67,IF(A43<malumot!$B$81,(Q43),IF(A43>malumot!$B$81,$H$44,0)))))) -> 46836 | C43: =C42-D42 -> 1444444.6 | D43: =IF(C43=0,L43,IF(C43>1,I43)) -> 1444444.6 | E43: =IF(C43=0,N42,IF(C43>1,L43)) -> 123132.88 | F43: =IF(C43=0,N42,IF(C43>1,M43)) -> 1567577.5 | G43: =B43-B42 -> 52 | H43: =DATE(YEAR(B43),12,31)-DATE(YEAR(B43),1,1)+1 -> 366 | I43: =IF($L$5=A43,K43,IF($L$5>A43,I42)) -> 1444444.6 | J43: =SUM($I$8:I42) -> 50555555 | K43: =$J$12-J43 -> 1444444.6 | L43: =ROUND(C43*malumot!$B$84/H43,2)*G43 -> 123132.88 | M43: =D43+E43 -> 1567577.5 | O43: =TEXT(R43,"ддд") -> Ср | P43: =IF(O43=$U$8,2,IF(O43=$V$8,1,0)) -> 0 | Q43: =DAY(malumot!$B$78)+P43 -> 1 | R43: =IF(A43<=malumot!$B$81,DATE(YEAR($B$8),MONTH($B$8)+A42,DAY(malumot!$B$78)),0) -> 46813
B44: ИТОГО | D44: =SUM(D8:D43) -> 52000000 | E44: =SUM(E8:E43) -> 46309512 | F44: =SUM(F8:F43) -> 98309512
A46: *В случае осуществления погашения платежей по кредиту в даты, отличные от указанных в графике погашения, сумма платежа меняется на сумму процентов, которые начисляются на сумму остатка долга по микрозайму в соответствии с п.п. 2.2. настоящего договора.
A48: =#REF! -> #REF! | D48: =#REF! -> #REF!
A50: =#REF! -> #REF! | D50: =#REF! -> #REF!
A51: =#REF! -> #REF! | D51: =#REF! -> #REF!
A52: =#REF! -> #REF! | D52: ="паспорт серии "&malumot!B16&", "&malumot!B20&"" -> паспорт серии AC 1659096, SURXONDARYO VILOYATI JARQO'RG'ON TUMANI IIB tomonidan 21.02.2019 yilda berilgan
A53: =#REF! -> #REF!
A54: =#REF! -> #REF! | D54: =#REF! -> #REF!
A55: =#REF! -> #REF! | D55: =#REF! -> #REF!
A56: =#REF! -> #REF! | D56: =#REF! -> #REF!
A58: =#REF! -> #REF! | D58: =#REF! -> #REF!
A60: =#REF! -> #REF! | D60: =#REF! -> #REF!
D62: =#REF! -> #REF!

Sheet Данные для послед. Залога
A1: № | B1: - | E1: ФИО | F1: дата | L1: № договора | M1: Сог. Сумма | N1: сог. Сумма (пропис.)
A2: 1 | B2: ha | C2: yoq | D2: ha | E2: TULYAGANOV XODJIAKBAR IRGASHEVICH | F2: 44207 | G2: =MONTH(F2) -> 1 | H2: =IF(G2=$A$26,$A$28,IF(G2=$B$26,$B$28,IF(G2=$C$26,$C$28,IF(G2=$D$26,$D$28,IF(G2=$E$26,$E$28,IF(G2=$F$26,$F$28,IF(G2=$K$26,$K$28,IF(G2=$L$26,$L$28,IF(G2=$M$26,$M$28,IF(G2=$N$26,$N$28,IF(G2=$O$26,$O$28,IF(G2=$P$26,$P$28,0)))))))))))) -> yanvar | I2: =DAY(F2) -> 11 | J2: =YEAR(F2) -> 2021 | K2: =""&I2&" "&H2&" "&J2&" г." -> 11 yanvar 2021 г. | L2: 5 | M2: 15000000 | N2: on besh million | O2: ="- №"&L2&" от "&K2&", заключенного с ООО «Clever Mikrokredit Tashkiloti» и "&E2&", по согласованной залоговой стоимость - "&FIXED(M2)&" ("&N2&") сум." -> - №5 от 11 yanvar 2021 г., заключенного с ООО «Clever Mikrokredit Tashkiloti» и TULYAGANOV XODJIAKBAR IRGASHEVICH, по согласованной залоговой стоимость - 15 000 000,00 (on besh million) сум. | P2: =IF(D2=$B$2,O2,IF(D2=$C$2,$B$1)) -> - №5 от 11 yanvar 2021 г., заключенного с ООО «Clever Mikrokredit Tashkiloti» и TULYAGANOV XODJIAKBAR IRGASHEVICH, по согласованной залоговой стоимость - 15 000 000,00 (on besh million) сум. | W2: =""&P2&" "&P3&" "&P4&" "&P5&" "&P6&" "&P7&" "&P8&" "&P9&" "&P10&" "&P11&" "&P12&" "&P13&" "&P14&" "&P15&" "&P16&" "&P17&" "&P18&" "&P19&" "&P20&" "&P21&"" -> - №5 от 11 yanvar 2021 г., заключенного с ООО «Clever Mikrokredit Tashkiloti» и TULYAGANOV XODJIAKBAR IRGASHEVICH, по согласованной залоговой стоимость - 15 000 000,00 (on besh million) сум. - №386 от 6 noyabr 2019 г., заключенного с ООО «Clever Mikrokredit Tashkiloti» и YUNUSOVA ZALOXAT MIRSULTANOVNA, по согласованной залоговой стоимость - 15 000 000,00 (on besh million) сум. - №33 от 21 yanvar 2021 г., заключенного с ООО «Clever Mikrokredit Tashkiloti» и YUNUSOVA ZALOXAT MIRSULTANOVNA, по согласованной залоговой стоимость - 15 000 000,00 (on besh million) сум. 0 0 0 0 0 0 0 0 0 0 0 0 0 0 0 0 0
A3: 2 | D3: ha | E3: YUNUSOVA ZALOXAT MIRSULTANOVNA | F3: 43775 | G3: =MONTH(F3) -> 11 | H3: =IF(G3=$A$26,$A$28,IF(G3=$B$26,$B$28,IF(G3=$C$26,$C$28,IF(G3=$D$26,$D$28,IF(G3=$E$26,$E$28,IF(G3=$F$26,$F$28,IF(G3=$K$26,$K$28,IF(G3=$L$26,$L$28,IF(G3=$M$26,$M$28,IF(G3=$N$26,$N$28,IF(G3=$O$26,$O$28,IF(G3=$P$26,$P$28,0)))))))))))) -> noyabr | I3: =DAY(F3) -> 6 | J3: =YEAR(F3) -> 2019 | K3: =""&I3&" "&H3&" "&J3&" г." -> 6 noyabr 2019 г. | L3: 386 | M3: 15000000 | N3: on besh million | O3: ="- №"&L3&" от "&K3&", заключенного с ООО «Clever Mikrokredit Tashkiloti» и "&E3&", по согласованной залоговой стоимость - "&FIXED(M3)&" ("&N3&") сум." -> - №386 от 6 noyabr 2019 г., заключенного с ООО «Clever Mikrokredit Tashkiloti» и YUNUSOVA ZALOXAT MIRSULTANOVNA, по согласованной залоговой стоимость - 15 000 000,00 (on besh million) сум. | P3: =IF(D3=$B$2,O3,IF(D3=$C$2,$B$1)) -> - №386 от 6 noyabr 2019 г., заключенного с ООО «Clever Mikrokredit Tashkiloti» и YUNUSOVA ZALOXAT MIRSULTANOVNA, по согласованной залоговой стоимость - 15 000 000,00 (on besh million) сум.
A4: 3 | D4: ha | E4: YUNUSOVA ZALOXAT MIRSULTANOVNA | F4: 44217 | G4: =MONTH(F4) -> 1 | H4: =IF(G4=$A$26,$A$28,IF(G4=$B$26,$B$28,IF(G4=$C$26,$C$28,IF(G4=$D$26,$D$28,IF(G4=$E$26,$E$28,IF(G4=$F$26,$F$28,IF(G4=$K$26,$K$28,IF(G4=$L$26,$L$28,IF(G4=$M$26,$M$28,IF(G4=$N$26,$N$28,IF(G4=$O$26,$O$28,IF(G4=$P$26,$P$28,0)))))))))))) -> yanvar | I4: =DAY(F4) -> 21 | J4: =YEAR(F4) -> 2021 | K4: =""&I4&" "&H4&" "&J4&" г." -> 21 yanvar 2021 г. | L4: 33 | M4: 15000000 | N4: on besh million | O4: ="- №"&L4&" от "&K4&", заключенного с ООО «Clever Mikrokredit Tashkiloti» и "&E4&", по согласованной залоговой стоимость - "&FIXED(M4)&" ("&N4&") сум." -> - №33 от 21 yanvar 2021 г., заключенного с ООО «Clever Mikrokredit Tashkiloti» и YUNUSOVA ZALOXAT MIRSULTANOVNA, по согласованной залоговой стоимость - 15 000 000,00 (on besh million) сум. | P4: =IF(D4=$B$2,O4,IF(D4=$C$2,$B$1)) -> - №33 от 21 yanvar 2021 г., заключенного с ООО «Clever Mikrokredit Tashkiloti» и YUNUSOVA ZALOXAT MIRSULTANOVNA, по согласованной залоговой стоимость - 15 000 000,00 (on besh million) сум.
A5: 4 | D5: ha | G5: =MONTH(F5) -> 1 | H5: =IF(G5=$A$26,$A$28,IF(G5=$B$26,$B$28,IF(G5=$C$26,$C$28,IF(G5=$D$26,$D$28,IF(G5=$E$26,$E$28,IF(G5=$F$26,$F$28,IF(G5=$K$26,$K$28,IF(G5=$L$26,$L$28,IF(G5=$M$26,$M$28,IF(G5=$N$26,$N$28,IF(G5=$O$26,$O$28,IF(G5=$P$26,$P$28,0)))))))))))) -> yanvar | I5: =DAY(F5) -> 0 | J5: =YEAR(F5) -> 1900 | K5: =""&I5&" "&H5&" "&J5&" г." -> 0 yanvar 1900 г. | P5: =IF(D5=$B$2,O5,IF(D5=$C$2,$B$1)) -> 0
A6: 5 | D6: ha | G6: =MONTH(F6) -> 1 | H6: =IF(G6=$A$26,$A$28,IF(G6=$B$26,$B$28,IF(G6=$C$26,$C$28,IF(G6=$D$26,$D$28,IF(G6=$E$26,$E$28,IF(G6=$F$26,$F$28,IF(G6=$K$26,$K$28,IF(G6=$L$26,$L$28,IF(G6=$M$26,$M$28,IF(G6=$N$26,$N$28,IF(G6=$O$26,$O$28,IF(G6=$P$26,$P$28,0)))))))))))) -> yanvar | I6: =DAY(F6) -> 0 | J6: =YEAR(F6) -> 1900 | K6: =""&I6&" "&H6&" "&J6&" г." -> 0 yanvar 1900 г. | P6: =IF(D6=$B$2,O6,IF(D6=$C$2,$B$1)) -> 0
A7: 6 | D7: ha | G7: =MONTH(F7) -> 1 | H7: =IF(G7=$A$26,$A$28,IF(G7=$B$26,$B$28,IF(G7=$C$26,$C$28,IF(G7=$D$26,$D$28,IF(G7=$E$26,$E$28,IF(G7=$F$26,$F$28,IF(G7=$K$26,$K$28,IF(G7=$L$26,$L$28,IF(G7=$M$26,$M$28,IF(G7=$N$26,$N$28,IF(G7=$O$26,$O$28,IF(G7=$P$26,$P$28,0)))))))))))) -> yanvar | I7: =DAY(F7) -> 0 | J7: =YEAR(F7) -> 1900 | K7: =""&I7&" "&H7&" "&J7&" г." -> 0 yanvar 1900 г. | P7: =IF(D7=$B$2,O7,IF(D7=$C$2,$B$1)) -> 0
A8: 7 | D8: ha | G8: =MONTH(F8) -> 1 | H8: =IF(G8=$A$26,$A$28,IF(G8=$B$26,$B$28,IF(G8=$C$26,$C$28,IF(G8=$D$26,$D$28,IF(G8=$E$26,$E$28,IF(G8=$F$26,$F$28,IF(G8=$K$26,$K$28,IF(G8=$L$26,$L$28,IF(G8=$M$26,$M$28,IF(G8=$N$26,$N$28,IF(G8=$O$26,$O$28,IF(G8=$P$26,$P$28,0)))))))))))) -> yanvar | I8: =DAY(F8) -> 0 | J8: =YEAR(F8) -> 1900 | K8: =""&I8&" "&H8&" "&J8&" г." -> 0 yanvar 1900 г. | P8: =IF(D8=$B$2,O8,IF(D8=$C$2,$B$1)) -> 0
A9: 8 | D9: ha | G9: =MONTH(F9) -> 1 | H9: =IF(G9=$A$26,$A$28,IF(G9=$B$26,$B$28,IF(G9=$C$26,$C$28,IF(G9=$D$26,$D$28,IF(G9=$E$26,$E$28,IF(G9=$F$26,$F$28,IF(G9=$K$26,$K$28,IF(G9=$L$26,$L$28,IF(G9=$M$26,$M$28,IF(G9=$N$26,$N$28,IF(G9=$O$26,$O$28,IF(G9=$P$26,$P$28,0)))))))))))) -> yanvar | I9: =DAY(F9) -> 0 | J9: =YEAR(F9) -> 1900 | K9: =""&I9&" "&H9&" "&J9&" г." -> 0 yanvar 1900 г. | P9: =IF(D9=$B$2,O9,IF(D9=$C$2,$B$1)) -> 0
A10: 9 | D10: ha | G10: =MONTH(F10) -> 1 | H10: =IF(G10=$A$26,$A$28,IF(G10=$B$26,$B$28,IF(G10=$C$26,$C$28,IF(G10=$D$26,$D$28,IF(G10=$E$26,$E$28,IF(G10=$F$26,$F$28,IF(G10=$K$26,$K$28,IF(G10=$L$26,$L$28,IF(G10=$M$26,$M$28,IF(G10=$N$26,$N$28,IF(G10=$O$26,$O$28,IF(G10=$P$26,$P$28,0)))))))))))) -> yanvar | I10: =DAY(F10) -> 0 | J10: =YEAR(F10) -> 1900 | K10: =""&I10&" "&H10&" "&J10&" г." -> 0 yanvar 1900 г. | P10: =IF(D10=$B$2,O10,IF(D10=$C$2,$B$1)) -> 0
A11: 10 | D11: ha | G11: =MONTH(F11) -> 1 | H11: =IF(G11=$A$26,$A$28,IF(G11=$B$26,$B$28,IF(G11=$C$26,$C$28,IF(G11=$D$26,$D$28,IF(G11=$E$26,$E$28,IF(G11=$F$26,$F$28,IF(G11=$K$26,$K$28,IF(G11=$L$26,$L$28,IF(G11=$M$26,$M$28,IF(G11=$N$26,$N$28,IF(G11=$O$26,$O$28,IF(G11=$P$26,$P$28,0)))))))))))) -> yanvar | I11: =DAY(F11) -> 0 | J11: =YEAR(F11) -> 1900 | K11: =""&I11&" "&H11&" "&J11&" г." -> 0 yanvar 1900 г. | P11: =IF(D11=$B$2,O11,IF(D11=$C$2,$B$1)) -> 0
A12: 11 | D12: ha | G12: =MONTH(F12) -> 1 | H12: =IF(G12=$A$26,$A$28,IF(G12=$B$26,$B$28,IF(G12=$C$26,$C$28,IF(G12=$D$26,$D$28,IF(G12=$E$26,$E$28,IF(G12=$F$26,$F$28,IF(G12=$K$26,$K$28,IF(G12=$L$26,$L$28,IF(G12=$M$26,$M$28,IF(G12=$N$26,$N$28,IF(G12=$O$26,$O$28,IF(G12=$P$26,$P$28,0)))))))))))) -> yanvar | I12: =DAY(F12) -> 0 | J12: =YEAR(F12) -> 1900 | K12: =""&I12&" "&H12&" "&J12&" г." -> 0 yanvar 1900 г. | P12: =IF(D12=$B$2,O12,IF(D12=$C$2,$B$1)) -> 0
A13: 12 | D13: ha | G13: =MONTH(F13) -> 1 | H13: =IF(G13=$A$26,$A$28,IF(G13=$B$26,$B$28,IF(G13=$C$26,$C$28,IF(G13=$D$26,$D$28,IF(G13=$E$26,$E$28,IF(G13=$F$26,$F$28,IF(G13=$K$26,$K$28,IF(G13=$L$26,$L$28,IF(G13=$M$26,$M$28,IF(G13=$N$26,$N$28,IF(G13=$O$26,$O$28,IF(G13=$P$26,$P$28,0)))))))))))) -> yanvar | I13: =DAY(F13) -> 0 | J13: =YEAR(F13) -> 1900 | K13: =""&I13&" "&H13&" "&J13&" г." -> 0 yanvar 1900 г. | P13: =IF(D13=$B$2,O13,IF(D13=$C$2,$B$1)) -> 0
A14: 13 | D14: ha | G14: =MONTH(F14) -> 1 | H14: =IF(G14=$A$26,$A$28,IF(G14=$B$26,$B$28,IF(G14=$C$26,$C$28,IF(G14=$D$26,$D$28,IF(G14=$E$26,$E$28,IF(G14=$F$26,$F$28,IF(G14=$K$26,$K$28,IF(G14=$L$26,$L$28,IF(G14=$M$26,$M$28,IF(G14=$N$26,$N$28,IF(G14=$O$26,$O$28,IF(G14=$P$26,$P$28,0)))))))))))) -> yanvar | I14: =DAY(F14) -> 0 | J14: =YEAR(F14) -> 1900 | K14: =""&I14&" "&H14&" "&J14&" г." -> 0 yanvar 1900 г. | P14: =IF(D14=$B$2,O14,IF(D14=$C$2,$B$1)) -> 0
A15: 14 | D15: ha | G15: =MONTH(F15) -> 1 | H15: =IF(G15=$A$26,$A$28,IF(G15=$B$26,$B$28,IF(G15=$C$26,$C$28,IF(G15=$D$26,$D$28,IF(G15=$E$26,$E$28,IF(G15=$F$26,$F$28,IF(G15=$K$26,$K$28,IF(G15=$L$26,$L$28,IF(G15=$M$26,$M$28,IF(G15=$N$26,$N$28,IF(G15=$O$26,$O$28,IF(G15=$P$26,$P$28,0)))))))))))) -> yanvar | I15: =DAY(F15) -> 0 | J15: =YEAR(F15) -> 1900 | K15: =""&I15&" "&H15&" "&J15&" г." -> 0 yanvar 1900 г. | P15: =IF(D15=$B$2,O15,IF(D15=$C$2,$B$1)) -> 0
A16: 15 | D16: ha | G16: =MONTH(F16) -> 1 | H16: =IF(G16=$A$26,$A$28,IF(G16=$B$26,$B$28,IF(G16=$C$26,$C$28,IF(G16=$D$26,$D$28,IF(G16=$E$26,$E$28,IF(G16=$F$26,$F$28,IF(G16=$K$26,$K$28,IF(G16=$L$26,$L$28,IF(G16=$M$26,$M$28,IF(G16=$N$26,$N$28,IF(G16=$O$26,$O$28,IF(G16=$P$26,$P$28,0)))))))))))) -> yanvar | I16: =DAY(F16) -> 0 | J16: =YEAR(F16) -> 1900 | K16: =""&I16&" "&H16&" "&J16&" г." -> 0 yanvar 1900 г. | P16: =IF(D16=$B$2,O16,IF(D16=$C$2,$B$1)) -> 0
... A21: 20 | D21: ha | G21: =MONTH(F21) -> 1 | H21: =IF(G21=$A$26,$A$28,IF(G21=$B$26,$B$28,IF(G21=$C$26,$C$28,IF(G21=$D$26,$D$28,IF(G21=$E$26,$E$28,IF(G21=$F$26,$F$28,IF(G21=$K$26,$K$28,IF(G21=$L$26,$L$28,IF(G21=$M$26,$M$28,IF(G21=$N$26,$N$28,IF(G21=$O$26,$O$28,IF(G21=$P$26,$P$28,0)))))))))))) -> yanvar | I21: =DAY(F21) -> 0 | J21: =YEAR(F21) -> 1900 | K21: =""&I21&" "&H21&" "&J21&" г." -> 0 yanvar 1900 г. | P21: =IF(D21=$B$2,O21,IF(D21=$C$2,$B$1)) -> 0
M22: =SUM(M2:M21)+malumot!B142 -> 123000000 | Q22: ottiz yetti million besh yuz ming
A25: =MONTH(F2) -> 1 | B25: =IF(A25=A26,A28,IF(A25=B26,B28,IF(A25=C26,C28,IF(A25=D26,D28,IF(A25=E26,E28,IF(A25=F26,F28,IF(A25=K26,K28,IF(A25=L26,L28,IF(A25=M26,M28,IF(A25=N26,N28,IF(A25=O26,O28,IF(A25=#REF!,#REF!,)))))))))))) -> yanvar | C25: =DAY(F2) -> 11 | D25: =YEAR(F2) -> 2021
A26: 1 | B26: 2 | C26: 3 | D26: 4 | E26: 5 | F26: 6 | K26: 7 | L26: 8 | M26: 9 | N26: 10 | O26: 11 | P26: 12
A28: yanvar | B28: fevral | C28: mart | D28: aprel | E28: may | F28: iyun | K28: июля | L28: avgust | M28: sentyabr | N28: oktyabr | O28: noyabr | P28: dekabr
A29: yanvar | B29: fevral | C29: mart | D29: aprel | E29: may | F29: iyun | K29: июль | L29: avgust | M29: sentyabr | N29: oktyabr | O29: noyabr | P29: dekabr

Sheet График аннуитет.
E1: Приложение №1
F2: ="к договору микрозайма "&malumot!B74&"" -> к договору микрозайма 24 mart 2025 y.dan №659-SR
A4: График погашения
A6: № | B6: Дата погашения | C6: Остаток основного долга | D6: Сумма погашения, сум
D7: основного долга | E7: процентов* | F7: всего*
A8: 1 | B8: ='График дифференц'!B8 -> 45748 | C8: =malumot!B75 -> 52000000 | D8: =IF(A8<malumot!$B$81,'График аннуитет.'!F8-'График аннуитет.'!E8,'График аннуитет.'!C8) -> 3343987.7 | E8: =ROUND(C8*malumot!$B$84/H8,2)*'График аннуитет.'!G8 -> 683835.6 | F8: =malumot!B90 -> 4027823.3 | G8: =B8-malumot!B67 -> 8 | H8: =DATE(YEAR(B8),12,31)-DATE(YEAR(B8),1,1)+1 -> 365
A9: 2 | B9: ='График дифференц'!B9 -> 45778 | C9: =C8-D8 -> 48656012 | D9: =IF(A9<malumot!$B$81,'График аннуитет.'!F9-'График аннуитет.'!E9,'График аннуитет.'!C9) -> 1628348.6 | E9: =ROUND(C9*malumot!$B$84/H9,2)*'График аннуитет.'!G9 -> 2399474.7 | F9: =IF(A9<malumot!$B$81,'График аннуитет.'!F8,'График аннуитет.'!D9+'График аннуитет.'!E9) -> 4027823.3 | G9: =B9-B8 -> 30 | H9: =DATE(YEAR(B9),12,31)-DATE(YEAR(B9),1,1)+1 -> 365
A10: 3 | B10: ='График дифференц'!B10 -> 45810 | C10: =C9-D9 -> 47027664 | D10: =IF(A10<malumot!$B$81,'График аннуитет.'!F10-'График аннуитет.'!E10,'График аннуитет.'!C10) -> 1554039.3 | E10: =ROUND(C10*malumot!$B$84/H10,2)*'График аннуитет.'!G10 -> 2473784 | F10: =IF(A10<malumot!$B$81,'График аннуитет.'!F9,'График аннуитет.'!D10+'График аннуитет.'!E10) -> 4027823.3 | G10: =B10-B9 -> 32 | H10: =DATE(YEAR(B10),12,31)-DATE(YEAR(B10),1,1)+1 -> 365
A11: 4 | B11: ='График дифференц'!B11 -> 45839 | C11: =C10-D10 -> 45473624 | D11: =IF(A11<malumot!$B$81,'График аннуитет.'!F11-'График аннуитет.'!E11,'График аннуитет.'!C11) -> 1860039.7 | E11: =ROUND(C11*malumot!$B$84/H11,2)*'График аннуитет.'!G11 -> 2167783.6 | F11: =IF(A11<malumot!$B$81,'График аннуитет.'!F10,'График аннуитет.'!D11+'График аннуитет.'!E11) -> 4027823.3 | G11: =B11-B10 -> 29 | H11: =DATE(YEAR(B11),12,31)-DATE(YEAR(B11),1,1)+1 -> 365
A12: 5 | B12: ='График дифференц'!B12 -> 45870 | C12: =C11-D11 -> 43613585 | D12: =IF(A12<malumot!$B$81,'График аннуитет.'!F12-'График аннуитет.'!E12,'График аннуитет.'!C12) -> 1805323 | E12: =ROUND(C12*malumot!$B$84/H12,2)*'График аннуитет.'!G12 -> 2222500.4 | F12: =IF(A12<malumot!$B$81,'График аннуитет.'!F11,'График аннуитет.'!D12+'График аннуитет.'!E12) -> 4027823.3 | G12: =B12-B11 -> 31 | H12: =DATE(YEAR(B12),12,31)-DATE(YEAR(B12),1,1)+1 -> 365
A13: 6 | B13: ='График дифференц'!B13 -> 45901 | C13: =C12-D12 -> 41808262 | D13: =IF(A13<malumot!$B$81,'График аннуитет.'!F13-'График аннуитет.'!E13,'График аннуитет.'!C13) -> 1897320.1 | E13: =ROUND(C13*malumot!$B$84/H13,2)*'График аннуитет.'!G13 -> 2130503.2 | F13: =IF(A13<malumot!$B$81,'График аннуитет.'!F12,'График аннуитет.'!D13+'График аннуитет.'!E13) -> 4027823.3 | G13: =B13-B12 -> 31 | H13: =DATE(YEAR(B13),12,31)-DATE(YEAR(B13),1,1)+1 -> 365
A14: 7 | B14: ='График дифференц'!B14 -> 45931 | C14: =C13-D13 -> 39910942 | D14: =IF(A14<malumot!$B$81,'График аннуитет.'!F14-'График аннуитет.'!E14,'График аннуитет.'!C14) -> 2059612.4 | E14: =ROUND(C14*malumot!$B$84/H14,2)*'График аннуитет.'!G14 -> 1968210.9 | F14: =IF(A14<malumot!$B$81,'График аннуитет.'!F13,'График аннуитет.'!D14+'График аннуитет.'!E14) -> 4027823.3 | G14: =B14-B13 -> 30 | H14: =DATE(YEAR(B14),12,31)-DATE(YEAR(B14),1,1)+1 -> 365
A15: 8 | B15: ='График дифференц'!B15 -> 45964 | C15: =C14-D14 -> 37851329 | D15: =IF(A15<malumot!$B$81,'График аннуитет.'!F15-'График аннуитет.'!E15,'График аннуитет.'!C15) -> 1974518.4 | E15: =ROUND(C15*malumot!$B$84/H15,2)*'График аннуитет.'!G15 -> 2053304.9 | F15: =IF(A15<malumot!$B$81,'График аннуитет.'!F14,'График аннуитет.'!D15+'График аннуитет.'!E15) -> 4027823.3 | G15: =B15-B14 -> 33 | H15: =DATE(YEAR(B15),12,31)-DATE(YEAR(B15),1,1)+1 -> 365
A16: 9 | B16: ='График дифференц'!B16 -> 45992 | C16: =C15-D15 -> 35876811 | D16: =IF(A16<malumot!$B$81,'График аннуитет.'!F16-'График аннуитет.'!E16,'График аннуитет.'!C16) -> 2376507.1 | E16: =ROUND(C16*malumot!$B$84/H16,2)*'График аннуитет.'!G16 -> 1651316.2 | F16: =IF(A16<malumot!$B$81,'График аннуитет.'!F15,'График аннуитет.'!D16+'График аннуитет.'!E16) -> 4027823.3 | G16: =B16-B15 -> 28 | H16: =DATE(YEAR(B16),12,31)-DATE(YEAR(B16),1,1)+1 -> 365
A17: 10 | B17: ='График дифференц'!B17 -> 46023 | C17: =C16-D16 -> 33500304 | D17: =IF(A17<malumot!$B$81,'График аннуитет.'!F17-'График аннуитет.'!E17,'График аннуитет.'!C17) -> 2320684.6 | E17: =ROUND(C17*malumot!$B$84/H17,2)*'График аннуитет.'!G17 -> 1707138.7 | F17: =IF(A17<malumot!$B$81,'График аннуитет.'!F16,'График аннуитет.'!D17+'График аннуитет.'!E17) -> 4027823.3 | G17: =B17-B16 -> 31 | H17: =DATE(YEAR(B17),12,31)-DATE(YEAR(B17),1,1)+1 -> 365
A18: 11 | B18: ='График дифференц'!B18 -> 46055 | C18: =C17-D17 -> 31179619 | D18: =IF(A18<malumot!$B$81,'График аннуитет.'!F18-'График аннуитет.'!E18,'График аннуитет.'!C18) -> 2387689.9 | E18: =ROUND(C18*malumot!$B$84/H18,2)*'График аннуитет.'!G18 -> 1640133.4 | F18: =IF(A18<malumot!$B$81,'График аннуитет.'!F17,'График аннуитет.'!D18+'График аннуитет.'!E18) -> 4027823.3 | G18: =B18-B17 -> 32 | H18: =DATE(YEAR(B18),12,31)-DATE(YEAR(B18),1,1)+1 -> 365
A19: 12 | B19: ='График дифференц'!B19 -> 46083 | C19: =C18-D18 -> 28791929 | D19: =IF(A19<malumot!$B$81,'График аннуитет.'!F19-'График аннуитет.'!E19,'График аннуитет.'!C19) -> 2702605.7 | E19: =ROUND(C19*malumot!$B$84/H19,2)*'График аннуитет.'!G19 -> 1325217.6 | F19: =IF(A19<malumot!$B$81,'График аннуитет.'!F18,'График аннуитет.'!D19+'График аннуитет.'!E19) -> 4027823.3 | G19: =B19-B18 -> 28 | H19: =DATE(YEAR(B19),12,31)-DATE(YEAR(B19),1,1)+1 -> 365
A20: 13 | B20: ='График дифференц'!B20 -> 46113 | C20: =C19-D19 -> 26089323 | D20: =IF(A20<malumot!$B$81,'График аннуитет.'!F20-'График аннуитет.'!E20,'График аннуитет.'!C20) -> 2741226.5 | E20: =ROUND(C20*malumot!$B$84/H20,2)*'График аннуитет.'!G20 -> 1286596.8 | F20: =IF(A20<malumot!$B$81,'График аннуитет.'!F19,'График аннуитет.'!D20+'График аннуитет.'!E20) -> 4027823.3 | G20: =B20-B19 -> 30 | H20: =DATE(YEAR(B20),12,31)-DATE(YEAR(B20),1,1)+1 -> 365
... A31: 24 | B31: ='График дифференц'!B31 -> 46447 | C31: =C30-D30 -> -12600524 | D31: =IF(A31<malumot!$B$81,'График аннуитет.'!F31-'График аннуитет.'!E31,'График аннуитет.'!C31) -> 4607792.6 | E31: =ROUND(C31*malumot!$B$84/H31,2)*'График аннуитет.'!G31 -> -579969.32 | F31: =IF(A31<malumot!$B$81,'График аннуитет.'!F30,'График аннуитет.'!D31+'График аннуитет.'!E31) -> 4027823.3 | G31: =B31-B30 -> 28 | H31: =DATE(YEAR(B31),12,31)-DATE(YEAR(B31),1,1)+1 -> 365
A32: =1+A31 -> 25 | B32: ='График дифференц'!B32 -> 46478 | C32: =C31-D31 -> -17208316 | D32: =IF(A32<malumot!$B$81,'График аннуитет.'!F32-'График аннуитет.'!E32,'График аннуитет.'!C32) -> 4904740.2 | E32: =ROUND(C32*malumot!$B$84/H32,2)*'График аннуитет.'!G32 -> -876916.84 | F32: =IF(A32<malumot!$B$81,'График аннуитет.'!F31,'График аннуитет.'!D32+'График аннуитет.'!E32) -> 4027823.3 | G32: =B32-B31 -> 31 | H32: =DATE(YEAR(B32),12,31)-DATE(YEAR(B32),1,1)+1 -> 365
A33: =1+A32 -> 26 | B33: ='График дифференц'!B33 -> 46510 | C33: =C32-D32 -> -22113057 | D33: =IF(A33<malumot!$B$81,'График аннуитет.'!F33-'График аннуитет.'!E33,'График аннуитет.'!C33) -> 5191030.7 | E33: =ROUND(C33*malumot!$B$84/H33,2)*'График аннуитет.'!G33 -> -1163207.4 | F33: =IF(A33<malumot!$B$81,'График аннуитет.'!F32,'График аннуитет.'!D33+'График аннуитет.'!E33) -> 4027823.3 | G33: =B33-B32 -> 32 | H33: =DATE(YEAR(B33),12,31)-DATE(YEAR(B33),1,1)+1 -> 365
A34: =1+A33 -> 27 | B34: ='График дифференц'!B34 -> 46539 | C34: =C33-D33 -> -27304087 | D34: =IF(A34<malumot!$B$81,'График аннуитет.'!F34-'График аннуитет.'!E34,'График аннуитет.'!C34) -> 5329442.8 | E34: =ROUND(C34*malumot!$B$84/H34,2)*'График аннуитет.'!G34 -> -1301619.5 | F34: =IF(A34<malumot!$B$81,'График аннуитет.'!F33,'График аннуитет.'!D34+'График аннуитет.'!E34) -> 4027823.3 | G34: =B34-B33 -> 29 | H34: =DATE(YEAR(B34),12,31)-DATE(YEAR(B34),1,1)+1 -> 365
A35: =1+A34 -> 28 | B35: ='График дифференц'!B35 -> 46569 | C35: =C34-D34 -> -32633530 | D35: =IF(A35<malumot!$B$81,'График аннуитет.'!F35-'График аннуитет.'!E35,'График аннуитет.'!C35) -> 5637148.1 | E35: =ROUND(C35*malumot!$B$84/H35,2)*'График аннуитет.'!G35 -> -1609324.8 | F35: =IF(A35<malumot!$B$81,'График аннуитет.'!F34,'График аннуитет.'!D35+'График аннуитет.'!E35) -> 4027823.3 | G35: =B35-B34 -> 30 | H35: =DATE(YEAR(B35),12,31)-DATE(YEAR(B35),1,1)+1 -> 365
A36: =1+A35 -> 29 | B36: ='График дифференц'!B36 -> 46601 | C36: =C35-D35 -> -38270678 | D36: =IF(A36<malumot!$B$81,'График аннуитет.'!F36-'График аннуитет.'!E36,'График аннуитет.'!C36) -> 6040965.7 | E36: =ROUND(C36*malumot!$B$84/H36,2)*'График аннуитет.'!G36 -> -2013142.4 | F36: =IF(A36<malumot!$B$81,'График аннуитет.'!F35,'График аннуитет.'!D36+'График аннуитет.'!E36) -> 4027823.3 | G36: =B36-B35 -> 32 | H36: =DATE(YEAR(B36),12,31)-DATE(YEAR(B36),1,1)+1 -> 365
A37: =1+A36 -> 30 | B37: ='График дифференц'!B37 -> 46631 | C37: =C36-D36 -> -44311644 | D37: =IF(A37<malumot!$B$81,'График аннуитет.'!F37-'График аннуитет.'!E37,'График аннуитет.'!C37) -> 6213055.1 | E37: =ROUND(C37*malumot!$B$84/H37,2)*'График аннуитет.'!G37 -> -2185231.8 | F37: =IF(A37<malumot!$B$81,'График аннуитет.'!F36,'График аннуитет.'!D37+'График аннуитет.'!E37) -> 4027823.3 | G37: =B37-B36 -> 30 | H37: =DATE(YEAR(B37),12,31)-DATE(YEAR(B37),1,1)+1 -> 365
A38: =1+A37 -> 31 | B38: ='График дифференц'!B38 -> 46661 | C38: =C37-D37 -> -50524699 | D38: =IF(A38<malumot!$B$81,'График аннуитет.'!F38-'График аннуитет.'!E38,'График аннуитет.'!C38) -> 6519452.3 | E38: =ROUND(C38*malumot!$B$84/H38,2)*'График аннуитет.'!G38 -> -2491629 | F38: =IF(A38<malumot!$B$81,'График аннуитет.'!F37,'График аннуитет.'!D38+'График аннуитет.'!E38) -> 4027823.3 | G38: =B38-B37 -> 30 | H38: =DATE(YEAR(B38),12,31)-DATE(YEAR(B38),1,1)+1 -> 365
A39: =1+A38 -> 32 | B39: ='График дифференц'!B39 -> 46692 | C39: =C38-D38 -> -57044151 | D39: =IF(A39<malumot!$B$81,'График аннуитет.'!F39-'График аннуитет.'!E39,'График аннуитет.'!C39) -> 6934730.8 | E39: =ROUND(C39*malumot!$B$84/H39,2)*'График аннуитет.'!G39 -> -2906907.5 | F39: =IF(A39<malumot!$B$81,'График аннуитет.'!F38,'График аннуитет.'!D39+'График аннуитет.'!E39) -> 4027823.3 | G39: =B39-B38 -> 31 | H39: =DATE(YEAR(B39),12,31)-DATE(YEAR(B39),1,1)+1 -> 365
A40: =1+A39 -> 33 | B40: ='График дифференц'!B40 -> 46722 | C40: =C39-D39 -> -63978882 | D40: =IF(A40<malumot!$B$81,'График аннуитет.'!F40-'График аннуитет.'!E40,'График аннуитет.'!C40) -> 7182946.4 | E40: =ROUND(C40*malumot!$B$84/H40,2)*'График аннуитет.'!G40 -> -3155123.1 | F40: =IF(A40<malumot!$B$81,'График аннуитет.'!F39,'График аннуитет.'!D40+'График аннуитет.'!E40) -> 4027823.3 | G40: =B40-B39 -> 30 | H40: =DATE(YEAR(B40),12,31)-DATE(YEAR(B40),1,1)+1 -> 365
A41: =1+A40 -> 34 | B41: ='График дифференц'!B41 -> 46755 | C41: =C40-D40 -> -71161829 | D41: =IF(A41<malumot!$B$81,'График аннуитет.'!F41-'График аннуитет.'!E41,'График аннуитет.'!C41) -> 7877561.7 | E41: =ROUND(C41*malumot!$B$84/H41,2)*'График аннуитет.'!G41 -> -3849738.4 | F41: =IF(A41<malumot!$B$81,'График аннуитет.'!F40,'График аннуитет.'!D41+'График аннуитет.'!E41) -> 4027823.3 | G41: =B41-B40 -> 33 | H41: =DATE(YEAR(B41),12,31)-DATE(YEAR(B41),1,1)+1 -> 366
A42: =1+A41 -> 35 | B42: ='График дифференц'!B42 -> 46784 | C42: =C41-D41 -> -79039390 | D42: =IF(A42<malumot!$B$81,'График аннуитет.'!F42-'График аннуитет.'!E42,'График аннуитет.'!C42) -> 7785433.7 | E42: =ROUND(C42*malumot!$B$84/H42,2)*'График аннуитет.'!G42 -> -3757610.3 | F42: =IF(A42<malumot!$B$81,'График аннуитет.'!F41,'График аннуитет.'!D42+'График аннуитет.'!E42) -> 4027823.3 | G42: =B42-B41 -> 29 | H42: =DATE(YEAR(B42),12,31)-DATE(YEAR(B42),1,1)+1 -> 366
A43: =1+A42 -> 36 | B43: ='График дифференц'!B43 -> 46836 | C43: =C42-D42 -> -86824824 | D43: =IF(A43<malumot!$B$81,'График аннуитет.'!F43-'График аннуитет.'!E43,'График аннуитет.'!C43) -> -86824824 | E43: =ROUND(C43*malumot!$B$84/H43,2)*'График аннуитет.'!G43 -> -7401460.6 | F43: =IF(A43<malumot!$B$81,'График аннуитет.'!F42,'График аннуитет.'!D43+'График аннуитет.'!E43) -> -94226285 | G43: =B43-B42 -> 52 | H43: =DATE(YEAR(B43),12,31)-DATE(YEAR(B43),1,1)+1 -> 366
B44: ИТОГО | D44: =SUM(D8:D43) -> 52000000 | E44: =SUM(E8:E43) -> -5252468.4 | F44: =SUM(F8:F43) -> 46747532
A46: *В случае осуществления погашения платежей по кредиту в даты, отличные от указанных в графике погашения, сумма платежа меняется на сумму процентов, которые начисляются на сумму остатка долга по микрозайму в соответствии с п.п. 2.2. настоящего договора.
A48: =#REF! -> #REF! | D48: =#REF! -> #REF!
A50: =#REF! -> #REF! | D50: =#REF! -> #REF!
A51: =#REF! -> #REF! | D51: =#REF! -> #REF!
A52: =#REF! -> #REF! | D52: ="паспорт серии "&malumot!B16&", "&malumot!B20&"" -> паспорт серии AC 1659096, SURXONDARYO VILOYATI JARQO'RG'ON TUMANI IIB tomonidan 21.02.2019 yilda berilgan
A53: =#REF! -> #REF!
A54: =#REF! -> #REF! | D54: =#REF! -> #REF!
A55: =#REF! -> #REF! | D55: =#REF! -> #REF!
A56: =#REF! -> #REF! | D56: =#REF! -> #REF!
A58: =#REF! -> #REF! | D58: =#REF! -> #REF!
A60: =#REF! -> #REF! | D60: =#REF! -> #REF!

Sheet xulosa
A1: =""&malumot!B153&" mikromoliya tashkilotining Xulosasi" -> «CLEVER MIKROMOLIYA TASHKILOTI» MChJ mikromoliya tashkilotining Xulosasi
A3: MIJOZ HAQIDA MA'LUMOTLAR
A4: ="Mijozning to'liq ismi sharifi: "&malumot!B5&"" -> Mijozning to'liq ismi sharifi: SHAYMARDANOVA SABOXAT YULDASHEVNA
A5: ="Tug'ilgan sanasi: "&malumot!B15&"" -> Tug'ilgan sanasi: 09.11.1976 yil
A6: ="Pasport seriyasi "&malumot!B16&" "&malumot!B20&", amal qilish muddati - "&malumot!B21&"" -> Pasport seriyasi AC 1659096 SURXONDARYO VILOYATI JARQO'RG'ON TUMANI IIB tomonidan 21.02.2019 yilda berilgan, amal qilish muddati - 20.02.2029 y.
A7: ="Ro‘yxatdan o‘tgan manzili: "&malumot!B28&", mo'ljal: "&malumot!B26&"" -> Ro‘yxatdan o‘tgan manzili: SURXONDARYO VILOYATI JARQO'RG'ON TUMANI QORAYONTOQ MFY IBN SINO KO'CHASI 114-UY, mo'ljal: QORAYONTOQ BEKAT
A8: ="Ish joyi: "&malumot!B52&" lavozimi "&malumot!B49&"da "&malumot!B44&"" -> Ish joyi: lavozimi Yakka tartibdagi tadbirkorda Yakka tartibdagi tadbirkor
A10: ="Mijoz tomonidan so’ralgan "&malumot!B65&" shartlari:" -> Mijoz tomonidan so’ralgan mikroqarz shartlari:
A11: ='Кредитная заявка'!A13:D13 -> Mikroqarz summasi: 52 000 000,00 (ellik ikki million so'm) so'm.
A12: ='Кредитная заявка'!A14:D14 -> Mikroqarz muddati: 36 (o'ttiz olti) oy.
A13: ='Кредитная заявка'!A15:D15 -> Mikroqarzdan foydalanganlik uchun foiz stavkasi: yillik 60% (Oltmish) foiz
A14: ='Кредитная заявка'!A16:D16 -> Mikroqarz bo'yicha asosiy qarz va foizlarni to'lash:
A15: ='Кредитная заявка'!A19:D19 -> - mikroqarz shartnomasi bo'yicha har oy differensial to'lovlari amalga oshiriladi
A16: ='Кредитная заявка'!A20:D20 -> Oxirgi yakuniy to'lov mikroqarz shartnomasi tuzilgan kundan boshlab oxirgi oyning oxirgi kunida amalga oshiriladi
A17: ='Кредитная заявка'!A21:D21 -> Mikroqarz ta’minoti::
A18: ='Кредитная заявка'!A22:D22 -> Egalik huquqi XUDOYKULOV ALMURAT KURBONAZAROVICHga tegishli bo'lgan garovga olingan avtomobil markasi LADA VESTA, rangi - SARIQ JELTO- ORANJEVIY, ishlab chiqarilgan yili - 2019, davlat raqam belgisi 75M497WA, kuzov turi - YENGIL SEDAN, kuzov raqami XTAGFL110KY258232, dvigatel raqami 3977458, shassi raqami - RAKAMSIZ
A19: Mijozning moliyaviy holati
A20: ="Anketaga muvofiq "&malumot!B9&"ning o‘rtacha oylik daromadi "&FIXED(malumot!B60)&" so‘mni tashkil etdi." -> Anketaga muvofiq SHAYMARDANOVA S.Y.ning o‘rtacha oylik daromadi 14 000 000,00 so‘mni tashkil etdi.
A21: ="Mijozning o'rtacha oylik xarajatlari "&FIXED(mijoz_anketasi!F27)&" so'mni tashkil etdi" -> Mijozning o'rtacha oylik xarajatlari 1 650 000,00 so'mni tashkil etdi
A22: =IF(malumot!B77=malumot!C77,xulosa!A23:E23,xulosa!A24:E24) -> Mikroqarz shartnomasi bo'yicha birinchi oy uchun to'lov 4 027 823,32 so'mni tashkil etadi.
A23: =""&malumot!C64&" shartnomasi bo'yicha birinchi oy uchun to'lov "&FIXED(malumot!B90)&" so'mni tashkil etadi." -> Mikroqarz shartnomasi bo'yicha birinchi oy uchun to'lov 4 027 823,32 so'mni tashkil etadi.
A24: =""&malumot!C64&" bo‘yicha oylik "&malumot!B77&" to‘lovi miqdori "&FIXED(malumot!B90)&" so‘mni tashkil etadi." -> Mikroqarz bo‘yicha oylik differensial to‘lovi miqdori 4 027 823,32 so‘mni tashkil etadi.
A25: Mijoz quyidagi majburiyatlarga ega : TOSHKЕNT Sh., "KAPITALBANK" AT BANKINING YAGONA FILIALI 174 661 821.46 so`m. Ayni paytda muddati o'tgan qarzdorligi mavjud emas. O‘rtacha oylik to‘lov 6 725 664.14 so‘mni tashkil qiladi.
A26: =""&malumot!C64&" bo’yicha ta’minot:" -> Mikroqarz bo’yicha ta’minot:
A27: =" - "&malumot!B123&" ga mulk huquqi asosida tegishli avtotransport vositasi "&malumot!B131&" , quyidagi tafsilotlarga muvofiq:" -> - XUDOYKULOV ALMURAT KURBONAZAROVICH ga mulk huquqi asosida tegishli avtotransport vositasi LADA VESTA , quyidagi tafsilotlarga muvofiq:
A28: =" - "&malumot!C123&" ga mulk huquqi asosida tegishli ko'chmas mulk shaklida "&malumot!C132&", manzili: "&malumot!C129&", quyidagi tafsilotlarga muvofiq:" -> - 0 ga mulk huquqi asosida tegishli ko'chmas mulk shaklida 3 - xonali yakka tartibdagi uy-joy, manzili: SAMARQAND VILOYATI TAYLOQ TUMANI CHAROG'BON MFY YANGI TAYLOQ QISHLOG'I 6 TURAR JOY 12 QAVAT 58 XONADON, quyidagi tafsilotlarga muvofiq:
A29: =IF(malumot!B109="Avtotransport",xulosa!A27:E27,xulosa!A28:E28) -> - XUDOYKULOV ALMURAT KURBONAZAROVICH ga mulk huquqi asosida tegishli avtotransport vositasi LADA VESTA , quyidagi tafsilotlarga muvofiq:
A30: =dalolatnoma!A29 -> Nomi | B30: =dalolatnoma!B29 -> Kuzov turi va kuzov raqami* | C30: =dalolatnoma!C29 -> Dvigatel va shassi raqami* | D30: =dalolatnoma!D29 -> Ishlab chiqarilgan yili va rangi* | E30: =dalolatnoma!E29 -> Kelishilgan garov qiymati, so'm
A31: =dalolatnoma!A30 -> LADA VESTA | B31: =dalolatnoma!B30 -> kuzov turi - YENGIL SEDAN, kuzov raqami XTAGFL110KY258232 | C31: =dalolatnoma!C30 -> dvigatel raqami 3977458, shassi raqami - RAKAMSIZ | D31: =dalolatnoma!D30 -> rangi - SARIQ JELTO- ORANJEVIY, ishlab chiqarilgan yili - 2019 | E31: =dalolatnoma!E30 -> 78 000 000,00 (yetmish sakkiz million so'm)
A32: =dalolatnoma!A22 -> -* avtotransport egasi: XUDOYKULOV ALMURAT KURBONAZAROVICH
A33: =dalolatnoma!A23 -> -* texnik pasport: AAG 3367573 24.01.2024 y.
A34: =dalolatnoma!A24 -> -* roʻyxatdan oʻtgan manzili/garaj manzili: SURXONDARYO VILOYATI JARQO'RG'ON TUMANI OQQURG'ON QFY QORAYONTOQ MFY IBN SINO KO'CHASI 114-UY
A35: =dalolatnoma!A25 -> -* davlat raqami: 75M497WA
A37: =""&malumot!B153&" mikromoliya tashkilotining Xulosasi" -> «CLEVER MIKROMOLIYA TASHKILOTI» MChJ mikromoliya tashkilotining Xulosasi
A38: =""&malumot!B153&" kredit qo‘mitasining xulosasiga quyidagi shartlarda "&malumot!B10&"ga "&malumot!B65&" berish masalasi kiritiladi:" -> «CLEVER MIKROMOLIYA TASHKILOTI» MChJ kredit qo‘mitasining xulosasiga quyidagi shartlarda SHAYMARDANOVA SABOXAT YULDASHEVNAga mikroqarz berish masalasi kiritiladi:
A39: =A11 -> Mikroqarz summasi: 52 000 000,00 (ellik ikki million so'm) so'm.
A40: =A12 -> Mikroqarz muddati: 36 (o'ttiz olti) oy.
A41: =A13 -> Mikroqarzdan foydalanganlik uchun foiz stavkasi: yillik 60% (Oltmish) foiz
A42: =A14 -> Mikroqarz bo'yicha asosiy qarz va foizlarni to'lash:
A43: =A15 -> - mikroqarz shartnomasi bo'yicha har oy differensial to'lovlari amalga oshiriladi
A44: =A16 -> Oxirgi yakuniy to'lov mikroqarz shartnomasi tuzilgan kundan boshlab oxirgi oyning oxirgi kunida amalga oshiriladi
A45: =A17 -> Mikroqarz ta’minoti::
A46: =A18 -> Egalik huquqi XUDOYKULOV ALMURAT KURBONAZAROVICHga tegishli bo'lgan garovga olingan avtomobil markasi LADA VESTA, rangi - SARIQ JELTO- ORANJEVIY, ishlab chiqarilgan yili - 2019, davlat raqam belgisi 75M497WA, kuzov turi - YENGIL SEDAN, kuzov raqami XTAGFL110KY258232, dvigatel raqami 3977458, shassi raqami - RAKAMSIZ
A48: =""&malumot!B153&" mikromoliya tashkilotining xulosasi "&TEXT(malumot!B2,"ДД.ММ.ГГГГ")&" y. tayyorlangan" -> «CLEVER MIKROMOLIYA TASHKILOTI» MChJ mikromoliya tashkilotining xulosasi 24.03.2025 y. tayyorlangan
A51: =""&malumot!B153&" mikromoliya tashkilotining Kredit qo‘mitasi a’zolari "&malumot!B153&" mikromoliya tashkilotining xulosasi va Mijoz tomonidan taqdim etilgan ma’lumotlar bilan tanishdilar:" -> «CLEVER MIKROMOLIYA TASHKILOTI» MChJ mikromoliya tashkilotining Kredit qo‘mitasi a’zolari «CLEVER MIKROMOLIYA TASHKILOTI» MChJ mikromoliya tashkilotining xulosasi va Mijoz tomonidan taqdim etilgan ma’lumotlar bilan tanishdilar:
B53: Imzolaganlar ro'yxati:
B54: =malumot!A156 -> Surxondaryo filiali boshlig'i | C54: =malumot!B156 -> A.PARDAYEV
B55: =malumot!A165 -> Kreditlash bo’limi boshlig’i | C55: =malumot!B165 -> B. Mominov
B56: =malumot!A166 -> Monitoring bo’limi boshlig’i | C56: =malumot!B166 -> B. Jumanazarov
B57: Ijrochi direktor: | C57: N. Abduraximov

Sheet dalolatnoma
A2: ="GAROV PREDMETI QIYMATINI KELISHISH №"&malumot!B147&" SONLI DALOLATNOMASI " -> GAROV PREDMETI QIYMATINI KELISHISH №1 SONLI DALOLATNOMASI
A4: Toshkent shahri | E4: =malumot!B148 -> 24 mart 2025 y.
A6: =IF(malumot!B109="avtotransport",dalolatnoma!A10:E10,dalolatnoma!A7:E7) -> «CLEVER MIKROMOLIYA TASHKILOTI» MChJning (1-tomon) vakili bo‘lgan Surxondaryo filiali boshlig'i A.PARDAYEV, O‘zbekiston Respublikasi fuqarosi SHAYMARDANOVA SABOXAT YULDASHEVNA (2-tomon) va garovga beruvchi O‘zbekiston Respublikasi fuqarosi XUDOYKULOV ALMURAT KURBONAZAROVICH (3-tomon) o’rtalarida, 24 mart 2025 y.dan №659-SR-sonli Mikroqarz shartnomasiga muvofiq 1-tomon 2-tomonga berilgan mikroqarz bo‘yicha ta’minot sifatida taqdim etilgan, 3-tomonga mulk huquqi asosida tegishli bo‘lgan mulkning garov qiymatini kelishish muzokaralari o’tkazildi.
A7: =IF(malumot!B99="ha",dalolatnoma!A9:E9,dalolatnoma!A8:E8) -> «CLEVER MIKROMOLIYA TASHKILOTI» MChJning (1-tomon) vakili bo‘lgan Surxondaryo filiali boshlig'i A.PARDAYEV, va O‘zbekiston Respublikasi fuqarosi SHAYMARDANOVA SABOXAT YULDASHEVNA (2-tomon) va garov egasi 0 (3-tomon) 24 mart 2025 y.dan №659-SR Mikroqarz shartnomasiga muvofiq 1-tomon 2-tomonga berilgan mikroqarz bo‘yicha ta’minot sifatida taqdim etilgan, 2-tomonga mulk huquqi asosida tegishli bo‘lgan mulkning garov qiymatini kelishish muzokaralari o’tkazildi.
A8: =""&malumot!B153&"ning (1-tomon) vakili bo‘lgan "&malumot!A156&" "&malumot!B156&", va O‘zbekiston Respublikasi fuqarosi "&malumot!B5&" (2-tomon) va garov egasi "&malumot!C123&" (3-tomon) "&malumot!B74&" "&malumot!C64&" shartnomasiga muvofiq 1-tomon 2-tomonga berilgan "&malumot!B65&" bo‘yicha ta’minot sifatida taqdim etilgan, 2-tomonga mulk huquqi asosida tegishli bo‘lgan mulkning garov qiymatini kelishish muzokaralari o’tkazildi. " -> «CLEVER MIKROMOLIYA TASHKILOTI» MChJning (1-tomon) vakili bo‘lgan Surxondaryo filiali boshlig'i A.PARDAYEV, va O‘zbekiston Respublikasi fuqarosi SHAYMARDANOVA SABOXAT YULDASHEVNA (2-tomon) va garov egasi 0 (3-tomon) 24 mart 2025 y.dan №659-SR Mikroqarz shartnomasiga muvofiq 1-tomon 2-tomonga berilgan mikroqarz bo‘yicha ta’minot sifatida taqdim etilgan, 2-tomonga mulk huquqi asosida tegishli bo‘lgan mulkning garov qiymatini kelishish muzokaralari o’tkazildi.
A9: =""&malumot!B153&"ning (1-tomon) vakili bo‘lgan "&malumot!A156&" "&malumot!B156&", va O‘zbekiston Respublikasi fuqarosi "&malumot!B5&" (2-tomon) va garov egasi "&malumot!C123&" (3-tomon) "&malumot!B74&" "&malumot!C64&" shartnomasiga muvofiq 1-tomon 2-tomonga berilgan "&malumot!B65&" bo‘yicha ta’minot sifatida taqdim etilgan, 2-tomonga mulk huquqi asosida tegishli bo‘lgan mulkning garov qiymatini kelishish muzokaralari o’tkazildi. " -> «CLEVER MIKROMOLIYA TASHKILOTI» MChJning (1-tomon) vakili bo‘lgan Surxondaryo filiali boshlig'i A.PARDAYEV, va O‘zbekiston Respublikasi fuqarosi SHAYMARDANOVA SABOXAT YULDASHEVNA (2-tomon) va garov egasi 0 (3-tomon) 24 mart 2025 y.dan №659-SR Mikroqarz shartnomasiga muvofiq 1-tomon 2-tomonga berilgan mikroqarz bo‘yicha ta’minot sifatida taqdim etilgan, 2-tomonga mulk huquqi asosida tegishli bo‘lgan mulkning garov qiymatini kelishish muzokaralari o’tkazildi.
A10: =IF(malumot!B99="ha",dalolatnoma!A12:E12,dalolatnoma!A11:E11) -> «CLEVER MIKROMOLIYA TASHKILOTI» MChJning (1-tomon) vakili bo‘lgan Surxondaryo filiali boshlig'i A.PARDAYEV, O‘zbekiston Respublikasi fuqarosi SHAYMARDANOVA SABOXAT YULDASHEVNA (2-tomon) va garovga beruvchi O‘zbekiston Respublikasi fuqarosi XUDOYKULOV ALMURAT KURBONAZAROVICH (3-tomon) o’rtalarida, 24 mart 2025 y.dan №659-SR-sonli Mikroqarz shartnomasiga muvofiq 1-tomon 2-tomonga berilgan mikroqarz bo‘yicha ta’minot sifatida taqdim etilgan, 3-tomonga mulk huquqi asosida tegishli bo‘lgan mulkning garov qiymatini kelishish muzokaralari o’tkazildi.
A11: =""&malumot!B153&"ning (1-tomon) vakili bo‘lgan "&malumot!A156&" "&malumot!B156&", O‘zbekiston Respublikasi fuqarosi "&malumot!B5&" (2-tomon) va garovga beruvchi O‘zbekiston Respublikasi fuqarosi "&malumot!B123&" (3-tomon) o’rtalarida, "&malumot!B74&"-sonli "&malumot!C64&" shartnomasiga muvofiq 1-tomon 2-tomonga berilgan "&malumot!B65&" bo‘yicha ta’minot sifatida taqdim etilgan, 3-tomonga mulk huquqi asosida tegishli bo‘lgan mulkning garov qiymatini kelishish muzokaralari o’tkazildi." -> «CLEVER MIKROMOLIYA TASHKILOTI» MChJning (1-tomon) vakili bo‘lgan Surxondaryo filiali boshlig'i A.PARDAYEV, O‘zbekiston Respublikasi fuqarosi SHAYMARDANOVA SABOXAT YULDASHEVNA (2-tomon) va garovga beruvchi O‘zbekiston Respublikasi fuqarosi XUDOYKULOV ALMURAT KURBONAZAROVICH (3-tomon) o’rtalarida, 24 mart 2025 y.dan №659-SR-sonli Mikroqarz shartnomasiga muvofiq 1-tomon 2-tomonga berilgan mikroqarz bo‘yicha ta’minot sifatida taqdim etilgan, 3-tomonga mulk huquqi asosida tegishli bo‘lgan mulkning garov qiymatini kelishish muzokaralari o’tkazildi.
A12: =""&malumot!B153&"ning (1-tomon) vakili bo‘lgan "&malumot!A156&" "&malumot!B156&", O‘zbekiston Respublikasi fuqarosi va garovga beruvchi "&malumot!B5&" (2-tomon) o’rtalarida, "&malumot!B74&"-sonli "&malumot!C64&" shartnomasiga muvofiq 1-tomon 2-tomonga berilgan "&malumot!B65&" bo‘yicha ta’minot sifatida taqdim etilgan, 2-tomonga mulk huquqi asosida tegishli bo‘lgan mulkning garov qiymatini kelishish muzokaralari o’tkazildi." -> «CLEVER MIKROMOLIYA TASHKILOTI» MChJning (1-tomon) vakili bo‘lgan Surxondaryo filiali boshlig'i A.PARDAYEV, O‘zbekiston Respublikasi fuqarosi va garovga beruvchi SHAYMARDANOVA SABOXAT YULDASHEVNA (2-tomon) o’rtalarida, 24 mart 2025 y.dan №659-SR-sonli Mikroqarz shartnomasiga muvofiq 1-tomon 2-tomonga berilgan mikroqarz bo‘yicha ta’minot sifatida taqdim etilgan, 2-tomonga mulk huquqi asosida tegishli bo‘lgan mulkning garov qiymatini kelishish muzokaralari o’tkazildi.
A13: ="Garov predmeti sifatida "&malumot!B131&", 3-tomonga egalik huquqi tegishli bo'lgan, quyidagi tafsilotlarga ega avtotransport vositasi taqdim etiladi:" -> Garov predmeti sifatida LADA VESTA, 3-tomonga egalik huquqi tegishli bo'lgan, quyidagi tafsilotlarga ega avtotransport vositasi taqdim etiladi:
A14: ="Garov predmeti sifatida "&malumot!B131&", 2-tomonga egalik huquqi tegishli bo'lgan, quyidagi tafsilotlarga ega avtotransport vositasi taqdim etiladi:" -> Garov predmeti sifatida LADA VESTA, 2-tomonga egalik huquqi tegishli bo'lgan, quyidagi tafsilotlarga ega avtotransport vositasi taqdim etiladi:
A15: =IF(malumot!B99="ha",dalolatnoma!A14:E14,dalolatnoma!A13:E13) -> Garov predmeti sifatida LADA VESTA, 3-tomonga egalik huquqi tegishli bo'lgan, quyidagi tafsilotlarga ega avtotransport vositasi taqdim etiladi:
A16: ="Garov predmeti sifatida "&malumot!C132&", 2-tomonga egalik huquqi tegishli bo'lgan, quyidagi tafsilotlarga ega ko'chmas mulk taqdim etiladi:" -> Garov predmeti sifatida 3 - xonali yakka tartibdagi uy-joy, 2-tomonga egalik huquqi tegishli bo'lgan, quyidagi tafsilotlarga ega ko'chmas mulk taqdim etiladi:
A17: ="Garov predmeti sifatida "&malumot!C132&", 3-tomonga egalik huquqi tegishli bo'lgan, quyidagi tafsilotlarga ega ko'chmas mulk taqdim etiladi:" -> Garov predmeti sifatida 3 - xonali yakka tartibdagi uy-joy, 3-tomonga egalik huquqi tegishli bo'lgan, quyidagi tafsilotlarga ega ko'chmas mulk taqdim etiladi:
A18: =IF(malumot!B99="ha",dalolatnoma!A16:E16,dalolatnoma!A17:E17) -> Garov predmeti sifatida 3 - xonali yakka tartibdagi uy-joy, 3-tomonga egalik huquqi tegishli bo'lgan, quyidagi tafsilotlarga ega ko'chmas mulk taqdim etiladi:
A19: =IF(malumot!B109="Avtotransport",dalolatnoma!A15:E15,dalolatnoma!A18:E18) -> Garov predmeti sifatida LADA VESTA, 3-tomonga egalik huquqi tegishli bo'lgan, quyidagi tafsilotlarga ega avtotransport vositasi taqdim etiladi:
A20: Nomi | B20: =IF(malumot!B109=malumot!C109,"Kuzov turi va kuzov raqami*","Foydali maydoni") -> Kuzov turi va kuzov raqami* | D20: =IF(malumot!B109=malumot!C109,"Dvigatel va shassi raqami*","Yashash maydoni") -> Dvigatel va shassi raqami* | E20: =IF(malumot!B109=malumot!C109,"Ishlab chiqarilgan yili va rangi**","Umumiy maydoni") -> Ishlab chiqarilgan yili va rangi**
A21: =IF(malumot!B109=malumot!C109,malumot!B131,malumot!C131) -> LADA VESTA | B21: =IF(malumot!B109=malumot!C109,malumot!B133,CONCATENATE(malumot!F136," ","kv.m")) -> kuzov turi - YENGIL SEDAN, kuzov raqami XTAGFL110KY258232 | D21: =IF(malumot!B109=malumot!C109,malumot!B136,malumot!E139) -> dvigatel raqami 3977458, shassi raqami - RAKAMSIZ | E21: =IF(malumot!B109=malumot!C109,malumot!B139,malumot!E136) -> rangi - SARIQ JELTO- ORANJEVIY, ishlab chiqarilgan yili - 2019
A22: ="-* "&IF(malumot!B109=malumot!C109,"avtotransport "&"egasi: "&malumot!B123&"","ko'chmas mulk"&" egasi: "&malumot!B123&"") -> -* avtotransport egasi: XUDOYKULOV ALMURAT KURBONAZAROVICH
A23: =IF(malumot!B109=malumot!C109,"-* texnik pasport: "&malumot!B130&"","-* reest raqami: "&malumot!C130&"") -> -* texnik pasport: AAG 3367573 24.01.2024 y.
A24: =IF(malumot!B109=malumot!C109,"-* roʻyxatdan oʻtgan manzili/garaj manzili: "&malumot!B128&"","-* kadastr raqami: "&malumot!C133&"") -> -* roʻyxatdan oʻtgan manzili/garaj manzili: SURXONDARYO VILOYATI JARQO'RG'ON TUMANI OQQURG'ON QFY QORAYONTOQ MFY IBN SINO KO'CHASI 114-UY
A25: =IF(malumot!B109=malumot!C109,"-* davlat raqami: "&malumot!B132&"","-* manzili: "&malumot!C129&"") -> -* davlat raqami: 75M497WA
A26: =IF(malumot!B99="ha",dalolatnoma!A28:E28,dalolatnoma!A27:E27) -> Tomonlar o’rtasida o’tkazilgan muzokaralar natijalariga ko‘ra, 2-tomon ta’minot sifatida quyidagi tafsilotlarga ega bo’lgan garov predmetini taqdim etadi, 1-tomon esa ushbu garov predmetini 24 mart 2025 y.dan №659-SR mikroqarz shartnomasi bo‘yicha berilgan mikroqarz bo‘yicha 78 000 000,00 (yetmish sakkiz million so'm) so’m bo‘lgan kelishilgan garov qiymatida qabul qiladi::
A27: ="Tomonlar o’rtasida o’tkazilgan muzokaralar natijalariga ko‘ra, 2-tomon ta’minot sifatida quyidagi tafsilotlarga ega bo’lgan garov predmetini taqdim etadi, 1-tomon esa ushbu garov predmetini "&malumot!B74&" "&malumot!B65&" shartnomasi bo‘yicha berilgan "&malumot!B65&" bo‘yicha "&FIXED(malumot!B142,2)&" ("&malumot!B143&") so’m bo‘lgan kelishilgan garov qiymatida qabul qiladi::" -> Tomonlar o’rtasida o’tkazilgan muzokaralar natijalariga ko‘ra, 2-tomon ta’minot sifatida quyidagi tafsilotlarga ega bo’lgan garov predmetini taqdim etadi, 1-tomon esa ushbu garov predmetini 24 mart 2025 y.dan №659-SR mikroqarz shartnomasi bo‘yicha berilgan mikroqarz bo‘yicha 78 000 000,00 (yetmish sakkiz million so'm) so’m bo‘lgan kelishilgan garov qiymatida qabul qiladi::
A28: ="Tomonlar o’rtasida o’tkazilgan muzokaralar natijalariga ko‘ra, 2-tomon ta’minot sifatida quyidagi tafsilotlarga ega bo’lgan garov predmetini taqdim etadi, 1-tomon esa ushbu garov predmetini "&malumot!B74&" "&malumot!C64&" shartnomasi bo‘yicha berilgan "&malumot!B65&" bo‘yicha "&FIXED(malumot!B142,2)&" ("&malumot!B143&") so’m bo‘lgan kelishilgan garov qiymatida qabul qiladi::" -> Tomonlar o’rtasida o’tkazilgan muzokaralar natijalariga ko‘ra, 2-tomon ta’minot sifatida quyidagi tafsilotlarga ega bo’lgan garov predmetini taqdim etadi, 1-tomon esa ushbu garov predmetini 24 mart 2025 y.dan №659-SR Mikroqarz shartnomasi bo‘yicha berilgan mikroqarz bo‘yicha 78 000 000,00 (yetmish sakkiz million so'm) so’m bo‘lgan kelishilgan garov qiymatida qabul qiladi::
A29: Nomi | B29: =B20 -> Kuzov turi va kuzov raqami* | C29: =D20 -> Dvigatel va shassi raqami* | D29: =IF(malumot!B109=malumot!C109,"Ishlab chiqarilgan yili va rangi*","Foydalanishga topshirilgan sanasi") -> Ishlab chiqarilgan yili va rangi* | E29: Kelishilgan garov qiymati, so'm
A30: =A21 -> LADA VESTA | B30: =B21 -> kuzov turi - YENGIL SEDAN, kuzov raqami XTAGFL110KY258232 | C30: =D21 -> dvigatel raqami 3977458, shassi raqami - RAKAMSIZ | D30: =IF(malumot!B109=malumot!C109,E21,TEXT(malumot!C141,"ДД.ММ.ГГГГ")) -> rangi - SARIQ JELTO- ORANJEVIY, ishlab chiqarilgan yili - 2019 | E30: =""&FIXED(malumot!B142,2)&" ("&malumot!B143&")" -> 78 000 000,00 (yetmish sakkiz million so'm)
A32: Наименование | B32: Полезная площадь | C32: Жилая площадь | D32: Общая площадь | E32: Согласованная залоговая стоимость, сум
A33: =#REF! -> #REF! | B33: =#REF! -> #REF! | C33: =#REF! -> #REF! | D33: =#REF! -> #REF! | E33: =""&FIXED(malumot!C142,2)&" ("&malumot!B143&")" -> 78 000 000,00 (yetmish sakkiz million so'm)
A35: =#REF! -> #REF! | B35: =#REF! -> #REF! | C35: =#REF! -> #REF! | D35: =#REF! -> #REF!
A36: =#REF! -> #REF! | B36: =#REF! -> #REF! | C36: =#REF! -> #REF! | D36: =#REF! -> #REF!
A37: =#REF! -> #REF! | B37: =#REF! -> #REF! | C37: =#REF! -> #REF! | D37: =#REF! -> #REF!
A38: =#REF! -> #REF! | B38: =#REF! -> #REF! | C38: =#REF! -> #REF! | D38: =#REF! -> #REF!
A39: =#REF! -> #REF! | B39: =#REF! -> #REF! | C39: =#REF! -> #REF! | D39: =#REF! -> #REF!
A40: =#REF! -> #REF! | B40: =#REF! -> #REF! | C40: =#REF! -> #REF! | D40: =#REF! -> #REF!
A41: =#REF! -> #REF! | B41: =#REF! -> #REF! | C41: =#REF! -> #REF! | D41: =#REF! -> #REF!
A42: =#REF! -> #REF! | B42: =#REF! -> #REF! | C42: =#REF! -> #REF! | D42: =#REF! -> #REF!
A43: =#REF! -> #REF! | B43: =#REF! -> #REF! | C43: =#REF! -> #REF! | D43: =#REF! -> #REF!
A44: =#REF! -> #REF! | B44: =#REF! -> #REF! | C44: =#REF! -> #REF! | D44: =#REF! -> #REF! | E44: =FIXED(malumot!C142,2) -> 78 000 000,00
A46: ="“Birinchi talabga ko‘ra, yuqoridagi avtomobil Mikrokredit shartnomasi bo‘yicha garovga qo‘yilgan edi:: "&'Данные для послед. Залога'!W2&"" -> “Birinchi talabga ko‘ra, yuqoridagi avtomobil Mikrokredit shartnomasi bo‘yicha garovga qo‘yilgan edi:: - №5 от 11 yanvar 2021 г., заключенного с ООО «Clever Mikrokredit Tashkiloti» и TULYAGANOV XODJIAKBAR IRGASHEVICH, по согласованной залоговой стоимость - 15 000 000,00 (on besh million) сум. - №386 от 6 noyabr 2019 г., заключенного с ООО «Clever Mikrokredit Tashkiloti» и YUNUSOVA ZALOXAT MIRSULTANOVNA, по согласованной залоговой стоимость - 15 000 000,00 (on besh million) сум. - №33 от 21 yanvar 2021 г., заключенного с ООО «Clever Mikrokredit Tashkiloti» и YUNUSOVA ZALOXAT MIRSULTANOVNA, по согласованной залоговой стоимость - 15 000 000,00 (on besh million) сум. 0 0 0 0 0 0 0 0 0 0 0 0 0 0 0 0 0
A47: Shu bilan birga, garov predmetining kelishilgan garov qiymati deganda ushbu mulk garov sifatida taqdim etilgan/qabul qilingan qiymati tushuniladi.
A48: ="Shunday qilib, garov predmetining kelishilgan garov qiymati "&FIXED(malumot!B142)&" ("&malumot!B143&") so‘mni tashkil etadi." -> Shunday qilib, garov predmetining kelishilgan garov qiymati 78 000 000,00 (yetmish sakkiz million so'm) so‘mni tashkil etadi.
D49: =IF(malumot!B98=malumot!C98,malumot!C142,IF(malumot!B98=malumot!D98,'Данные для послед. Залога'!M22,0)) -> 78000000 | E49: =IF(malumot!B98=malumot!C98,malumot!B143,IF(malumot!B98=malumot!D98,'Данные для послед. Залога'!Q22,0)) -> yetmish sakkiz million so'm
A50: 1-tomondan:
A51: =malumot!B154 -> «CLEVER MIKROMOLIYA TASHKILOTI» MChJ
A52: =""&malumot!A156&"" -> Surxondaryo filiali boshlig'i | E52: =malumot!B156 -> A.PARDAYEV
A55: Начальник отдела кредитования
A56: =malumot!B154 -> «CLEVER MIKROMOLIYA TASHKILOTI» MChJ | D56: ="_______________ "&malumot!B165&"" -> _______________ B. Mominov
A58: 2-tomondan:
A59: O'zbekiston Respublikasi fuqarosi | D59: ="_______________ "&malumot!B7&"" -> _______________ SHAYMARDANOVA S.Y.
D60: =IF(malumot!B99="да","",malumot!B124) -> XUDOYKULOV A.K.
A61: =+IF(malumot!B99="ha"," ","3-tomondan:") -> 3-tomondan: | F61: =IF(malumot!B100=malumot!D100,B7,"")
A62: =+IF(malumot!B99="ha"," ","O'zbekiston Respublikasi fuqarosi") -> O'zbekiston Respublikasi fuqarosi | D62: ="_______________ "&malumot!B118&"" -> _______________ XUDOYKULOV A.K.
A63: =IF(malumot!B100=malumot!C100,"_______________ "&malumot!B118&"","_______________ "&malumot!B7&"") -> _______________ XUDOYKULOV A.K. | C63: ='заявление залогодателя'!A20

Sheet grafik
E3: =""&malumot!B74&" "&malumot!B65&" shartnomasiga 1 sonli ilova" -> 24 mart 2025 y.dan №659-SR mikroqarz shartnomasiga 1 sonli ilova
A5: To'lov jadvali
A7: № | B7: To'lov muddati | C7: Asosiy qarz qoldig'i | D7: To'lov miqdori, so'm
D8: asosiy qarz | E8: foizlar | F8: jami*
A9: 1 | B9: ='График аннуитет.'!B8 -> 45748 | C9: =IF(malumot!$B$77=malumot!$C$77,'График дифференц'!C8,IF(malumot!$B$77=malumot!$D$77,'График аннуитет.'!C8)) -> 52000000 | D9: =IF(malumot!$B$77=malumot!$C$77,'График дифференц'!D8,IF(malumot!$B$77=malumot!$D$77,'График аннуитет.'!D8)) -> 1444444.4 | E9: =IF(malumot!$B$77=malumot!$C$77,'График дифференц'!E8,IF(malumot!$B$77=malumot!$D$77,'График аннуитет.'!E8)) -> 683835.6 | F9: =IF(malumot!$B$77=malumot!$C$77,'График дифференц'!F8,IF(malumot!$B$77=malumot!$D$77,'График аннуитет.'!F8)) -> 2128280
A10: 2 | B10: ='График аннуитет.'!B9 -> 45778 | C10: =IF(malumot!$B$77=malumot!$C$77,'График дифференц'!C9,IF(malumot!$B$77=malumot!$D$77,'График аннуитет.'!C9)) -> 50555556 | D10: =IF(malumot!$B$77=malumot!$C$77,'График дифференц'!D9,IF(malumot!$B$77=malumot!$D$77,'График аннуитет.'!D9)) -> 1444444.4 | E10: =IF(malumot!$B$77=malumot!$C$77,'График дифференц'!E9,IF(malumot!$B$77=malumot!$D$77,'График аннуитет.'!E9)) -> 2493150.6 | F10: =IF(malumot!$B$77=malumot!$C$77,'График дифференц'!F9,IF(malumot!$B$77=malumot!$D$77,'График аннуитет.'!F9)) -> 3937595
A11: 3 | B11: ='График аннуитет.'!B10 -> 45810 | C11: =IF(malumot!$B$77=malumot!$C$77,'График дифференц'!C10,IF(malumot!$B$77=malumot!$D$77,'График аннуитет.'!C10)) -> 49111111 | D11: =IF(malumot!$B$77=malumot!$C$77,'График дифференц'!D10,IF(malumot!$B$77=malumot!$D$77,'График аннуитет.'!D10)) -> 1444444.4 | E11: =IF(malumot!$B$77=malumot!$C$77,'График дифференц'!E10,IF(malumot!$B$77=malumot!$D$77,'График аннуитет.'!E10)) -> 2583378.9 | F11: =IF(malumot!$B$77=malumot!$C$77,'График дифференц'!F10,IF(malumot!$B$77=malumot!$D$77,'График аннуитет.'!F10)) -> 4027823.3
A12: 4 | B12: ='График аннуитет.'!B11 -> 45839 | C12: =IF(malumot!$B$77=malumot!$C$77,'График дифференц'!C11,IF(malumot!$B$77=malumot!$D$77,'График аннуитет.'!C11)) -> 47666667 | D12: =IF(malumot!$B$77=malumot!$C$77,'График дифференц'!D11,IF(malumot!$B$77=malumot!$D$77,'График аннуитет.'!D11)) -> 1444444.4 | E12: =IF(malumot!$B$77=malumot!$C$77,'График дифференц'!E11,IF(malumot!$B$77=malumot!$D$77,'График аннуитет.'!E11)) -> 2272328.6 | F12: =IF(malumot!$B$77=malumot!$C$77,'График дифференц'!F11,IF(malumot!$B$77=malumot!$D$77,'График аннуитет.'!F11)) -> 3716773.1 | H12: GRAFIKTA BO'SH JOY BO'LSA SKRIT' QILIB TASHLANG!!!
A13: 5 | B13: ='График аннуитет.'!B12 -> 45870 | C13: =IF(malumot!$B$77=malumot!$C$77,'График дифференц'!C12,IF(malumot!$B$77=malumot!$D$77,'График аннуитет.'!C12)) -> 46222222 | D13: =IF(malumot!$B$77=malumot!$C$77,'График дифференц'!D12,IF(malumot!$B$77=malumot!$D$77,'График аннуитет.'!D12)) -> 1444444.4 | E13: =IF(malumot!$B$77=malumot!$C$77,'График дифференц'!E12,IF(malumot!$B$77=malumot!$D$77,'График аннуитет.'!E12)) -> 2355433.9 | F13: =IF(malumot!$B$77=malumot!$C$77,'График дифференц'!F12,IF(malumot!$B$77=malumot!$D$77,'График аннуитет.'!F12)) -> 3799878.4
A14: 6 | B14: ='График аннуитет.'!B13 -> 45901 | C14: =IF(malumot!$B$77=malumot!$C$77,'График дифференц'!C13,IF(malumot!$B$77=malumot!$D$77,'График аннуитет.'!C13)) -> 44777778 | D14: =IF(malumot!$B$77=malumot!$C$77,'График дифференц'!D13,IF(malumot!$B$77=malumot!$D$77,'График аннуитет.'!D13)) -> 1444444.4 | E14: =IF(malumot!$B$77=malumot!$C$77,'График дифференц'!E13,IF(malumot!$B$77=malumot!$D$77,'График аннуитет.'!E13)) -> 2281826.6 | F14: =IF(malumot!$B$77=malumot!$C$77,'График дифференц'!F13,IF(malumot!$B$77=malumot!$D$77,'График аннуитет.'!F13)) -> 3726271
A15: 7 | B15: ='График аннуитет.'!B14 -> 45931 | C15: =IF(malumot!$B$77=malumot!$C$77,'График дифференц'!C14,IF(malumot!$B$77=malumot!$D$77,'График аннуитет.'!C14)) -> 43333333 | D15: =IF(malumot!$B$77=malumot!$C$77,'График дифференц'!D14,IF(malumot!$B$77=malumot!$D$77,'График аннуитет.'!D14)) -> 1444444.4 | E15: =IF(malumot!$B$77=malumot!$C$77,'График дифференц'!E14,IF(malumot!$B$77=malumot!$D$77,'График аннуитет.'!E14)) -> 2136986.4 | F15: =IF(malumot!$B$77=malumot!$C$77,'График дифференц'!F14,IF(malumot!$B$77=malumot!$D$77,'График аннуитет.'!F14)) -> 3581430.8
A16: 8 | B16: ='График аннуитет.'!B15 -> 45964 | C16: =IF(malumot!$B$77=malumot!$C$77,'График дифференц'!C15,IF(malumot!$B$77=malumot!$D$77,'График аннуитет.'!C15)) -> 41888889 | D16: =IF(malumot!$B$77=malumot!$C$77,'График дифференц'!D15,IF(malumot!$B$77=malumot!$D$77,'График аннуитет.'!D15)) -> 1444444.4 | E16: =IF(malumot!$B$77=malumot!$C$77,'График дифференц'!E15,IF(malumot!$B$77=malumot!$D$77,'График аннуитет.'!E15)) -> 2272328.9 | F16: =IF(malumot!$B$77=malumot!$C$77,'График дифференц'!F15,IF(malumot!$B$77=malumot!$D$77,'График аннуитет.'!F15)) -> 3716773.3
A17: 9 | B17: ='График аннуитет.'!B16 -> 45992 | C17: =IF(malumot!$B$77=malumot!$C$77,'График дифференц'!C16,IF(malumot!$B$77=malumot!$D$77,'График аннуитет.'!C16)) -> 40444444 | D17: =IF(malumot!$B$77=malumot!$C$77,'График дифференц'!D16,IF(malumot!$B$77=malumot!$D$77,'График аннуитет.'!D16)) -> 1444444.4 | E17: =IF(malumot!$B$77=malumot!$C$77,'График дифференц'!E16,IF(malumot!$B$77=malumot!$D$77,'График аннуитет.'!E16)) -> 1861552.6 | F17: =IF(malumot!$B$77=malumot!$C$77,'График дифференц'!F16,IF(malumot!$B$77=malumot!$D$77,'График аннуитет.'!F16)) -> 3305997
A18: 10 | B18: ='График аннуитет.'!B17 -> 46023 | C18: =IF(malumot!$B$77=malumot!$C$77,'График дифференц'!C17,IF(malumot!$B$77=malumot!$D$77,'График аннуитет.'!C17)) -> 39000000 | D18: =IF(malumot!$B$77=malumot!$C$77,'График дифференц'!D17,IF(malumot!$B$77=malumot!$D$77,'График аннуитет.'!D17)) -> 1444444.4 | E18: =IF(malumot!$B$77=malumot!$C$77,'График дифференц'!E17,IF(malumot!$B$77=malumot!$D$77,'График аннуитет.'!E17)) -> 1987397.3 | F18: =IF(malumot!$B$77=malumot!$C$77,'График дифференц'!F17,IF(malumot!$B$77=malumot!$D$77,'График аннуитет.'!F17)) -> 3431841.7
A19: 11 | B19: ='График аннуитет.'!B18 -> 46055 | C19: =IF(malumot!$B$77=malumot!$C$77,'График дифференц'!C18,IF(malumot!$B$77=malumot!$D$77,'График аннуитет.'!C18)) -> 37555556 | D19: =IF(malumot!$B$77=malumot!$C$77,'График дифференц'!D18,IF(malumot!$B$77=malumot!$D$77,'График аннуитет.'!D18)) -> 1444444.4 | E19: =IF(malumot!$B$77=malumot!$C$77,'График дифференц'!E18,IF(malumot!$B$77=malumot!$D$77,'График аннуитет.'!E18)) -> 1975525.1 | F19: =IF(malumot!$B$77=malumot!$C$77,'График дифференц'!F18,IF(malumot!$B$77=malumot!$D$77,'График аннуитет.'!F18)) -> 3419969.6
A20: 12 | B20: ='График аннуитет.'!B19 -> 46083 | C20: =IF(malumot!$B$77=malumot!$C$77,'График дифференц'!C19,IF(malumot!$B$77=malumot!$D$77,'График аннуитет.'!C19)) -> 36111111 | D20: =IF(malumot!$B$77=malumot!$C$77,'График дифференц'!D19,IF(malumot!$B$77=malumot!$D$77,'График аннуитет.'!D19)) -> 1444444.4 | E20: =IF(malumot!$B$77=malumot!$C$77,'График дифференц'!E19,IF(malumot!$B$77=malumot!$D$77,'График аннуитет.'!E19)) -> 1662100.4 | F20: =IF(malumot!$B$77=malumot!$C$77,'График дифференц'!F19,IF(malumot!$B$77=malumot!$D$77,'График аннуитет.'!F19)) -> 3106544.9
A21: 13 | B21: ='График аннуитет.'!B20 -> 46113 | C21: =IF(malumot!$B$77=malumot!$C$77,'График дифференц'!C20,IF(malumot!$B$77=malumot!$D$77,'График аннуитет.'!C20)) -> 34666667 | D21: =IF(malumot!$B$77=malumot!$C$77,'График дифференц'!D20,IF(malumot!$B$77=malumot!$D$77,'График аннуитет.'!D20)) -> 1444444.4 | E21: =IF(malumot!$B$77=malumot!$C$77,'График дифференц'!E20,IF(malumot!$B$77=malumot!$D$77,'График аннуитет.'!E20)) -> 1709589 | F21: =IF(malumot!$B$77=malumot!$C$77,'График дифференц'!F20,IF(malumot!$B$77=malumot!$D$77,'График аннуитет.'!F20)) -> 3154033.4
A22: 14 | B22: ='График аннуитет.'!B21 -> 46143 | C22: =IF(malumot!$B$77=malumot!$C$77,'График дифференц'!C21,IF(malumot!$B$77=malumot!$D$77,'График аннуитет.'!C21)) -> 33222222 | D22: =IF(malumot!$B$77=malumot!$C$77,'График дифференц'!D21,IF(malumot!$B$77=malumot!$D$77,'График аннуитет.'!D21)) -> 1444444.4 | E22: =IF(malumot!$B$77=malumot!$C$77,'График дифференц'!E21,IF(malumot!$B$77=malumot!$D$77,'График аннуитет.'!E21)) -> 1638356.1 | F22: =IF(malumot!$B$77=malumot!$C$77,'График дифференц'!F21,IF(malumot!$B$77=malumot!$D$77,'График аннуитет.'!F21)) -> 3082800.5
A23: 15 | B23: ='График аннуитет.'!B22 -> 46174 | C23: =IF(malumot!$B$77=malumot!$C$77,'График дифференц'!C22,IF(malumot!$B$77=malumot!$D$77,'График аннуитет.'!C22)) -> 31777778 | D23: =IF(malumot!$B$77=malumot!$C$77,'График дифференц'!D22,IF(malumot!$B$77=malumot!$D$77,'График аннуитет.'!D22)) -> 1444444.4 | E23: =IF(malumot!$B$77=malumot!$C$77,'График дифференц'!E22,IF(malumot!$B$77=malumot!$D$77,'График аннуитет.'!E22)) -> 1619360.6 | F23: =IF(malumot!$B$77=malumot!$C$77,'График дифференц'!F22,IF(malumot!$B$77=malumot!$D$77,'График аннуитет.'!F22)) -> 3063805.1
A24: 16 | B24: ='График аннуитет.'!B23 -> 46204 | C24: =IF(malumot!$B$77=malumot!$C$77,'График дифференц'!C23,IF(malumot!$B$77=malumot!$D$77,'График аннуитет.'!C23)) -> 30333333 | D24: =IF(malumot!$B$77=malumot!$C$77,'График дифференц'!D23,IF(malumot!$B$77=malumot!$D$77,'График аннуитет.'!D23)) -> 1444444.4 | E24: =IF(malumot!$B$77=malumot!$C$77,'График дифференц'!E23,IF(malumot!$B$77=malumot!$D$77,'График аннуитет.'!E23)) -> 1495890.3 | F24: =IF(malumot!$B$77=malumot!$C$77,'График дифференц'!F23,IF(malumot!$B$77=malumot!$D$77,'График аннуитет.'!F23)) -> 2940334.7
... A26: 18 | B26: ='График аннуитет.'!B25 -> 46266 | C26: =IF(malumot!$B$77=malumot!$C$77,'График дифференц'!C25,IF(malumot!$B$77=malumot!$D$77,'График аннуитет.'!C25)) -> 27444445 | D26: =IF(malumot!$B$77=malumot!$C$77,'График дифференц'!D25,IF(malumot!$B$77=malumot!$D$77,'График аннуитет.'!D25)) -> 1444444.4 | E26: =IF(malumot!$B$77=malumot!$C$77,'График дифференц'!E25,IF(malumot!$B$77=malumot!$D$77,'График аннуитет.'!E25)) -> 1308310.6 | F26: =IF(malumot!$B$77=malumot!$C$77,'График дифференц'!F25,IF(malumot!$B$77=malumot!$D$77,'График аннуитет.'!F25)) -> 2752755.1
A27: =1+A26 -> 19 | B27: ='График аннуитет.'!B26 -> 46296 | C27: =IF(malumot!$B$77=malumot!$C$77,'График дифференц'!C26,IF(malumot!$B$77=malumot!$D$77,'График аннуитет.'!C26)) -> 26000000 | D27: =IF(malumot!$B$77=malumot!$C$77,'График дифференц'!D26,IF(malumot!$B$77=malumot!$D$77,'График аннуитет.'!D26)) -> 1444444.4 | E27: =IF(malumot!$B$77=malumot!$C$77,'График дифференц'!E26,IF(malumot!$B$77=malumot!$D$77,'График аннуитет.'!E26)) -> 1282191.9 | F27: =IF(malumot!$B$77=malumot!$C$77,'График дифференц'!F26,IF(malumot!$B$77=malumot!$D$77,'График аннуитет.'!F26)) -> 2726636.3
A28: =1+A27 -> 20 | B28: ='График аннуитет.'!B27 -> 46328 | C28: =IF(malumot!$B$77=malumot!$C$77,'График дифференц'!C27,IF(malumot!$B$77=malumot!$D$77,'График аннуитет.'!C27)) -> 24555556 | D28: =IF(malumot!$B$77=malumot!$C$77,'График дифференц'!D27,IF(malumot!$B$77=malumot!$D$77,'График аннуитет.'!D27)) -> 1444444.4 | E28: =IF(malumot!$B$77=malumot!$C$77,'График дифференц'!E27,IF(malumot!$B$77=malumot!$D$77,'График аннуитет.'!E27)) -> 1291689.6 | F28: =IF(malumot!$B$77=malumot!$C$77,'График дифференц'!F27,IF(malumot!$B$77=malumot!$D$77,'График аннуитет.'!F27)) -> 2736134
A29: =1+A28 -> 21 | B29: ='График аннуитет.'!B28 -> 46357 | C29: =IF(malumot!$B$77=malumot!$C$77,'График дифференц'!C28,IF(malumot!$B$77=malumot!$D$77,'График аннуитет.'!C28)) -> 23111111 | D29: =IF(malumot!$B$77=malumot!$C$77,'График дифференц'!D28,IF(malumot!$B$77=malumot!$D$77,'График аннуитет.'!D28)) -> 1444444.4 | E29: =IF(malumot!$B$77=malumot!$C$77,'График дифференц'!E28,IF(malumot!$B$77=malumot!$D$77,'График аннуитет.'!E28)) -> 1101735.2 | F29: =IF(malumot!$B$77=malumot!$C$77,'График дифференц'!F28,IF(malumot!$B$77=malumot!$D$77,'График аннуитет.'!F28)) -> 2546179.7
A30: =1+A29 -> 22 | B30: ='График аннуитет.'!B29 -> 46388 | C30: =IF(malumot!$B$77=malumot!$C$77,'График дифференц'!C29,IF(malumot!$B$77=malumot!$D$77,'График аннуитет.'!C29)) -> 21666667 | D30: =IF(malumot!$B$77=malumot!$C$77,'График дифференц'!D29,IF(malumot!$B$77=malumot!$D$77,'График аннуитет.'!D29)) -> 1444444.4 | E30: =IF(malumot!$B$77=malumot!$C$77,'График дифференц'!E29,IF(malumot!$B$77=malumot!$D$77,'График аннуитет.'!E29)) -> 1104109.6 | F30: =IF(malumot!$B$77=malumot!$C$77,'График дифференц'!F29,IF(malumot!$B$77=malumot!$D$77,'График аннуитет.'!F29)) -> 2548554.1
A31: =1+A30 -> 23 | B31: ='График аннуитет.'!B30 -> 46419 | C31: =IF(malumot!$B$77=malumot!$C$77,'График дифференц'!C30,IF(malumot!$B$77=malumot!$D$77,'График аннуитет.'!C30)) -> 20222222 | D31: =IF(malumot!$B$77=malumot!$C$77,'График дифференц'!D30,IF(malumot!$B$77=malumot!$D$77,'График аннуитет.'!D30)) -> 1444444.4 | E31: =IF(malumot!$B$77=malumot!$C$77,'График дифференц'!E30,IF(malumot!$B$77=malumot!$D$77,'График аннуитет.'!E30)) -> 1030502.3 | F31: =IF(malumot!$B$77=malumot!$C$77,'График дифференц'!F30,IF(malumot!$B$77=malumot!$D$77,'График аннуитет.'!F30)) -> 2474946.8
A32: =1+A31 -> 24 | B32: ='График аннуитет.'!B31 -> 46447 | C32: =IF(malumot!$B$77=malumot!$C$77,'График дифференц'!C31,IF(malumot!$B$77=malumot!$D$77,'График аннуитет.'!C31)) -> 18777778 | D32: =IF(malumot!$B$77=malumot!$C$77,'График дифференц'!D31,IF(malumot!$B$77=malumot!$D$77,'График аннуитет.'!D31)) -> 1444444.4 | E32: =IF(malumot!$B$77=malumot!$C$77,'График дифференц'!E31,IF(malumot!$B$77=malumot!$D$77,'График аннуитет.'!E31)) -> 864292.24 | F32: =IF(malumot!$B$77=malumot!$C$77,'График дифференц'!F31,IF(malumot!$B$77=malumot!$D$77,'График аннуитет.'!F31)) -> 2308736.7
A33: =1+A32 -> 25 | B33: =IF('График аннуитет.'!B32=FALSE,"",'График аннуитет.'!B32) -> 46478 | C33: =IF(malumot!$B$77=malumot!$C$77,'График дифференц'!C32,IF(malumot!$B$77=malumot!$D$77,'График аннуитет.'!C32)) -> 17333333 | D33: =IF(malumot!$B$77=malumot!$C$77,'График дифференц'!D32,IF(malumot!$B$77=malumot!$D$77,'График аннуитет.'!D32)) -> 1444444.4 | E33: =IF(malumot!$B$77=malumot!$C$77,'График дифференц'!E32,IF(malumot!$B$77=malumot!$D$77,'График аннуитет.'!E32)) -> 883287.65 | F33: =IF(malumot!$B$77=malumot!$C$77,'График дифференц'!F32,IF(malumot!$B$77=malumot!$D$77,'График аннуитет.'!F32)) -> 2327732.1
A34: =1+A33 -> 26 | B34: =IF('График аннуитет.'!B33=FALSE,"",'График аннуитет.'!B33) -> 46510 | C34: =IF(malumot!$B$77=malumot!$C$77,'График дифференц'!C33,IF(malumot!$B$77=malumot!$D$77,'График аннуитет.'!C33)) -> 15888889 | D34: =IF(malumot!$B$77=malumot!$C$77,'График дифференц'!D33,IF(malumot!$B$77=malumot!$D$77,'График аннуитет.'!D33)) -> 1444444.4 | E34: =IF(malumot!$B$77=malumot!$C$77,'График дифференц'!E33,IF(malumot!$B$77=malumot!$D$77,'График аннуитет.'!E33)) -> 835799.04 | F34: =IF(malumot!$B$77=malumot!$C$77,'График дифференц'!F33,IF(malumot!$B$77=malumot!$D$77,'График аннуитет.'!F33)) -> 2280243.5
A35: =1+A34 -> 27 | B35: =IF('График аннуитет.'!B34=FALSE,"",'График аннуитет.'!B34) -> 46539 | C35: =IF(malumot!$B$77=malumot!$C$77,'График дифференц'!C34,IF(malumot!$B$77=malumot!$D$77,'График аннуитет.'!C34)) -> 14444445 | D35: =IF(malumot!$B$77=malumot!$C$77,'График дифференц'!D34,IF(malumot!$B$77=malumot!$D$77,'График аннуитет.'!D34)) -> 1444444.4 | E35: =IF(malumot!$B$77=malumot!$C$77,'График дифференц'!E34,IF(malumot!$B$77=malumot!$D$77,'График аннуитет.'!E34)) -> 688584.41 | F35: =IF(malumot!$B$77=malumot!$C$77,'График дифференц'!F34,IF(malumot!$B$77=malumot!$D$77,'График аннуитет.'!F34)) -> 2133028.9
A36: =1+A35 -> 28 | B36: =IF('График аннуитет.'!B35=FALSE,"",'График аннуитет.'!B35) -> 46569 | C36: =IF(malumot!$B$77=malumot!$C$77,'График дифференц'!C35,IF(malumot!$B$77=malumot!$D$77,'График аннуитет.'!C35)) -> 13000000 | D36: =IF(malumot!$B$77=malumot!$C$77,'График дифференц'!D35,IF(malumot!$B$77=malumot!$D$77,'График аннуитет.'!D35)) -> 1444444.4 | E36: =IF(malumot!$B$77=malumot!$C$77,'График дифференц'!E35,IF(malumot!$B$77=malumot!$D$77,'График аннуитет.'!E35)) -> 641095.8 | F36: =IF(malumot!$B$77=malumot!$C$77,'График дифференц'!F35,IF(malumot!$B$77=malumot!$D$77,'График аннуитет.'!F35)) -> 2085540.2
A37: =1+A36 -> 29 | B37: =IF('График аннуитет.'!B36=FALSE,"",'График аннуитет.'!B36) -> 46601 | C37: =IF(malumot!$B$77=malumot!$C$77,'График дифференц'!C36,IF(malumot!$B$77=malumot!$D$77,'График аннуитет.'!C36)) -> 11555556 | D37: =IF(malumot!$B$77=malumot!$C$77,'График дифференц'!D36,IF(malumot!$B$77=malumot!$D$77,'График аннуитет.'!D36)) -> 1444444.4 | E37: =IF(malumot!$B$77=malumot!$C$77,'График дифференц'!E36,IF(malumot!$B$77=malumot!$D$77,'График аннуитет.'!E36)) -> 607853.76 | F37: =IF(malumot!$B$77=malumot!$C$77,'График дифференц'!F36,IF(malumot!$B$77=malumot!$D$77,'График аннуитет.'!F36)) -> 2052298.2
A38: =1+A37 -> 30 | B38: =IF('График аннуитет.'!B37=FALSE,"",'График аннуитет.'!B37) -> 46631 | C38: =IF(malumot!$B$77=malumot!$C$77,'График дифференц'!C37,IF(malumot!$B$77=malumot!$D$77,'График аннуитет.'!C37)) -> 10111111 | D38: =IF(malumot!$B$77=malumot!$C$77,'График дифференц'!D37,IF(malumot!$B$77=malumot!$D$77,'График аннуитет.'!D37)) -> 1444444.4 | E38: =IF(malumot!$B$77=malumot!$C$77,'График дифференц'!E37,IF(malumot!$B$77=malumot!$D$77,'График аннуитет.'!E37)) -> 498630 | F38: =IF(malumot!$B$77=malumot!$C$77,'График дифференц'!F37,IF(malumot!$B$77=malumot!$D$77,'График аннуитет.'!F37)) -> 1943074.4
A39: =1+A38 -> 31 | B39: =IF('График аннуитет.'!B38=FALSE,"",'График аннуитет.'!B38) -> 46661 | C39: =IF(malumot!$B$77=malumot!$C$77,'График дифференц'!C38,IF(malumot!$B$77=malumot!$D$77,'График аннуитет.'!C38)) -> 8666666.8 | D39: =IF(malumot!$B$77=malumot!$C$77,'График дифференц'!D38,IF(malumot!$B$77=malumot!$D$77,'График аннуитет.'!D38)) -> 1444444.4 | E39: =IF(malumot!$B$77=malumot!$C$77,'График дифференц'!E38,IF(malumot!$B$77=malumot!$D$77,'График аннуитет.'!E38)) -> 427397.4 | F39: =IF(malumot!$B$77=malumot!$C$77,'График дифференц'!F38,IF(malumot!$B$77=malumot!$D$77,'График аннуитет.'!F38)) -> 1871841.8
A40: =1+A39 -> 32 | B40: =IF('График аннуитет.'!B39=FALSE,"",'График аннуитет.'!B39) -> 46692 | C40: =IF(malumot!$B$77=malumot!$C$77,'График дифференц'!C39,IF(malumot!$B$77=malumot!$D$77,'График аннуитет.'!C39)) -> 7222222.4 | D40: =IF(malumot!$B$77=malumot!$C$77,'График дифференц'!D39,IF(malumot!$B$77=malumot!$D$77,'График аннуитет.'!D39)) -> 1444444.4 | E40: =IF(malumot!$B$77=malumot!$C$77,'График дифференц'!E39,IF(malumot!$B$77=malumot!$D$77,'График аннуитет.'!E39)) -> 368036.65 | F40: =IF(malumot!$B$77=malumot!$C$77,'График дифференц'!F39,IF(malumot!$B$77=malumot!$D$77,'График аннуитет.'!F39)) -> 1812481.1
A41: =1+A40 -> 33 | B41: =IF('График аннуитет.'!B40=FALSE,"",'График аннуитет.'!B40) -> 46722 | C41: =IF(malumot!$B$77=malumot!$C$77,'График дифференц'!C40,IF(malumot!$B$77=malumot!$D$77,'График аннуитет.'!C40)) -> 5777777.9 | D41: =IF(malumot!$B$77=malumot!$C$77,'График дифференц'!D40,IF(malumot!$B$77=malumot!$D$77,'График аннуитет.'!D40)) -> 1444444.4 | E41: =IF(malumot!$B$77=malumot!$C$77,'График дифференц'!E40,IF(malumot!$B$77=malumot!$D$77,'График аннуитет.'!E40)) -> 284931.6 | F41: =IF(malumot!$B$77=malumot!$C$77,'График дифференц'!F40,IF(malumot!$B$77=malumot!$D$77,'График аннуитет.'!F40)) -> 1729376
A42: =1+A41 -> 34 | B42: =IF('График аннуитет.'!B41=FALSE,"",'График аннуитет.'!B41) -> 46755 | C42: =IF(malumot!$B$77=malumot!$C$77,'График дифференц'!C41,IF(malumot!$B$77=malumot!$D$77,'График аннуитет.'!C41)) -> 4333333.5 | D42: =IF(malumot!$B$77=malumot!$C$77,'График дифференц'!D41,IF(malumot!$B$77=malumot!$D$77,'График аннуитет.'!D41)) -> 1444444.4 | E42: =IF(malumot!$B$77=malumot!$C$77,'График дифференц'!E41,IF(malumot!$B$77=malumot!$D$77,'График аннуитет.'!E41)) -> 234426.39 | F42: =IF(malumot!$B$77=malumot!$C$77,'График дифференц'!F41,IF(malumot!$B$77=malumot!$D$77,'График аннуитет.'!F41)) -> 1678870.8
A43: =1+A42 -> 35 | B43: =IF('График аннуитет.'!B42=FALSE,"",'График аннуитет.'!B42) -> 46784 | C43: =IF(malumot!$B$77=malumot!$C$77,'График дифференц'!C42,IF(malumot!$B$77=malumot!$D$77,'График аннуитет.'!C42)) -> 2888889 | D43: =IF(malumot!$B$77=malumot!$C$77,'График дифференц'!D42,IF(malumot!$B$77=malumot!$D$77,'График аннуитет.'!D42)) -> 1444444.4 | E43: =IF(malumot!$B$77=malumot!$C$77,'График дифференц'!E42,IF(malumot!$B$77=malumot!$D$77,'График аннуитет.'!E42)) -> 137340.52 | F43: =IF(malumot!$B$77=malumot!$C$77,'График дифференц'!F42,IF(malumot!$B$77=malumot!$D$77,'График аннуитет.'!F42)) -> 1581785
A44: =1+A43 -> 36 | B44: =IF('График аннуитет.'!B43=FALSE,"",'График аннуитет.'!B43) -> 46836 | C44: =IF(malumot!$B$77=malumot!$C$77,'График дифференц'!C43,IF(malumot!$B$77=malumot!$D$77,'График аннуитет.'!C43)) -> 1444444.6 | D44: =IF(malumot!$B$77=malumot!$C$77,'График дифференц'!D43,IF(malumot!$B$77=malumot!$D$77,'График аннуитет.'!D43)) -> 1444444.6 | E44: =IF(malumot!$B$77=malumot!$C$77,'График дифференц'!E43,IF(malumot!$B$77=malumot!$D$77,'График аннуитет.'!E43)) -> 123132.88 | F44: =IF(malumot!$B$77=malumot!$C$77,'График дифференц'!F43,IF(malumot!$B$77=malumot!$D$77,'График аннуитет.'!F43)) -> 1567577.5
B45: JAMI | D45: =SUM(D9:D44) -> 52000000 | E45: =SUM(E9:E44) -> 46309512 | F45: =SUM(F9:F44) -> 98309512
A47: ="*"&malumot!C64&" bo‘yicha to‘lovlar to‘lov jadvalida ko‘rsatilmagan sanalarda to‘langan taqdirda, to‘lov summasi mikroqarz shartnomasining 2.2.-bandiga muvofiq "&malumot!B65&" qoldig‘iga hisoblangan foizlar summasiga o‘zgartiriladi." -> *Mikroqarz bo‘yicha to‘lovlar to‘lov jadvalida ko‘rsatilmagan sanalarda to‘langan taqdirda, to‘lov summasi mikroqarz shartnomasining 2.2.-bandiga muvofiq mikroqarz qoldig‘iga hisoblangan foizlar summasiga o‘zgartiriladi.
A49: «Mikromoliya tashkiloti » | D49: «Qarz oluvchi»
A51: =shartnoma!A117 -> «CLEVER MIKROMOLIYA TASHKILOTI» MChJ | D51: =shartnoma!B117 -> SHAYMARDANOVA SABOXAT YULDASHEVNA
A52: =shartnoma!A119 -> Manzil: Toshkent shahri, Olmazor tumani, Sagbon ko'chasi, 30 boshi berk, 6-uy | D52: =shartnoma!B119 -> Manzil: SURXONDAEYO VILOYATU JARQO'RG'ON TUMANI QORAYONTOQ MFY IBN SINO KO'CHASI 114-UY
A53: =shartnoma!A120 -> h/r: №20216000705068380001 | D53: =shartnoma!B121 -> Pasport: AC 1659096, SURXONDARYO VILOYATI JARQO'RG'ON TUMANI IIB tomonidan 21.02.2019 yilda berilgan
A54: =shartnoma!A121 -> MFO: №01042 в ATB “Kapitalbank” Sergeli filiali
A55: =shartnoma!A122 -> STIR: 306365847 | D55: =shartnoma!B122 -> Tel: 94-706-67-09 UY RAQAMI
A56: =shartnoma!A123 -> Tel: (78) 113 31 33 | D56: =shartnoma!B123 -> 93-763-00-67 MIJOZ
A57: =shartnoma!A124 -> (78) 113 31 34 | D57: =shartnoma!B124 -> 93-761-09-76 TURMUSH O'RTOG'I
D58: =IF(shartnoma!B125=0,"",shartnoma!B125)
B59: =malumot!A156 -> Surxondaryo filiali boshlig'i | D59: =shartnoma!B127 -> SHAYMARDANOVA S.Y. __________________
B60: =malumot!B156 -> A.PARDAYEV

Sheet ariza
C1: =malumot!B153&" Ijrochi direktori" -> «CLEVER MIKROMOLIYA TASHKILOTI» MChJ Ijrochi direktori
C2: N.Abduraximovga
C4: =malumot!B22&" manzilida istiqomat qiluvchi" -> SURXONDAEYO VILOYATU JARQO'RG'ON TUMANI QORAYONTOQ MFY IBN SINO KO'CHASI 114-UY manzilida istiqomat qiluvchi
C5: =malumot!B5&" tomonidan" -> SHAYMARDANOVA SABOXAT YULDASHEVNA tomonidan
C6: ="Pasport: "&malumot!B16&", "&malumot!B20 -> Pasport: AC 1659096, SURXONDARYO VILOYATI JARQO'RG'ON TUMANI IIB tomonidan 21.02.2019 yilda berilgan
A8: ARIZA
A9: =" Men, " & malumot!B5 & " sizdan " & malumot!B2 & " yildagi " & malumot!B1 & "-sonli kredit shartnomasiga asosan " & malumot!B75 & "(" & malumot!B76 & ")" & "so'm pul mablag'larini quyidagi rekvizitlar asosida o'tkazib berishingizni so'rayman: " -> Men, SHAYMARDANOVA SABOXAT YULDASHEVNA sizdan 24.03.2025 yildagi №659-SR-sonli kredit shartnomasiga asosan 52000000(ellik ikki million so'm)so'm pul mablag'larini quyidagi rekvizitlar asosida o'tkazib berishingizni so'rayman:
A10: =malumot!A92 -> Bank nomi: | B10: =malumot!B92 -> «Davr bank»
A11: =malumot!A93 -> H/r: | B11: =malumot!B93 -> 2312 0000 1000 0112 1001
A12: =malumot!A94 -> MFO: | B12: =malumot!B94 -> 01121
A13: =malumot!A95 -> STIR: | B13: =malumot!B95 -> 207212359
A14: =malumot!A96 -> Karta raqami: | B14: =malumot!B96 -> 6262 7300 8771 9516
A16: =malumot!B5 -> SHAYMARDANOVA SABOXAT YULDASHEVNA | D16: P________________
D17: (imzo)

Sheet muqova
B2: =malumot!B154 -> «CLEVER MIKROMOLIYA TASHKILOTI» MChJ
B12: =malumot!B5 -> SHAYMARDANOVA SABOXAT YULDASHEVNA
B19: =""&malumot!C64&" shartnoma "&malumot!B74&"" -> Mikroqarz shartnoma 24 mart 2025 y.dan №659-SR
B24: =" Foiz stavkasi: "&malumot!B85&"%" -> Foiz stavkasi: 60%
B25: =" "&malumot!C64&" muddati: "&malumot!B81&" oy" -> Mikroqarz muddati: 36 oy
B26: =" "&malumot!C64&" miqdori: "&FIXED(malumot!B75,2)&" so'm" -> Mikroqarz miqdori: 52 000 000,00 so'm
B40: ="Toshkent sh., "&malumot!B70&"" -> Toshkent sh., 24 mart 2025 y.

Sheet mijoz_anketasi
A1: MIJOZNING ANKETASI
A2: Anketa kredit menejeri tomonidan mijozning javoblarini kiritish orqali to'ldiriladi, kerak bo'lganda, Mijoz tomonidan tanlangan javob variantlarini belgilash orqali amalga oshiriladi
A3: 1. MIJOZ HAQIDA MA'LUMOTLAR:
A4: =xulosa!A4:E4 -> Mijozning to'liq ismi sharifi: SHAYMARDANOVA SABOXAT YULDASHEVNA
A5: =xulosa!A5:E5 -> Tug'ilgan sanasi: 09.11.1976 yil
A6: =xulosa!A6:E6 -> Pasport seriyasi AC 1659096 SURXONDARYO VILOYATI JARQO'RG'ON TUMANI IIB tomonidan 21.02.2019 yilda berilgan, amal qilish muddati - 20.02.2029 y.
A7: ="Fuqaroligi: "&malumot!B32&"" -> Fuqaroligi: O’zbekiston Respublikasi
A8: =xulosa!A7:E7 -> Ro‘yxatdan o‘tgan manzili: SURXONDARYO VILOYATI JARQO'RG'ON TUMANI QORAYONTOQ MFY IBN SINO KO'CHASI 114-UY, mo'ljal: QORAYONTOQ BEKAT
A9: =IF(malumot!B23="mos keladi"," ",mijoz_anketasi!A10:F10)
A10: ="Haqiqatdan yashash joy manzili: "&malumot!B28&"" -> Haqiqatdan yashash joy manzili: SURXONDARYO VILOYATI JARQO'RG'ON TUMANI QORAYONTOQ MFY IBN SINO KO'CHASI 114-UY
A11: =xulosa!A8:E8 -> Ish joyi: lavozimi Yakka tartibdagi tadbirkorda Yakka tartibdagi tadbirkor
A12: 2. Mijoz bilan ulanich uchun aloqa ma'lumotlari:
A13: ="Uy telefoni raqami: "&malumot!B40&"" -> Uy telefoni raqami: 94-706-67-09 UY RAQAMI
A14: ="Uyali telefon raqami: "&malumot!B41&"" -> Uyali telefon raqami: 93-763-00-67 MIJOZ
A15: ="Uyali telefon raqami: "&malumot!B42&"" -> Uyali telefon raqami: 93-761-09-76 TURMUSH O'RTOG'I
A16: ="Uyali telefon raqami: "&malumot!B42&"" -> Uyali telefon raqami: 93-761-09-76 TURMUSH O'RTOG'I
A17: ="Ish telefoni raqami: "&malumot!B43&"" -> Ish telefoni raqami:
A18: 3. MIJOZNING ISH JOYI HAQIDA MA'LUMOT:
A19: ="Muassasa nomlanishi:"&malumot!B58&"" -> Muassasa nomlanishi:Yakka tartibdagi tadbirkor
A20: ="Ro‘yxatdan o‘tish manzili:"&malumot!B50&"" -> Ro‘yxatdan o‘tish manzili:
A21: ="Lavozimi: "&malumot!B59&"" -> Lavozimi: Yakka tartibdagi tadbirkor
A22: 4. MIJOZNING OYLIK DAROMADLARI VA XARAJATLARI HAQIDA MA'LUMOT
A23: Daromad manbalari | B23: Mijoz | C23: Turmush o'rtog'i | D23: Boshqa oila a'zolari | E23: Xarajatlar | F23: Мiqdori
A24: ish haqi (asosiy ish) | B24: =malumot!B60 -> 14000000 | C24: 0 | D24: 0 | E24: uy-joy va kommunal xizmatlar uchun to'lov | F24: 700000
A25: ish haqi (o‘rindoshlik) | B25: 0 | C25: 0 | D25: 0 | E25: oilaviy xarajatlar | F25: 450000
A26: boshqa daromadlar | B26: =malumot!B61 -> 0 | C26: 0 | D26: 0 | E26: boshqa xarajatlar | F26: 500000
A27: JAMI | B27: =B24+B25+B26 -> 14000000 | C27: =SUM(C24:C26) -> 0 | D27: =SUM(D24:D26) -> 0 | F27: =F24+F25+F26 -> 1650000
A28: ="Men, "&malumot!B5&", ushbu anketada ko‘rsatilgan barcha ma'lumotlar anketa to'ldirilgan sanada to'g'ri va aniq ekanligini tasdiqlayman." -> Men, SHAYMARDANOVA SABOXAT YULDASHEVNA, ushbu anketada ko‘rsatilgan barcha ma'lumotlar anketa to'ldirilgan sanada to'g'ri va aniq ekanligini tasdiqlayman.
A29: ="Men, "&malumot!B5&", quyidagilarni tan olaman va roziman::" -> Men, SHAYMARDANOVA SABOXAT YULDASHEVNA, quyidagilarni tan olaman va roziman::
A30: ="1. Ushbu anketada ko‘rsatilgan har qanday ma’lumot "&malumot!B153&", uning xodimlari va huquqiy vorislari tomonidan istalgan manbaa va ma’lumotlardan foydalangan holda istalgan vaqtda tekshirilishi va qayta tekshirilishi mumkin." -> 1. Ushbu anketada ko‘rsatilgan har qanday ma’lumot «CLEVER MIKROMOLIYA TASHKILOTI» MChJ, uning xodimlari va huquqiy vorislari tomonidan istalgan manbaa va ma’lumotlardan foydalangan holda istalgan vaqtda tekshirilishi va qayta tekshirilishi mumkin.
A31: ="2. Mazkur anketaning "&malumot!B153&" tomonidan qabul qilinishi “Clever Mikromoliya Tashkiloti” MChJ tomonidan menga "&malumot!B65&" berish majburiyatini yuklamaydi." -> 2. Mazkur anketaning «CLEVER MIKROMOLIYA TASHKILOTI» MChJ tomonidan qabul qilinishi “Clever Mikromoliya Tashkiloti” MChJ tomonidan menga mikroqarz berish majburiyatini yuklamaydi.
A32: Men, _________________________________________________________________ (to'liq ismi sharifi), ushbu anketadagi barcha ma'lumotlar anketa to'ldirilgan sanada to'g'ri ekanligini tasdiqlayman va ushbu anketaning 1- va 2-bandlarini tan olaman va ularga rozilik bildiraman. Mazkur anketaning 4-bo'limida ko'rsatilgan daromadlarim haqidagi ma'lumotlarni qabul qilishingizni va moliyaviy tahlilda foydalanishingizni so’rayman.
A34: Mijozning to'liq ismi sharifi | D34: Sana | E34: Imzo
D35: =malumot!B2 -> 24.03.2025

Sheet majburiyatnoma
A3: MAJBURIYATNOMA
A4: =" Men, fuqaro "&malumot!B5&" "&malumot!B155&" bilan "&malumot!B69&" sanasidagi "&malumot!B66&"-sonli shartnomaning garov ta'minoti sifatida taqdim etilayotgan mulk "&malumot!B131&" rusumli avtotransport vositasini qonunga xilof ravishda o‘zlashtirmaslikka, yashirmaslikka, nobud qilmaslikka yoki unga shikast yetkazmaslik majburiyatini olaman." -> Men, fuqaro SHAYMARDANOVA SABOXAT YULDASHEVNA «CLEVER MIKROMOLIYA TASHKILOTI» MChJ bilan 24 mart 2025 y. sanasidagi №659-SR-sonli shartnomaning garov ta'minoti sifatida taqdim etilayotgan mulk LADA VESTA rusumli avtotransport vositasini qonunga xilof ravishda o‘zlashtirmaslikka, yashirmaslikka, nobud qilmaslikka yoki unga shikast yetkazmaslik majburiyatini olaman.
A5: Ushbu majburiyatlarimni bajarmagan taqdirimda O'zbekiston Respublikasi jinoyat kodeksining 233-moddasi talablari asosida javobgarlik tog'risida ogohlantrildim.
A7: =malumot!B5 -> SHAYMARDANOVA SABOXAT YULDASHEVNA | B7: Imzo_____________
A11: ="sana: "&TEXT(malumot!B2,"ДД.ММ.ГГГГ")&" y." -> sana: 24.03.2025 y.

Sheet Анкета 2
A2: ANKETA
E3: =malumot!B68 -> 24 mart 2025 y.
A5: Mijozning to'liq ismi sharifi | C5: =malumot!B8 -> SHAYMARDANOVA SABOXAT YULDASHEVNA
A7: Siz ommaviy mansabdor shaxsmisiz? | D7: Ha
D8: Yo'q
A9: Yaqin qarindoshlaringiz orasida ommaviy mansabdor shaxslar bormi? | D9: Ha
D10: Yo'q
A11: Do'stlaringiz yoki yaqinlaringizdan birontasi ommaviy mansabdor shaxsmi? | D11: Ha
D12: Yo'q
A13: Yuqoridagi savollardan biriga «Ha» deb javob bergan bo'lsangiz, javobingizni qisqacha tushuntirib bering:
A18: Siz bank amaliyotlarini amalga oshirishda uchinchi shaxsning manfaatlarini ifodalaysizmi? | D18: Ha
D19: Yo'q
A20: Agar oldingi savolga «HA» deb javob bergan bo'lsangiz, bank operatsiyalarini bajarich uchun ishonchnomangiz bormi? | D20: Ha
D21: Yo'q
A23: Agar oldingi savolga «YO'Q» deb javob bergan bo'lsangiz, javobingizni qisqacha tushuntirib bering:
A28: Ommaviy mansabdor shaxslar — doimiy, vaqtincha yoki maxsus vakolatli organ tomonidan tayinlangan yoki saylangan, tashkiliy-maʼmuriy funktsiyalarni bajaruvchi hamda xorijiy davlatning qonun chiqaruvchi, ijro etuvchi, maʼmuriy yoki sud organida yoxud xalqaro tashkilotda yuridik ahamiyatga molik harakatlarni amalga oshirishga vakolatli shaxslar, shuningdek xorijiy davlatlar korxonalarining yuqori martabali rahbarlari, taniqli siyosatchilar va xorijiy davlatlar siyosiy partiyalarining taniqli a'zolari.
A30: Anketadagi barcha ma'lumotlar to'g'ri, agar o'zgarishlar bo'lsa, men bu haqida xabardor qilish majburiyatini o'z zimmamga olaman.
A33: =C5 -> SHAYMARDANOVA SABOXAT YULDASHEVNA

Sheet Кредитная заявка
C1: =""&malumot!B153&"ning "&malumot!A156&"" -> «CLEVER MIKROMOLIYA TASHKILOTI» MChJning Surxondaryo filiali boshlig'i
D2: =""&malumot!B156&"ga" -> A.PARDAYEVga
A4: =""&malumot!C64&" olish uchun Ariza" -> Mikroqarz olish uchun Ariza
A6: =""&malumot!B28&".-da yashovchi O‘zbekiston Respublikasi fuqarosi "&malumot!B8&"dan. " -> SURXONDARYO VILOYATI JARQO'RG'ON TUMANI QORAYONTOQ MFY IBN SINO KO'CHASI 114-UY.-da yashovchi O‘zbekiston Respublikasi fuqarosi SHAYMARDANOVA SABOXAT YULDASHEVNAdan.
A7: ="Tug'ilgan kuni: "&malumot!B15&"" -> Tug'ilgan kuni: 09.11.1976 yil
A8: ="Pasport seriyasi: "&malumot!B16&" "&malumot!B20&"" -> Pasport seriyasi: AC 1659096 SURXONDARYO VILOYATI JARQO'RG'ON TUMANI IIB tomonidan 21.02.2019 yilda berilgan
A9: ="Asosiy ish joyi : "&malumot!B58&"" -> Asosiy ish joyi : Yakka tartibdagi tadbirkor
A10: ="Lavozimi: "&malumot!B59&"" -> Lavozimi: Yakka tartibdagi tadbirkor
A11: ="O’rtacha oylik daromadi: "&FIXED(malumot!B60,2)&" so'm." -> O’rtacha oylik daromadi: 14 000 000,00 so'm.
A12: ="Menga quyidagi shartlarda "&malumot!B65&" berishingizni so’rayman:" -> Menga quyidagi shartlarda mikroqarz berishingizni so’rayman:
A13: =""&malumot!C64&" summasi: "&FIXED(malumot!B75,2)&" ("&malumot!B76&") so'm." -> Mikroqarz summasi: 52 000 000,00 (ellik ikki million so'm) so'm.
A14: =""&malumot!C64&" muddati: "&malumot!B81&" ("&malumot!B82&") oy." -> Mikroqarz muddati: 36 (o'ttiz olti) oy.
A15: =""&malumot!C64&"dan foydalanganlik uchun foiz stavkasi: yillik "&malumot!B85&"% ("&malumot!B86&") foiz" -> Mikroqarzdan foydalanganlik uchun foiz stavkasi: yillik 60% (Oltmish) foiz
A16: =""&malumot!C64&" bo'yicha asosiy qarz va foizlarni to'lash:" -> Mikroqarz bo'yicha asosiy qarz va foizlarni to'lash:
A17: =" - "&malumot!B65&" shartnomasi bo'yicha har oy differensial to'lovlari amalga oshiriladi" -> - mikroqarz shartnomasi bo'yicha har oy differensial to'lovlari amalga oshiriladi
A18: =" - "&malumot!B65&" shartnomasi bo'yicha har oy annuitet to'lovlari amalga oshiriladi" -> - mikroqarz shartnomasi bo'yicha har oy annuitet to'lovlari amalga oshiriladi
A19: =IF(malumot!B77=malumot!C77,'Кредитная заявка'!A17:D17,IF(malumot!B77=malumot!D77,'Кредитная заявка'!A18:D18)) -> - mikroqarz shartnomasi bo'yicha har oy differensial to'lovlari amalga oshiriladi
A20: =IF(DAY(malumot!E67)<15," "," Oxirgi yakuniy to'lov "&malumot!B65&" shartnomasi tuzilgan kundan boshlab oxirgi oyning oxirgi kunida amalga oshiriladi") -> Oxirgi yakuniy to'lov mikroqarz shartnomasi tuzilgan kundan boshlab oxirgi oyning oxirgi kunida amalga oshiriladi
A21: =""&malumot!C64&" ta’minoti::" -> Mikroqarz ta’minoti::
A22: =IF(malumot!B109="Avtotransport",A26,A23) -> Egalik huquqi XUDOYKULOV ALMURAT KURBONAZAROVICHga tegishli bo'lgan garovga olingan avtomobil markasi LADA VESTA, rangi - SARIQ JELTO- ORANJEVIY, ishlab chiqarilgan yili - 2019, davlat raqam belgisi 75M497WA, kuzov turi - YENGIL SEDAN, kuzov raqami XTAGFL110KY258232, dvigatel raqami 3977458, shassi raqami - RAKAMSIZ
A23: =IF(malumot!B98=malumot!C98,A25,IF(malumot!B98=malumot!D98,A24,0)) -> Egalik huquqi 0ga tegishli bo'lgan umumiy maydoni - 72,13 va yashash maydoni - 37,39 3 - xonali yakka tartibdagi uy-joy, SAMARQAND VILOYATI TAYLOQ TUMANI CHAROG'BON MFY YANGI TAYLOQ QISHLOG'I 6 TURAR JOY 12 QAVAT 58 XONADON
A24: =" - Navbatdagi garov (ipoteka) Egalik huquqi asosida "&malumot!C123&"ga "&malumot!C132&", umumiy maydoni - "&malumot!C136&" va yashash maydoni - "&malumot!C139&", manzili: "&malumot!C129&"." -> - Navbatdagi garov (ipoteka) Egalik huquqi asosida 0ga 3 - xonali yakka tartibdagi uy-joy, umumiy maydoni - 72,13 va yashash maydoni - 37,39, manzili: SAMARQAND VILOYATI TAYLOQ TUMANI CHAROG'BON MFY YANGI TAYLOQ QISHLOG'I 6 TURAR JOY 12 QAVAT 58 XONADON.
A25: =" Egalik huquqi "&malumot!C123&"ga tegishli bo'lgan umumiy maydoni - "&malumot!C136&" va yashash maydoni - "&malumot!C139&" "&malumot!C132&", "&malumot!C129&" " -> Egalik huquqi 0ga tegishli bo'lgan umumiy maydoni - 72,13 va yashash maydoni - 37,39 3 - xonali yakka tartibdagi uy-joy, SAMARQAND VILOYATI TAYLOQ TUMANI CHAROG'BON MFY YANGI TAYLOQ QISHLOG'I 6 TURAR JOY 12 QAVAT 58 XONADON
A26: =IF(malumot!B98=malumot!C98,'Кредитная заявка'!A28:D28,IF(malumot!B98=malumot!D98,'Кредитная заявка'!A27:D27,0)) -> Egalik huquqi XUDOYKULOV ALMURAT KURBONAZAROVICHga tegishli bo'lgan garovga olingan avtomobil markasi LADA VESTA, rangi - SARIQ JELTO- ORANJEVIY, ishlab chiqarilgan yili - 2019, davlat raqam belgisi 75M497WA, kuzov turi - YENGIL SEDAN, kuzov raqami XTAGFL110KY258232, dvigatel raqami 3977458, shassi raqami - RAKAMSIZ
A27: =" Egalik huquqi "&malumot!B123&"ga tegishli bo'lgan "&malumot!B131&", "&malumot!B139&", davlat raqam belgisi "&malumot!B132&", "&malumot!B133&", "&malumot!B136&" avtotransport vositasi " -> Egalik huquqi XUDOYKULOV ALMURAT KURBONAZAROVICHga tegishli bo'lgan LADA VESTA, rangi - SARIQ JELTO- ORANJEVIY, ishlab chiqarilgan yili - 2019, davlat raqam belgisi 75M497WA, kuzov turi - YENGIL SEDAN, kuzov raqami XTAGFL110KY258232, dvigatel raqami 3977458, shassi raqami - RAKAMSIZ avtotransport vositasi
A28: =" Egalik huquqi "&malumot!B123&"ga tegishli bo'lgan garovga olingan avtomobil markasi "&malumot!B131&", "&malumot!B139&", davlat raqam belgisi "&malumot!B132&", "&malumot!B133&", "&malumot!B136&"" -> Egalik huquqi XUDOYKULOV ALMURAT KURBONAZAROVICHga tegishli bo'lgan garovga olingan avtomobil markasi LADA VESTA, rangi - SARIQ JELTO- ORANJEVIY, ishlab chiqarilgan yili - 2019, davlat raqam belgisi 75M497WA, kuzov turi - YENGIL SEDAN, kuzov raqami XTAGFL110KY258232, dvigatel raqami 3977458, shassi raqami - RAKAMSIZ
A30: ="Mazkur ariza bilan "&malumot!B153&"ga men va soʻralayotgan "&malumot!B65&" boʻyicha barcha zarur maʼlumotlarni quyida ko’rsatilgan tashkilotlarga taqdim etish va olishga roziligimni bildirib, ushbu amaliyotlarni o’tkazish uchun huquq beraman:" -> Mazkur ariza bilan «CLEVER MIKROMOLIYA TASHKILOTI» MChJga men va soʻralayotgan mikroqarz boʻyicha barcha zarur maʼlumotlarni quyida ko’rsatilgan tashkilotlarga taqdim etish va olishga roziligimni bildirib, ushbu amaliyotlarni o’tkazish uchun huquq beraman:
A31: □ O‘zbekiston Respublikasi Markaziy banki huzuridagi kredit axborotining davlat reestri;
A32: □ Kredit-axborot tahliliy markazi «O‘zbekiston Respublikasi kredit byurosi» MChJ;
A33: □ Garov reestri taqdim etilgan garov mulki haqida.
A34: ="Ariza berilgan sana: "&TEXT(malumot!B2,"ДД.ММ.ГГГГ")&"y." -> Ariza berilgan sana: 24.03.2025y.
A36: Ariza berilgan kuniga barcha ma'lumotlar ishonchligini tasdiqlab, ushbu arizani imzolayman
A39: =malumot!B5 -> SHAYMARDANOVA SABOXAT YULDASHEVNA | D39: P________________
D40: (imzo)

Sheet заявление залогодателя
B6: =malumot!B154 -> «CLEVER MIKROMOLIYA TASHKILOTI» MChJ
B7: =""&malumot!A156&" "&malumot!B156&"ga" -> Surxondaryo filiali boshlig'i A.PARDAYEVga
B8: =""&malumot!B117&"dan" -> XUDOYKULOV ALMURAT KURBONAZAROVICHdan
B9: =malumot!B117 -> XUDOYKULOV ALMURAT KURBONAZAROVICH
B10: =malumot!C117 -> 0
B11: dan
A13: =IF(malumot!B109="Avtotransport",A14,A15) -> SHAYMARDANOVA SABOXAT YULDASHEVNA tomonidan so’ralayotgan 36 (o'ttiz olti) oy muddatga, 52 000 000 (ellik ikki million so'm) miqdoridagi mikroqarzning ta’minoti sifatida menga mulk huquqi asosida tegishli bo’lgan LADA VESTA, kuzov turi - YENGIL SEDAN, kuzov raqami XTAGFL110KY258232, dvigatel raqami 3977458, shassi raqami - RAKAMSIZ, rangi - SARIQ JELTO- ORANJEVIY, ishlab chiqarilgan yili - 2019, avtotransport vositasini qabul qilishingizni so’rayman:
A14: =""&malumot!B12&" tomonidan so’ralayotgan "&malumot!B81&" ("&malumot!B82&") oy muddatga, "&FIXED(malumot!B75,0)&" ("&malumot!B76&") miqdoridagi "&malumot!B65&"ning ta’minoti sifatida menga mulk huquqi asosida tegishli bo’lgan "&malumot!B131&", "&malumot!B133&", "&malumot!B136&", "&malumot!B139&", avtotransport vositasini qabul qilishingizni so’rayman:" -> SHAYMARDANOVA SABOXAT YULDASHEVNA tomonidan so’ralayotgan 36 (o'ttiz olti) oy muddatga, 52 000 000 (ellik ikki million so'm) miqdoridagi mikroqarzning ta’minoti sifatida menga mulk huquqi asosida tegishli bo’lgan LADA VESTA, kuzov turi - YENGIL SEDAN, kuzov raqami XTAGFL110KY258232, dvigatel raqami 3977458, shassi raqami - RAKAMSIZ, rangi - SARIQ JELTO- ORANJEVIY, ishlab chiqarilgan yili - 2019, avtotransport vositasini qabul qilishingizni so’rayman:
A15: =""&malumot!B12&" tomonidan so’ralayotgan "&malumot!B81&" ("&malumot!B82&") oy muddatga, "&FIXED(malumot!B75,0)&" ("&malumot!B76&") miqdoridagi "&malumot!B65&"ning ta’minoti sifatida menga mulk huquqi asosida tegishli bo’lgan "&malumot!C132&", umumiy maydoni "&malumot!C136&" va yashash maydoni "&malumot!C139&" "&malumot!C129&" manzilda joylashgan ko'chmas mulkni qabul qilishingizni so’rayman:" -> SHAYMARDANOVA SABOXAT YULDASHEVNA tomonidan so’ralayotgan 36 (o'ttiz olti) oy muddatga, 52 000 000 (ellik ikki million so'm) miqdoridagi mikroqarzning ta’minoti sifatida menga mulk huquqi asosida tegishli bo’lgan 3 - xonali yakka tartibdagi uy-joy, umumiy maydoni 72,13 va yashash maydoni 37,39 SAMARQAND VILOYATI TAYLOQ TUMANI CHAROG'BON MFY YANGI TAYLOQ QISHLOG'I 6 TURAR JOY 12 QAVAT 58 XONADON manzilda joylashgan ko'chmas mulkni qabul qilishingizni so’rayman:
B18: Sana:
A19: =IF(malumot!B100=malumot!C100,malumot!B118,malumot!B7) -> XUDOYKULOV A.K. | B19: =malumot!B2 -> 24.03.2025
A20: =IF(malumot!B100=malumot!D100,CONCATENATE(A24," ",A28,A22),"")
A22: =" xususiy faoliyat ko'rsatuvchi notarius tomonidan "&malumot!B104&" "&malumot!B105&" berilgan ishonchnomaga asosan " -> xususiy faoliyat ko'rsatuvchi notarius tomonidan berilgan ishonchnomaga asosan
A24: ="№"&malumot!B106& "" -> №
A25: =malumot!B108 -> 00.01.1900
A26: =TEXT(A25,"ДД.ММ.ГГГГ") -> 00.01.1900
A27: sanasidan
A28: =CONCATENATE(A26,A27) -> 00.01.1900 sanasidan

Sheet Письмо
A2: Исх №15/06-001
A3: от 15.06.2021 г.
E6: В НОТАРИАЛЬНУЮ
E7: КОНТОРУ Г.САМАРКАНД
A9: =" Между ООО «Clever Mikrokredit Tashkiloti» и "&malumot!B5&" (паспорт: "&malumot!B16&" "&malumot!B20&") заключен договор микрозайма "&malumot!B74&", на сумму "&FIXED(malumot!B75)&" ("&malumot!B76&") сум, сроком на "&malumot!B81&" ("&malumot!B82&") месяцев. В качестве своевременного исполнения обязательств по договору Микрозайма "&malumot!B74&" планирует предоставить нижеследующее "&IF(malumot!B109=malumot!C109,"автотранспортного средство марки "&malumot!B131&" принадлежащее на правах собственности "&malumot!B123&"","недвижимого имущества в виде "&malumot!C132&", общей площадью - "&malumot!C136&" и жилой площадью - "&malumot!C139&", расположенного по адресу: "&malumot!C129&", принадлежащее на правах собственности "&malumot!C123&".") -> Между ООО «Clever Mikrokredit Tashkiloti» и SHAYMARDANOVA SABOXAT YULDASHEVNA (паспорт: AC 1659096 SURXONDARYO VILOYATI JARQO'RG'ON TUMANI IIB tomonidan 21.02.2019 yilda berilgan) заключен договор микрозайма 24 mart 2025 y.dan №659-SR, на сумму 52 000 000,00 (ellik ikki million so'm) сум, сроком на 36 (o'ttiz olti) месяцев. В качестве своевременного исполнения обязательств по договору Микрозайма 24 mart 2025 y.dan №659-SR планирует предоставить нижеследующее автотранспортного средство марки LADA VESTA принадлежащее на правах собственности XUDOYKULOV ALMURAT KURBONAZAROVICH
A11: =buyruq!A19 -> Nomi | B11: =buyruq!B19 -> Kuzov turi va kuzov raqami* | C11: =buyruq!C19 -> Dvigatel va shassi raqami* | D11: =buyruq!D19 -> Ishlab chiqarilgan yili va rangi* | E11: =buyruq!E19 -> Kelishilgan garov qiymati, so'm
A12: =buyruq!A20 -> LADA VESTA | B12: =buyruq!B20 -> kuzov turi - YENGIL SEDAN, kuzov raqami XTAGFL110KY258232 | C12: =buyruq!C20 -> dvigatel raqami 3977458, shassi raqami - RAKAMSIZ | D12: =buyruq!D20 -> rangi - SARIQ JELTO- ORANJEVIY, ishlab chiqarilgan yili - 2019 | E12: =buyruq!E20 -> 78 000 000,00 (yetmish sakkiz million so'm)
A13: =buyruq!A21:E21 -> -* avtotransport egasi: XUDOYKULOV ALMURAT KURBONAZAROVICH
A14: =buyruq!A22:E22 -> -* texnik pasport: AAG 3367573 24.01.2024 y.
A15: =buyruq!A23:E23 -> -* roʻyxatdan oʻtgan manzili/garaj manzili: SURXONDARYO VILOYATI JARQO'RG'ON TUMANI OQQURG'ON QFY QORAYONTOQ MFY IBN SINO KO'CHASI 114-UY
A16: =buyruq!A24:E24 -> -* davlat raqami: 75M497WA
A19: =dalolatnoma!A32 -> Наименование | B19: =dalolatnoma!B32 -> Полезная площадь | C19: =dalolatnoma!C32 -> Жилая площадь | D19: =dalolatnoma!D32 -> Общая площадь | E19: =dalolatnoma!E32 -> Согласованная залоговая стоимость, сум
A20: =dalolatnoma!A33 -> #REF! | B20: =dalolatnoma!B33 -> #REF! | C20: =dalolatnoma!C33 -> #REF! | D20: =dalolatnoma!D33 -> #REF! | E20: =""&FIXED(malumot!C142,2)&" ("&malumot!C143&")" -> 78 000 000,00 (yetmish sakkiz million so'm)
A21: =dalolatnoma!A34 -> 0 | B21: =dalolatnoma!B34 -> 0 | C21: =dalolatnoma!C34 -> 0 | D21: =dalolatnoma!D34 -> 0
A22: =dalolatnoma!A35 -> #REF! | B22: =dalolatnoma!B35 -> #REF! | C22: =dalolatnoma!C35 -> #REF! | D22: =dalolatnoma!D35 -> #REF!
A23: =dalolatnoma!A36 -> #REF! | B23: =dalolatnoma!B36 -> #REF! | C23: =dalolatnoma!C36 -> #REF! | D23: =dalolatnoma!D36 -> #REF!
A24: =dalolatnoma!A37 -> #REF! | B24: =dalolatnoma!B37 -> #REF! | C24: =dalolatnoma!C37 -> #REF! | D24: =dalolatnoma!D37 -> #REF!
A25: =dalolatnoma!A38 -> #REF! | B25: =dalolatnoma!B38 -> #REF! | C25: =dalolatnoma!C38 -> #REF! | D25: =dalolatnoma!D38 -> #REF!
A26: =dalolatnoma!A39 -> #REF! | B26: =dalolatnoma!B39 -> #REF! | C26: =dalolatnoma!C39 -> #REF! | D26: =dalolatnoma!D39 -> #REF!
A27: =dalolatnoma!A40 -> #REF! | B27: =dalolatnoma!B40 -> #REF! | C27: =dalolatnoma!C40 -> #REF! | D27: =dalolatnoma!D40 -> #REF!
A28: =dalolatnoma!A41 -> #REF! | B28: =dalolatnoma!B41 -> #REF! | C28: =dalolatnoma!C41 -> #REF! | D28: =dalolatnoma!D41 -> #REF!
A29: =dalolatnoma!A42 -> #REF! | B29: =dalolatnoma!B42 -> #REF! | C29: =dalolatnoma!C42 -> #REF! | D29: =dalolatnoma!D42 -> #REF!
A30: =dalolatnoma!A43 -> #REF! | B30: =dalolatnoma!B43 -> #REF! | C30: =dalolatnoma!C43 -> #REF! | D30: =dalolatnoma!D43 -> #REF!
A31: =dalolatnoma!A44 -> #REF! | B31: =dalolatnoma!B44 -> #REF! | C31: =dalolatnoma!C44 -> #REF! | D31: =dalolatnoma!D44 -> #REF! | E31: =dalolatnoma!E44 -> 78 000 000,00
A32: =_xlfn.SINGLE(dalolatnoma!#REF!) -> #REF!
A33: =_xlfn.SINGLE(dalolatnoma!#REF!) -> #REF!
A34: =_xlfn.SINGLE(dalolatnoma!#REF!) -> #REF!
A35: =_xlfn.SINGLE(dalolatnoma!#REF!) -> #REF!
A37: =dalolatnoma!A46:E46 -> “Birinchi talabga ko‘ra, yuqoridagi avtomobil Mikrokredit shartnomasi bo‘yicha garovga qo‘yilgan edi:: - №5 от 11 yanvar 2021 г., заключенного с ООО «Clever Mikrokredit Tashkiloti» и TULYAGANOV XODJIAKBAR IRGASHEVICH, по согласованной залоговой стоимость - 15 000 000,00 (on besh million) сум. - №386 от 6 noyabr 2019 г., заключенного с ООО «Clever Mikrokredit Tashkiloti» и YUNUSOVA ZALOXAT MIRSULTANOVNA, по согласованной залоговой стоимость - 15 000 000,00 (on besh million) сум. - №33 от 21 yanvar 2021 г., заключенного с ООО «Clever Mikrokredit Tashkiloti» и YUNUSOVA ZALOXAT MIRSULTANOVNA, по согласованной залоговой стоимость - 15 000 000,00 (on besh million) сум. 0 0 0 0 0 0 0 0 0 0 0 0 0 0 0 0 0
A38: =dalolatnoma!A47:E47 -> Shu bilan birga, garov predmetining kelishilgan garov qiymati deganda ushbu mulk garov sifatida taqdim etilgan/qabul qilingan qiymati tushuniladi.
A39: ="Учитывая вышеизложенное, ООО «Clever Mikrokredit Tashkiloti» даёт свое согласие на предоставление вышеуказанного имущества в виде последующего залога по договору микрозайма "&malumot!B74&", при сохранении запрета." -> Учитывая вышеизложенное, ООО «Clever Mikrokredit Tashkiloti» даёт свое согласие на предоставление вышеуказанного имущества в виде последующего залога по договору микрозайма 24 mart 2025 y.dan №659-SR, при сохранении запрета.
A41: С уважением,
A43: Исполнительный директора
A44: ООО «Clever Mikrokredit Tashkiloti» | E44: Г.В. Тян

Sheet  Акт мониторинга 1
A2: =""&" "&malumot!B74&"-sonli "&" "&malumot!C64&" shartnomasi bo‘yicha garovga qo‘yilgan mol-mulkni tekshirish bo’yicha "&malumot!B5&" bilan tuzilgan dalolatnomasi" -> 24 mart 2025 y.dan №659-SR-sonli Mikroqarz shartnomasi bo‘yicha garovga qo‘yilgan mol-mulkni tekshirish bo’yicha SHAYMARDANOVA SABOXAT YULDASHEVNA bilan tuzilgan dalolatnomasi
A5: Toshkent shahri | H5: =TEXT(malumot!D2,"ДД.ММ.ГГГГ") -> 20.09.2025
A7: =" Men, “СLEVER MIKROMOLYA TASHKILOTI” "&malumot!A156&"i "&malumot!B156&", jismoniy shaxs "&" "&malumot!B5&" "&" "&malumot!B74&"-sonli "&malumot!B65&" shartnomasi bo‘yicha garovga qo‘yilgan mol-mulkni ko‘zdan kechirdim" -> Men, “СLEVER MIKROMOLYA TASHKILOTI” Surxondaryo filiali boshlig'ii A.PARDAYEV, jismoniy shaxs SHAYMARDANOVA SABOXAT YULDASHEVNA 24 mart 2025 y.dan №659-SR-sonli mikroqarz shartnomasi bo‘yicha garovga qo‘yilgan mol-mulkni ko‘zdan kechirdim
A8: Garov sifatida quyida ko’rsatilgan mulk qabul qilinadi:
A9: =dalolatnoma!A20 -> Nomi | C9: =dalolatnoma!B20 -> Kuzov turi va kuzov raqami* | E9: =dalolatnoma!D20 -> Dvigatel va shassi raqami* | G9: =dalolatnoma!E20 -> Ishlab chiqarilgan yili va rangi**
A10: =dalolatnoma!A21 -> LADA VESTA | C10: =dalolatnoma!B21 -> kuzov turi - YENGIL SEDAN, kuzov raqami XTAGFL110KY258232 | E10: =dalolatnoma!D21 -> dvigatel raqami 3977458, shassi raqami - RAKAMSIZ | G10: =dalolatnoma!E21 -> rangi - SARIQ JELTO- ORANJEVIY, ishlab chiqarilgan yili - 2019
A11: =dalolatnoma!A22:E22 -> -* avtotransport egasi: XUDOYKULOV ALMURAT KURBONAZAROVICH
A12: =dalolatnoma!A23:E23 -> -* texnik pasport: AAG 3367573 24.01.2024 y.
A13: =dalolatnoma!A24:E24 -> -* roʻyxatdan oʻtgan manzili/garaj manzili: SURXONDARYO VILOYATI JARQO'RG'ON TUMANI OQQURG'ON QFY QORAYONTOQ MFY IBN SINO KO'CHASI 114-UY
A14: =dalolatnoma!A25:E25 -> -* davlat raqami: 75M497WA
A15: =+"Shu bilan birga, yuqoridagi mulkning kelishilgan garov qiymati "&dalolatnoma!E30 -> Shu bilan birga, yuqoridagi mulkning kelishilgan garov qiymati 78 000 000,00 (yetmish sakkiz million so'm)
A17: Garovga qo‘yilgan mol-mulkni ko‘zdan kechirish natijasida ushbu mulk qoniqarli holatda ekanligi ma’lum bo‘ldi va bu haqida mazkur dalolatnoma tuzildi
A22: =malumot!A156 -> Surxondaryo filiali boshlig'i | H22: =malumot!B156 -> A.PARDAYEV
A24: Monitoring bo'limi boshlig'i | H24: =malumot!B166 -> B. Jumanazarov
A26: Jismoniy shaxs, qarzdor | H26: =malumot!B7 -> SHAYMARDANOVA S.Y.

Sheet  Акт мониторинга 2
A2: =""&" "&malumot!B74&"-sonli "&" "&malumot!C64&" shartnomasi bo‘yicha garovga qo‘yilgan mol-mulkni tekshirish bo’yicha "&malumot!B5&" bilan tuzilgan dalolatnomasi" -> 24 mart 2025 y.dan №659-SR-sonli Mikroqarz shartnomasi bo‘yicha garovga qo‘yilgan mol-mulkni tekshirish bo’yicha SHAYMARDANOVA SABOXAT YULDASHEVNA bilan tuzilgan dalolatnomasi
A5: Toshkent shahri | H5: =TEXT(+malumot!B2+360,"ДД.ММ.ГГГГ") -> 19.03.2026
A7: =" Men, "&malumot!B153&" "&malumot!A156&"i "&malumot!B156&", jismoniy shaxs "&" "&malumot!B5&" "&" "&malumot!B74&"-sonli "&malumot!C64&" shartnomasi bo‘yicha garovga qo‘yilgan mol-mulkni ko‘zdan kechirdim" -> Men, «CLEVER MIKROMOLIYA TASHKILOTI» MChJ Surxondaryo filiali boshlig'ii A.PARDAYEV, jismoniy shaxs SHAYMARDANOVA SABOXAT YULDASHEVNA 24 mart 2025 y.dan №659-SR-sonli Mikroqarz shartnomasi bo‘yicha garovga qo‘yilgan mol-mulkni ko‘zdan kechirdim
A8: Garov sifatida quyida ko’rsatilgan mulk qabul qilinadi:
A9: =' Акт мониторинга 1'!A9 -> Nomi | C9: =' Акт мониторинга 1'!C9 -> Kuzov turi va kuzov raqami* | E9: =' Акт мониторинга 1'!E9 -> Dvigatel va shassi raqami* | G9: =' Акт мониторинга 1'!G9 -> Ishlab chiqarilgan yili va rangi**
A10: =' Акт мониторинга 1'!A10 -> LADA VESTA | C10: =' Акт мониторинга 1'!C10 -> kuzov turi - YENGIL SEDAN, kuzov raqami XTAGFL110KY258232 | E10: =' Акт мониторинга 1'!E10 -> dvigatel raqami 3977458, shassi raqami - RAKAMSIZ | G10: =' Акт мониторинга 1'!G10 -> rangi - SARIQ JELTO- ORANJEVIY, ishlab chiqarilgan yili - 2019
A11: =dalolatnoma!A22:E22 -> -* avtotransport egasi: XUDOYKULOV ALMURAT KURBONAZAROVICH
A12: =dalolatnoma!A23:E23 -> -* texnik pasport: AAG 3367573 24.01.2024 y.
A13: =dalolatnoma!A24:E24 -> -* roʻyxatdan oʻtgan manzili/garaj manzili: SURXONDARYO VILOYATI JARQO'RG'ON TUMANI OQQURG'ON QFY QORAYONTOQ MFY IBN SINO KO'CHASI 114-UY
A14: =dalolatnoma!A25:E25 -> -* davlat raqami: 75M497WA
A15: =+"Shu bilan birga, yuqoridagi mulkning kelishilgan garov qiymati "&dalolatnoma!E30 -> Shu bilan birga, yuqoridagi mulkning kelishilgan garov qiymati 78 000 000,00 (yetmish sakkiz million so'm)
A17: Garovga qo‘yilgan mol-mulkni ko‘zdan kechirish natijasida ushbu mulk qoniqarli holatda ekanligi ma’lum bo‘ldi va bu haqida mazkur dalolatnoma tuzildi
A22: =malumot!A156 -> Surxondaryo filiali boshlig'i | H22: =malumot!B156 -> A.PARDAYEV
A24: Monitoring bo'limi boshlig'i | H24: =malumot!B166 -> B. Jumanazarov
A26: Jismoniy shaxs, qarzdor | H26: =malumot!B7 -> SHAYMARDANOVA S.Y.

Sheet  Акт мониторинга 3
A2: =""&" "&malumot!B74&"-sonli "&" "&malumot!C64&" shartnomasi bo‘yicha garovga qo‘yilgan mol-mulkni tekshirish bo’yicha "&malumot!B5&" bilan tuzilgan dalolatnomasi" -> 24 mart 2025 y.dan №659-SR-sonli Mikroqarz shartnomasi bo‘yicha garovga qo‘yilgan mol-mulkni tekshirish bo’yicha SHAYMARDANOVA SABOXAT YULDASHEVNA bilan tuzilgan dalolatnomasi
A5: Toshkent shahri | H5: =TEXT(+malumot!B2+540,"ДД.ММ.ГГГГ") -> 15.09.2026
A7: =" Men, "&malumot!B153&" "&malumot!A156&"i "&malumot!B156&", jismoniy shaxs "&" "&malumot!B5&" "&" "&malumot!B74&"-sonli "&malumot!C64&" shartnomasi bo‘yicha garovga qo‘yilgan mol-mulkni ko‘zdan kechirdim" -> Men, «CLEVER MIKROMOLIYA TASHKILOTI» MChJ Surxondaryo filiali boshlig'ii A.PARDAYEV, jismoniy shaxs SHAYMARDANOVA SABOXAT YULDASHEVNA 24 mart 2025 y.dan №659-SR-sonli Mikroqarz shartnomasi bo‘yicha garovga qo‘yilgan mol-mulkni ko‘zdan kechirdim
A8: Garov sifatida quyida ko’rsatilgan mulk qabul qilinadi:
A9: =' Акт мониторинга 1'!A9 -> Nomi | C9: =' Акт мониторинга 1'!C9 -> Kuzov turi va kuzov raqami* | E9: =' Акт мониторинга 1'!E9 -> Dvigatel va shassi raqami* | G9: =' Акт мониторинга 1'!G9 -> Ishlab chiqarilgan yili va rangi**
A10: =' Акт мониторинга 1'!A10 -> LADA VESTA | C10: =' Акт мониторинга 1'!C10 -> kuzov turi - YENGIL SEDAN, kuzov raqami XTAGFL110KY258232 | E10: =' Акт мониторинга 1'!E10 -> dvigatel raqami 3977458, shassi raqami - RAKAMSIZ | G10: =' Акт мониторинга 1'!G10 -> rangi - SARIQ JELTO- ORANJEVIY, ishlab chiqarilgan yili - 2019
A11: =dalolatnoma!A22:E22 -> -* avtotransport egasi: XUDOYKULOV ALMURAT KURBONAZAROVICH
A12: =dalolatnoma!A23:E23 -> -* texnik pasport: AAG 3367573 24.01.2024 y.
A13: =dalolatnoma!A24:E24 -> -* roʻyxatdan oʻtgan manzili/garaj manzili: SURXONDARYO VILOYATI JARQO'RG'ON TUMANI OQQURG'ON QFY QORAYONTOQ MFY IBN SINO KO'CHASI 114-UY
A14: =dalolatnoma!A25:E25 -> -* davlat raqami: 75M497WA
